---- AspectJ Properties ---
AspectJ Compiler 1.6.11 built on Tuesday Mar 15, 2011 at 15:31:04 GMT
---- Dump Properties ---
Dump file: ajcore.20150913.182859.574.txt
Dump reason: org.aspectj.bridge.AbortException
Dump on exception: true
Dump at exit condition: abort
---- Exception Information ---
Message: abort trouble in: 
public class org.springframework.beans.propertyeditors.FileEditor extends java.beans.PropertyEditorSupport:
  private final org.springframework.core.io.ResourceEditor resourceEditor
  public void <init>():
                    ALOAD_0     // Lorg/springframework/beans/propertyeditors/FileEditor; this   (line 65)
                    INVOKESPECIAL java.beans.PropertyEditorSupport.<init> ()V
    constructor-execution(void org.springframework.beans.propertyeditors.FileEditor.<init>())
    |               ALOAD_0     // Lorg/springframework/beans/propertyeditors/FileEditor; this   (line 66)
    |               NEW org.springframework.core.io.ResourceEditor
    |               DUP
    |               INVOKESPECIAL org.springframework.core.io.ResourceEditor.<init> ()V
    |               PUTFIELD org.springframework.beans.propertyeditors.FileEditor.resourceEditor Lorg/springframework/core/io/ResourceEditor;
    |               RETURN   (line 67)
    constructor-execution(void org.springframework.beans.propertyeditors.FileEditor.<init>())
  end public void <init>()

  public void <init>(org.springframework.core.io.ResourceEditor):
                    ALOAD_0     // Lorg/springframework/beans/propertyeditors/FileEditor; this   (line 74)
                    INVOKESPECIAL java.beans.PropertyEditorSupport.<init> ()V
    constructor-execution(void org.springframework.beans.propertyeditors.FileEditor.<init>(org.springframework.core.io.ResourceEditor))
    |               ALOAD_1     // Lorg/springframework/core/io/ResourceEditor; resourceEditor   (line 75)
    |               LDC "ResourceEditor must not be null"
    |               INVOKESTATIC org.springframework.util.Assert.notNull (Ljava/lang/Object;Ljava/lang/String;)V
    |               ALOAD_0     // Lorg/springframework/beans/propertyeditors/FileEditor; this   (line 76)
    |               ALOAD_1     // Lorg/springframework/core/io/ResourceEditor; resourceEditor
    |               PUTFIELD org.springframework.beans.propertyeditors.FileEditor.resourceEditor Lorg/springframework/core/io/ResourceEditor;
    |               RETURN   (line 77)
    constructor-execution(void org.springframework.beans.propertyeditors.FileEditor.<init>(org.springframework.core.io.ResourceEditor))
  end public void <init>(org.springframework.core.io.ResourceEditor)

  public void setAsText(String) throws java.lang.IllegalArgumentException:
                    ALOAD_1     // Ljava/lang/String; text   (line 82)
                    INVOKESTATIC org.springframework.util.StringUtils.hasText (Ljava/lang/String;)Z
                    IFNE L0
                    ALOAD_0     // Lorg/springframework/beans/propertyeditors/FileEditor; this   (line 83)
                    ACONST_NULL
                    INVOKEVIRTUAL org.springframework.beans.propertyeditors.FileEditor.setValue (Ljava/lang/Object;)V
                    RETURN   (line 84)
                L0: ALOAD_1     // Ljava/lang/String; text   (line 89)
                    INVOKESTATIC org.springframework.util.ResourceUtils.isUrl (Ljava/lang/String;)Z
                    IFNE L1
                    NEW java.io.File   (line 90)
                    DUP
                    ALOAD_1     // Ljava/lang/String; text
                    INVOKESPECIAL java.io.File.<init> (Ljava/lang/String;)V
                    ASTORE_2
                    ALOAD_2     // Ljava/io/File; file   (line 91)
                    INVOKEVIRTUAL java.io.File.isAbsolute ()Z
                    IFEQ L1
                    ALOAD_0     // Lorg/springframework/beans/propertyeditors/FileEditor; this   (line 92)
                    ALOAD_2     // Ljava/io/File; file
                    INVOKEVIRTUAL org.springframework.beans.propertyeditors.FileEditor.setValue (Ljava/lang/Object;)V
                    RETURN   (line 93)
                L1: ALOAD_0     // Lorg/springframework/beans/propertyeditors/FileEditor; this   (line 98)
                    GETFIELD org.springframework.beans.propertyeditors.FileEditor.resourceEditor Lorg/springframework/core/io/ResourceEditor;
                    ALOAD_1     // Ljava/lang/String; text
                    INVOKEVIRTUAL org.springframework.core.io.ResourceEditor.setAsText (Ljava/lang/String;)V
                    ALOAD_0     // Lorg/springframework/beans/propertyeditors/FileEditor; this   (line 99)
                    GETFIELD org.springframework.beans.propertyeditors.FileEditor.resourceEditor Lorg/springframework/core/io/ResourceEditor;
                    INVOKEVIRTUAL org.springframework.core.io.ResourceEditor.getValue ()Ljava/lang/Object;
                    CHECKCAST org.springframework.core.io.Resource
                    ASTORE_2
                    ALOAD_1     // Ljava/lang/String; text   (line 102)
                    INVOKESTATIC org.springframework.util.ResourceUtils.isUrl (Ljava/lang/String;)Z
                    IFNE L2
                    ALOAD_2     // Lorg/springframework/core/io/Resource; resource
                    INVOKEINTERFACE org.springframework.core.io.Resource.exists ()Z
                    IFEQ L3
    catch java.io.IOException -> E0
    |           L2: ALOAD_0     // Lorg/springframework/beans/propertyeditors/FileEditor; this   (line 104)
    |               ALOAD_2     // Lorg/springframework/core/io/Resource; resource
    |               INVOKEINTERFACE org.springframework.core.io.Resource.getFile ()Ljava/io/File;
    |               INVOKEVIRTUAL org.springframework.beans.propertyeditors.FileEditor.setValue (Ljava/lang/Object;)V
    catch java.io.IOException -> E0
                    GOTO L4
                E0: ASTORE_3   (line 106)
                    NEW java.lang.IllegalArgumentException   (line 107)
                    DUP
                    NEW java.lang.StringBuilder   (line 108)
                    DUP
                    LDC "Could not retrieve File for "
                    INVOKESPECIAL java.lang.StringBuilder.<init> (Ljava/lang/String;)V
                    ALOAD_2     // Lorg/springframework/core/io/Resource; resource
                    INVOKEVIRTUAL java.lang.StringBuilder.append (Ljava/lang/Object;)Ljava/lang/StringBuilder;
                    LDC ": "
                    INVOKEVIRTUAL java.lang.StringBuilder.append (Ljava/lang/String;)Ljava/lang/StringBuilder;
                    ALOAD_3     // Ljava/io/IOException; ex
                    INVOKEVIRTUAL java.io.IOException.getMessage ()Ljava/lang/String;
                    INVOKEVIRTUAL java.lang.StringBuilder.append (Ljava/lang/String;)Ljava/lang/StringBuilder;
                    INVOKEVIRTUAL java.lang.StringBuilder.toString ()Ljava/lang/String;
                    INVOKESPECIAL java.lang.IllegalArgumentException.<init> (Ljava/lang/String;)V   (line 107)
                    ATHROW
                L3: ALOAD_0     // Lorg/springframework/beans/propertyeditors/FileEditor; this   (line 113)
                    NEW java.io.File
                    DUP
                    ALOAD_1     // Ljava/lang/String; text
                    INVOKESPECIAL java.io.File.<init> (Ljava/lang/String;)V
                    INVOKEVIRTUAL org.springframework.beans.propertyeditors.FileEditor.setValue (Ljava/lang/Object;)V
                L4: RETURN   (line 115)
  end public void setAsText(String) throws java.lang.IllegalArgumentException

  public String getAsText():
                    ALOAD_0     // Lorg/springframework/beans/propertyeditors/FileEditor; this   (line 119)
                    INVOKEVIRTUAL org.springframework.beans.propertyeditors.FileEditor.getValue ()Ljava/lang/Object;
                    CHECKCAST java.io.File
                    ASTORE_1
                    ALOAD_1     // Ljava/io/File; value   (line 120)
                    IFNULL L0
                    ALOAD_1     // Ljava/io/File; value
                    INVOKEVIRTUAL java.io.File.getPath ()Ljava/lang/String;
                    GOTO L1
                L0: LDC ""
                L1: ARETURN
  end public String getAsText()

end public class org.springframework.beans.propertyeditors.FileEditor
 -- (NullPointerException) null
null
java.lang.NullPointerException

org.aspectj.bridge.AbortException: trouble in: 
public class org.springframework.beans.propertyeditors.FileEditor extends java.beans.PropertyEditorSupport:
  private final org.springframework.core.io.ResourceEditor resourceEditor
  public void <init>():
                    ALOAD_0     // Lorg/springframework/beans/propertyeditors/FileEditor; this   (line 65)
                    INVOKESPECIAL java.beans.PropertyEditorSupport.<init> ()V
    constructor-execution(void org.springframework.beans.propertyeditors.FileEditor.<init>())
    |               ALOAD_0     // Lorg/springframework/beans/propertyeditors/FileEditor; this   (line 66)
    |               NEW org.springframework.core.io.ResourceEditor
    |               DUP
    |               INVOKESPECIAL org.springframework.core.io.ResourceEditor.<init> ()V
    |               PUTFIELD org.springframework.beans.propertyeditors.FileEditor.resourceEditor Lorg/springframework/core/io/ResourceEditor;
    |               RETURN   (line 67)
    constructor-execution(void org.springframework.beans.propertyeditors.FileEditor.<init>())
  end public void <init>()

  public void <init>(org.springframework.core.io.ResourceEditor):
                    ALOAD_0     // Lorg/springframework/beans/propertyeditors/FileEditor; this   (line 74)
                    INVOKESPECIAL java.beans.PropertyEditorSupport.<init> ()V
    constructor-execution(void org.springframework.beans.propertyeditors.FileEditor.<init>(org.springframework.core.io.ResourceEditor))
    |               ALOAD_1     // Lorg/springframework/core/io/ResourceEditor; resourceEditor   (line 75)
    |               LDC "ResourceEditor must not be null"
    |               INVOKESTATIC org.springframework.util.Assert.notNull (Ljava/lang/Object;Ljava/lang/String;)V
    |               ALOAD_0     // Lorg/springframework/beans/propertyeditors/FileEditor; this   (line 76)
    |               ALOAD_1     // Lorg/springframework/core/io/ResourceEditor; resourceEditor
    |               PUTFIELD org.springframework.beans.propertyeditors.FileEditor.resourceEditor Lorg/springframework/core/io/ResourceEditor;
    |               RETURN   (line 77)
    constructor-execution(void org.springframework.beans.propertyeditors.FileEditor.<init>(org.springframework.core.io.ResourceEditor))
  end public void <init>(org.springframework.core.io.ResourceEditor)

  public void setAsText(String) throws java.lang.IllegalArgumentException:
                    ALOAD_1     // Ljava/lang/String; text   (line 82)
                    INVOKESTATIC org.springframework.util.StringUtils.hasText (Ljava/lang/String;)Z
                    IFNE L0
                    ALOAD_0     // Lorg/springframework/beans/propertyeditors/FileEditor; this   (line 83)
                    ACONST_NULL
                    INVOKEVIRTUAL org.springframework.beans.propertyeditors.FileEditor.setValue (Ljava/lang/Object;)V
                    RETURN   (line 84)
                L0: ALOAD_1     // Ljava/lang/String; text   (line 89)
                    INVOKESTATIC org.springframework.util.ResourceUtils.isUrl (Ljava/lang/String;)Z
                    IFNE L1
                    NEW java.io.File   (line 90)
                    DUP
                    ALOAD_1     // Ljava/lang/String; text
                    INVOKESPECIAL java.io.File.<init> (Ljava/lang/String;)V
                    ASTORE_2
                    ALOAD_2     // Ljava/io/File; file   (line 91)
                    INVOKEVIRTUAL java.io.File.isAbsolute ()Z
                    IFEQ L1
                    ALOAD_0     // Lorg/springframework/beans/propertyeditors/FileEditor; this   (line 92)
                    ALOAD_2     // Ljava/io/File; file
                    INVOKEVIRTUAL org.springframework.beans.propertyeditors.FileEditor.setValue (Ljava/lang/Object;)V
                    RETURN   (line 93)
                L1: ALOAD_0     // Lorg/springframework/beans/propertyeditors/FileEditor; this   (line 98)
                    GETFIELD org.springframework.beans.propertyeditors.FileEditor.resourceEditor Lorg/springframework/core/io/ResourceEditor;
                    ALOAD_1     // Ljava/lang/String; text
                    INVOKEVIRTUAL org.springframework.core.io.ResourceEditor.setAsText (Ljava/lang/String;)V
                    ALOAD_0     // Lorg/springframework/beans/propertyeditors/FileEditor; this   (line 99)
                    GETFIELD org.springframework.beans.propertyeditors.FileEditor.resourceEditor Lorg/springframework/core/io/ResourceEditor;
                    INVOKEVIRTUAL org.springframework.core.io.ResourceEditor.getValue ()Ljava/lang/Object;
                    CHECKCAST org.springframework.core.io.Resource
                    ASTORE_2
                    ALOAD_1     // Ljava/lang/String; text   (line 102)
                    INVOKESTATIC org.springframework.util.ResourceUtils.isUrl (Ljava/lang/String;)Z
                    IFNE L2
                    ALOAD_2     // Lorg/springframework/core/io/Resource; resource
                    INVOKEINTERFACE org.springframework.core.io.Resource.exists ()Z
                    IFEQ L3
    catch java.io.IOException -> E0
    |           L2: ALOAD_0     // Lorg/springframework/beans/propertyeditors/FileEditor; this   (line 104)
    |               ALOAD_2     // Lorg/springframework/core/io/Resource; resource
    |               INVOKEINTERFACE org.springframework.core.io.Resource.getFile ()Ljava/io/File;
    |               INVOKEVIRTUAL org.springframework.beans.propertyeditors.FileEditor.setValue (Ljava/lang/Object;)V
    catch java.io.IOException -> E0
                    GOTO L4
                E0: ASTORE_3   (line 106)
                    NEW java.lang.IllegalArgumentException   (line 107)
                    DUP
                    NEW java.lang.StringBuilder   (line 108)
                    DUP
                    LDC "Could not retrieve File for "
                    INVOKESPECIAL java.lang.StringBuilder.<init> (Ljava/lang/String;)V
                    ALOAD_2     // Lorg/springframework/core/io/Resource; resource
                    INVOKEVIRTUAL java.lang.StringBuilder.append (Ljava/lang/Object;)Ljava/lang/StringBuilder;
                    LDC ": "
                    INVOKEVIRTUAL java.lang.StringBuilder.append (Ljava/lang/String;)Ljava/lang/StringBuilder;
                    ALOAD_3     // Ljava/io/IOException; ex
                    INVOKEVIRTUAL java.io.IOException.getMessage ()Ljava/lang/String;
                    INVOKEVIRTUAL java.lang.StringBuilder.append (Ljava/lang/String;)Ljava/lang/StringBuilder;
                    INVOKEVIRTUAL java.lang.StringBuilder.toString ()Ljava/lang/String;
                    INVOKESPECIAL java.lang.IllegalArgumentException.<init> (Ljava/lang/String;)V   (line 107)
                    ATHROW
                L3: ALOAD_0     // Lorg/springframework/beans/propertyeditors/FileEditor; this   (line 113)
                    NEW java.io.File
                    DUP
                    ALOAD_1     // Ljava/lang/String; text
                    INVOKESPECIAL java.io.File.<init> (Ljava/lang/String;)V
                    INVOKEVIRTUAL org.springframework.beans.propertyeditors.FileEditor.setValue (Ljava/lang/Object;)V
                L4: RETURN   (line 115)
  end public void setAsText(String) throws java.lang.IllegalArgumentException

  public String getAsText():
                    ALOAD_0     // Lorg/springframework/beans/propertyeditors/FileEditor; this   (line 119)
                    INVOKEVIRTUAL org.springframework.beans.propertyeditors.FileEditor.getValue ()Ljava/lang/Object;
                    CHECKCAST java.io.File
                    ASTORE_1
                    ALOAD_1     // Ljava/io/File; value   (line 120)
                    IFNULL L0
                    ALOAD_1     // Ljava/io/File; value
                    INVOKEVIRTUAL java.io.File.getPath ()Ljava/lang/String;
                    GOTO L1
                L0: LDC ""
                L1: ARETURN
  end public String getAsText()

end public class org.springframework.beans.propertyeditors.FileEditor

	at org.aspectj.bridge.MessageWriter.handleMessage(MessageWriter.java:47)
	at org.aspectj.weaver.tools.WeavingAdaptor$WeavingAdaptorMessageWriter.handleMessage(WeavingAdaptor.java:737)
	at org.aspectj.weaver.tools.WeavingAdaptor$WeavingAdaptorMessageHolder.handleMessage(WeavingAdaptor.java:682)
	at org.aspectj.weaver.bcel.BcelWeaver.weave(BcelWeaver.java:1712)
	at org.aspectj.weaver.bcel.BcelWeaver.weaveWithoutDump(BcelWeaver.java:1631)
	at org.aspectj.weaver.bcel.BcelWeaver.weaveAndNotify(BcelWeaver.java:1394)
	at org.aspectj.weaver.bcel.BcelWeaver.weave(BcelWeaver.java:1180)
	at org.aspectj.weaver.tools.WeavingAdaptor.getWovenBytes(WeavingAdaptor.java:467)
	at org.aspectj.weaver.tools.WeavingAdaptor.weaveClass(WeavingAdaptor.java:318)
	at org.aspectj.weaver.loadtime.Aj.preProcess(Aj.java:96)
	at org.aspectj.weaver.loadtime.ClassPreProcessorAgentAdapter.transform(ClassPreProcessorAgentAdapter.java:54)
	at sun.instrument.TransformerManager.transform(TransformerManager.java:188)
	at sun.instrument.InstrumentationImpl.transform(InstrumentationImpl.java:428)
	at java.lang.ClassLoader.defineClass1(Native Method)
	at java.lang.ClassLoader.defineClass(ClassLoader.java:760)
	at java.security.SecureClassLoader.defineClass(SecureClassLoader.java:142)
	at java.net.URLClassLoader.defineClass(URLClassLoader.java:467)
	at java.net.URLClassLoader.access$100(URLClassLoader.java:73)
	at java.net.URLClassLoader$1.run(URLClassLoader.java:368)
	at java.net.URLClassLoader$1.run(URLClassLoader.java:362)
	at java.security.AccessController.doPrivileged(Native Method)
	at java.net.URLClassLoader.findClass(URLClassLoader.java:361)
	at java.lang.ClassLoader.loadClass(ClassLoader.java:424)
	at sun.misc.Launcher$AppClassLoader.loadClass(Launcher.java:331)
	at java.lang.ClassLoader.loadClass(ClassLoader.java:357)
	at org.springframework.beans.support.ResourceEditorRegistrar.registerCustomEditors(ResourceEditorRegistrar.java:89)
	at org.springframework.beans.factory.support.AbstractBeanFactory.registerCustomEditors(AbstractBeanFactory.java:1039)
	at org.springframework.beans.factory.support.AbstractBeanFactory.initBeanWrapper(AbstractBeanFactory.java:1019)
	at org.springframework.beans.factory.support.ConstructorResolver.instantiateUsingFactoryMethod(ConstructorResolver.java:341)
	at org.springframework.beans.factory.support.AbstractAutowireCapableBeanFactory.instantiateUsingFactoryMethod(AbstractAutowireCapableBeanFactory.java:983)
	at org.springframework.beans.factory.support.AbstractAutowireCapableBeanFactory.createBeanInstance(AbstractAutowireCapableBeanFactory.java:879)
	at org.springframework.beans.factory.support.AbstractAutowireCapableBeanFactory.doCreateBean(AbstractAutowireCapableBeanFactory.java:485)
	at org.springframework.beans.factory.support.AbstractAutowireCapableBeanFactory.createBean(AbstractAutowireCapableBeanFactory.java:456)
	at org.springframework.beans.factory.support.AbstractBeanFactory$1.getObject(AbstractBeanFactory.java:291)
	at org.springframework.beans.factory.support.DefaultSingletonBeanRegistry.getSingleton(DefaultSingletonBeanRegistry.java:222)
	at org.springframework.beans.factory.support.AbstractBeanFactory.doGetBean(AbstractBeanFactory.java:288)
	at org.springframework.beans.factory.support.AbstractBeanFactory.getBean(AbstractBeanFactory.java:190)
	at org.springframework.beans.factory.support.DefaultListableBeanFactory.preInstantiateSingletons(DefaultListableBeanFactory.java:580)
	at org.springframework.context.support.AbstractApplicationContext.finishBeanFactoryInitialization(AbstractApplicationContext.java:895)
	at org.springframework.context.support.AbstractApplicationContext.refresh(AbstractApplicationContext.java:425)
	at org.springframework.context.support.ClassPathXmlApplicationContext.<init>(ClassPathXmlApplicationContext.java:139)
	at org.springframework.context.support.ClassPathXmlApplicationContext.<init>(ClassPathXmlApplicationContext.java:83)
	at foo.ConfigureApp.main(ConfigureApp.java:9)
---- System Properties ---
java.runtime.name=Java(TM) SE Runtime Environment
sun.boot.library.path=C:\Program Files\Java\jdk1.8.0_45\jre\bin
java.vm.version=25.45-b02
java.vm.vendor=Oracle Corporation
java.vendor.url=http://java.oracle.com/
path.separator=;
java.vm.name=Java HotSpot(TM) 64-Bit Server VM
file.encoding.pkg=sun.io
user.country=US
user.script=
sun.java.launcher=SUN_STANDARD
sun.os.patch.level=
java.vm.specification.name=Java Virtual Machine Specification
user.dir=E:\Eclipse Latest\SpringChap3.3
java.runtime.version=1.8.0_45-b15
java.awt.graphicsenv=sun.awt.Win32GraphicsEnvironment
java.endorsed.dirs=C:\Program Files\Java\jdk1.8.0_45\jre\lib\endorsed
os.arch=amd64
java.io.tmpdir=C:\Users\SANJUS~1\AppData\Local\Temp\
line.separator=

java.vm.specification.vendor=Oracle Corporation
user.variant=
os.name=Windows 7
sun.jnu.encoding=Cp1252
java.library.path=C:\Program Files\Java\jdk1.8.0_45\bin;C:\Windows\Sun\Java\bin;C:\Windows\system32;C:\Windows;C:/Program Files/Java/jdk1.8.0_45/bin/../jre/bin/server;C:/Program Files/Java/jdk1.8.0_45/bin/../jre/bin;C:/Program Files/Java/jdk1.8.0_45/bin/../jre/lib/amd64;C:\oraclexe\app\oracle\product\10.2.0\server\bin;C:\Program Files\Java\jdk1.8.0_45\bin;C:\Program Files (x86)\Java\jre1.8.0_45\bin;C:\ProgramData\Oracle\Java\javapath;C:\Windows\system32;C:\Windows;C:\Windows\System32\Wbem;C:\Windows\System32\WindowsPowerShell\v1.0\;C:\Python27;;E:\Eclipse Latest\eclipse-jee-luna-SR2-win32-x86_64\eclipse;;.
java.specification.name=Java Platform API Specification
java.class.version=52.0
sun.management.compiler=HotSpot 64-Bit Tiered Compilers
os.version=6.1
user.home=C:\Users\sanju singh
user.timezone=Asia/Calcutta
java.awt.printerjob=sun.awt.windows.WPrinterJob
file.encoding=Cp1252
java.specification.version=1.8
java.class.path=E:\Eclipse Latest\SpringChap3.3\bin;E:\Eclipse Latest\SpringJar\extra Jar\aopalliance-1.0.jar;E:\Eclipse Latest\SpringJar\extra Jar\asm-3.3.1.jar;E:\Eclipse Latest\SpringJar\extra Jar\aspectjrt-1.6.11.jar;E:\Eclipse Latest\SpringJar\extra Jar\aspectjweaver-1.6.11.jar;E:\Eclipse Latest\SpringJar\extra Jar\cglib-2.2.2.jar;E:\Eclipse Latest\SpringJar\extra Jar\commons-logging-1.1.1.jar;E:\Eclipse Latest\SpringJar\extra Jar\junit-4.8.2.jar;E:\Eclipse Latest\SpringJar\extra Jar\spring-aop-3.0.5.RELEASE.jar;E:\Eclipse Latest\SpringJar\extra Jar\spring-asm-3.0.5.RELEASE.jar;E:\Eclipse Latest\SpringJar\extra Jar\spring-beans-3.0.5.RELEASE.jar;E:\Eclipse Latest\SpringJar\extra Jar\spring-context-3.0.5.RELEASE.jar;E:\Eclipse Latest\SpringJar\extra Jar\spring-core-3.0.5.RELEASE.jar;E:\Eclipse Latest\SpringJar\extra Jar\spring-expression-3.0.5.RELEASE.jar;E:\Eclipse Latest\SpringJar\spring-aspects-4.1.6.RELEASE.jar;E:\TestJar\aspectjweaver-1.6.11.jar
user.name=sanju singh
java.vm.specification.version=1.8
sun.java.command=foo.ConfigureApp
java.home=C:\Program Files\Java\jdk1.8.0_45\jre
sun.arch.data.model=64
user.language=en
java.specification.vendor=Oracle Corporation
awt.toolkit=sun.awt.windows.WToolkit
java.vm.info=mixed mode
java.version=1.8.0_45
java.ext.dirs=C:\Program Files\Java\jdk1.8.0_45\jre\lib\ext;C:\Windows\Sun\Java\lib\ext
sun.boot.class.path=C:\Program Files\Java\jdk1.8.0_45\jre\lib\resources.jar;C:\Program Files\Java\jdk1.8.0_45\jre\lib\rt.jar;C:\Program Files\Java\jdk1.8.0_45\jre\lib\sunrsasign.jar;C:\Program Files\Java\jdk1.8.0_45\jre\lib\jsse.jar;C:\Program Files\Java\jdk1.8.0_45\jre\lib\jce.jar;C:\Program Files\Java\jdk1.8.0_45\jre\lib\charsets.jar;C:\Program Files\Java\jdk1.8.0_45\jre\lib\jfr.jar;C:\Program Files\Java\jdk1.8.0_45\jre\classes
java.vendor=Oracle Corporation
file.separator=\
java.vendor.url.bug=http://bugreport.sun.com/bugreport/
sun.io.unicode.encoding=UnicodeLittle
sun.cpu.endian=little
sun.desktop=windows
sun.cpu.isalist=amd64
---- Command Line ---
Empty
---- Full Classpath ---
Empty
---- Compiler Messages ---
Empty
