---- AspectJ Properties ---
AspectJ Compiler 1.6.11 built on Tuesday Mar 15, 2011 at 15:31:04 GMT
---- Dump Properties ---
Dump file: ajcore.20150913.185856.579.txt
Dump reason: abort
Dump on exception: true
Dump at exit condition: abort
---- System Properties ---
java.runtime.name=Java(TM) SE Runtime Environment
sun.boot.library.path=C:\Program Files\Java\jdk1.8.0_45\jre\bin
java.vm.version=25.45-b02
java.vm.vendor=Oracle Corporation
java.vendor.url=http://java.oracle.com/
path.separator=;
java.vm.name=Java HotSpot(TM) 64-Bit Server VM
file.encoding.pkg=sun.io
user.country=US
user.script=
sun.java.launcher=SUN_STANDARD
sun.os.patch.level=
java.vm.specification.name=Java Virtual Machine Specification
user.dir=E:\Eclipse Latest\SpringChap3.3
java.runtime.version=1.8.0_45-b15
java.awt.graphicsenv=sun.awt.Win32GraphicsEnvironment
java.endorsed.dirs=C:\Program Files\Java\jdk1.8.0_45\jre\lib\endorsed
os.arch=amd64
java.io.tmpdir=C:\Users\SANJUS~1\AppData\Local\Temp\
line.separator=

java.vm.specification.vendor=Oracle Corporation
user.variant=
os.name=Windows 7
sun.jnu.encoding=Cp1252
java.library.path=C:\Program Files\Java\jdk1.8.0_45\bin;C:\Windows\Sun\Java\bin;C:\Windows\system32;C:\Windows;C:/Program Files/Java/jdk1.8.0_45/bin/../jre/bin/server;C:/Program Files/Java/jdk1.8.0_45/bin/../jre/bin;C:/Program Files/Java/jdk1.8.0_45/bin/../jre/lib/amd64;C:\oraclexe\app\oracle\product\10.2.0\server\bin;C:\Program Files\Java\jdk1.8.0_45\bin;C:\Program Files (x86)\Java\jre1.8.0_45\bin;C:\ProgramData\Oracle\Java\javapath;C:\Windows\system32;C:\Windows;C:\Windows\System32\Wbem;C:\Windows\System32\WindowsPowerShell\v1.0\;C:\Python27;;E:\Eclipse Latest\eclipse-jee-luna-SR2-win32-x86_64\eclipse;;.
java.specification.name=Java Platform API Specification
java.class.version=52.0
sun.management.compiler=HotSpot 64-Bit Tiered Compilers
os.version=6.1
user.home=C:\Users\sanju singh
user.timezone=Asia/Calcutta
java.awt.printerjob=sun.awt.windows.WPrinterJob
file.encoding=Cp1252
java.specification.version=1.8
java.class.path=E:\Eclipse Latest\SpringChap3.3\bin;E:\Eclipse Latest\SpringJar\extra Jar\aopalliance-1.0.jar;E:\Eclipse Latest\SpringJar\extra Jar\asm-3.3.1.jar;E:\Eclipse Latest\SpringJar\extra Jar\aspectjrt-1.6.11.jar;E:\Eclipse Latest\SpringJar\extra Jar\aspectjweaver-1.6.11.jar;E:\Eclipse Latest\SpringJar\extra Jar\cglib-2.2.2.jar;E:\Eclipse Latest\SpringJar\extra Jar\commons-logging-1.1.1.jar;E:\Eclipse Latest\SpringJar\extra Jar\junit-4.8.2.jar;E:\Eclipse Latest\SpringJar\extra Jar\spring-aop-3.0.5.RELEASE.jar;E:\Eclipse Latest\SpringJar\extra Jar\spring-asm-3.0.5.RELEASE.jar;E:\Eclipse Latest\SpringJar\extra Jar\spring-beans-3.0.5.RELEASE.jar;E:\Eclipse Latest\SpringJar\extra Jar\spring-context-3.0.5.RELEASE.jar;E:\Eclipse Latest\SpringJar\extra Jar\spring-core-3.0.5.RELEASE.jar;E:\Eclipse Latest\SpringJar\extra Jar\spring-expression-3.0.5.RELEASE.jar;E:\Eclipse Latest\SpringJar\spring-aspects-4.1.6.RELEASE.jar;E:\TestJar\aspectjweaver-1.6.11.jar
user.name=sanju singh
java.vm.specification.version=1.8
sun.java.command=foo.ConfigureApp
java.home=C:\Program Files\Java\jdk1.8.0_45\jre
sun.arch.data.model=64
user.language=en
java.specification.vendor=Oracle Corporation
awt.toolkit=sun.awt.windows.WToolkit
java.vm.info=mixed mode
java.version=1.8.0_45
java.ext.dirs=C:\Program Files\Java\jdk1.8.0_45\jre\lib\ext;C:\Windows\Sun\Java\lib\ext
sun.boot.class.path=C:\Program Files\Java\jdk1.8.0_45\jre\lib\resources.jar;C:\Program Files\Java\jdk1.8.0_45\jre\lib\rt.jar;C:\Program Files\Java\jdk1.8.0_45\jre\lib\sunrsasign.jar;C:\Program Files\Java\jdk1.8.0_45\jre\lib\jsse.jar;C:\Program Files\Java\jdk1.8.0_45\jre\lib\jce.jar;C:\Program Files\Java\jdk1.8.0_45\jre\lib\charsets.jar;C:\Program Files\Java\jdk1.8.0_45\jre\lib\jfr.jar;C:\Program Files\Java\jdk1.8.0_45\jre\classes
java.vendor=Oracle Corporation
file.separator=\
java.vendor.url.bug=http://bugreport.sun.com/bugreport/
sun.io.unicode.encoding=UnicodeLittle
sun.cpu.endian=little
sun.desktop=windows
sun.cpu.isalist=amd64
---- Command Line ---
Empty
---- Full Classpath ---
Empty
---- Compiler Messages ---
info AspectJ Weaver Version 1.6.11 built on Tuesday Mar 15, 2011 at 15:31:04 GMT
info register classloader sun.misc.Launcher$AppClassLoader@14dad5dc
info using configuration file:/E:/Eclipse%20Latest/SpringJar/spring-aspects-4.1.6.RELEASE.jar!/META-INF/aop.xml
error can't determine annotations of missing type org.springframework.cache.annotation.CachePut
when weaving type org.springframework.beans.factory.support.BeanDefinitionReaderUtils
when weaving classes 
when weaving 
 [Xlint:cantFindType]
error can't determine annotations of missing type org.springframework.cache.annotation.Cacheable
when weaving type org.springframework.beans.factory.support.BeanDefinitionReaderUtils
when weaving classes 
when weaving 
 [Xlint:cantFindType]
error can't determine annotations of missing type org.springframework.cache.annotation.CacheEvict
when weaving type org.springframework.beans.factory.support.BeanDefinitionReaderUtils
when weaving classes 
when weaving 
 [Xlint:cantFindType]
error can't determine annotations of missing type org.springframework.cache.annotation.Caching
when weaving type org.springframework.beans.factory.support.BeanDefinitionReaderUtils
when weaving classes 
when weaving 
 [Xlint:cantFindType]
error can't determine annotations of missing type org.springframework.transaction.annotation.Transactional
when weaving type org.springframework.beans.factory.support.BeanDefinitionReaderUtils
when weaving classes 
when weaving 
 [Xlint:cantFindType]
abort trouble in: 
public class org.springframework.beans.factory.support.BeanDefinitionReaderUtils extends java.lang.Object:
  public static final String GENERATED_BEAN_NAME_SEPARATOR = "#"
  public void <init>():
                    ALOAD_0     // Lorg/springframework/beans/factory/support/BeanDefinitionReaderUtils; this   (line 37)
                    INVOKESPECIAL java.lang.Object.<init> ()V
    constructor-execution(void org.springframework.beans.factory.support.BeanDefinitionReaderUtils.<init>())
    |               RETURN
    constructor-execution(void org.springframework.beans.factory.support.BeanDefinitionReaderUtils.<init>())
  end public void <init>()

  public static org.springframework.beans.factory.support.AbstractBeanDefinition createBeanDefinition(String, String, ClassLoader) throws java.lang.ClassNotFoundException:
                    NEW org.springframework.beans.factory.support.GenericBeanDefinition   (line 59)
                    DUP
                    INVOKESPECIAL org.springframework.beans.factory.support.GenericBeanDefinition.<init> ()V
                    ASTORE_3
                    ALOAD_3     // Lorg/springframework/beans/factory/support/GenericBeanDefinition; bd   (line 60)
                    ALOAD_0     // Ljava/lang/String; parentName
                    INVOKEVIRTUAL org.springframework.beans.factory.support.GenericBeanDefinition.setParentName (Ljava/lang/String;)V
                    ALOAD_1     // Ljava/lang/String; className   (line 61)
                    IFNULL L1
                    ALOAD_2     // Ljava/lang/ClassLoader; classLoader   (line 62)
                    IFNULL L0
                    ALOAD_3     // Lorg/springframework/beans/factory/support/GenericBeanDefinition; bd   (line 63)
                    ALOAD_1     // Ljava/lang/String; className
                    ALOAD_2     // Ljava/lang/ClassLoader; classLoader
                    INVOKESTATIC org.springframework.util.ClassUtils.forName (Ljava/lang/String;Ljava/lang/ClassLoader;)Ljava/lang/Class;
                    INVOKEVIRTUAL org.springframework.beans.factory.support.GenericBeanDefinition.setBeanClass (Ljava/lang/Class;)V
                    GOTO L1
                L0: ALOAD_3     // Lorg/springframework/beans/factory/support/GenericBeanDefinition; bd   (line 66)
                    ALOAD_1     // Ljava/lang/String; className
                    INVOKEVIRTUAL org.springframework.beans.factory.support.GenericBeanDefinition.setBeanClassName (Ljava/lang/String;)V
                L1: ALOAD_3     // Lorg/springframework/beans/factory/support/GenericBeanDefinition; bd   (line 69)
                    ARETURN
  end public static org.springframework.beans.factory.support.AbstractBeanDefinition createBeanDefinition(String, String, ClassLoader) throws java.lang.ClassNotFoundException

  public static String generateBeanName(org.springframework.beans.factory.config.BeanDefinition, org.springframework.beans.factory.support.BeanDefinitionRegistry, boolean) throws org.springframework.beans.factory.BeanDefinitionStoreException:
                    ALOAD_0     // Lorg/springframework/beans/factory/config/BeanDefinition; definition   (line 89)
                    INVOKEINTERFACE org.springframework.beans.factory.config.BeanDefinition.getBeanClassName ()Ljava/lang/String;
                    ASTORE_3
                    ALOAD_3     // Ljava/lang/String; generatedBeanName   (line 90)
                    IFNONNULL L1
                    ALOAD_0     // Lorg/springframework/beans/factory/config/BeanDefinition; definition   (line 91)
                    INVOKEINTERFACE org.springframework.beans.factory.config.BeanDefinition.getParentName ()Ljava/lang/String;
                    IFNULL L0
                    NEW java.lang.StringBuilder   (line 92)
                    DUP
                    ALOAD_0     // Lorg/springframework/beans/factory/config/BeanDefinition; definition
                    INVOKEINTERFACE org.springframework.beans.factory.config.BeanDefinition.getParentName ()Ljava/lang/String;
                    INVOKESTATIC java.lang.String.valueOf (Ljava/lang/Object;)Ljava/lang/String;
                    INVOKESPECIAL java.lang.StringBuilder.<init> (Ljava/lang/String;)V
                    LDC "$child"
                    INVOKEVIRTUAL java.lang.StringBuilder.append (Ljava/lang/String;)Ljava/lang/StringBuilder;
                    INVOKEVIRTUAL java.lang.StringBuilder.toString ()Ljava/lang/String;
                    ASTORE_3     // Ljava/lang/String; generatedBeanName
                    GOTO L1
                L0: ALOAD_0     // Lorg/springframework/beans/factory/config/BeanDefinition; definition   (line 94)
                    INVOKEINTERFACE org.springframework.beans.factory.config.BeanDefinition.getFactoryBeanName ()Ljava/lang/String;
                    IFNULL L1
                    NEW java.lang.StringBuilder   (line 95)
                    DUP
                    ALOAD_0     // Lorg/springframework/beans/factory/config/BeanDefinition; definition
                    INVOKEINTERFACE org.springframework.beans.factory.config.BeanDefinition.getFactoryBeanName ()Ljava/lang/String;
                    INVOKESTATIC java.lang.String.valueOf (Ljava/lang/Object;)Ljava/lang/String;
                    INVOKESPECIAL java.lang.StringBuilder.<init> (Ljava/lang/String;)V
                    LDC "$created"
                    INVOKEVIRTUAL java.lang.StringBuilder.append (Ljava/lang/String;)Ljava/lang/StringBuilder;
                    INVOKEVIRTUAL java.lang.StringBuilder.toString ()Ljava/lang/String;
                    ASTORE_3     // Ljava/lang/String; generatedBeanName
                L1: ALOAD_3     // Ljava/lang/String; generatedBeanName   (line 98)
                    INVOKESTATIC org.springframework.util.StringUtils.hasText (Ljava/lang/String;)Z
                    IFNE L2
                    NEW org.springframework.beans.factory.BeanDefinitionStoreException   (line 99)
                    DUP
                    LDC "Unnamed bean definition specifies neither 'class' nor 'parent' nor 'factory-bean' - can't generate bean name"
                    INVOKESPECIAL org.springframework.beans.factory.BeanDefinitionStoreException.<init> (Ljava/lang/String;)V
                    ATHROW
                L2: ALOAD_3     // Ljava/lang/String; generatedBeanName   (line 103)
                    ASTORE 4
                    ILOAD_2     // Z isInnerBean   (line 104)
                    IFEQ L3
                    NEW java.lang.StringBuilder   (line 106)
                    DUP
                    ALOAD_3     // Ljava/lang/String; generatedBeanName
                    INVOKESTATIC java.lang.String.valueOf (Ljava/lang/Object;)Ljava/lang/String;
                    INVOKESPECIAL java.lang.StringBuilder.<init> (Ljava/lang/String;)V
                    LDC "#"
                    INVOKEVIRTUAL java.lang.StringBuilder.append (Ljava/lang/String;)Ljava/lang/StringBuilder;
                    ALOAD_0     // Lorg/springframework/beans/factory/config/BeanDefinition; definition
                    INVOKESTATIC org.springframework.util.ObjectUtils.getIdentityHexString (Ljava/lang/Object;)Ljava/lang/String;
                    INVOKEVIRTUAL java.lang.StringBuilder.append (Ljava/lang/String;)Ljava/lang/StringBuilder;
                    INVOKEVIRTUAL java.lang.StringBuilder.toString ()Ljava/lang/String;
                    ASTORE 4     // Ljava/lang/String; id
                    GOTO L6
                L3: ICONST_M1   (line 111)
                    ISTORE 5
                    GOTO L5   (line 112)
                L4: IINC 5 1     // I counter   (line 113)
                    NEW java.lang.StringBuilder   (line 114)
                    DUP
                    ALOAD_3     // Ljava/lang/String; generatedBeanName
                    INVOKESTATIC java.lang.String.valueOf (Ljava/lang/Object;)Ljava/lang/String;
                    INVOKESPECIAL java.lang.StringBuilder.<init> (Ljava/lang/String;)V
                    LDC "#"
                    INVOKEVIRTUAL java.lang.StringBuilder.append (Ljava/lang/String;)Ljava/lang/StringBuilder;
                    ILOAD 5     // I counter
                    INVOKEVIRTUAL java.lang.StringBuilder.append (I)Ljava/lang/StringBuilder;
                    INVOKEVIRTUAL java.lang.StringBuilder.toString ()Ljava/lang/String;
                    ASTORE 4     // Ljava/lang/String; id
                L5: ILOAD 5     // I counter   (line 112)
                    ICONST_M1
                    IF_ICMPEQ L4
                    ALOAD_1     // Lorg/springframework/beans/factory/support/BeanDefinitionRegistry; registry
                    ALOAD 4     // Ljava/lang/String; id
                    INVOKEINTERFACE org.springframework.beans.factory.support.BeanDefinitionRegistry.containsBeanDefinition (Ljava/lang/String;)Z
                    IFNE L4
                L6: ALOAD 4     // Ljava/lang/String; id   (line 117)
                    ARETURN
  end public static String generateBeanName(org.springframework.beans.factory.config.BeanDefinition, org.springframework.beans.factory.support.BeanDefinitionRegistry, boolean) throws org.springframework.beans.factory.BeanDefinitionStoreException

  public static String generateBeanName(org.springframework.beans.factory.config.BeanDefinition, org.springframework.beans.factory.support.BeanDefinitionRegistry) throws org.springframework.beans.factory.BeanDefinitionStoreException:
                    ALOAD_0     // Lorg/springframework/beans/factory/config/BeanDefinition; beanDefinition   (line 133)
                    ALOAD_1     // Lorg/springframework/beans/factory/support/BeanDefinitionRegistry; registry
                    ICONST_0
                    INVOKESTATIC org.springframework.beans.factory.support.BeanDefinitionReaderUtils.generateBeanName (Lorg/springframework/beans/factory/config/BeanDefinition;Lorg/springframework/beans/factory/support/BeanDefinitionRegistry;Z)Ljava/lang/String;
                    ARETURN
  end public static String generateBeanName(org.springframework.beans.factory.config.BeanDefinition, org.springframework.beans.factory.support.BeanDefinitionRegistry) throws org.springframework.beans.factory.BeanDefinitionStoreException

  public static void registerBeanDefinition(org.springframework.beans.factory.config.BeanDefinitionHolder, org.springframework.beans.factory.support.BeanDefinitionRegistry) throws org.springframework.beans.factory.BeanDefinitionStoreException:
                    ALOAD_0     // Lorg/springframework/beans/factory/config/BeanDefinitionHolder; definitionHolder   (line 147)
                    INVOKEVIRTUAL org.springframework.beans.factory.config.BeanDefinitionHolder.getBeanName ()Ljava/lang/String;
                    ASTORE_2
                    ALOAD_1     // Lorg/springframework/beans/factory/support/BeanDefinitionRegistry; registry   (line 148)
                    ALOAD_2     // Ljava/lang/String; beanName
                    ALOAD_0     // Lorg/springframework/beans/factory/config/BeanDefinitionHolder; definitionHolder
                    INVOKEVIRTUAL org.springframework.beans.factory.config.BeanDefinitionHolder.getBeanDefinition ()Lorg/springframework/beans/factory/config/BeanDefinition;
                    INVOKEINTERFACE org.springframework.beans.factory.support.BeanDefinitionRegistry.registerBeanDefinition (Ljava/lang/String;Lorg/springframework/beans/factory/config/BeanDefinition;)V
                    ALOAD_0     // Lorg/springframework/beans/factory/config/BeanDefinitionHolder; definitionHolder   (line 151)
                    INVOKEVIRTUAL org.springframework.beans.factory.config.BeanDefinitionHolder.getAliases ()[Ljava/lang/String;
                    ASTORE_3
                    ALOAD_3     // [Ljava/lang/String; aliases   (line 152)
                    IFNULL L2
                    ALOAD_3     // [Ljava/lang/String; aliases   (line 153)
                    DUP
                    ASTORE 7
                    ARRAYLENGTH
                    ISTORE 6
                    ICONST_0
                    ISTORE 5
                    GOTO L1
                L0: ALOAD 7
                    ILOAD 5
                    AALOAD
                    ASTORE 4
                    ALOAD_1     // Lorg/springframework/beans/factory/support/BeanDefinitionRegistry; registry   (line 154)
                    ALOAD_2     // Ljava/lang/String; beanName
                    ALOAD 4     // Ljava/lang/String; aliase
                    INVOKEINTERFACE org.springframework.beans.factory.support.BeanDefinitionRegistry.registerAlias (Ljava/lang/String;Ljava/lang/String;)V
                    IINC 5 1   (line 153)
                L1: ILOAD 5
                    ILOAD 6
                    IF_ICMPLT L0
                L2: RETURN   (line 157)
  end public static void registerBeanDefinition(org.springframework.beans.factory.config.BeanDefinitionHolder, org.springframework.beans.factory.support.BeanDefinitionRegistry) throws org.springframework.beans.factory.BeanDefinitionStoreException

  public static String registerWithGeneratedName(org.springframework.beans.factory.support.AbstractBeanDefinition, org.springframework.beans.factory.support.BeanDefinitionRegistry) throws org.springframework.beans.factory.BeanDefinitionStoreException:
                    ALOAD_0     // Lorg/springframework/beans/factory/support/AbstractBeanDefinition; definition   (line 172)
                    ALOAD_1     // Lorg/springframework/beans/factory/support/BeanDefinitionRegistry; registry
                    ICONST_0
                    INVOKESTATIC org.springframework.beans.factory.support.BeanDefinitionReaderUtils.generateBeanName (Lorg/springframework/beans/factory/config/BeanDefinition;Lorg/springframework/beans/factory/support/BeanDefinitionRegistry;Z)Ljava/lang/String;
                    ASTORE_2
                    ALOAD_1     // Lorg/springframework/beans/factory/support/BeanDefinitionRegistry; registry   (line 173)
                    ALOAD_2     // Ljava/lang/String; generatedName
                    ALOAD_0     // Lorg/springframework/beans/factory/support/AbstractBeanDefinition; definition
                    INVOKEINTERFACE org.springframework.beans.factory.support.BeanDefinitionRegistry.registerBeanDefinition (Ljava/lang/String;Lorg/springframework/beans/factory/config/BeanDefinition;)V
                    ALOAD_2     // Ljava/lang/String; generatedName   (line 174)
                    ARETURN
  end public static String registerWithGeneratedName(org.springframework.beans.factory.support.AbstractBeanDefinition, org.springframework.beans.factory.support.BeanDefinitionRegistry) throws org.springframework.beans.factory.BeanDefinitionStoreException

end public class org.springframework.beans.factory.support.BeanDefinitionReaderUtils
 -- (NullPointerException) null
null
java.lang.NullPointerException
	at org.aspectj.weaver.UnresolvedType.forSignature(UnresolvedType.java:361)
	at org.aspectj.weaver.bcel.BcelObjectType.getDeclaredInterfaces(BcelObjectType.java:275)
	at org.aspectj.weaver.ReferenceType.getDeclaredInterfaces(ReferenceType.java:624)
	at org.aspectj.weaver.ResolvedType.getDirectSupertypes(ResolvedType.java:76)
	at org.aspectj.weaver.patterns.TypePattern.matchesSubtypes(TypePattern.java:178)
	at org.aspectj.weaver.patterns.ExactTypePattern.matchesSubtypes(ExactTypePattern.java:74)
	at org.aspectj.weaver.patterns.TypePattern.matchesStatically(TypePattern.java:130)
	at org.aspectj.weaver.patterns.OrTypePattern.matchesStatically(OrTypePattern.java:76)
	at org.aspectj.weaver.patterns.SignaturePattern.matchesExactlyMethod(SignaturePattern.java:505)
	at org.aspectj.weaver.patterns.SignaturePattern.matchesExactly(SignaturePattern.java:360)
	at org.aspectj.weaver.patterns.SignaturePattern.matches(SignaturePattern.java:320)
	at org.aspectj.weaver.patterns.KindedPointcut.matchInternal(KindedPointcut.java:202)
	at org.aspectj.weaver.patterns.Pointcut.match(Pointcut.java:137)
	at org.aspectj.weaver.patterns.AndPointcut.matchInternal(AndPointcut.java:51)
	at org.aspectj.weaver.patterns.Pointcut.match(Pointcut.java:137)
	at org.aspectj.weaver.patterns.OrPointcut.matchInternal(OrPointcut.java:54)
	at org.aspectj.weaver.patterns.Pointcut.match(Pointcut.java:137)
	at org.aspectj.weaver.ShadowMunger.match(ShadowMunger.java:113)
	at org.aspectj.weaver.Advice.match(Advice.java:109)
	at org.aspectj.weaver.bcel.BcelAdvice.match(BcelAdvice.java:149)
	at org.aspectj.weaver.bcel.BcelClassWeaver.match(BcelClassWeaver.java:3116)
	at org.aspectj.weaver.bcel.BcelClassWeaver.match(BcelClassWeaver.java:2550)
	at org.aspectj.weaver.bcel.BcelClassWeaver.weave(BcelClassWeaver.java:474)
	at org.aspectj.weaver.bcel.BcelClassWeaver.weave(BcelClassWeaver.java:100)
	at org.aspectj.weaver.bcel.BcelWeaver.weave(BcelWeaver.java:1687)
	at org.aspectj.weaver.bcel.BcelWeaver.weaveWithoutDump(BcelWeaver.java:1631)
	at org.aspectj.weaver.bcel.BcelWeaver.weaveAndNotify(BcelWeaver.java:1394)
	at org.aspectj.weaver.bcel.BcelWeaver.weave(BcelWeaver.java:1180)
	at org.aspectj.weaver.tools.WeavingAdaptor.getWovenBytes(WeavingAdaptor.java:467)
	at org.aspectj.weaver.tools.WeavingAdaptor.weaveClass(WeavingAdaptor.java:318)
	at org.aspectj.weaver.loadtime.Aj.preProcess(Aj.java:96)
	at org.aspectj.weaver.loadtime.ClassPreProcessorAgentAdapter.transform(ClassPreProcessorAgentAdapter.java:54)
	at sun.instrument.TransformerManager.transform(TransformerManager.java:188)
	at sun.instrument.InstrumentationImpl.transform(InstrumentationImpl.java:428)
	at java.lang.ClassLoader.defineClass1(Native Method)
	at java.lang.ClassLoader.defineClass(ClassLoader.java:760)
	at java.security.SecureClassLoader.defineClass(SecureClassLoader.java:142)
	at java.net.URLClassLoader.defineClass(URLClassLoader.java:467)
	at java.net.URLClassLoader.access$100(URLClassLoader.java:73)
	at java.net.URLClassLoader$1.run(URLClassLoader.java:368)
	at java.net.URLClassLoader$1.run(URLClassLoader.java:362)
	at java.security.AccessController.doPrivileged(Native Method)
	at java.net.URLClassLoader.findClass(URLClassLoader.java:361)
	at java.lang.ClassLoader.loadClass(ClassLoader.java:424)
	at sun.misc.Launcher$AppClassLoader.loadClass(Launcher.java:331)
	at java.lang.ClassLoader.loadClass(ClassLoader.java:357)
	at org.springframework.beans.factory.xml.ParserContext.registerBeanComponent(ParserContext.java:120)
	at org.springframework.aop.config.SpringConfiguredBeanDefinitionParser.parse(SpringConfiguredBeanDefinitionParser.java:59)
	at org.springframework.beans.factory.xml.NamespaceHandlerSupport.parse(NamespaceHandlerSupport.java:73)
	at org.springframework.beans.factory.xml.BeanDefinitionParserDelegate.parseCustomElement(BeanDefinitionParserDelegate.java:1335)
	at org.springframework.beans.factory.xml.BeanDefinitionParserDelegate.parseCustomElement(BeanDefinitionParserDelegate.java:1325)
	at org.springframework.beans.factory.xml.DefaultBeanDefinitionDocumentReader.parseBeanDefinitions(DefaultBeanDefinitionDocumentReader.java:135)
	at org.springframework.beans.factory.xml.DefaultBeanDefinitionDocumentReader.registerBeanDefinitions(DefaultBeanDefinitionDocumentReader.java:93)
	at org.springframework.beans.factory.xml.XmlBeanDefinitionReader.registerBeanDefinitions(XmlBeanDefinitionReader.java:493)
	at org.springframework.beans.factory.xml.XmlBeanDefinitionReader.doLoadBeanDefinitions(XmlBeanDefinitionReader.java:390)
	at org.springframework.beans.factory.xml.XmlBeanDefinitionReader.loadBeanDefinitions(XmlBeanDefinitionReader.java:334)
	at org.springframework.beans.factory.xml.XmlBeanDefinitionReader.loadBeanDefinitions(XmlBeanDefinitionReader.java:302)
	at org.springframework.beans.factory.support.AbstractBeanDefinitionReader.loadBeanDefinitions(AbstractBeanDefinitionReader.java:143)
	at org.springframework.beans.factory.support.AbstractBeanDefinitionReader.loadBeanDefinitions(AbstractBeanDefinitionReader.java:178)
	at org.springframework.beans.factory.support.AbstractBeanDefinitionReader.loadBeanDefinitions(AbstractBeanDefinitionReader.java:149)
	at org.springframework.beans.factory.support.AbstractBeanDefinitionReader.loadBeanDefinitions(AbstractBeanDefinitionReader.java:212)
	at org.springframework.context.support.AbstractXmlApplicationContext.loadBeanDefinitions(AbstractXmlApplicationContext.java:126)
	at org.springframework.context.support.AbstractXmlApplicationContext.loadBeanDefinitions(AbstractXmlApplicationContext.java:92)
	at org.springframework.context.support.AbstractRefreshableApplicationContext.refreshBeanFactory(AbstractRefreshableApplicationContext.java:130)
	at org.springframework.context.support.AbstractApplicationContext.obtainFreshBeanFactory(AbstractApplicationContext.java:467)
	at org.springframework.context.support.AbstractApplicationContext.refresh(AbstractApplicationContext.java:397)
	at org.springframework.context.support.ClassPathXmlApplicationContext.<init>(ClassPathXmlApplicationContext.java:139)
	at org.springframework.context.support.ClassPathXmlApplicationContext.<init>(ClassPathXmlApplicationContext.java:83)
	at foo.ConfigureApp.main(ConfigureApp.java:9)

error can't determine annotations of missing type org.springframework.cache.annotation.CachePut
when weaving type org.springframework.beans.factory.support.GenericBeanDefinition
when weaving classes 
when weaving 
 [Xlint:cantFindType]
error can't determine annotations of missing type org.springframework.cache.annotation.Cacheable
when weaving type org.springframework.beans.factory.support.GenericBeanDefinition
when weaving classes 
when weaving 
 [Xlint:cantFindType]
error can't determine annotations of missing type org.springframework.cache.annotation.CacheEvict
when weaving type org.springframework.beans.factory.support.GenericBeanDefinition
when weaving classes 
when weaving 
 [Xlint:cantFindType]
error can't determine annotations of missing type org.springframework.cache.annotation.Caching
when weaving type org.springframework.beans.factory.support.GenericBeanDefinition
when weaving classes 
when weaving 
 [Xlint:cantFindType]
error can't determine annotations of missing type org.springframework.transaction.annotation.Transactional
when weaving type org.springframework.beans.factory.support.GenericBeanDefinition
when weaving classes 
when weaving 
 [Xlint:cantFindType]
abort trouble in: 
public class org.springframework.beans.factory.support.GenericBeanDefinition extends org.springframework.beans.factory.support.AbstractBeanDefinition:
  private String parentName
  public void <init>():
                    ALOAD_0     // Lorg/springframework/beans/factory/support/GenericBeanDefinition; this   (line 55)
                    INVOKESPECIAL org.springframework.beans.factory.support.AbstractBeanDefinition.<init> ()V
    constructor-execution(void org.springframework.beans.factory.support.GenericBeanDefinition.<init>())
    |               RETURN   (line 56)
    constructor-execution(void org.springframework.beans.factory.support.GenericBeanDefinition.<init>())
  end public void <init>()

  public void <init>(org.springframework.beans.factory.config.BeanDefinition):
                    ALOAD_0     // Lorg/springframework/beans/factory/support/GenericBeanDefinition; this   (line 64)
                    ALOAD_1     // Lorg/springframework/beans/factory/config/BeanDefinition; original
                    INVOKESPECIAL org.springframework.beans.factory.support.AbstractBeanDefinition.<init> (Lorg/springframework/beans/factory/config/BeanDefinition;)V
    constructor-execution(void org.springframework.beans.factory.support.GenericBeanDefinition.<init>(org.springframework.beans.factory.config.BeanDefinition))
    |               RETURN   (line 65)
    constructor-execution(void org.springframework.beans.factory.support.GenericBeanDefinition.<init>(org.springframework.beans.factory.config.BeanDefinition))
  end public void <init>(org.springframework.beans.factory.config.BeanDefinition)

  public void setParentName(String):
                    ALOAD_0     // Lorg/springframework/beans/factory/support/GenericBeanDefinition; this   (line 69)
                    ALOAD_1     // Ljava/lang/String; parentName
                    PUTFIELD org.springframework.beans.factory.support.GenericBeanDefinition.parentName Ljava/lang/String;
                    RETURN   (line 70)
  end public void setParentName(String)

  public String getParentName():
                    ALOAD_0     // Lorg/springframework/beans/factory/support/GenericBeanDefinition; this   (line 73)
                    GETFIELD org.springframework.beans.factory.support.GenericBeanDefinition.parentName Ljava/lang/String;
                    ARETURN
  end public String getParentName()

  public org.springframework.beans.factory.support.AbstractBeanDefinition cloneBeanDefinition():
                    NEW org.springframework.beans.factory.support.GenericBeanDefinition   (line 79)
                    DUP
                    ALOAD_0     // Lorg/springframework/beans/factory/support/GenericBeanDefinition; this
                    INVOKESPECIAL org.springframework.beans.factory.support.GenericBeanDefinition.<init> (Lorg/springframework/beans/factory/config/BeanDefinition;)V
                    ARETURN
  end public org.springframework.beans.factory.support.AbstractBeanDefinition cloneBeanDefinition()

  public boolean equals(Object):
                    ALOAD_0     // Lorg/springframework/beans/factory/support/GenericBeanDefinition; this   (line 84)
                    ALOAD_1     // Ljava/lang/Object; other
                    IF_ACMPEQ L1
                    ALOAD_1     // Ljava/lang/Object; other
                    INSTANCEOF org.springframework.beans.factory.support.GenericBeanDefinition
                    IFEQ L0
                    ALOAD_0     // Lorg/springframework/beans/factory/support/GenericBeanDefinition; this
                    ALOAD_1     // Ljava/lang/Object; other
                    INVOKESPECIAL org.springframework.beans.factory.support.AbstractBeanDefinition.equals (Ljava/lang/Object;)Z
                    IFNE L1
                L0: ICONST_0
                    IRETURN
                L1: ICONST_1
                    IRETURN
  end public boolean equals(Object)

  public String toString():
                    NEW java.lang.StringBuilder   (line 89)
                    DUP
                    LDC "Generic bean: "
                    INVOKESPECIAL java.lang.StringBuilder.<init> (Ljava/lang/String;)V
                    ALOAD_0     // Lorg/springframework/beans/factory/support/GenericBeanDefinition; this
                    INVOKESPECIAL org.springframework.beans.factory.support.AbstractBeanDefinition.toString ()Ljava/lang/String;
                    INVOKEVIRTUAL java.lang.StringBuilder.append (Ljava/lang/String;)Ljava/lang/StringBuilder;
                    INVOKEVIRTUAL java.lang.StringBuilder.toString ()Ljava/lang/String;
                    ARETURN
  end public String toString()

end public class org.springframework.beans.factory.support.GenericBeanDefinition
 -- (NullPointerException) null
null
java.lang.NullPointerException
	at org.aspectj.weaver.UnresolvedType.forSignature(UnresolvedType.java:361)
	at org.aspectj.weaver.bcel.BcelObjectType.getDeclaredInterfaces(BcelObjectType.java:275)
	at org.aspectj.weaver.ReferenceType.getDeclaredInterfaces(ReferenceType.java:624)
	at org.aspectj.weaver.ResolvedType.getDirectSupertypes(ResolvedType.java:76)
	at org.aspectj.weaver.patterns.TypePattern.matchesSubtypes(TypePattern.java:178)
	at org.aspectj.weaver.patterns.ExactTypePattern.matchesSubtypes(ExactTypePattern.java:74)
	at org.aspectj.weaver.patterns.TypePattern.matchesStatically(TypePattern.java:130)
	at org.aspectj.weaver.patterns.OrTypePattern.matchesStatically(OrTypePattern.java:76)
	at org.aspectj.weaver.patterns.SignaturePattern.matchesExactlyMethod(SignaturePattern.java:505)
	at org.aspectj.weaver.patterns.SignaturePattern.matchesExactly(SignaturePattern.java:360)
	at org.aspectj.weaver.patterns.SignaturePattern.matches(SignaturePattern.java:320)
	at org.aspectj.weaver.patterns.KindedPointcut.matchInternal(KindedPointcut.java:202)
	at org.aspectj.weaver.patterns.Pointcut.match(Pointcut.java:137)
	at org.aspectj.weaver.patterns.AndPointcut.matchInternal(AndPointcut.java:51)
	at org.aspectj.weaver.patterns.Pointcut.match(Pointcut.java:137)
	at org.aspectj.weaver.patterns.OrPointcut.matchInternal(OrPointcut.java:54)
	at org.aspectj.weaver.patterns.Pointcut.match(Pointcut.java:137)
	at org.aspectj.weaver.ShadowMunger.match(ShadowMunger.java:113)
	at org.aspectj.weaver.Advice.match(Advice.java:109)
	at org.aspectj.weaver.bcel.BcelAdvice.match(BcelAdvice.java:149)
	at org.aspectj.weaver.bcel.BcelClassWeaver.match(BcelClassWeaver.java:3116)
	at org.aspectj.weaver.bcel.BcelClassWeaver.match(BcelClassWeaver.java:2550)
	at org.aspectj.weaver.bcel.BcelClassWeaver.weave(BcelClassWeaver.java:474)
	at org.aspectj.weaver.bcel.BcelClassWeaver.weave(BcelClassWeaver.java:100)
	at org.aspectj.weaver.bcel.BcelWeaver.weave(BcelWeaver.java:1687)
	at org.aspectj.weaver.bcel.BcelWeaver.weaveWithoutDump(BcelWeaver.java:1631)
	at org.aspectj.weaver.bcel.BcelWeaver.weaveAndNotify(BcelWeaver.java:1394)
	at org.aspectj.weaver.bcel.BcelWeaver.weave(BcelWeaver.java:1180)
	at org.aspectj.weaver.tools.WeavingAdaptor.getWovenBytes(WeavingAdaptor.java:467)
	at org.aspectj.weaver.tools.WeavingAdaptor.weaveClass(WeavingAdaptor.java:318)
	at org.aspectj.weaver.loadtime.Aj.preProcess(Aj.java:96)
	at org.aspectj.weaver.loadtime.ClassPreProcessorAgentAdapter.transform(ClassPreProcessorAgentAdapter.java:54)
	at sun.instrument.TransformerManager.transform(TransformerManager.java:188)
	at sun.instrument.InstrumentationImpl.transform(InstrumentationImpl.java:428)
	at java.lang.ClassLoader.defineClass1(Native Method)
	at java.lang.ClassLoader.defineClass(ClassLoader.java:760)
	at java.security.SecureClassLoader.defineClass(SecureClassLoader.java:142)
	at java.net.URLClassLoader.defineClass(URLClassLoader.java:467)
	at java.net.URLClassLoader.access$100(URLClassLoader.java:73)
	at java.net.URLClassLoader$1.run(URLClassLoader.java:368)
	at java.net.URLClassLoader$1.run(URLClassLoader.java:362)
	at java.security.AccessController.doPrivileged(Native Method)
	at java.net.URLClassLoader.findClass(URLClassLoader.java:361)
	at java.lang.ClassLoader.loadClass(ClassLoader.java:424)
	at sun.misc.Launcher$AppClassLoader.loadClass(Launcher.java:331)
	at java.lang.ClassLoader.loadClass(ClassLoader.java:357)
	at org.springframework.beans.factory.xml.ParserContext.registerBeanComponent(ParserContext.java:120)
	at org.springframework.aop.config.SpringConfiguredBeanDefinitionParser.parse(SpringConfiguredBeanDefinitionParser.java:59)
	at org.springframework.beans.factory.xml.NamespaceHandlerSupport.parse(NamespaceHandlerSupport.java:73)
	at org.springframework.beans.factory.xml.BeanDefinitionParserDelegate.parseCustomElement(BeanDefinitionParserDelegate.java:1335)
	at org.springframework.beans.factory.xml.BeanDefinitionParserDelegate.parseCustomElement(BeanDefinitionParserDelegate.java:1325)
	at org.springframework.beans.factory.xml.DefaultBeanDefinitionDocumentReader.parseBeanDefinitions(DefaultBeanDefinitionDocumentReader.java:135)
	at org.springframework.beans.factory.xml.DefaultBeanDefinitionDocumentReader.registerBeanDefinitions(DefaultBeanDefinitionDocumentReader.java:93)
	at org.springframework.beans.factory.xml.XmlBeanDefinitionReader.registerBeanDefinitions(XmlBeanDefinitionReader.java:493)
	at org.springframework.beans.factory.xml.XmlBeanDefinitionReader.doLoadBeanDefinitions(XmlBeanDefinitionReader.java:390)
	at org.springframework.beans.factory.xml.XmlBeanDefinitionReader.loadBeanDefinitions(XmlBeanDefinitionReader.java:334)
	at org.springframework.beans.factory.xml.XmlBeanDefinitionReader.loadBeanDefinitions(XmlBeanDefinitionReader.java:302)
	at org.springframework.beans.factory.support.AbstractBeanDefinitionReader.loadBeanDefinitions(AbstractBeanDefinitionReader.java:143)
	at org.springframework.beans.factory.support.AbstractBeanDefinitionReader.loadBeanDefinitions(AbstractBeanDefinitionReader.java:178)
	at org.springframework.beans.factory.support.AbstractBeanDefinitionReader.loadBeanDefinitions(AbstractBeanDefinitionReader.java:149)
	at org.springframework.beans.factory.support.AbstractBeanDefinitionReader.loadBeanDefinitions(AbstractBeanDefinitionReader.java:212)
	at org.springframework.context.support.AbstractXmlApplicationContext.loadBeanDefinitions(AbstractXmlApplicationContext.java:126)
	at org.springframework.context.support.AbstractXmlApplicationContext.loadBeanDefinitions(AbstractXmlApplicationContext.java:92)
	at org.springframework.context.support.AbstractRefreshableApplicationContext.refreshBeanFactory(AbstractRefreshableApplicationContext.java:130)
	at org.springframework.context.support.AbstractApplicationContext.obtainFreshBeanFactory(AbstractApplicationContext.java:467)
	at org.springframework.context.support.AbstractApplicationContext.refresh(AbstractApplicationContext.java:397)
	at org.springframework.context.support.ClassPathXmlApplicationContext.<init>(ClassPathXmlApplicationContext.java:139)
	at org.springframework.context.support.ClassPathXmlApplicationContext.<init>(ClassPathXmlApplicationContext.java:83)
	at foo.ConfigureApp.main(ConfigureApp.java:9)

error can't determine annotations of missing type org.springframework.cache.annotation.CachePut
when weaving type org.springframework.beans.factory.parsing.BeanEntry
when weaving classes 
when weaving 
 [Xlint:cantFindType]
error can't determine annotations of missing type org.springframework.cache.annotation.Cacheable
when weaving type org.springframework.beans.factory.parsing.BeanEntry
when weaving classes 
when weaving 
 [Xlint:cantFindType]
error can't determine annotations of missing type org.springframework.cache.annotation.CacheEvict
when weaving type org.springframework.beans.factory.parsing.BeanEntry
when weaving classes 
when weaving 
 [Xlint:cantFindType]
error can't determine annotations of missing type org.springframework.cache.annotation.Caching
when weaving type org.springframework.beans.factory.parsing.BeanEntry
when weaving classes 
when weaving 
 [Xlint:cantFindType]
error can't determine annotations of missing type org.springframework.transaction.annotation.Transactional
when weaving type org.springframework.beans.factory.parsing.BeanEntry
when weaving classes 
when weaving 
 [Xlint:cantFindType]
abort trouble in: 
public class org.springframework.beans.factory.parsing.BeanEntry extends java.lang.Object implements org.springframework.beans.factory.parsing.ParseState$Entry:
  private String beanDefinitionName
  public void <init>(String):
                    ALOAD_0     // Lorg/springframework/beans/factory/parsing/BeanEntry; this   (line 34)
                    INVOKESPECIAL java.lang.Object.<init> ()V
    constructor-execution(void org.springframework.beans.factory.parsing.BeanEntry.<init>(java.lang.String))
    |               ALOAD_0     // Lorg/springframework/beans/factory/parsing/BeanEntry; this   (line 35)
    |               ALOAD_1     // Ljava/lang/String; beanDefinitionName
    |               PUTFIELD org.springframework.beans.factory.parsing.BeanEntry.beanDefinitionName Ljava/lang/String;
    |               RETURN   (line 36)
    constructor-execution(void org.springframework.beans.factory.parsing.BeanEntry.<init>(java.lang.String))
  end public void <init>(String)

  public String toString():
                    NEW java.lang.StringBuilder   (line 41)
                    DUP
                    LDC "Bean '"
                    INVOKESPECIAL java.lang.StringBuilder.<init> (Ljava/lang/String;)V
                    ALOAD_0     // Lorg/springframework/beans/factory/parsing/BeanEntry; this
                    GETFIELD org.springframework.beans.factory.parsing.BeanEntry.beanDefinitionName Ljava/lang/String;
                    INVOKEVIRTUAL java.lang.StringBuilder.append (Ljava/lang/String;)Ljava/lang/StringBuilder;
                    LDC "'"
                    INVOKEVIRTUAL java.lang.StringBuilder.append (Ljava/lang/String;)Ljava/lang/StringBuilder;
                    INVOKEVIRTUAL java.lang.StringBuilder.toString ()Ljava/lang/String;
                    ARETURN
  end public String toString()

end public class org.springframework.beans.factory.parsing.BeanEntry
 -- (NullPointerException) null
null
java.lang.NullPointerException
	at org.aspectj.weaver.UnresolvedType.forSignature(UnresolvedType.java:361)
	at org.aspectj.weaver.bcel.BcelObjectType.getDeclaredInterfaces(BcelObjectType.java:275)
	at org.aspectj.weaver.ReferenceType.getDeclaredInterfaces(ReferenceType.java:624)
	at org.aspectj.weaver.ResolvedType.getDirectSupertypes(ResolvedType.java:76)
	at org.aspectj.weaver.patterns.TypePattern.matchesSubtypes(TypePattern.java:178)
	at org.aspectj.weaver.patterns.ExactTypePattern.matchesSubtypes(ExactTypePattern.java:74)
	at org.aspectj.weaver.patterns.TypePattern.matchesStatically(TypePattern.java:130)
	at org.aspectj.weaver.patterns.OrTypePattern.matchesStatically(OrTypePattern.java:76)
	at org.aspectj.weaver.patterns.SignaturePattern.matchesExactlyMethod(SignaturePattern.java:505)
	at org.aspectj.weaver.patterns.SignaturePattern.matchesExactly(SignaturePattern.java:360)
	at org.aspectj.weaver.patterns.SignaturePattern.matches(SignaturePattern.java:320)
	at org.aspectj.weaver.patterns.KindedPointcut.matchInternal(KindedPointcut.java:202)
	at org.aspectj.weaver.patterns.Pointcut.match(Pointcut.java:137)
	at org.aspectj.weaver.patterns.AndPointcut.matchInternal(AndPointcut.java:51)
	at org.aspectj.weaver.patterns.Pointcut.match(Pointcut.java:137)
	at org.aspectj.weaver.patterns.OrPointcut.matchInternal(OrPointcut.java:54)
	at org.aspectj.weaver.patterns.Pointcut.match(Pointcut.java:137)
	at org.aspectj.weaver.ShadowMunger.match(ShadowMunger.java:113)
	at org.aspectj.weaver.Advice.match(Advice.java:109)
	at org.aspectj.weaver.bcel.BcelAdvice.match(BcelAdvice.java:149)
	at org.aspectj.weaver.bcel.BcelClassWeaver.match(BcelClassWeaver.java:3116)
	at org.aspectj.weaver.bcel.BcelClassWeaver.match(BcelClassWeaver.java:2550)
	at org.aspectj.weaver.bcel.BcelClassWeaver.weave(BcelClassWeaver.java:474)
	at org.aspectj.weaver.bcel.BcelClassWeaver.weave(BcelClassWeaver.java:100)
	at org.aspectj.weaver.bcel.BcelWeaver.weave(BcelWeaver.java:1687)
	at org.aspectj.weaver.bcel.BcelWeaver.weaveWithoutDump(BcelWeaver.java:1631)
	at org.aspectj.weaver.bcel.BcelWeaver.weaveAndNotify(BcelWeaver.java:1394)
	at org.aspectj.weaver.bcel.BcelWeaver.weave(BcelWeaver.java:1180)
	at org.aspectj.weaver.tools.WeavingAdaptor.getWovenBytes(WeavingAdaptor.java:467)
	at org.aspectj.weaver.tools.WeavingAdaptor.weaveClass(WeavingAdaptor.java:318)
	at org.aspectj.weaver.loadtime.Aj.preProcess(Aj.java:96)
	at org.aspectj.weaver.loadtime.ClassPreProcessorAgentAdapter.transform(ClassPreProcessorAgentAdapter.java:54)
	at sun.instrument.TransformerManager.transform(TransformerManager.java:188)
	at sun.instrument.InstrumentationImpl.transform(InstrumentationImpl.java:428)
	at java.lang.ClassLoader.defineClass1(Native Method)
	at java.lang.ClassLoader.defineClass(ClassLoader.java:760)
	at java.security.SecureClassLoader.defineClass(SecureClassLoader.java:142)
	at java.net.URLClassLoader.defineClass(URLClassLoader.java:467)
	at java.net.URLClassLoader.access$100(URLClassLoader.java:73)
	at java.net.URLClassLoader$1.run(URLClassLoader.java:368)
	at java.net.URLClassLoader$1.run(URLClassLoader.java:362)
	at java.security.AccessController.doPrivileged(Native Method)
	at java.net.URLClassLoader.findClass(URLClassLoader.java:361)
	at java.lang.ClassLoader.loadClass(ClassLoader.java:424)
	at sun.misc.Launcher$AppClassLoader.loadClass(Launcher.java:331)
	at java.lang.ClassLoader.loadClass(ClassLoader.java:357)
	at org.springframework.beans.factory.xml.BeanDefinitionParserDelegate.parseBeanDefinitionElement(BeanDefinitionParserDelegate.java:460)
	at org.springframework.beans.factory.xml.BeanDefinitionParserDelegate.parseBeanDefinitionElement(BeanDefinitionParserDelegate.java:396)
	at org.springframework.beans.factory.xml.BeanDefinitionParserDelegate.parseBeanDefinitionElement(BeanDefinitionParserDelegate.java:365)
	at org.springframework.beans.factory.xml.DefaultBeanDefinitionDocumentReader.processBeanDefinition(DefaultBeanDefinitionDocumentReader.java:258)
	at org.springframework.beans.factory.xml.DefaultBeanDefinitionDocumentReader.parseDefaultElement(DefaultBeanDefinitionDocumentReader.java:153)
	at org.springframework.beans.factory.xml.DefaultBeanDefinitionDocumentReader.parseBeanDefinitions(DefaultBeanDefinitionDocumentReader.java:132)
	at org.springframework.beans.factory.xml.DefaultBeanDefinitionDocumentReader.registerBeanDefinitions(DefaultBeanDefinitionDocumentReader.java:93)
	at org.springframework.beans.factory.xml.XmlBeanDefinitionReader.registerBeanDefinitions(XmlBeanDefinitionReader.java:493)
	at org.springframework.beans.factory.xml.XmlBeanDefinitionReader.doLoadBeanDefinitions(XmlBeanDefinitionReader.java:390)
	at org.springframework.beans.factory.xml.XmlBeanDefinitionReader.loadBeanDefinitions(XmlBeanDefinitionReader.java:334)
	at org.springframework.beans.factory.xml.XmlBeanDefinitionReader.loadBeanDefinitions(XmlBeanDefinitionReader.java:302)
	at org.springframework.beans.factory.support.AbstractBeanDefinitionReader.loadBeanDefinitions(AbstractBeanDefinitionReader.java:143)
	at org.springframework.beans.factory.support.AbstractBeanDefinitionReader.loadBeanDefinitions(AbstractBeanDefinitionReader.java:178)
	at org.springframework.beans.factory.support.AbstractBeanDefinitionReader.loadBeanDefinitions(AbstractBeanDefinitionReader.java:149)
	at org.springframework.beans.factory.support.AbstractBeanDefinitionReader.loadBeanDefinitions(AbstractBeanDefinitionReader.java:212)
	at org.springframework.context.support.AbstractXmlApplicationContext.loadBeanDefinitions(AbstractXmlApplicationContext.java:126)
	at org.springframework.context.support.AbstractXmlApplicationContext.loadBeanDefinitions(AbstractXmlApplicationContext.java:92)
	at org.springframework.context.support.AbstractRefreshableApplicationContext.refreshBeanFactory(AbstractRefreshableApplicationContext.java:130)
	at org.springframework.context.support.AbstractApplicationContext.obtainFreshBeanFactory(AbstractApplicationContext.java:467)
	at org.springframework.context.support.AbstractApplicationContext.refresh(AbstractApplicationContext.java:397)
	at org.springframework.context.support.ClassPathXmlApplicationContext.<init>(ClassPathXmlApplicationContext.java:139)
	at org.springframework.context.support.ClassPathXmlApplicationContext.<init>(ClassPathXmlApplicationContext.java:83)
	at foo.ConfigureApp.main(ConfigureApp.java:9)

error can't determine annotations of missing type org.springframework.cache.annotation.CachePut
when weaving type org.springframework.util.xml.DomUtils
when weaving classes 
when weaving 
 [Xlint:cantFindType]
error can't determine annotations of missing type org.springframework.cache.annotation.Cacheable
when weaving type org.springframework.util.xml.DomUtils
when weaving classes 
when weaving 
 [Xlint:cantFindType]
error can't determine annotations of missing type org.springframework.cache.annotation.CacheEvict
when weaving type org.springframework.util.xml.DomUtils
when weaving classes 
when weaving 
 [Xlint:cantFindType]
error can't determine annotations of missing type org.springframework.cache.annotation.Caching
when weaving type org.springframework.util.xml.DomUtils
when weaving classes 
when weaving 
 [Xlint:cantFindType]
error can't determine annotations of missing type org.springframework.transaction.annotation.Transactional
when weaving type org.springframework.util.xml.DomUtils
when weaving classes 
when weaving 
 [Xlint:cantFindType]
abort trouble in: 
public abstract class org.springframework.util.xml.DomUtils extends java.lang.Object:
  public void <init>():
                    ALOAD_0     // Lorg/springframework/util/xml/DomUtils; this   (line 46)
                    INVOKESPECIAL java.lang.Object.<init> ()V
    constructor-execution(void org.springframework.util.xml.DomUtils.<init>())
    |               RETURN
    constructor-execution(void org.springframework.util.xml.DomUtils.<init>())
  end public void <init>()

  public static java.util.List getChildElementsByTagName(org.w3c.dom.Element, String[]):
                    ALOAD_0     // Lorg/w3c/dom/Element; ele   (line 60)
                    LDC "Element must not be null"
                    INVOKESTATIC org.springframework.util.Assert.notNull (Ljava/lang/Object;Ljava/lang/String;)V
                    ALOAD_1     // [Ljava/lang/String; childEleNames   (line 61)
                    LDC "Element names collection must not be null"
                    INVOKESTATIC org.springframework.util.Assert.notNull (Ljava/lang/Object;Ljava/lang/String;)V
                    ALOAD_1     // [Ljava/lang/String; childEleNames   (line 62)
                    INVOKESTATIC java.util.Arrays.asList ([Ljava/lang/Object;)Ljava/util/List;
                    ASTORE_2
                    ALOAD_0     // Lorg/w3c/dom/Element; ele   (line 63)
                    INVOKEINTERFACE org.w3c.dom.Element.getChildNodes ()Lorg/w3c/dom/NodeList;
                    ASTORE_3
                    NEW java.util.ArrayList   (line 64)
                    DUP
                    INVOKESPECIAL java.util.ArrayList.<init> ()V
                    ASTORE 4
                    ICONST_0   (line 65)
                    ISTORE 5
                    GOTO L2
                L0: ALOAD_3     // Lorg/w3c/dom/NodeList; nl   (line 66)
                    ILOAD 5     // I i
                    INVOKEINTERFACE org.w3c.dom.NodeList.item (I)Lorg/w3c/dom/Node;
                    ASTORE 6
                    ALOAD 6     // Lorg/w3c/dom/Node; node   (line 67)
                    INSTANCEOF org.w3c.dom.Element
                    IFEQ L1
                    ALOAD 6     // Lorg/w3c/dom/Node; node
                    ALOAD_2     // Ljava/util/List; childEleNameList
                    INVOKESTATIC org.springframework.util.xml.DomUtils.nodeNameMatch (Lorg/w3c/dom/Node;Ljava/util/Collection;)Z
                    IFEQ L1
                    ALOAD 4     // Ljava/util/List; childEles   (line 68)
                    ALOAD 6     // Lorg/w3c/dom/Node; node
                    CHECKCAST org.w3c.dom.Element
                    INVOKEINTERFACE java.util.List.add (Ljava/lang/Object;)Z
                    POP
                L1: IINC 5 1     // I i   (line 65)
                L2: ILOAD 5     // I i
                    ALOAD_3     // Lorg/w3c/dom/NodeList; nl
                    INVOKEINTERFACE org.w3c.dom.NodeList.getLength ()I
                    IF_ICMPLT L0
                    ALOAD 4     // Ljava/util/List; childEles   (line 71)
                    ARETURN
  end public static java.util.List getChildElementsByTagName(org.w3c.dom.Element, String[])

  public static java.util.List getChildElementsByTagName(org.w3c.dom.Element, String):
                    ALOAD_0     // Lorg/w3c/dom/Element; ele   (line 86)
                    ICONST_1
                    ANEWARRAY java.lang.String
                    DUP
                    ICONST_0
                    ALOAD_1     // Ljava/lang/String; childEleName
                    AASTORE
                    INVOKESTATIC org.springframework.util.xml.DomUtils.getChildElementsByTagName (Lorg/w3c/dom/Element;[Ljava/lang/String;)Ljava/util/List;
                    ARETURN
  end public static java.util.List getChildElementsByTagName(org.w3c.dom.Element, String)

  public static org.w3c.dom.Element getChildElementByTagName(org.w3c.dom.Element, String):
                    ALOAD_0     // Lorg/w3c/dom/Element; ele   (line 97)
                    LDC "Element must not be null"
                    INVOKESTATIC org.springframework.util.Assert.notNull (Ljava/lang/Object;Ljava/lang/String;)V
                    ALOAD_1     // Ljava/lang/String; childEleName   (line 98)
                    LDC "Element name must not be null"
                    INVOKESTATIC org.springframework.util.Assert.notNull (Ljava/lang/Object;Ljava/lang/String;)V
                    ALOAD_0     // Lorg/w3c/dom/Element; ele   (line 99)
                    INVOKEINTERFACE org.w3c.dom.Element.getChildNodes ()Lorg/w3c/dom/NodeList;
                    ASTORE_2
                    ICONST_0   (line 100)
                    ISTORE_3
                    GOTO L2
                L0: ALOAD_2     // Lorg/w3c/dom/NodeList; nl   (line 101)
                    ILOAD_3     // I i
                    INVOKEINTERFACE org.w3c.dom.NodeList.item (I)Lorg/w3c/dom/Node;
                    ASTORE 4
                    ALOAD 4     // Lorg/w3c/dom/Node; node   (line 102)
                    INSTANCEOF org.w3c.dom.Element
                    IFEQ L1
                    ALOAD 4     // Lorg/w3c/dom/Node; node
                    ALOAD_1     // Ljava/lang/String; childEleName
                    INVOKESTATIC org.springframework.util.xml.DomUtils.nodeNameMatch (Lorg/w3c/dom/Node;Ljava/lang/String;)Z
                    IFEQ L1
                    ALOAD 4     // Lorg/w3c/dom/Node; node   (line 103)
                    CHECKCAST org.w3c.dom.Element
                    ARETURN
                L1: IINC_3 1     // I i   (line 100)
                L2: ILOAD_3     // I i
                    ALOAD_2     // Lorg/w3c/dom/NodeList; nl
                    INVOKEINTERFACE org.w3c.dom.NodeList.getLength ()I
                    IF_ICMPLT L0
                    ACONST_NULL   (line 106)
                    ARETURN
  end public static org.w3c.dom.Element getChildElementByTagName(org.w3c.dom.Element, String)

  public static String getChildElementValueByTagName(org.w3c.dom.Element, String):
                    ALOAD_0     // Lorg/w3c/dom/Element; ele   (line 117)
                    ALOAD_1     // Ljava/lang/String; childEleName
                    INVOKESTATIC org.springframework.util.xml.DomUtils.getChildElementByTagName (Lorg/w3c/dom/Element;Ljava/lang/String;)Lorg/w3c/dom/Element;
                    ASTORE_2
                    ALOAD_2     // Lorg/w3c/dom/Element; child   (line 118)
                    IFNULL L0
                    ALOAD_2     // Lorg/w3c/dom/Element; child
                    INVOKESTATIC org.springframework.util.xml.DomUtils.getTextValue (Lorg/w3c/dom/Element;)Ljava/lang/String;
                    GOTO L1
                L0: ACONST_NULL
                L1: ARETURN
  end public static String getChildElementValueByTagName(org.w3c.dom.Element, String)

  public static java.util.List getChildElements(org.w3c.dom.Element):
                    ALOAD_0     // Lorg/w3c/dom/Element; ele   (line 128)
                    LDC "Element must not be null"
                    INVOKESTATIC org.springframework.util.Assert.notNull (Ljava/lang/Object;Ljava/lang/String;)V
                    ALOAD_0     // Lorg/w3c/dom/Element; ele   (line 129)
                    INVOKEINTERFACE org.w3c.dom.Element.getChildNodes ()Lorg/w3c/dom/NodeList;
                    ASTORE_1
                    NEW java.util.ArrayList   (line 130)
                    DUP
                    INVOKESPECIAL java.util.ArrayList.<init> ()V
                    ASTORE_2
                    ICONST_0   (line 131)
                    ISTORE_3
                    GOTO L2
                L0: ALOAD_1     // Lorg/w3c/dom/NodeList; nl   (line 132)
                    ILOAD_3     // I i
                    INVOKEINTERFACE org.w3c.dom.NodeList.item (I)Lorg/w3c/dom/Node;
                    ASTORE 4
                    ALOAD 4     // Lorg/w3c/dom/Node; node   (line 133)
                    INSTANCEOF org.w3c.dom.Element
                    IFEQ L1
                    ALOAD_2     // Ljava/util/List; childEles   (line 134)
                    ALOAD 4     // Lorg/w3c/dom/Node; node
                    CHECKCAST org.w3c.dom.Element
                    INVOKEINTERFACE java.util.List.add (Ljava/lang/Object;)Z
                    POP
                L1: IINC_3 1     // I i   (line 131)
                L2: ILOAD_3     // I i
                    ALOAD_1     // Lorg/w3c/dom/NodeList; nl
                    INVOKEINTERFACE org.w3c.dom.NodeList.getLength ()I
                    IF_ICMPLT L0
                    ALOAD_2     // Ljava/util/List; childEles   (line 137)
                    ARETURN
  end public static java.util.List getChildElements(org.w3c.dom.Element)

  public static String getTextValue(org.w3c.dom.Element):
                    ALOAD_0     // Lorg/w3c/dom/Element; valueEle   (line 149)
                    LDC "Element must not be null"
                    INVOKESTATIC org.springframework.util.Assert.notNull (Ljava/lang/Object;Ljava/lang/String;)V
                    NEW java.lang.StringBuilder   (line 150)
                    DUP
                    INVOKESPECIAL java.lang.StringBuilder.<init> ()V
                    ASTORE_1
                    ALOAD_0     // Lorg/w3c/dom/Element; valueEle   (line 151)
                    INVOKEINTERFACE org.w3c.dom.Element.getChildNodes ()Lorg/w3c/dom/NodeList;
                    ASTORE_2
                    ICONST_0   (line 152)
                    ISTORE_3
                    GOTO L4
                L0: ALOAD_2     // Lorg/w3c/dom/NodeList; nl   (line 153)
                    ILOAD_3     // I i
                    INVOKEINTERFACE org.w3c.dom.NodeList.item (I)Lorg/w3c/dom/Node;
                    ASTORE 4
                    ALOAD 4     // Lorg/w3c/dom/Node; item   (line 154)
                    INSTANCEOF org.w3c.dom.CharacterData
                    IFEQ L1
                    ALOAD 4     // Lorg/w3c/dom/Node; item
                    INSTANCEOF org.w3c.dom.Comment
                    IFEQ L2
                L1: ALOAD 4     // Lorg/w3c/dom/Node; item
                    INSTANCEOF org.w3c.dom.EntityReference
                    IFEQ L3
                L2: ALOAD_1     // Ljava/lang/StringBuilder; sb   (line 155)
                    ALOAD 4     // Lorg/w3c/dom/Node; item
                    INVOKEINTERFACE org.w3c.dom.Node.getNodeValue ()Ljava/lang/String;
                    INVOKEVIRTUAL java.lang.StringBuilder.append (Ljava/lang/String;)Ljava/lang/StringBuilder;
                    POP
                L3: IINC_3 1     // I i   (line 152)
                L4: ILOAD_3     // I i
                    ALOAD_2     // Lorg/w3c/dom/NodeList; nl
                    INVOKEINTERFACE org.w3c.dom.NodeList.getLength ()I
                    IF_ICMPLT L0
                    ALOAD_1     // Ljava/lang/StringBuilder; sb   (line 158)
                    INVOKEVIRTUAL java.lang.StringBuilder.toString ()Ljava/lang/String;
                    ARETURN
  end public static String getTextValue(org.w3c.dom.Element)

  public static boolean nodeNameEquals(org.w3c.dom.Node, String):
                    ALOAD_0     // Lorg/w3c/dom/Node; node   (line 166)
                    LDC "Node must not be null"
                    INVOKESTATIC org.springframework.util.Assert.notNull (Ljava/lang/Object;Ljava/lang/String;)V
                    ALOAD_1     // Ljava/lang/String; desiredName   (line 167)
                    LDC "Desired name must not be null"
                    INVOKESTATIC org.springframework.util.Assert.notNull (Ljava/lang/Object;Ljava/lang/String;)V
                    ALOAD_0     // Lorg/w3c/dom/Node; node   (line 168)
                    ALOAD_1     // Ljava/lang/String; desiredName
                    INVOKESTATIC org.springframework.util.xml.DomUtils.nodeNameMatch (Lorg/w3c/dom/Node;Ljava/lang/String;)Z
                    IRETURN
  end public static boolean nodeNameEquals(org.w3c.dom.Node, String)

  public static org.xml.sax.ContentHandler createContentHandler(org.w3c.dom.Node):
                    NEW org.springframework.util.xml.DomContentHandler   (line 178)
                    DUP
                    ALOAD_0     // Lorg/w3c/dom/Node; node
                    INVOKESPECIAL org.springframework.util.xml.DomContentHandler.<init> (Lorg/w3c/dom/Node;)V
                    ARETURN
  end public static org.xml.sax.ContentHandler createContentHandler(org.w3c.dom.Node)

  private static boolean nodeNameMatch(org.w3c.dom.Node, String):
                    ALOAD_1     // Ljava/lang/String; desiredName   (line 183)
                    ALOAD_0     // Lorg/w3c/dom/Node; node
                    INVOKEINTERFACE org.w3c.dom.Node.getNodeName ()Ljava/lang/String;
                    INVOKEVIRTUAL java.lang.String.equals (Ljava/lang/Object;)Z
                    IFNE L0
                    ALOAD_1     // Ljava/lang/String; desiredName
                    ALOAD_0     // Lorg/w3c/dom/Node; node
                    INVOKEINTERFACE org.w3c.dom.Node.getLocalName ()Ljava/lang/String;
                    INVOKEVIRTUAL java.lang.String.equals (Ljava/lang/Object;)Z
                    IFNE L0
                    ICONST_0
                    IRETURN
                L0: ICONST_1
                    IRETURN
  end private static boolean nodeNameMatch(org.w3c.dom.Node, String)

  private static boolean nodeNameMatch(org.w3c.dom.Node, java.util.Collection):
                    ALOAD_1     // Ljava/util/Collection; desiredNames   (line 188)
                    ALOAD_0     // Lorg/w3c/dom/Node; node
                    INVOKEINTERFACE org.w3c.dom.Node.getNodeName ()Ljava/lang/String;
                    INVOKEINTERFACE java.util.Collection.contains (Ljava/lang/Object;)Z
                    IFNE L0
                    ALOAD_1     // Ljava/util/Collection; desiredNames
                    ALOAD_0     // Lorg/w3c/dom/Node; node
                    INVOKEINTERFACE org.w3c.dom.Node.getLocalName ()Ljava/lang/String;
                    INVOKEINTERFACE java.util.Collection.contains (Ljava/lang/Object;)Z
                    IFNE L0
                    ICONST_0
                    IRETURN
                L0: ICONST_1
                    IRETURN
  end private static boolean nodeNameMatch(org.w3c.dom.Node, java.util.Collection)

end public abstract class org.springframework.util.xml.DomUtils
 -- (NullPointerException) null
null
java.lang.NullPointerException
	at org.aspectj.weaver.UnresolvedType.forSignature(UnresolvedType.java:361)
	at org.aspectj.weaver.bcel.BcelObjectType.getDeclaredInterfaces(BcelObjectType.java:275)
	at org.aspectj.weaver.ReferenceType.getDeclaredInterfaces(ReferenceType.java:624)
	at org.aspectj.weaver.ResolvedType.getDirectSupertypes(ResolvedType.java:76)
	at org.aspectj.weaver.patterns.TypePattern.matchesSubtypes(TypePattern.java:178)
	at org.aspectj.weaver.patterns.ExactTypePattern.matchesSubtypes(ExactTypePattern.java:74)
	at org.aspectj.weaver.patterns.TypePattern.matchesStatically(TypePattern.java:130)
	at org.aspectj.weaver.patterns.OrTypePattern.matchesStatically(OrTypePattern.java:76)
	at org.aspectj.weaver.patterns.SignaturePattern.matchesExactlyMethod(SignaturePattern.java:505)
	at org.aspectj.weaver.patterns.SignaturePattern.matchesExactly(SignaturePattern.java:360)
	at org.aspectj.weaver.patterns.SignaturePattern.matches(SignaturePattern.java:320)
	at org.aspectj.weaver.patterns.KindedPointcut.matchInternal(KindedPointcut.java:202)
	at org.aspectj.weaver.patterns.Pointcut.match(Pointcut.java:137)
	at org.aspectj.weaver.patterns.AndPointcut.matchInternal(AndPointcut.java:51)
	at org.aspectj.weaver.patterns.Pointcut.match(Pointcut.java:137)
	at org.aspectj.weaver.patterns.OrPointcut.matchInternal(OrPointcut.java:54)
	at org.aspectj.weaver.patterns.Pointcut.match(Pointcut.java:137)
	at org.aspectj.weaver.ShadowMunger.match(ShadowMunger.java:113)
	at org.aspectj.weaver.Advice.match(Advice.java:109)
	at org.aspectj.weaver.bcel.BcelAdvice.match(BcelAdvice.java:149)
	at org.aspectj.weaver.bcel.BcelClassWeaver.match(BcelClassWeaver.java:3116)
	at org.aspectj.weaver.bcel.BcelClassWeaver.match(BcelClassWeaver.java:2550)
	at org.aspectj.weaver.bcel.BcelClassWeaver.weave(BcelClassWeaver.java:474)
	at org.aspectj.weaver.bcel.BcelClassWeaver.weave(BcelClassWeaver.java:100)
	at org.aspectj.weaver.bcel.BcelWeaver.weave(BcelWeaver.java:1687)
	at org.aspectj.weaver.bcel.BcelWeaver.weaveWithoutDump(BcelWeaver.java:1631)
	at org.aspectj.weaver.bcel.BcelWeaver.weaveAndNotify(BcelWeaver.java:1394)
	at org.aspectj.weaver.bcel.BcelWeaver.weave(BcelWeaver.java:1180)
	at org.aspectj.weaver.tools.WeavingAdaptor.getWovenBytes(WeavingAdaptor.java:467)
	at org.aspectj.weaver.tools.WeavingAdaptor.weaveClass(WeavingAdaptor.java:318)
	at org.aspectj.weaver.loadtime.Aj.preProcess(Aj.java:96)
	at org.aspectj.weaver.loadtime.ClassPreProcessorAgentAdapter.transform(ClassPreProcessorAgentAdapter.java:54)
	at sun.instrument.TransformerManager.transform(TransformerManager.java:188)
	at sun.instrument.InstrumentationImpl.transform(InstrumentationImpl.java:428)
	at java.lang.ClassLoader.defineClass1(Native Method)
	at java.lang.ClassLoader.defineClass(ClassLoader.java:760)
	at java.security.SecureClassLoader.defineClass(SecureClassLoader.java:142)
	at java.net.URLClassLoader.defineClass(URLClassLoader.java:467)
	at java.net.URLClassLoader.access$100(URLClassLoader.java:73)
	at java.net.URLClassLoader$1.run(URLClassLoader.java:368)
	at java.net.URLClassLoader$1.run(URLClassLoader.java:362)
	at java.security.AccessController.doPrivileged(Native Method)
	at java.net.URLClassLoader.findClass(URLClassLoader.java:361)
	at java.lang.ClassLoader.loadClass(ClassLoader.java:424)
	at sun.misc.Launcher$AppClassLoader.loadClass(Launcher.java:331)
	at java.lang.ClassLoader.loadClass(ClassLoader.java:357)
	at org.springframework.beans.factory.xml.BeanDefinitionParserDelegate.parseBeanDefinitionElement(BeanDefinitionParserDelegate.java:475)
	at org.springframework.beans.factory.xml.BeanDefinitionParserDelegate.parseBeanDefinitionElement(BeanDefinitionParserDelegate.java:396)
	at org.springframework.beans.factory.xml.BeanDefinitionParserDelegate.parseBeanDefinitionElement(BeanDefinitionParserDelegate.java:365)
	at org.springframework.beans.factory.xml.DefaultBeanDefinitionDocumentReader.processBeanDefinition(DefaultBeanDefinitionDocumentReader.java:258)
	at org.springframework.beans.factory.xml.DefaultBeanDefinitionDocumentReader.parseDefaultElement(DefaultBeanDefinitionDocumentReader.java:153)
	at org.springframework.beans.factory.xml.DefaultBeanDefinitionDocumentReader.parseBeanDefinitions(DefaultBeanDefinitionDocumentReader.java:132)
	at org.springframework.beans.factory.xml.DefaultBeanDefinitionDocumentReader.registerBeanDefinitions(DefaultBeanDefinitionDocumentReader.java:93)
	at org.springframework.beans.factory.xml.XmlBeanDefinitionReader.registerBeanDefinitions(XmlBeanDefinitionReader.java:493)
	at org.springframework.beans.factory.xml.XmlBeanDefinitionReader.doLoadBeanDefinitions(XmlBeanDefinitionReader.java:390)
	at org.springframework.beans.factory.xml.XmlBeanDefinitionReader.loadBeanDefinitions(XmlBeanDefinitionReader.java:334)
	at org.springframework.beans.factory.xml.XmlBeanDefinitionReader.loadBeanDefinitions(XmlBeanDefinitionReader.java:302)
	at org.springframework.beans.factory.support.AbstractBeanDefinitionReader.loadBeanDefinitions(AbstractBeanDefinitionReader.java:143)
	at org.springframework.beans.factory.support.AbstractBeanDefinitionReader.loadBeanDefinitions(AbstractBeanDefinitionReader.java:178)
	at org.springframework.beans.factory.support.AbstractBeanDefinitionReader.loadBeanDefinitions(AbstractBeanDefinitionReader.java:149)
	at org.springframework.beans.factory.support.AbstractBeanDefinitionReader.loadBeanDefinitions(AbstractBeanDefinitionReader.java:212)
	at org.springframework.context.support.AbstractXmlApplicationContext.loadBeanDefinitions(AbstractXmlApplicationContext.java:126)
	at org.springframework.context.support.AbstractXmlApplicationContext.loadBeanDefinitions(AbstractXmlApplicationContext.java:92)
	at org.springframework.context.support.AbstractRefreshableApplicationContext.refreshBeanFactory(AbstractRefreshableApplicationContext.java:130)
	at org.springframework.context.support.AbstractApplicationContext.obtainFreshBeanFactory(AbstractApplicationContext.java:467)
	at org.springframework.context.support.AbstractApplicationContext.refresh(AbstractApplicationContext.java:397)
	at org.springframework.context.support.ClassPathXmlApplicationContext.<init>(ClassPathXmlApplicationContext.java:139)
	at org.springframework.context.support.ClassPathXmlApplicationContext.<init>(ClassPathXmlApplicationContext.java:83)
	at foo.ConfigureApp.main(ConfigureApp.java:9)

error can't determine annotations of missing type org.springframework.cache.annotation.CachePut
when weaving type org.springframework.beans.factory.parsing.PropertyEntry
when weaving classes 
when weaving 
 [Xlint:cantFindType]
error can't determine annotations of missing type org.springframework.cache.annotation.Cacheable
when weaving type org.springframework.beans.factory.parsing.PropertyEntry
when weaving classes 
when weaving 
 [Xlint:cantFindType]
error can't determine annotations of missing type org.springframework.cache.annotation.CacheEvict
when weaving type org.springframework.beans.factory.parsing.PropertyEntry
when weaving classes 
when weaving 
 [Xlint:cantFindType]
error can't determine annotations of missing type org.springframework.cache.annotation.Caching
when weaving type org.springframework.beans.factory.parsing.PropertyEntry
when weaving classes 
when weaving 
 [Xlint:cantFindType]
error can't determine annotations of missing type org.springframework.transaction.annotation.Transactional
when weaving type org.springframework.beans.factory.parsing.PropertyEntry
when weaving classes 
when weaving 
 [Xlint:cantFindType]
abort trouble in: 
public class org.springframework.beans.factory.parsing.PropertyEntry extends java.lang.Object implements org.springframework.beans.factory.parsing.ParseState$Entry:
  private final String name
  public void <init>(String):
                    ALOAD_0     // Lorg/springframework/beans/factory/parsing/PropertyEntry; this   (line 38)
                    INVOKESPECIAL java.lang.Object.<init> ()V
    constructor-execution(void org.springframework.beans.factory.parsing.PropertyEntry.<init>(java.lang.String))
    |               ALOAD_1     // Ljava/lang/String; name   (line 39)
    |               INVOKESTATIC org.springframework.util.StringUtils.hasText (Ljava/lang/String;)Z
    |               IFNE L0
    |               NEW java.lang.IllegalArgumentException   (line 40)
    |               DUP
    |               NEW java.lang.StringBuilder
    |               DUP
    |               LDC "Invalid property name '"
    |               INVOKESPECIAL java.lang.StringBuilder.<init> (Ljava/lang/String;)V
    |               ALOAD_1     // Ljava/lang/String; name
    |               INVOKEVIRTUAL java.lang.StringBuilder.append (Ljava/lang/String;)Ljava/lang/StringBuilder;
    |               LDC "'."
    |               INVOKEVIRTUAL java.lang.StringBuilder.append (Ljava/lang/String;)Ljava/lang/StringBuilder;
    |               INVOKEVIRTUAL java.lang.StringBuilder.toString ()Ljava/lang/String;
    |               INVOKESPECIAL java.lang.IllegalArgumentException.<init> (Ljava/lang/String;)V
    |               ATHROW
    |           L0: ALOAD_0     // Lorg/springframework/beans/factory/parsing/PropertyEntry; this   (line 42)
    |               ALOAD_1     // Ljava/lang/String; name
    |               PUTFIELD org.springframework.beans.factory.parsing.PropertyEntry.name Ljava/lang/String;
    |               RETURN   (line 43)
    constructor-execution(void org.springframework.beans.factory.parsing.PropertyEntry.<init>(java.lang.String))
  end public void <init>(String)

  public String toString():
                    NEW java.lang.StringBuilder   (line 48)
                    DUP
                    LDC "Property '"
                    INVOKESPECIAL java.lang.StringBuilder.<init> (Ljava/lang/String;)V
                    ALOAD_0     // Lorg/springframework/beans/factory/parsing/PropertyEntry; this
                    GETFIELD org.springframework.beans.factory.parsing.PropertyEntry.name Ljava/lang/String;
                    INVOKEVIRTUAL java.lang.StringBuilder.append (Ljava/lang/String;)Ljava/lang/StringBuilder;
                    LDC "'"
                    INVOKEVIRTUAL java.lang.StringBuilder.append (Ljava/lang/String;)Ljava/lang/StringBuilder;
                    INVOKEVIRTUAL java.lang.StringBuilder.toString ()Ljava/lang/String;
                    ARETURN
  end public String toString()

end public class org.springframework.beans.factory.parsing.PropertyEntry
 -- (NullPointerException) null
null
java.lang.NullPointerException
	at org.aspectj.weaver.UnresolvedType.forSignature(UnresolvedType.java:361)
	at org.aspectj.weaver.bcel.BcelObjectType.getDeclaredInterfaces(BcelObjectType.java:275)
	at org.aspectj.weaver.ReferenceType.getDeclaredInterfaces(ReferenceType.java:624)
	at org.aspectj.weaver.ResolvedType.getDirectSupertypes(ResolvedType.java:76)
	at org.aspectj.weaver.patterns.TypePattern.matchesSubtypes(TypePattern.java:178)
	at org.aspectj.weaver.patterns.ExactTypePattern.matchesSubtypes(ExactTypePattern.java:74)
	at org.aspectj.weaver.patterns.TypePattern.matchesStatically(TypePattern.java:130)
	at org.aspectj.weaver.patterns.OrTypePattern.matchesStatically(OrTypePattern.java:76)
	at org.aspectj.weaver.patterns.SignaturePattern.matchesExactlyMethod(SignaturePattern.java:505)
	at org.aspectj.weaver.patterns.SignaturePattern.matchesExactly(SignaturePattern.java:360)
	at org.aspectj.weaver.patterns.SignaturePattern.matches(SignaturePattern.java:320)
	at org.aspectj.weaver.patterns.KindedPointcut.matchInternal(KindedPointcut.java:202)
	at org.aspectj.weaver.patterns.Pointcut.match(Pointcut.java:137)
	at org.aspectj.weaver.patterns.AndPointcut.matchInternal(AndPointcut.java:51)
	at org.aspectj.weaver.patterns.Pointcut.match(Pointcut.java:137)
	at org.aspectj.weaver.patterns.OrPointcut.matchInternal(OrPointcut.java:54)
	at org.aspectj.weaver.patterns.Pointcut.match(Pointcut.java:137)
	at org.aspectj.weaver.ShadowMunger.match(ShadowMunger.java:113)
	at org.aspectj.weaver.Advice.match(Advice.java:109)
	at org.aspectj.weaver.bcel.BcelAdvice.match(BcelAdvice.java:149)
	at org.aspectj.weaver.bcel.BcelClassWeaver.match(BcelClassWeaver.java:3116)
	at org.aspectj.weaver.bcel.BcelClassWeaver.match(BcelClassWeaver.java:2550)
	at org.aspectj.weaver.bcel.BcelClassWeaver.weave(BcelClassWeaver.java:474)
	at org.aspectj.weaver.bcel.BcelClassWeaver.weave(BcelClassWeaver.java:100)
	at org.aspectj.weaver.bcel.BcelWeaver.weave(BcelWeaver.java:1687)
	at org.aspectj.weaver.bcel.BcelWeaver.weaveWithoutDump(BcelWeaver.java:1631)
	at org.aspectj.weaver.bcel.BcelWeaver.weaveAndNotify(BcelWeaver.java:1394)
	at org.aspectj.weaver.bcel.BcelWeaver.weave(BcelWeaver.java:1180)
	at org.aspectj.weaver.tools.WeavingAdaptor.getWovenBytes(WeavingAdaptor.java:467)
	at org.aspectj.weaver.tools.WeavingAdaptor.weaveClass(WeavingAdaptor.java:318)
	at org.aspectj.weaver.loadtime.Aj.preProcess(Aj.java:96)
	at org.aspectj.weaver.loadtime.ClassPreProcessorAgentAdapter.transform(ClassPreProcessorAgentAdapter.java:54)
	at sun.instrument.TransformerManager.transform(TransformerManager.java:188)
	at sun.instrument.InstrumentationImpl.transform(InstrumentationImpl.java:428)
	at java.lang.ClassLoader.defineClass1(Native Method)
	at java.lang.ClassLoader.defineClass(ClassLoader.java:760)
	at java.security.SecureClassLoader.defineClass(SecureClassLoader.java:142)
	at java.net.URLClassLoader.defineClass(URLClassLoader.java:467)
	at java.net.URLClassLoader.access$100(URLClassLoader.java:73)
	at java.net.URLClassLoader$1.run(URLClassLoader.java:368)
	at java.net.URLClassLoader$1.run(URLClassLoader.java:362)
	at java.security.AccessController.doPrivileged(Native Method)
	at java.net.URLClassLoader.findClass(URLClassLoader.java:361)
	at java.lang.ClassLoader.loadClass(ClassLoader.java:424)
	at sun.misc.Launcher$AppClassLoader.loadClass(Launcher.java:331)
	at java.lang.ClassLoader.loadClass(ClassLoader.java:357)
	at org.springframework.beans.factory.xml.BeanDefinitionParserDelegate.parsePropertyElement(BeanDefinitionParserDelegate.java:826)
	at org.springframework.beans.factory.xml.BeanDefinitionParserDelegate.parsePropertyElements(BeanDefinitionParserDelegate.java:697)
	at org.springframework.beans.factory.xml.BeanDefinitionParserDelegate.parseBeanDefinitionElement(BeanDefinitionParserDelegate.java:482)
	at org.springframework.beans.factory.xml.BeanDefinitionParserDelegate.parseBeanDefinitionElement(BeanDefinitionParserDelegate.java:396)
	at org.springframework.beans.factory.xml.BeanDefinitionParserDelegate.parseBeanDefinitionElement(BeanDefinitionParserDelegate.java:365)
	at org.springframework.beans.factory.xml.DefaultBeanDefinitionDocumentReader.processBeanDefinition(DefaultBeanDefinitionDocumentReader.java:258)
	at org.springframework.beans.factory.xml.DefaultBeanDefinitionDocumentReader.parseDefaultElement(DefaultBeanDefinitionDocumentReader.java:153)
	at org.springframework.beans.factory.xml.DefaultBeanDefinitionDocumentReader.parseBeanDefinitions(DefaultBeanDefinitionDocumentReader.java:132)
	at org.springframework.beans.factory.xml.DefaultBeanDefinitionDocumentReader.registerBeanDefinitions(DefaultBeanDefinitionDocumentReader.java:93)
	at org.springframework.beans.factory.xml.XmlBeanDefinitionReader.registerBeanDefinitions(XmlBeanDefinitionReader.java:493)
	at org.springframework.beans.factory.xml.XmlBeanDefinitionReader.doLoadBeanDefinitions(XmlBeanDefinitionReader.java:390)
	at org.springframework.beans.factory.xml.XmlBeanDefinitionReader.loadBeanDefinitions(XmlBeanDefinitionReader.java:334)
	at org.springframework.beans.factory.xml.XmlBeanDefinitionReader.loadBeanDefinitions(XmlBeanDefinitionReader.java:302)
	at org.springframework.beans.factory.support.AbstractBeanDefinitionReader.loadBeanDefinitions(AbstractBeanDefinitionReader.java:143)
	at org.springframework.beans.factory.support.AbstractBeanDefinitionReader.loadBeanDefinitions(AbstractBeanDefinitionReader.java:178)
	at org.springframework.beans.factory.support.AbstractBeanDefinitionReader.loadBeanDefinitions(AbstractBeanDefinitionReader.java:149)
	at org.springframework.beans.factory.support.AbstractBeanDefinitionReader.loadBeanDefinitions(AbstractBeanDefinitionReader.java:212)
	at org.springframework.context.support.AbstractXmlApplicationContext.loadBeanDefinitions(AbstractXmlApplicationContext.java:126)
	at org.springframework.context.support.AbstractXmlApplicationContext.loadBeanDefinitions(AbstractXmlApplicationContext.java:92)
	at org.springframework.context.support.AbstractRefreshableApplicationContext.refreshBeanFactory(AbstractRefreshableApplicationContext.java:130)
	at org.springframework.context.support.AbstractApplicationContext.obtainFreshBeanFactory(AbstractApplicationContext.java:467)
	at org.springframework.context.support.AbstractApplicationContext.refresh(AbstractApplicationContext.java:397)
	at org.springframework.context.support.ClassPathXmlApplicationContext.<init>(ClassPathXmlApplicationContext.java:139)
	at org.springframework.context.support.ClassPathXmlApplicationContext.<init>(ClassPathXmlApplicationContext.java:83)
	at foo.ConfigureApp.main(ConfigureApp.java:9)

error can't determine annotations of missing type org.springframework.cache.annotation.CachePut
when weaving type org.springframework.beans.factory.config.TypedStringValue
when weaving classes 
when weaving 
 [Xlint:cantFindType]
error can't determine annotations of missing type org.springframework.cache.annotation.Cacheable
when weaving type org.springframework.beans.factory.config.TypedStringValue
when weaving classes 
when weaving 
 [Xlint:cantFindType]
error can't determine annotations of missing type org.springframework.cache.annotation.CacheEvict
when weaving type org.springframework.beans.factory.config.TypedStringValue
when weaving classes 
when weaving 
 [Xlint:cantFindType]
error can't determine annotations of missing type org.springframework.cache.annotation.Caching
when weaving type org.springframework.beans.factory.config.TypedStringValue
when weaving classes 
when weaving 
 [Xlint:cantFindType]
error can't determine annotations of missing type org.springframework.transaction.annotation.Transactional
when weaving type org.springframework.beans.factory.config.TypedStringValue
when weaving classes 
when weaving 
 [Xlint:cantFindType]
abort trouble in: 
public class org.springframework.beans.factory.config.TypedStringValue extends java.lang.Object implements org.springframework.beans.BeanMetadataElement:
  private String value
  private volatile Object targetType
  private Object source
  private String specifiedTypeName
  private volatile boolean dynamic
  public void <init>(String):
                    ALOAD_0     // Lorg/springframework/beans/factory/config/TypedStringValue; this   (line 54)
                    INVOKESPECIAL java.lang.Object.<init> ()V
    constructor-execution(void org.springframework.beans.factory.config.TypedStringValue.<init>(java.lang.String))
    |               ALOAD_0     // Lorg/springframework/beans/factory/config/TypedStringValue; this   (line 55)
    |               ALOAD_1     // Ljava/lang/String; value
    |               INVOKEVIRTUAL org.springframework.beans.factory.config.TypedStringValue.setValue (Ljava/lang/String;)V
    |               RETURN   (line 56)
    constructor-execution(void org.springframework.beans.factory.config.TypedStringValue.<init>(java.lang.String))
  end public void <init>(String)

  public void <init>(String, Class):
                    ALOAD_0     // Lorg/springframework/beans/factory/config/TypedStringValue; this   (line 64)
                    INVOKESPECIAL java.lang.Object.<init> ()V
    constructor-execution(void org.springframework.beans.factory.config.TypedStringValue.<init>(java.lang.String, java.lang.Class))
    |               ALOAD_0     // Lorg/springframework/beans/factory/config/TypedStringValue; this   (line 65)
    |               ALOAD_1     // Ljava/lang/String; value
    |               INVOKEVIRTUAL org.springframework.beans.factory.config.TypedStringValue.setValue (Ljava/lang/String;)V
    |               ALOAD_0     // Lorg/springframework/beans/factory/config/TypedStringValue; this   (line 66)
    |               ALOAD_2     // Ljava/lang/Class; targetType
    |               INVOKEVIRTUAL org.springframework.beans.factory.config.TypedStringValue.setTargetType (Ljava/lang/Class;)V
    |               RETURN   (line 67)
    constructor-execution(void org.springframework.beans.factory.config.TypedStringValue.<init>(java.lang.String, java.lang.Class))
  end public void <init>(String, Class)

  public void <init>(String, String):
                    ALOAD_0     // Lorg/springframework/beans/factory/config/TypedStringValue; this   (line 75)
                    INVOKESPECIAL java.lang.Object.<init> ()V
    constructor-execution(void org.springframework.beans.factory.config.TypedStringValue.<init>(java.lang.String, java.lang.String))
    |               ALOAD_0     // Lorg/springframework/beans/factory/config/TypedStringValue; this   (line 76)
    |               ALOAD_1     // Ljava/lang/String; value
    |               INVOKEVIRTUAL org.springframework.beans.factory.config.TypedStringValue.setValue (Ljava/lang/String;)V
    |               ALOAD_0     // Lorg/springframework/beans/factory/config/TypedStringValue; this   (line 77)
    |               ALOAD_2     // Ljava/lang/String; targetTypeName
    |               INVOKEVIRTUAL org.springframework.beans.factory.config.TypedStringValue.setTargetTypeName (Ljava/lang/String;)V
    |               RETURN   (line 78)
    constructor-execution(void org.springframework.beans.factory.config.TypedStringValue.<init>(java.lang.String, java.lang.String))
  end public void <init>(String, String)

  public void setValue(String):
                    ALOAD_0     // Lorg/springframework/beans/factory/config/TypedStringValue; this   (line 88)
                    ALOAD_1     // Ljava/lang/String; value
                    PUTFIELD org.springframework.beans.factory.config.TypedStringValue.value Ljava/lang/String;
                    RETURN   (line 89)
  end public void setValue(String)

  public String getValue():
                    ALOAD_0     // Lorg/springframework/beans/factory/config/TypedStringValue; this   (line 95)
                    GETFIELD org.springframework.beans.factory.config.TypedStringValue.value Ljava/lang/String;
                    ARETURN
  end public String getValue()

  public void setTargetType(Class):
                    ALOAD_1     // Ljava/lang/Class; targetType   (line 105)
                    LDC "'targetType' must not be null"
                    INVOKESTATIC org.springframework.util.Assert.notNull (Ljava/lang/Object;Ljava/lang/String;)V
                    ALOAD_0     // Lorg/springframework/beans/factory/config/TypedStringValue; this   (line 106)
                    ALOAD_1     // Ljava/lang/Class; targetType
                    PUTFIELD org.springframework.beans.factory.config.TypedStringValue.targetType Ljava/lang/Object;
                    RETURN   (line 107)
  end public void setTargetType(Class)

  public Class getTargetType():
                    ALOAD_0     // Lorg/springframework/beans/factory/config/TypedStringValue; this   (line 113)
                    GETFIELD org.springframework.beans.factory.config.TypedStringValue.targetType Ljava/lang/Object;
                    ASTORE_1
                    ALOAD_1     // Ljava/lang/Object; targetTypeValue   (line 114)
                    INSTANCEOF java.lang.Class
                    IFNE L0
                    NEW java.lang.IllegalStateException   (line 115)
                    DUP
                    LDC "Typed String value does not carry a resolved target type"
                    INVOKESPECIAL java.lang.IllegalStateException.<init> (Ljava/lang/String;)V
                    ATHROW
                L0: ALOAD_1     // Ljava/lang/Object; targetTypeValue   (line 117)
                    CHECKCAST java.lang.Class
                    ARETURN
  end public Class getTargetType()

  public void setTargetTypeName(String):
                    ALOAD_1     // Ljava/lang/String; targetTypeName   (line 124)
                    LDC "'targetTypeName' must not be null"
                    INVOKESTATIC org.springframework.util.Assert.notNull (Ljava/lang/Object;Ljava/lang/String;)V
                    ALOAD_0     // Lorg/springframework/beans/factory/config/TypedStringValue; this   (line 125)
                    ALOAD_1     // Ljava/lang/String; targetTypeName
                    PUTFIELD org.springframework.beans.factory.config.TypedStringValue.targetType Ljava/lang/Object;
                    RETURN   (line 126)
  end public void setTargetTypeName(String)

  public String getTargetTypeName():
                    ALOAD_0     // Lorg/springframework/beans/factory/config/TypedStringValue; this   (line 132)
                    GETFIELD org.springframework.beans.factory.config.TypedStringValue.targetType Ljava/lang/Object;
                    ASTORE_1
                    ALOAD_1     // Ljava/lang/Object; targetTypeValue   (line 133)
                    INSTANCEOF java.lang.Class
                    IFEQ L0
                    ALOAD_1     // Ljava/lang/Object; targetTypeValue   (line 134)
                    CHECKCAST java.lang.Class
                    INVOKEVIRTUAL java.lang.Class.getName ()Ljava/lang/String;
                    ARETURN
                L0: ALOAD_1     // Ljava/lang/Object; targetTypeValue   (line 137)
                    CHECKCAST java.lang.String
                    ARETURN
  end public String getTargetTypeName()

  public boolean hasTargetType():
                    ALOAD_0     // Lorg/springframework/beans/factory/config/TypedStringValue; this   (line 145)
                    GETFIELD org.springframework.beans.factory.config.TypedStringValue.targetType Ljava/lang/Object;
                    INSTANCEOF java.lang.Class
                    IRETURN
  end public boolean hasTargetType()

  public Class resolveTargetType(ClassLoader) throws java.lang.ClassNotFoundException:
                    ALOAD_0     // Lorg/springframework/beans/factory/config/TypedStringValue; this   (line 157)
                    GETFIELD org.springframework.beans.factory.config.TypedStringValue.targetType Ljava/lang/Object;
                    IFNONNULL L0
                    ACONST_NULL   (line 158)
                    ARETURN
                L0: ALOAD_0     // Lorg/springframework/beans/factory/config/TypedStringValue; this   (line 160)
                    INVOKEVIRTUAL org.springframework.beans.factory.config.TypedStringValue.getTargetTypeName ()Ljava/lang/String;
                    ALOAD_1     // Ljava/lang/ClassLoader; classLoader
                    INVOKESTATIC org.springframework.util.ClassUtils.forName (Ljava/lang/String;Ljava/lang/ClassLoader;)Ljava/lang/Class;
                    ASTORE_2
                    ALOAD_0     // Lorg/springframework/beans/factory/config/TypedStringValue; this   (line 161)
                    ALOAD_2     // Ljava/lang/Class; resolvedClass
                    PUTFIELD org.springframework.beans.factory.config.TypedStringValue.targetType Ljava/lang/Object;
                    ALOAD_2     // Ljava/lang/Class; resolvedClass   (line 162)
                    ARETURN
  end public Class resolveTargetType(ClassLoader) throws java.lang.ClassNotFoundException

  public void setSource(Object):
                    ALOAD_0     // Lorg/springframework/beans/factory/config/TypedStringValue; this   (line 171)
                    ALOAD_1     // Ljava/lang/Object; source
                    PUTFIELD org.springframework.beans.factory.config.TypedStringValue.source Ljava/lang/Object;
                    RETURN   (line 172)
  end public void setSource(Object)

  public Object getSource():
                    ALOAD_0     // Lorg/springframework/beans/factory/config/TypedStringValue; this   (line 175)
                    GETFIELD org.springframework.beans.factory.config.TypedStringValue.source Ljava/lang/Object;
                    ARETURN
  end public Object getSource()

  public void setSpecifiedTypeName(String):
                    ALOAD_0     // Lorg/springframework/beans/factory/config/TypedStringValue; this   (line 182)
                    ALOAD_1     // Ljava/lang/String; specifiedTypeName
                    PUTFIELD org.springframework.beans.factory.config.TypedStringValue.specifiedTypeName Ljava/lang/String;
                    RETURN   (line 183)
  end public void setSpecifiedTypeName(String)

  public String getSpecifiedTypeName():
                    ALOAD_0     // Lorg/springframework/beans/factory/config/TypedStringValue; this   (line 189)
                    GETFIELD org.springframework.beans.factory.config.TypedStringValue.specifiedTypeName Ljava/lang/String;
                    ARETURN
  end public String getSpecifiedTypeName()

  public void setDynamic():
                    ALOAD_0     // Lorg/springframework/beans/factory/config/TypedStringValue; this   (line 197)
                    ICONST_1
                    PUTFIELD org.springframework.beans.factory.config.TypedStringValue.dynamic Z
                    RETURN   (line 198)
  end public void setDynamic()

  public boolean isDynamic():
                    ALOAD_0     // Lorg/springframework/beans/factory/config/TypedStringValue; this   (line 204)
                    GETFIELD org.springframework.beans.factory.config.TypedStringValue.dynamic Z
                    IRETURN
  end public boolean isDynamic()

  public boolean equals(Object):
                    ALOAD_0     // Lorg/springframework/beans/factory/config/TypedStringValue; this   (line 210)
                    ALOAD_1     // Ljava/lang/Object; other
                    IF_ACMPNE L0
                    ICONST_1   (line 211)
                    IRETURN
                L0: ALOAD_1     // Ljava/lang/Object; other   (line 213)
                    INSTANCEOF org.springframework.beans.factory.config.TypedStringValue
                    IFNE L1
                    ICONST_0   (line 214)
                    IRETURN
                L1: ALOAD_1     // Ljava/lang/Object; other   (line 216)
                    CHECKCAST org.springframework.beans.factory.config.TypedStringValue
                    ASTORE_2
                    ALOAD_0     // Lorg/springframework/beans/factory/config/TypedStringValue; this   (line 217)
                    GETFIELD org.springframework.beans.factory.config.TypedStringValue.value Ljava/lang/String;
                    ALOAD_2     // Lorg/springframework/beans/factory/config/TypedStringValue; otherValue
                    GETFIELD org.springframework.beans.factory.config.TypedStringValue.value Ljava/lang/String;
                    INVOKESTATIC org.springframework.util.ObjectUtils.nullSafeEquals (Ljava/lang/Object;Ljava/lang/Object;)Z
                    IFEQ L2
                    ALOAD_0     // Lorg/springframework/beans/factory/config/TypedStringValue; this   (line 218)
                    GETFIELD org.springframework.beans.factory.config.TypedStringValue.targetType Ljava/lang/Object;
                    ALOAD_2     // Lorg/springframework/beans/factory/config/TypedStringValue; otherValue
                    GETFIELD org.springframework.beans.factory.config.TypedStringValue.targetType Ljava/lang/Object;
                    INVOKESTATIC org.springframework.util.ObjectUtils.nullSafeEquals (Ljava/lang/Object;Ljava/lang/Object;)Z
                    IFEQ L2
                    ICONST_1
                    IRETURN
                L2: ICONST_0
                    IRETURN   (line 217)
  end public boolean equals(Object)

  public int hashCode():
                    ALOAD_0     // Lorg/springframework/beans/factory/config/TypedStringValue; this   (line 223)
                    GETFIELD org.springframework.beans.factory.config.TypedStringValue.value Ljava/lang/String;
                    INVOKESTATIC org.springframework.util.ObjectUtils.nullSafeHashCode (Ljava/lang/Object;)I
                    BIPUSH 29
                    IMUL
                    ALOAD_0     // Lorg/springframework/beans/factory/config/TypedStringValue; this
                    GETFIELD org.springframework.beans.factory.config.TypedStringValue.targetType Ljava/lang/Object;
                    INVOKESTATIC org.springframework.util.ObjectUtils.nullSafeHashCode (Ljava/lang/Object;)I
                    IADD
                    IRETURN
  end public int hashCode()

  public String toString():
                    NEW java.lang.StringBuilder   (line 228)
                    DUP
                    LDC "TypedStringValue: value ["
                    INVOKESPECIAL java.lang.StringBuilder.<init> (Ljava/lang/String;)V
                    ALOAD_0     // Lorg/springframework/beans/factory/config/TypedStringValue; this
                    GETFIELD org.springframework.beans.factory.config.TypedStringValue.value Ljava/lang/String;
                    INVOKEVIRTUAL java.lang.StringBuilder.append (Ljava/lang/String;)Ljava/lang/StringBuilder;
                    LDC "], target type ["
                    INVOKEVIRTUAL java.lang.StringBuilder.append (Ljava/lang/String;)Ljava/lang/StringBuilder;
                    ALOAD_0     // Lorg/springframework/beans/factory/config/TypedStringValue; this
                    GETFIELD org.springframework.beans.factory.config.TypedStringValue.targetType Ljava/lang/Object;
                    INVOKEVIRTUAL java.lang.StringBuilder.append (Ljava/lang/Object;)Ljava/lang/StringBuilder;
                    LDC "]"
                    INVOKEVIRTUAL java.lang.StringBuilder.append (Ljava/lang/String;)Ljava/lang/StringBuilder;
                    INVOKEVIRTUAL java.lang.StringBuilder.toString ()Ljava/lang/String;
                    ARETURN
  end public String toString()

end public class org.springframework.beans.factory.config.TypedStringValue
 -- (NullPointerException) null
null
java.lang.NullPointerException
	at org.aspectj.weaver.UnresolvedType.forSignature(UnresolvedType.java:361)
	at org.aspectj.weaver.bcel.BcelObjectType.getDeclaredInterfaces(BcelObjectType.java:275)
	at org.aspectj.weaver.ReferenceType.getDeclaredInterfaces(ReferenceType.java:624)
	at org.aspectj.weaver.ResolvedType.getDirectSupertypes(ResolvedType.java:76)
	at org.aspectj.weaver.patterns.TypePattern.matchesSubtypes(TypePattern.java:178)
	at org.aspectj.weaver.patterns.ExactTypePattern.matchesSubtypes(ExactTypePattern.java:74)
	at org.aspectj.weaver.patterns.TypePattern.matchesStatically(TypePattern.java:130)
	at org.aspectj.weaver.patterns.OrTypePattern.matchesStatically(OrTypePattern.java:76)
	at org.aspectj.weaver.patterns.SignaturePattern.matchesExactlyMethod(SignaturePattern.java:505)
	at org.aspectj.weaver.patterns.SignaturePattern.matchesExactly(SignaturePattern.java:360)
	at org.aspectj.weaver.patterns.SignaturePattern.matches(SignaturePattern.java:320)
	at org.aspectj.weaver.patterns.KindedPointcut.matchInternal(KindedPointcut.java:202)
	at org.aspectj.weaver.patterns.Pointcut.match(Pointcut.java:137)
	at org.aspectj.weaver.patterns.AndPointcut.matchInternal(AndPointcut.java:51)
	at org.aspectj.weaver.patterns.Pointcut.match(Pointcut.java:137)
	at org.aspectj.weaver.patterns.OrPointcut.matchInternal(OrPointcut.java:54)
	at org.aspectj.weaver.patterns.Pointcut.match(Pointcut.java:137)
	at org.aspectj.weaver.ShadowMunger.match(ShadowMunger.java:113)
	at org.aspectj.weaver.Advice.match(Advice.java:109)
	at org.aspectj.weaver.bcel.BcelAdvice.match(BcelAdvice.java:149)
	at org.aspectj.weaver.bcel.BcelClassWeaver.match(BcelClassWeaver.java:3116)
	at org.aspectj.weaver.bcel.BcelClassWeaver.match(BcelClassWeaver.java:2550)
	at org.aspectj.weaver.bcel.BcelClassWeaver.weave(BcelClassWeaver.java:474)
	at org.aspectj.weaver.bcel.BcelClassWeaver.weave(BcelClassWeaver.java:100)
	at org.aspectj.weaver.bcel.BcelWeaver.weave(BcelWeaver.java:1687)
	at org.aspectj.weaver.bcel.BcelWeaver.weaveWithoutDump(BcelWeaver.java:1631)
	at org.aspectj.weaver.bcel.BcelWeaver.weaveAndNotify(BcelWeaver.java:1394)
	at org.aspectj.weaver.bcel.BcelWeaver.weave(BcelWeaver.java:1180)
	at org.aspectj.weaver.tools.WeavingAdaptor.getWovenBytes(WeavingAdaptor.java:467)
	at org.aspectj.weaver.tools.WeavingAdaptor.weaveClass(WeavingAdaptor.java:318)
	at org.aspectj.weaver.loadtime.Aj.preProcess(Aj.java:96)
	at org.aspectj.weaver.loadtime.ClassPreProcessorAgentAdapter.transform(ClassPreProcessorAgentAdapter.java:54)
	at sun.instrument.TransformerManager.transform(TransformerManager.java:188)
	at sun.instrument.InstrumentationImpl.transform(InstrumentationImpl.java:428)
	at java.lang.ClassLoader.defineClass1(Native Method)
	at java.lang.ClassLoader.defineClass(ClassLoader.java:760)
	at java.security.SecureClassLoader.defineClass(SecureClassLoader.java:142)
	at java.net.URLClassLoader.defineClass(URLClassLoader.java:467)
	at java.net.URLClassLoader.access$100(URLClassLoader.java:73)
	at java.net.URLClassLoader$1.run(URLClassLoader.java:368)
	at java.net.URLClassLoader$1.run(URLClassLoader.java:362)
	at java.security.AccessController.doPrivileged(Native Method)
	at java.net.URLClassLoader.findClass(URLClassLoader.java:361)
	at java.lang.ClassLoader.loadClass(ClassLoader.java:424)
	at sun.misc.Launcher$AppClassLoader.loadClass(Launcher.java:331)
	at java.lang.ClassLoader.loadClass(ClassLoader.java:357)
	at org.springframework.beans.factory.xml.BeanDefinitionParserDelegate.parsePropertyValue(BeanDefinitionParserDelegate.java:929)
	at org.springframework.beans.factory.xml.BeanDefinitionParserDelegate.parsePropertyElement(BeanDefinitionParserDelegate.java:832)
	at org.springframework.beans.factory.xml.BeanDefinitionParserDelegate.parsePropertyElements(BeanDefinitionParserDelegate.java:697)
	at org.springframework.beans.factory.xml.BeanDefinitionParserDelegate.parseBeanDefinitionElement(BeanDefinitionParserDelegate.java:482)
	at org.springframework.beans.factory.xml.BeanDefinitionParserDelegate.parseBeanDefinitionElement(BeanDefinitionParserDelegate.java:396)
	at org.springframework.beans.factory.xml.BeanDefinitionParserDelegate.parseBeanDefinitionElement(BeanDefinitionParserDelegate.java:365)
	at org.springframework.beans.factory.xml.DefaultBeanDefinitionDocumentReader.processBeanDefinition(DefaultBeanDefinitionDocumentReader.java:258)
	at org.springframework.beans.factory.xml.DefaultBeanDefinitionDocumentReader.parseDefaultElement(DefaultBeanDefinitionDocumentReader.java:153)
	at org.springframework.beans.factory.xml.DefaultBeanDefinitionDocumentReader.parseBeanDefinitions(DefaultBeanDefinitionDocumentReader.java:132)
	at org.springframework.beans.factory.xml.DefaultBeanDefinitionDocumentReader.registerBeanDefinitions(DefaultBeanDefinitionDocumentReader.java:93)
	at org.springframework.beans.factory.xml.XmlBeanDefinitionReader.registerBeanDefinitions(XmlBeanDefinitionReader.java:493)
	at org.springframework.beans.factory.xml.XmlBeanDefinitionReader.doLoadBeanDefinitions(XmlBeanDefinitionReader.java:390)
	at org.springframework.beans.factory.xml.XmlBeanDefinitionReader.loadBeanDefinitions(XmlBeanDefinitionReader.java:334)
	at org.springframework.beans.factory.xml.XmlBeanDefinitionReader.loadBeanDefinitions(XmlBeanDefinitionReader.java:302)
	at org.springframework.beans.factory.support.AbstractBeanDefinitionReader.loadBeanDefinitions(AbstractBeanDefinitionReader.java:143)
	at org.springframework.beans.factory.support.AbstractBeanDefinitionReader.loadBeanDefinitions(AbstractBeanDefinitionReader.java:178)
	at org.springframework.beans.factory.support.AbstractBeanDefinitionReader.loadBeanDefinitions(AbstractBeanDefinitionReader.java:149)
	at org.springframework.beans.factory.support.AbstractBeanDefinitionReader.loadBeanDefinitions(AbstractBeanDefinitionReader.java:212)
	at org.springframework.context.support.AbstractXmlApplicationContext.loadBeanDefinitions(AbstractXmlApplicationContext.java:126)
	at org.springframework.context.support.AbstractXmlApplicationContext.loadBeanDefinitions(AbstractXmlApplicationContext.java:92)
	at org.springframework.context.support.AbstractRefreshableApplicationContext.refreshBeanFactory(AbstractRefreshableApplicationContext.java:130)
	at org.springframework.context.support.AbstractApplicationContext.obtainFreshBeanFactory(AbstractApplicationContext.java:467)
	at org.springframework.context.support.AbstractApplicationContext.refresh(AbstractApplicationContext.java:397)
	at org.springframework.context.support.ClassPathXmlApplicationContext.<init>(ClassPathXmlApplicationContext.java:139)
	at org.springframework.context.support.ClassPathXmlApplicationContext.<init>(ClassPathXmlApplicationContext.java:83)
	at foo.ConfigureApp.main(ConfigureApp.java:9)

error can't determine annotations of missing type org.springframework.cache.annotation.CachePut
when weaving type org.springframework.context.expression.StandardBeanExpressionResolver
when weaving classes 
when weaving 
 [Xlint:cantFindType]
error can't determine annotations of missing type org.springframework.cache.annotation.Cacheable
when weaving type org.springframework.context.expression.StandardBeanExpressionResolver
when weaving classes 
when weaving 
 [Xlint:cantFindType]
error can't determine annotations of missing type org.springframework.cache.annotation.CacheEvict
when weaving type org.springframework.context.expression.StandardBeanExpressionResolver
when weaving classes 
when weaving 
 [Xlint:cantFindType]
error can't determine annotations of missing type org.springframework.cache.annotation.Caching
when weaving type org.springframework.context.expression.StandardBeanExpressionResolver
when weaving classes 
when weaving 
 [Xlint:cantFindType]
error can't determine annotations of missing type org.springframework.transaction.annotation.Transactional
when weaving type org.springframework.context.expression.StandardBeanExpressionResolver
when weaving classes 
when weaving 
 [Xlint:cantFindType]
abort trouble in: 
public class org.springframework.context.expression.StandardBeanExpressionResolver extends java.lang.Object implements org.springframework.beans.factory.config.BeanExpressionResolver:
  public static final String DEFAULT_EXPRESSION_PREFIX = "#{"
  public static final String DEFAULT_EXPRESSION_SUFFIX = "}"
  private String expressionPrefix
  private String expressionSuffix
  private org.springframework.expression.ExpressionParser expressionParser
  private final java.util.Map expressionCache [Signature(Ljava/util/Map<Ljava/lang/String;Lorg/springframework/expression/Expression;>;)]
  private final java.util.Map evaluationCache [Signature(Ljava/util/Map<Lorg/springframework/beans/factory/config/BeanExpressionContext;Lorg/springframework/expression/spel/support/StandardEvaluationContext;>;)]
  private final org.springframework.expression.ParserContext beanExpressionParserContext
  public void <init>():
                    ALOAD_0     // Lorg/springframework/context/expression/StandardBeanExpressionResolver; this   (line 48)
                    INVOKESPECIAL java.lang.Object.<init> ()V
    constructor-execution(void org.springframework.context.expression.StandardBeanExpressionResolver.<init>())
    |               ALOAD_0     // Lorg/springframework/context/expression/StandardBeanExpressionResolver; this   (line 57)
    |               LDC "#{"
    |               PUTFIELD org.springframework.context.expression.StandardBeanExpressionResolver.expressionPrefix Ljava/lang/String;
    |               ALOAD_0     // Lorg/springframework/context/expression/StandardBeanExpressionResolver; this   (line 59)
    |               LDC "}"
    |               PUTFIELD org.springframework.context.expression.StandardBeanExpressionResolver.expressionSuffix Ljava/lang/String;
    |               ALOAD_0     // Lorg/springframework/context/expression/StandardBeanExpressionResolver; this   (line 61)
    |               NEW org.springframework.expression.spel.standard.SpelExpressionParser
    |               DUP
    |               INVOKESPECIAL org.springframework.expression.spel.standard.SpelExpressionParser.<init> ()V
    |               PUTFIELD org.springframework.context.expression.StandardBeanExpressionResolver.expressionParser Lorg/springframework/expression/ExpressionParser;
    |               ALOAD_0     // Lorg/springframework/context/expression/StandardBeanExpressionResolver; this   (line 63)
    |               NEW java.util.concurrent.ConcurrentHashMap
    |               DUP
    |               INVOKESPECIAL java.util.concurrent.ConcurrentHashMap.<init> ()V
    |               PUTFIELD org.springframework.context.expression.StandardBeanExpressionResolver.expressionCache Ljava/util/Map;
    |               ALOAD_0     // Lorg/springframework/context/expression/StandardBeanExpressionResolver; this   (line 65)
    |               NEW java.util.concurrent.ConcurrentHashMap   (line 66)
    |               DUP
    |               INVOKESPECIAL java.util.concurrent.ConcurrentHashMap.<init> ()V
    |               PUTFIELD org.springframework.context.expression.StandardBeanExpressionResolver.evaluationCache Ljava/util/Map;
    |               ALOAD_0     // Lorg/springframework/context/expression/StandardBeanExpressionResolver; this   (line 68)
    |               NEW org.springframework.context.expression.StandardBeanExpressionResolver$1
    |               DUP
    |               ALOAD_0     // Lorg/springframework/context/expression/StandardBeanExpressionResolver; this
    |               INVOKESPECIAL org.springframework.context.expression.StandardBeanExpressionResolver$1.<init> (Lorg/springframework/context/expression/StandardBeanExpressionResolver;)V
    |               PUTFIELD org.springframework.context.expression.StandardBeanExpressionResolver.beanExpressionParserContext Lorg/springframework/expression/ParserContext;
    |               RETURN   (line 48)
    constructor-execution(void org.springframework.context.expression.StandardBeanExpressionResolver.<init>())
  end public void <init>()

  public void setExpressionPrefix(String):
                    ALOAD_1     // Ljava/lang/String; expressionPrefix   (line 87)
                    LDC "Expression prefix must not be empty"
                    INVOKESTATIC org.springframework.util.Assert.hasText (Ljava/lang/String;Ljava/lang/String;)V
                    ALOAD_0     // Lorg/springframework/context/expression/StandardBeanExpressionResolver; this   (line 88)
                    ALOAD_1     // Ljava/lang/String; expressionPrefix
                    PUTFIELD org.springframework.context.expression.StandardBeanExpressionResolver.expressionPrefix Ljava/lang/String;
                    RETURN   (line 89)
  end public void setExpressionPrefix(String)

  public void setExpressionSuffix(String):
                    ALOAD_1     // Ljava/lang/String; expressionSuffix   (line 97)
                    LDC "Expression suffix must not be empty"
                    INVOKESTATIC org.springframework.util.Assert.hasText (Ljava/lang/String;Ljava/lang/String;)V
                    ALOAD_0     // Lorg/springframework/context/expression/StandardBeanExpressionResolver; this   (line 98)
                    ALOAD_1     // Ljava/lang/String; expressionSuffix
                    PUTFIELD org.springframework.context.expression.StandardBeanExpressionResolver.expressionSuffix Ljava/lang/String;
                    RETURN   (line 99)
  end public void setExpressionSuffix(String)

  public void setExpressionParser(org.springframework.expression.ExpressionParser):
                    ALOAD_1     // Lorg/springframework/expression/ExpressionParser; expressionParser   (line 107)
                    LDC "ExpressionParser must not be null"
                    INVOKESTATIC org.springframework.util.Assert.notNull (Ljava/lang/Object;Ljava/lang/String;)V
                    ALOAD_0     // Lorg/springframework/context/expression/StandardBeanExpressionResolver; this   (line 108)
                    ALOAD_1     // Lorg/springframework/expression/ExpressionParser; expressionParser
                    PUTFIELD org.springframework.context.expression.StandardBeanExpressionResolver.expressionParser Lorg/springframework/expression/ExpressionParser;
                    RETURN   (line 109)
  end public void setExpressionParser(org.springframework.expression.ExpressionParser)

  public Object evaluate(String, org.springframework.beans.factory.config.BeanExpressionContext) throws org.springframework.beans.BeansException:
                    ALOAD_1     // Ljava/lang/String; value   (line 113)
                    INVOKESTATIC org.springframework.util.StringUtils.hasLength (Ljava/lang/String;)Z
                    IFNE L0
                    ALOAD_1     // Ljava/lang/String; value   (line 114)
                    ARETURN
    catch java.lang.Exception -> E0
    |           L0: ALOAD_0     // Lorg/springframework/context/expression/StandardBeanExpressionResolver; this   (line 117)
    |               GETFIELD org.springframework.context.expression.StandardBeanExpressionResolver.expressionCache Ljava/util/Map;
    |               ALOAD_1     // Ljava/lang/String; value
    |               INVOKEINTERFACE java.util.Map.get (Ljava/lang/Object;)Ljava/lang/Object;
    |               CHECKCAST org.springframework.expression.Expression
    |               ASTORE_3
    |               ALOAD_3     // Lorg/springframework/expression/Expression; expr   (line 118)
    |               IFNONNULL L1
    |               ALOAD_0     // Lorg/springframework/context/expression/StandardBeanExpressionResolver; this   (line 119)
    |               GETFIELD org.springframework.context.expression.StandardBeanExpressionResolver.expressionParser Lorg/springframework/expression/ExpressionParser;
    |               ALOAD_1     // Ljava/lang/String; value
    |               ALOAD_0     // Lorg/springframework/context/expression/StandardBeanExpressionResolver; this
    |               GETFIELD org.springframework.context.expression.StandardBeanExpressionResolver.beanExpressionParserContext Lorg/springframework/expression/ParserContext;
    |               INVOKEINTERFACE org.springframework.expression.ExpressionParser.parseExpression (Ljava/lang/String;Lorg/springframework/expression/ParserContext;)Lorg/springframework/expression/Expression;
    |               ASTORE_3     // Lorg/springframework/expression/Expression; expr
    |               ALOAD_0     // Lorg/springframework/context/expression/StandardBeanExpressionResolver; this   (line 120)
    |               GETFIELD org.springframework.context.expression.StandardBeanExpressionResolver.expressionCache Ljava/util/Map;
    |               ALOAD_1     // Ljava/lang/String; value
    |               ALOAD_3     // Lorg/springframework/expression/Expression; expr
    |               INVOKEINTERFACE java.util.Map.put (Ljava/lang/Object;Ljava/lang/Object;)Ljava/lang/Object;
    |               POP
    |           L1: ALOAD_0     // Lorg/springframework/context/expression/StandardBeanExpressionResolver; this   (line 122)
    |               GETFIELD org.springframework.context.expression.StandardBeanExpressionResolver.evaluationCache Ljava/util/Map;
    |               ALOAD_2     // Lorg/springframework/beans/factory/config/BeanExpressionContext; evalContext
    |               INVOKEINTERFACE java.util.Map.get (Ljava/lang/Object;)Ljava/lang/Object;
    |               CHECKCAST org.springframework.expression.spel.support.StandardEvaluationContext
    |               ASTORE 4
    |               ALOAD 4     // Lorg/springframework/expression/spel/support/StandardEvaluationContext; sec   (line 123)
    |               IFNONNULL L3
    |               NEW org.springframework.expression.spel.support.StandardEvaluationContext   (line 124)
    |               DUP
    |               INVOKESPECIAL org.springframework.expression.spel.support.StandardEvaluationContext.<init> ()V
    |               ASTORE 4     // Lorg/springframework/expression/spel/support/StandardEvaluationContext; sec
    |               ALOAD 4     // Lorg/springframework/expression/spel/support/StandardEvaluationContext; sec   (line 125)
    |               ALOAD_2     // Lorg/springframework/beans/factory/config/BeanExpressionContext; evalContext
    |               INVOKEVIRTUAL org.springframework.expression.spel.support.StandardEvaluationContext.setRootObject (Ljava/lang/Object;)V
    |               ALOAD 4     // Lorg/springframework/expression/spel/support/StandardEvaluationContext; sec   (line 126)
    |               NEW org.springframework.context.expression.BeanExpressionContextAccessor
    |               DUP
    |               INVOKESPECIAL org.springframework.context.expression.BeanExpressionContextAccessor.<init> ()V
    |               INVOKEVIRTUAL org.springframework.expression.spel.support.StandardEvaluationContext.addPropertyAccessor (Lorg/springframework/expression/PropertyAccessor;)V
    |               ALOAD 4     // Lorg/springframework/expression/spel/support/StandardEvaluationContext; sec   (line 127)
    |               NEW org.springframework.context.expression.BeanFactoryAccessor
    |               DUP
    |               INVOKESPECIAL org.springframework.context.expression.BeanFactoryAccessor.<init> ()V
    |               INVOKEVIRTUAL org.springframework.expression.spel.support.StandardEvaluationContext.addPropertyAccessor (Lorg/springframework/expression/PropertyAccessor;)V
    |               ALOAD 4     // Lorg/springframework/expression/spel/support/StandardEvaluationContext; sec   (line 128)
    |               NEW org.springframework.context.expression.MapAccessor
    |               DUP
    |               INVOKESPECIAL org.springframework.context.expression.MapAccessor.<init> ()V
    |               INVOKEVIRTUAL org.springframework.expression.spel.support.StandardEvaluationContext.addPropertyAccessor (Lorg/springframework/expression/PropertyAccessor;)V
    |               ALOAD 4     // Lorg/springframework/expression/spel/support/StandardEvaluationContext; sec   (line 129)
    |               NEW org.springframework.context.expression.BeanFactoryResolver
    |               DUP
    |               ALOAD_2     // Lorg/springframework/beans/factory/config/BeanExpressionContext; evalContext
    |               INVOKEVIRTUAL org.springframework.beans.factory.config.BeanExpressionContext.getBeanFactory ()Lorg/springframework/beans/factory/config/ConfigurableBeanFactory;
    |               INVOKESPECIAL org.springframework.context.expression.BeanFactoryResolver.<init> (Lorg/springframework/beans/factory/BeanFactory;)V
    |               INVOKEVIRTUAL org.springframework.expression.spel.support.StandardEvaluationContext.setBeanResolver (Lorg/springframework/expression/BeanResolver;)V
    |               ALOAD 4     // Lorg/springframework/expression/spel/support/StandardEvaluationContext; sec   (line 130)
    |               NEW org.springframework.expression.spel.support.StandardTypeLocator
    |               DUP
    |               ALOAD_2     // Lorg/springframework/beans/factory/config/BeanExpressionContext; evalContext
    |               INVOKEVIRTUAL org.springframework.beans.factory.config.BeanExpressionContext.getBeanFactory ()Lorg/springframework/beans/factory/config/ConfigurableBeanFactory;
    |               INVOKEINTERFACE org.springframework.beans.factory.config.ConfigurableBeanFactory.getBeanClassLoader ()Ljava/lang/ClassLoader;
    |               INVOKESPECIAL org.springframework.expression.spel.support.StandardTypeLocator.<init> (Ljava/lang/ClassLoader;)V
    |               INVOKEVIRTUAL org.springframework.expression.spel.support.StandardEvaluationContext.setTypeLocator (Lorg/springframework/expression/TypeLocator;)V
    |               ALOAD_2     // Lorg/springframework/beans/factory/config/BeanExpressionContext; evalContext   (line 131)
    |               INVOKEVIRTUAL org.springframework.beans.factory.config.BeanExpressionContext.getBeanFactory ()Lorg/springframework/beans/factory/config/ConfigurableBeanFactory;
    |               INVOKEINTERFACE org.springframework.beans.factory.config.ConfigurableBeanFactory.getConversionService ()Lorg/springframework/core/convert/ConversionService;
    |               ASTORE 5
    |               ALOAD 5     // Lorg/springframework/core/convert/ConversionService; conversionService   (line 132)
    |               IFNULL L2
    |               ALOAD 4     // Lorg/springframework/expression/spel/support/StandardEvaluationContext; sec   (line 133)
    |               NEW org.springframework.expression.spel.support.StandardTypeConverter
    |               DUP
    |               ALOAD 5     // Lorg/springframework/core/convert/ConversionService; conversionService
    |               INVOKESPECIAL org.springframework.expression.spel.support.StandardTypeConverter.<init> (Lorg/springframework/core/convert/ConversionService;)V
    |               INVOKEVIRTUAL org.springframework.expression.spel.support.StandardEvaluationContext.setTypeConverter (Lorg/springframework/expression/TypeConverter;)V
    |           L2: ALOAD_0     // Lorg/springframework/context/expression/StandardBeanExpressionResolver; this   (line 135)
    |               ALOAD 4     // Lorg/springframework/expression/spel/support/StandardEvaluationContext; sec
    |               INVOKEVIRTUAL org.springframework.context.expression.StandardBeanExpressionResolver.customizeEvaluationContext (Lorg/springframework/expression/spel/support/StandardEvaluationContext;)V
    |               ALOAD_0     // Lorg/springframework/context/expression/StandardBeanExpressionResolver; this   (line 136)
    |               GETFIELD org.springframework.context.expression.StandardBeanExpressionResolver.evaluationCache Ljava/util/Map;
    |               ALOAD_2     // Lorg/springframework/beans/factory/config/BeanExpressionContext; evalContext
    |               ALOAD 4     // Lorg/springframework/expression/spel/support/StandardEvaluationContext; sec
    |               INVOKEINTERFACE java.util.Map.put (Ljava/lang/Object;Ljava/lang/Object;)Ljava/lang/Object;
    |               POP
    |           L3: ALOAD_3     // Lorg/springframework/expression/Expression; expr   (line 138)
    |               ALOAD 4     // Lorg/springframework/expression/spel/support/StandardEvaluationContext; sec
    |               INVOKEINTERFACE org.springframework.expression.Expression.getValue (Lorg/springframework/expression/EvaluationContext;)Ljava/lang/Object;
    catch java.lang.Exception -> E0
                    ARETURN
                E0: ASTORE_3   (line 140)
                    NEW org.springframework.beans.factory.BeanExpressionException   (line 141)
                    DUP
                    LDC "Expression parsing failed"
                    ALOAD_3     // Ljava/lang/Exception; ex
                    INVOKESPECIAL org.springframework.beans.factory.BeanExpressionException.<init> (Ljava/lang/String;Ljava/lang/Throwable;)V
                    ATHROW
  end public Object evaluate(String, org.springframework.beans.factory.config.BeanExpressionContext) throws org.springframework.beans.BeansException

  protected void customizeEvaluationContext(org.springframework.expression.spel.support.StandardEvaluationContext):
                    RETURN   (line 150)
  end protected void customizeEvaluationContext(org.springframework.expression.spel.support.StandardEvaluationContext)

  static String access$0(org.springframework.context.expression.StandardBeanExpressionResolver):
                    ALOAD_0   (line 57)
                    GETFIELD org.springframework.context.expression.StandardBeanExpressionResolver.expressionPrefix Ljava/lang/String;
                    ARETURN
  end static String access$0(org.springframework.context.expression.StandardBeanExpressionResolver)

  static String access$1(org.springframework.context.expression.StandardBeanExpressionResolver):
                    ALOAD_0   (line 59)
                    GETFIELD org.springframework.context.expression.StandardBeanExpressionResolver.expressionSuffix Ljava/lang/String;
                    ARETURN
  end static String access$1(org.springframework.context.expression.StandardBeanExpressionResolver)

end public class org.springframework.context.expression.StandardBeanExpressionResolver
 -- (NullPointerException) null
null
java.lang.NullPointerException

error can't determine annotations of missing type org.springframework.cache.annotation.CachePut
when weaving type org.springframework.expression.PropertyAccessor
when weaving classes 
when weaving 
 [Xlint:cantFindType]
error can't determine annotations of missing type org.springframework.cache.annotation.Cacheable
when weaving type org.springframework.expression.PropertyAccessor
when weaving classes 
when weaving 
 [Xlint:cantFindType]
error can't determine annotations of missing type org.springframework.cache.annotation.CacheEvict
when weaving type org.springframework.expression.PropertyAccessor
when weaving classes 
when weaving 
 [Xlint:cantFindType]
error can't determine annotations of missing type org.springframework.cache.annotation.Caching
when weaving type org.springframework.expression.PropertyAccessor
when weaving classes 
when weaving 
 [Xlint:cantFindType]
error can't determine annotations of missing type org.springframework.transaction.annotation.Transactional
when weaving type org.springframework.expression.PropertyAccessor
when weaving classes 
when weaving 
 [Xlint:cantFindType]
