---- AspectJ Properties ---
AspectJ Compiler 1.6.11 built on Tuesday Mar 15, 2011 at 15:31:04 GMT
---- Dump Properties ---
Dump file: ajcore.20150913.182857.845.txt
Dump reason: org.aspectj.bridge.AbortException
Dump on exception: true
Dump at exit condition: abort
---- Exception Information ---
Message: abort trouble in: 
public abstract class org.springframework.util.xml.DomUtils extends java.lang.Object:
  public void <init>():
                    ALOAD_0     // Lorg/springframework/util/xml/DomUtils; this   (line 46)
                    INVOKESPECIAL java.lang.Object.<init> ()V
    constructor-execution(void org.springframework.util.xml.DomUtils.<init>())
    |               RETURN
    constructor-execution(void org.springframework.util.xml.DomUtils.<init>())
  end public void <init>()

  public static java.util.List getChildElementsByTagName(org.w3c.dom.Element, String[]):
                    ALOAD_0     // Lorg/w3c/dom/Element; ele   (line 60)
                    LDC "Element must not be null"
                    INVOKESTATIC org.springframework.util.Assert.notNull (Ljava/lang/Object;Ljava/lang/String;)V
                    ALOAD_1     // [Ljava/lang/String; childEleNames   (line 61)
                    LDC "Element names collection must not be null"
                    INVOKESTATIC org.springframework.util.Assert.notNull (Ljava/lang/Object;Ljava/lang/String;)V
                    ALOAD_1     // [Ljava/lang/String; childEleNames   (line 62)
                    INVOKESTATIC java.util.Arrays.asList ([Ljava/lang/Object;)Ljava/util/List;
                    ASTORE_2
                    ALOAD_0     // Lorg/w3c/dom/Element; ele   (line 63)
                    INVOKEINTERFACE org.w3c.dom.Element.getChildNodes ()Lorg/w3c/dom/NodeList;
                    ASTORE_3
                    NEW java.util.ArrayList   (line 64)
                    DUP
                    INVOKESPECIAL java.util.ArrayList.<init> ()V
                    ASTORE 4
                    ICONST_0   (line 65)
                    ISTORE 5
                    GOTO L2
                L0: ALOAD_3     // Lorg/w3c/dom/NodeList; nl   (line 66)
                    ILOAD 5     // I i
                    INVOKEINTERFACE org.w3c.dom.NodeList.item (I)Lorg/w3c/dom/Node;
                    ASTORE 6
                    ALOAD 6     // Lorg/w3c/dom/Node; node   (line 67)
                    INSTANCEOF org.w3c.dom.Element
                    IFEQ L1
                    ALOAD 6     // Lorg/w3c/dom/Node; node
                    ALOAD_2     // Ljava/util/List; childEleNameList
                    INVOKESTATIC org.springframework.util.xml.DomUtils.nodeNameMatch (Lorg/w3c/dom/Node;Ljava/util/Collection;)Z
                    IFEQ L1
                    ALOAD 4     // Ljava/util/List; childEles   (line 68)
                    ALOAD 6     // Lorg/w3c/dom/Node; node
                    CHECKCAST org.w3c.dom.Element
                    INVOKEINTERFACE java.util.List.add (Ljava/lang/Object;)Z
                    POP
                L1: IINC 5 1     // I i   (line 65)
                L2: ILOAD 5     // I i
                    ALOAD_3     // Lorg/w3c/dom/NodeList; nl
                    INVOKEINTERFACE org.w3c.dom.NodeList.getLength ()I
                    IF_ICMPLT L0
                    ALOAD 4     // Ljava/util/List; childEles   (line 71)
                    ARETURN
  end public static java.util.List getChildElementsByTagName(org.w3c.dom.Element, String[])

  public static java.util.List getChildElementsByTagName(org.w3c.dom.Element, String):
                    ALOAD_0     // Lorg/w3c/dom/Element; ele   (line 86)
                    ICONST_1
                    ANEWARRAY java.lang.String
                    DUP
                    ICONST_0
                    ALOAD_1     // Ljava/lang/String; childEleName
                    AASTORE
                    INVOKESTATIC org.springframework.util.xml.DomUtils.getChildElementsByTagName (Lorg/w3c/dom/Element;[Ljava/lang/String;)Ljava/util/List;
                    ARETURN
  end public static java.util.List getChildElementsByTagName(org.w3c.dom.Element, String)

  public static org.w3c.dom.Element getChildElementByTagName(org.w3c.dom.Element, String):
                    ALOAD_0     // Lorg/w3c/dom/Element; ele   (line 97)
                    LDC "Element must not be null"
                    INVOKESTATIC org.springframework.util.Assert.notNull (Ljava/lang/Object;Ljava/lang/String;)V
                    ALOAD_1     // Ljava/lang/String; childEleName   (line 98)
                    LDC "Element name must not be null"
                    INVOKESTATIC org.springframework.util.Assert.notNull (Ljava/lang/Object;Ljava/lang/String;)V
                    ALOAD_0     // Lorg/w3c/dom/Element; ele   (line 99)
                    INVOKEINTERFACE org.w3c.dom.Element.getChildNodes ()Lorg/w3c/dom/NodeList;
                    ASTORE_2
                    ICONST_0   (line 100)
                    ISTORE_3
                    GOTO L2
                L0: ALOAD_2     // Lorg/w3c/dom/NodeList; nl   (line 101)
                    ILOAD_3     // I i
                    INVOKEINTERFACE org.w3c.dom.NodeList.item (I)Lorg/w3c/dom/Node;
                    ASTORE 4
                    ALOAD 4     // Lorg/w3c/dom/Node; node   (line 102)
                    INSTANCEOF org.w3c.dom.Element
                    IFEQ L1
                    ALOAD 4     // Lorg/w3c/dom/Node; node
                    ALOAD_1     // Ljava/lang/String; childEleName
                    INVOKESTATIC org.springframework.util.xml.DomUtils.nodeNameMatch (Lorg/w3c/dom/Node;Ljava/lang/String;)Z
                    IFEQ L1
                    ALOAD 4     // Lorg/w3c/dom/Node; node   (line 103)
                    CHECKCAST org.w3c.dom.Element
                    ARETURN
                L1: IINC_3 1     // I i   (line 100)
                L2: ILOAD_3     // I i
                    ALOAD_2     // Lorg/w3c/dom/NodeList; nl
                    INVOKEINTERFACE org.w3c.dom.NodeList.getLength ()I
                    IF_ICMPLT L0
                    ACONST_NULL   (line 106)
                    ARETURN
  end public static org.w3c.dom.Element getChildElementByTagName(org.w3c.dom.Element, String)

  public static String getChildElementValueByTagName(org.w3c.dom.Element, String):
                    ALOAD_0     // Lorg/w3c/dom/Element; ele   (line 117)
                    ALOAD_1     // Ljava/lang/String; childEleName
                    INVOKESTATIC org.springframework.util.xml.DomUtils.getChildElementByTagName (Lorg/w3c/dom/Element;Ljava/lang/String;)Lorg/w3c/dom/Element;
                    ASTORE_2
                    ALOAD_2     // Lorg/w3c/dom/Element; child   (line 118)
                    IFNULL L0
                    ALOAD_2     // Lorg/w3c/dom/Element; child
                    INVOKESTATIC org.springframework.util.xml.DomUtils.getTextValue (Lorg/w3c/dom/Element;)Ljava/lang/String;
                    GOTO L1
                L0: ACONST_NULL
                L1: ARETURN
  end public static String getChildElementValueByTagName(org.w3c.dom.Element, String)

  public static java.util.List getChildElements(org.w3c.dom.Element):
                    ALOAD_0     // Lorg/w3c/dom/Element; ele   (line 128)
                    LDC "Element must not be null"
                    INVOKESTATIC org.springframework.util.Assert.notNull (Ljava/lang/Object;Ljava/lang/String;)V
                    ALOAD_0     // Lorg/w3c/dom/Element; ele   (line 129)
                    INVOKEINTERFACE org.w3c.dom.Element.getChildNodes ()Lorg/w3c/dom/NodeList;
                    ASTORE_1
                    NEW java.util.ArrayList   (line 130)
                    DUP
                    INVOKESPECIAL java.util.ArrayList.<init> ()V
                    ASTORE_2
                    ICONST_0   (line 131)
                    ISTORE_3
                    GOTO L2
                L0: ALOAD_1     // Lorg/w3c/dom/NodeList; nl   (line 132)
                    ILOAD_3     // I i
                    INVOKEINTERFACE org.w3c.dom.NodeList.item (I)Lorg/w3c/dom/Node;
                    ASTORE 4
                    ALOAD 4     // Lorg/w3c/dom/Node; node   (line 133)
                    INSTANCEOF org.w3c.dom.Element
                    IFEQ L1
                    ALOAD_2     // Ljava/util/List; childEles   (line 134)
                    ALOAD 4     // Lorg/w3c/dom/Node; node
                    CHECKCAST org.w3c.dom.Element
                    INVOKEINTERFACE java.util.List.add (Ljava/lang/Object;)Z
                    POP
                L1: IINC_3 1     // I i   (line 131)
                L2: ILOAD_3     // I i
                    ALOAD_1     // Lorg/w3c/dom/NodeList; nl
                    INVOKEINTERFACE org.w3c.dom.NodeList.getLength ()I
                    IF_ICMPLT L0
                    ALOAD_2     // Ljava/util/List; childEles   (line 137)
                    ARETURN
  end public static java.util.List getChildElements(org.w3c.dom.Element)

  public static String getTextValue(org.w3c.dom.Element):
                    ALOAD_0     // Lorg/w3c/dom/Element; valueEle   (line 149)
                    LDC "Element must not be null"
                    INVOKESTATIC org.springframework.util.Assert.notNull (Ljava/lang/Object;Ljava/lang/String;)V
                    NEW java.lang.StringBuilder   (line 150)
                    DUP
                    INVOKESPECIAL java.lang.StringBuilder.<init> ()V
                    ASTORE_1
                    ALOAD_0     // Lorg/w3c/dom/Element; valueEle   (line 151)
                    INVOKEINTERFACE org.w3c.dom.Element.getChildNodes ()Lorg/w3c/dom/NodeList;
                    ASTORE_2
                    ICONST_0   (line 152)
                    ISTORE_3
                    GOTO L4
                L0: ALOAD_2     // Lorg/w3c/dom/NodeList; nl   (line 153)
                    ILOAD_3     // I i
                    INVOKEINTERFACE org.w3c.dom.NodeList.item (I)Lorg/w3c/dom/Node;
                    ASTORE 4
                    ALOAD 4     // Lorg/w3c/dom/Node; item   (line 154)
                    INSTANCEOF org.w3c.dom.CharacterData
                    IFEQ L1
                    ALOAD 4     // Lorg/w3c/dom/Node; item
                    INSTANCEOF org.w3c.dom.Comment
                    IFEQ L2
                L1: ALOAD 4     // Lorg/w3c/dom/Node; item
                    INSTANCEOF org.w3c.dom.EntityReference
                    IFEQ L3
                L2: ALOAD_1     // Ljava/lang/StringBuilder; sb   (line 155)
                    ALOAD 4     // Lorg/w3c/dom/Node; item
                    INVOKEINTERFACE org.w3c.dom.Node.getNodeValue ()Ljava/lang/String;
                    INVOKEVIRTUAL java.lang.StringBuilder.append (Ljava/lang/String;)Ljava/lang/StringBuilder;
                    POP
                L3: IINC_3 1     // I i   (line 152)
                L4: ILOAD_3     // I i
                    ALOAD_2     // Lorg/w3c/dom/NodeList; nl
                    INVOKEINTERFACE org.w3c.dom.NodeList.getLength ()I
                    IF_ICMPLT L0
                    ALOAD_1     // Ljava/lang/StringBuilder; sb   (line 158)
                    INVOKEVIRTUAL java.lang.StringBuilder.toString ()Ljava/lang/String;
                    ARETURN
  end public static String getTextValue(org.w3c.dom.Element)

  public static boolean nodeNameEquals(org.w3c.dom.Node, String):
                    ALOAD_0     // Lorg/w3c/dom/Node; node   (line 166)
                    LDC "Node must not be null"
                    INVOKESTATIC org.springframework.util.Assert.notNull (Ljava/lang/Object;Ljava/lang/String;)V
                    ALOAD_1     // Ljava/lang/String; desiredName   (line 167)
                    LDC "Desired name must not be null"
                    INVOKESTATIC org.springframework.util.Assert.notNull (Ljava/lang/Object;Ljava/lang/String;)V
                    ALOAD_0     // Lorg/w3c/dom/Node; node   (line 168)
                    ALOAD_1     // Ljava/lang/String; desiredName
                    INVOKESTATIC org.springframework.util.xml.DomUtils.nodeNameMatch (Lorg/w3c/dom/Node;Ljava/lang/String;)Z
                    IRETURN
  end public static boolean nodeNameEquals(org.w3c.dom.Node, String)

  public static org.xml.sax.ContentHandler createContentHandler(org.w3c.dom.Node):
                    NEW org.springframework.util.xml.DomContentHandler   (line 178)
                    DUP
                    ALOAD_0     // Lorg/w3c/dom/Node; node
                    INVOKESPECIAL org.springframework.util.xml.DomContentHandler.<init> (Lorg/w3c/dom/Node;)V
                    ARETURN
  end public static org.xml.sax.ContentHandler createContentHandler(org.w3c.dom.Node)

  private static boolean nodeNameMatch(org.w3c.dom.Node, String):
                    ALOAD_1     // Ljava/lang/String; desiredName   (line 183)
                    ALOAD_0     // Lorg/w3c/dom/Node; node
                    INVOKEINTERFACE org.w3c.dom.Node.getNodeName ()Ljava/lang/String;
                    INVOKEVIRTUAL java.lang.String.equals (Ljava/lang/Object;)Z
                    IFNE L0
                    ALOAD_1     // Ljava/lang/String; desiredName
                    ALOAD_0     // Lorg/w3c/dom/Node; node
                    INVOKEINTERFACE org.w3c.dom.Node.getLocalName ()Ljava/lang/String;
                    INVOKEVIRTUAL java.lang.String.equals (Ljava/lang/Object;)Z
                    IFNE L0
                    ICONST_0
                    IRETURN
                L0: ICONST_1
                    IRETURN
  end private static boolean nodeNameMatch(org.w3c.dom.Node, String)

  private static boolean nodeNameMatch(org.w3c.dom.Node, java.util.Collection):
                    ALOAD_1     // Ljava/util/Collection; desiredNames   (line 188)
                    ALOAD_0     // Lorg/w3c/dom/Node; node
                    INVOKEINTERFACE org.w3c.dom.Node.getNodeName ()Ljava/lang/String;
                    INVOKEINTERFACE java.util.Collection.contains (Ljava/lang/Object;)Z
                    IFNE L0
                    ALOAD_1     // Ljava/util/Collection; desiredNames
                    ALOAD_0     // Lorg/w3c/dom/Node; node
                    INVOKEINTERFACE org.w3c.dom.Node.getLocalName ()Ljava/lang/String;
                    INVOKEINTERFACE java.util.Collection.contains (Ljava/lang/Object;)Z
                    IFNE L0
                    ICONST_0
                    IRETURN
                L0: ICONST_1
                    IRETURN
  end private static boolean nodeNameMatch(org.w3c.dom.Node, java.util.Collection)

end public abstract class org.springframework.util.xml.DomUtils
 -- (NullPointerException) null
null
java.lang.NullPointerException

org.aspectj.bridge.AbortException: trouble in: 
public abstract class org.springframework.util.xml.DomUtils extends java.lang.Object:
  public void <init>():
                    ALOAD_0     // Lorg/springframework/util/xml/DomUtils; this   (line 46)
                    INVOKESPECIAL java.lang.Object.<init> ()V
    constructor-execution(void org.springframework.util.xml.DomUtils.<init>())
    |               RETURN
    constructor-execution(void org.springframework.util.xml.DomUtils.<init>())
  end public void <init>()

  public static java.util.List getChildElementsByTagName(org.w3c.dom.Element, String[]):
                    ALOAD_0     // Lorg/w3c/dom/Element; ele   (line 60)
                    LDC "Element must not be null"
                    INVOKESTATIC org.springframework.util.Assert.notNull (Ljava/lang/Object;Ljava/lang/String;)V
                    ALOAD_1     // [Ljava/lang/String; childEleNames   (line 61)
                    LDC "Element names collection must not be null"
                    INVOKESTATIC org.springframework.util.Assert.notNull (Ljava/lang/Object;Ljava/lang/String;)V
                    ALOAD_1     // [Ljava/lang/String; childEleNames   (line 62)
                    INVOKESTATIC java.util.Arrays.asList ([Ljava/lang/Object;)Ljava/util/List;
                    ASTORE_2
                    ALOAD_0     // Lorg/w3c/dom/Element; ele   (line 63)
                    INVOKEINTERFACE org.w3c.dom.Element.getChildNodes ()Lorg/w3c/dom/NodeList;
                    ASTORE_3
                    NEW java.util.ArrayList   (line 64)
                    DUP
                    INVOKESPECIAL java.util.ArrayList.<init> ()V
                    ASTORE 4
                    ICONST_0   (line 65)
                    ISTORE 5
                    GOTO L2
                L0: ALOAD_3     // Lorg/w3c/dom/NodeList; nl   (line 66)
                    ILOAD 5     // I i
                    INVOKEINTERFACE org.w3c.dom.NodeList.item (I)Lorg/w3c/dom/Node;
                    ASTORE 6
                    ALOAD 6     // Lorg/w3c/dom/Node; node   (line 67)
                    INSTANCEOF org.w3c.dom.Element
                    IFEQ L1
                    ALOAD 6     // Lorg/w3c/dom/Node; node
                    ALOAD_2     // Ljava/util/List; childEleNameList
                    INVOKESTATIC org.springframework.util.xml.DomUtils.nodeNameMatch (Lorg/w3c/dom/Node;Ljava/util/Collection;)Z
                    IFEQ L1
                    ALOAD 4     // Ljava/util/List; childEles   (line 68)
                    ALOAD 6     // Lorg/w3c/dom/Node; node
                    CHECKCAST org.w3c.dom.Element
                    INVOKEINTERFACE java.util.List.add (Ljava/lang/Object;)Z
                    POP
                L1: IINC 5 1     // I i   (line 65)
                L2: ILOAD 5     // I i
                    ALOAD_3     // Lorg/w3c/dom/NodeList; nl
                    INVOKEINTERFACE org.w3c.dom.NodeList.getLength ()I
                    IF_ICMPLT L0
                    ALOAD 4     // Ljava/util/List; childEles   (line 71)
                    ARETURN
  end public static java.util.List getChildElementsByTagName(org.w3c.dom.Element, String[])

  public static java.util.List getChildElementsByTagName(org.w3c.dom.Element, String):
                    ALOAD_0     // Lorg/w3c/dom/Element; ele   (line 86)
                    ICONST_1
                    ANEWARRAY java.lang.String
                    DUP
                    ICONST_0
                    ALOAD_1     // Ljava/lang/String; childEleName
                    AASTORE
                    INVOKESTATIC org.springframework.util.xml.DomUtils.getChildElementsByTagName (Lorg/w3c/dom/Element;[Ljava/lang/String;)Ljava/util/List;
                    ARETURN
  end public static java.util.List getChildElementsByTagName(org.w3c.dom.Element, String)

  public static org.w3c.dom.Element getChildElementByTagName(org.w3c.dom.Element, String):
                    ALOAD_0     // Lorg/w3c/dom/Element; ele   (line 97)
                    LDC "Element must not be null"
                    INVOKESTATIC org.springframework.util.Assert.notNull (Ljava/lang/Object;Ljava/lang/String;)V
                    ALOAD_1     // Ljava/lang/String; childEleName   (line 98)
                    LDC "Element name must not be null"
                    INVOKESTATIC org.springframework.util.Assert.notNull (Ljava/lang/Object;Ljava/lang/String;)V
                    ALOAD_0     // Lorg/w3c/dom/Element; ele   (line 99)
                    INVOKEINTERFACE org.w3c.dom.Element.getChildNodes ()Lorg/w3c/dom/NodeList;
                    ASTORE_2
                    ICONST_0   (line 100)
                    ISTORE_3
                    GOTO L2
                L0: ALOAD_2     // Lorg/w3c/dom/NodeList; nl   (line 101)
                    ILOAD_3     // I i
                    INVOKEINTERFACE org.w3c.dom.NodeList.item (I)Lorg/w3c/dom/Node;
                    ASTORE 4
                    ALOAD 4     // Lorg/w3c/dom/Node; node   (line 102)
                    INSTANCEOF org.w3c.dom.Element
                    IFEQ L1
                    ALOAD 4     // Lorg/w3c/dom/Node; node
                    ALOAD_1     // Ljava/lang/String; childEleName
                    INVOKESTATIC org.springframework.util.xml.DomUtils.nodeNameMatch (Lorg/w3c/dom/Node;Ljava/lang/String;)Z
                    IFEQ L1
                    ALOAD 4     // Lorg/w3c/dom/Node; node   (line 103)
                    CHECKCAST org.w3c.dom.Element
                    ARETURN
                L1: IINC_3 1     // I i   (line 100)
                L2: ILOAD_3     // I i
                    ALOAD_2     // Lorg/w3c/dom/NodeList; nl
                    INVOKEINTERFACE org.w3c.dom.NodeList.getLength ()I
                    IF_ICMPLT L0
                    ACONST_NULL   (line 106)
                    ARETURN
  end public static org.w3c.dom.Element getChildElementByTagName(org.w3c.dom.Element, String)

  public static String getChildElementValueByTagName(org.w3c.dom.Element, String):
                    ALOAD_0     // Lorg/w3c/dom/Element; ele   (line 117)
                    ALOAD_1     // Ljava/lang/String; childEleName
                    INVOKESTATIC org.springframework.util.xml.DomUtils.getChildElementByTagName (Lorg/w3c/dom/Element;Ljava/lang/String;)Lorg/w3c/dom/Element;
                    ASTORE_2
                    ALOAD_2     // Lorg/w3c/dom/Element; child   (line 118)
                    IFNULL L0
                    ALOAD_2     // Lorg/w3c/dom/Element; child
                    INVOKESTATIC org.springframework.util.xml.DomUtils.getTextValue (Lorg/w3c/dom/Element;)Ljava/lang/String;
                    GOTO L1
                L0: ACONST_NULL
                L1: ARETURN
  end public static String getChildElementValueByTagName(org.w3c.dom.Element, String)

  public static java.util.List getChildElements(org.w3c.dom.Element):
                    ALOAD_0     // Lorg/w3c/dom/Element; ele   (line 128)
                    LDC "Element must not be null"
                    INVOKESTATIC org.springframework.util.Assert.notNull (Ljava/lang/Object;Ljava/lang/String;)V
                    ALOAD_0     // Lorg/w3c/dom/Element; ele   (line 129)
                    INVOKEINTERFACE org.w3c.dom.Element.getChildNodes ()Lorg/w3c/dom/NodeList;
                    ASTORE_1
                    NEW java.util.ArrayList   (line 130)
                    DUP
                    INVOKESPECIAL java.util.ArrayList.<init> ()V
                    ASTORE_2
                    ICONST_0   (line 131)
                    ISTORE_3
                    GOTO L2
                L0: ALOAD_1     // Lorg/w3c/dom/NodeList; nl   (line 132)
                    ILOAD_3     // I i
                    INVOKEINTERFACE org.w3c.dom.NodeList.item (I)Lorg/w3c/dom/Node;
                    ASTORE 4
                    ALOAD 4     // Lorg/w3c/dom/Node; node   (line 133)
                    INSTANCEOF org.w3c.dom.Element
                    IFEQ L1
                    ALOAD_2     // Ljava/util/List; childEles   (line 134)
                    ALOAD 4     // Lorg/w3c/dom/Node; node
                    CHECKCAST org.w3c.dom.Element
                    INVOKEINTERFACE java.util.List.add (Ljava/lang/Object;)Z
                    POP
                L1: IINC_3 1     // I i   (line 131)
                L2: ILOAD_3     // I i
                    ALOAD_1     // Lorg/w3c/dom/NodeList; nl
                    INVOKEINTERFACE org.w3c.dom.NodeList.getLength ()I
                    IF_ICMPLT L0
                    ALOAD_2     // Ljava/util/List; childEles   (line 137)
                    ARETURN
  end public static java.util.List getChildElements(org.w3c.dom.Element)

  public static String getTextValue(org.w3c.dom.Element):
                    ALOAD_0     // Lorg/w3c/dom/Element; valueEle   (line 149)
                    LDC "Element must not be null"
                    INVOKESTATIC org.springframework.util.Assert.notNull (Ljava/lang/Object;Ljava/lang/String;)V
                    NEW java.lang.StringBuilder   (line 150)
                    DUP
                    INVOKESPECIAL java.lang.StringBuilder.<init> ()V
                    ASTORE_1
                    ALOAD_0     // Lorg/w3c/dom/Element; valueEle   (line 151)
                    INVOKEINTERFACE org.w3c.dom.Element.getChildNodes ()Lorg/w3c/dom/NodeList;
                    ASTORE_2
                    ICONST_0   (line 152)
                    ISTORE_3
                    GOTO L4
                L0: ALOAD_2     // Lorg/w3c/dom/NodeList; nl   (line 153)
                    ILOAD_3     // I i
                    INVOKEINTERFACE org.w3c.dom.NodeList.item (I)Lorg/w3c/dom/Node;
                    ASTORE 4
                    ALOAD 4     // Lorg/w3c/dom/Node; item   (line 154)
                    INSTANCEOF org.w3c.dom.CharacterData
                    IFEQ L1
                    ALOAD 4     // Lorg/w3c/dom/Node; item
                    INSTANCEOF org.w3c.dom.Comment
                    IFEQ L2
                L1: ALOAD 4     // Lorg/w3c/dom/Node; item
                    INSTANCEOF org.w3c.dom.EntityReference
                    IFEQ L3
                L2: ALOAD_1     // Ljava/lang/StringBuilder; sb   (line 155)
                    ALOAD 4     // Lorg/w3c/dom/Node; item
                    INVOKEINTERFACE org.w3c.dom.Node.getNodeValue ()Ljava/lang/String;
                    INVOKEVIRTUAL java.lang.StringBuilder.append (Ljava/lang/String;)Ljava/lang/StringBuilder;
                    POP
                L3: IINC_3 1     // I i   (line 152)
                L4: ILOAD_3     // I i
                    ALOAD_2     // Lorg/w3c/dom/NodeList; nl
                    INVOKEINTERFACE org.w3c.dom.NodeList.getLength ()I
                    IF_ICMPLT L0
                    ALOAD_1     // Ljava/lang/StringBuilder; sb   (line 158)
                    INVOKEVIRTUAL java.lang.StringBuilder.toString ()Ljava/lang/String;
                    ARETURN
  end public static String getTextValue(org.w3c.dom.Element)

  public static boolean nodeNameEquals(org.w3c.dom.Node, String):
                    ALOAD_0     // Lorg/w3c/dom/Node; node   (line 166)
                    LDC "Node must not be null"
                    INVOKESTATIC org.springframework.util.Assert.notNull (Ljava/lang/Object;Ljava/lang/String;)V
                    ALOAD_1     // Ljava/lang/String; desiredName   (line 167)
                    LDC "Desired name must not be null"
                    INVOKESTATIC org.springframework.util.Assert.notNull (Ljava/lang/Object;Ljava/lang/String;)V
                    ALOAD_0     // Lorg/w3c/dom/Node; node   (line 168)
                    ALOAD_1     // Ljava/lang/String; desiredName
                    INVOKESTATIC org.springframework.util.xml.DomUtils.nodeNameMatch (Lorg/w3c/dom/Node;Ljava/lang/String;)Z
                    IRETURN
  end public static boolean nodeNameEquals(org.w3c.dom.Node, String)

  public static org.xml.sax.ContentHandler createContentHandler(org.w3c.dom.Node):
                    NEW org.springframework.util.xml.DomContentHandler   (line 178)
                    DUP
                    ALOAD_0     // Lorg/w3c/dom/Node; node
                    INVOKESPECIAL org.springframework.util.xml.DomContentHandler.<init> (Lorg/w3c/dom/Node;)V
                    ARETURN
  end public static org.xml.sax.ContentHandler createContentHandler(org.w3c.dom.Node)

  private static boolean nodeNameMatch(org.w3c.dom.Node, String):
                    ALOAD_1     // Ljava/lang/String; desiredName   (line 183)
                    ALOAD_0     // Lorg/w3c/dom/Node; node
                    INVOKEINTERFACE org.w3c.dom.Node.getNodeName ()Ljava/lang/String;
                    INVOKEVIRTUAL java.lang.String.equals (Ljava/lang/Object;)Z
                    IFNE L0
                    ALOAD_1     // Ljava/lang/String; desiredName
                    ALOAD_0     // Lorg/w3c/dom/Node; node
                    INVOKEINTERFACE org.w3c.dom.Node.getLocalName ()Ljava/lang/String;
                    INVOKEVIRTUAL java.lang.String.equals (Ljava/lang/Object;)Z
                    IFNE L0
                    ICONST_0
                    IRETURN
                L0: ICONST_1
                    IRETURN
  end private static boolean nodeNameMatch(org.w3c.dom.Node, String)

  private static boolean nodeNameMatch(org.w3c.dom.Node, java.util.Collection):
                    ALOAD_1     // Ljava/util/Collection; desiredNames   (line 188)
                    ALOAD_0     // Lorg/w3c/dom/Node; node
                    INVOKEINTERFACE org.w3c.dom.Node.getNodeName ()Ljava/lang/String;
                    INVOKEINTERFACE java.util.Collection.contains (Ljava/lang/Object;)Z
                    IFNE L0
                    ALOAD_1     // Ljava/util/Collection; desiredNames
                    ALOAD_0     // Lorg/w3c/dom/Node; node
                    INVOKEINTERFACE org.w3c.dom.Node.getLocalName ()Ljava/lang/String;
                    INVOKEINTERFACE java.util.Collection.contains (Ljava/lang/Object;)Z
                    IFNE L0
                    ICONST_0
                    IRETURN
                L0: ICONST_1
                    IRETURN
  end private static boolean nodeNameMatch(org.w3c.dom.Node, java.util.Collection)

end public abstract class org.springframework.util.xml.DomUtils

	at org.aspectj.bridge.MessageWriter.handleMessage(MessageWriter.java:47)
	at org.aspectj.weaver.tools.WeavingAdaptor$WeavingAdaptorMessageWriter.handleMessage(WeavingAdaptor.java:737)
	at org.aspectj.weaver.tools.WeavingAdaptor$WeavingAdaptorMessageHolder.handleMessage(WeavingAdaptor.java:682)
	at org.aspectj.weaver.bcel.BcelWeaver.weave(BcelWeaver.java:1712)
	at org.aspectj.weaver.bcel.BcelWeaver.weaveWithoutDump(BcelWeaver.java:1631)
	at org.aspectj.weaver.bcel.BcelWeaver.weaveAndNotify(BcelWeaver.java:1394)
	at org.aspectj.weaver.bcel.BcelWeaver.weave(BcelWeaver.java:1180)
	at org.aspectj.weaver.tools.WeavingAdaptor.getWovenBytes(WeavingAdaptor.java:467)
	at org.aspectj.weaver.tools.WeavingAdaptor.weaveClass(WeavingAdaptor.java:318)
	at org.aspectj.weaver.loadtime.Aj.preProcess(Aj.java:96)
	at org.aspectj.weaver.loadtime.ClassPreProcessorAgentAdapter.transform(ClassPreProcessorAgentAdapter.java:54)
	at sun.instrument.TransformerManager.transform(TransformerManager.java:188)
	at sun.instrument.InstrumentationImpl.transform(InstrumentationImpl.java:428)
	at java.lang.ClassLoader.defineClass1(Native Method)
	at java.lang.ClassLoader.defineClass(ClassLoader.java:760)
	at java.security.SecureClassLoader.defineClass(SecureClassLoader.java:142)
	at java.net.URLClassLoader.defineClass(URLClassLoader.java:467)
	at java.net.URLClassLoader.access$100(URLClassLoader.java:73)
	at java.net.URLClassLoader$1.run(URLClassLoader.java:368)
	at java.net.URLClassLoader$1.run(URLClassLoader.java:362)
	at java.security.AccessController.doPrivileged(Native Method)
	at java.net.URLClassLoader.findClass(URLClassLoader.java:361)
	at java.lang.ClassLoader.loadClass(ClassLoader.java:424)
	at sun.misc.Launcher$AppClassLoader.loadClass(Launcher.java:331)
	at java.lang.ClassLoader.loadClass(ClassLoader.java:357)
	at org.springframework.beans.factory.xml.BeanDefinitionParserDelegate.parseBeanDefinitionElement(BeanDefinitionParserDelegate.java:475)
	at org.springframework.beans.factory.xml.BeanDefinitionParserDelegate.parseBeanDefinitionElement(BeanDefinitionParserDelegate.java:396)
	at org.springframework.beans.factory.xml.BeanDefinitionParserDelegate.parseBeanDefinitionElement(BeanDefinitionParserDelegate.java:365)
	at org.springframework.beans.factory.xml.DefaultBeanDefinitionDocumentReader.processBeanDefinition(DefaultBeanDefinitionDocumentReader.java:258)
	at org.springframework.beans.factory.xml.DefaultBeanDefinitionDocumentReader.parseDefaultElement(DefaultBeanDefinitionDocumentReader.java:153)
	at org.springframework.beans.factory.xml.DefaultBeanDefinitionDocumentReader.parseBeanDefinitions(DefaultBeanDefinitionDocumentReader.java:132)
	at org.springframework.beans.factory.xml.DefaultBeanDefinitionDocumentReader.registerBeanDefinitions(DefaultBeanDefinitionDocumentReader.java:93)
	at org.springframework.beans.factory.xml.XmlBeanDefinitionReader.registerBeanDefinitions(XmlBeanDefinitionReader.java:493)
	at org.springframework.beans.factory.xml.XmlBeanDefinitionReader.doLoadBeanDefinitions(XmlBeanDefinitionReader.java:390)
	at org.springframework.beans.factory.xml.XmlBeanDefinitionReader.loadBeanDefinitions(XmlBeanDefinitionReader.java:334)
	at org.springframework.beans.factory.xml.XmlBeanDefinitionReader.loadBeanDefinitions(XmlBeanDefinitionReader.java:302)
	at org.springframework.beans.factory.support.AbstractBeanDefinitionReader.loadBeanDefinitions(AbstractBeanDefinitionReader.java:143)
	at org.springframework.beans.factory.support.AbstractBeanDefinitionReader.loadBeanDefinitions(AbstractBeanDefinitionReader.java:178)
	at org.springframework.beans.factory.support.AbstractBeanDefinitionReader.loadBeanDefinitions(AbstractBeanDefinitionReader.java:149)
	at org.springframework.beans.factory.support.AbstractBeanDefinitionReader.loadBeanDefinitions(AbstractBeanDefinitionReader.java:212)
	at org.springframework.context.support.AbstractXmlApplicationContext.loadBeanDefinitions(AbstractXmlApplicationContext.java:126)
	at org.springframework.context.support.AbstractXmlApplicationContext.loadBeanDefinitions(AbstractXmlApplicationContext.java:92)
	at org.springframework.context.support.AbstractRefreshableApplicationContext.refreshBeanFactory(AbstractRefreshableApplicationContext.java:130)
	at org.springframework.context.support.AbstractApplicationContext.obtainFreshBeanFactory(AbstractApplicationContext.java:467)
	at org.springframework.context.support.AbstractApplicationContext.refresh(AbstractApplicationContext.java:397)
	at org.springframework.context.support.ClassPathXmlApplicationContext.<init>(ClassPathXmlApplicationContext.java:139)
	at org.springframework.context.support.ClassPathXmlApplicationContext.<init>(ClassPathXmlApplicationContext.java:83)
	at foo.ConfigureApp.main(ConfigureApp.java:9)
---- System Properties ---
java.runtime.name=Java(TM) SE Runtime Environment
sun.boot.library.path=C:\Program Files\Java\jdk1.8.0_45\jre\bin
java.vm.version=25.45-b02
java.vm.vendor=Oracle Corporation
java.vendor.url=http://java.oracle.com/
path.separator=;
java.vm.name=Java HotSpot(TM) 64-Bit Server VM
file.encoding.pkg=sun.io
user.country=US
user.script=
sun.java.launcher=SUN_STANDARD
sun.os.patch.level=
java.vm.specification.name=Java Virtual Machine Specification
user.dir=E:\Eclipse Latest\SpringChap3.3
java.runtime.version=1.8.0_45-b15
java.awt.graphicsenv=sun.awt.Win32GraphicsEnvironment
java.endorsed.dirs=C:\Program Files\Java\jdk1.8.0_45\jre\lib\endorsed
os.arch=amd64
java.io.tmpdir=C:\Users\SANJUS~1\AppData\Local\Temp\
line.separator=

java.vm.specification.vendor=Oracle Corporation
user.variant=
os.name=Windows 7
sun.jnu.encoding=Cp1252
java.library.path=C:\Program Files\Java\jdk1.8.0_45\bin;C:\Windows\Sun\Java\bin;C:\Windows\system32;C:\Windows;C:/Program Files/Java/jdk1.8.0_45/bin/../jre/bin/server;C:/Program Files/Java/jdk1.8.0_45/bin/../jre/bin;C:/Program Files/Java/jdk1.8.0_45/bin/../jre/lib/amd64;C:\oraclexe\app\oracle\product\10.2.0\server\bin;C:\Program Files\Java\jdk1.8.0_45\bin;C:\Program Files (x86)\Java\jre1.8.0_45\bin;C:\ProgramData\Oracle\Java\javapath;C:\Windows\system32;C:\Windows;C:\Windows\System32\Wbem;C:\Windows\System32\WindowsPowerShell\v1.0\;C:\Python27;;E:\Eclipse Latest\eclipse-jee-luna-SR2-win32-x86_64\eclipse;;.
java.specification.name=Java Platform API Specification
java.class.version=52.0
sun.management.compiler=HotSpot 64-Bit Tiered Compilers
os.version=6.1
user.home=C:\Users\sanju singh
user.timezone=Asia/Calcutta
java.awt.printerjob=sun.awt.windows.WPrinterJob
file.encoding=Cp1252
java.specification.version=1.8
java.class.path=E:\Eclipse Latest\SpringChap3.3\bin;E:\Eclipse Latest\SpringJar\extra Jar\aopalliance-1.0.jar;E:\Eclipse Latest\SpringJar\extra Jar\asm-3.3.1.jar;E:\Eclipse Latest\SpringJar\extra Jar\aspectjrt-1.6.11.jar;E:\Eclipse Latest\SpringJar\extra Jar\aspectjweaver-1.6.11.jar;E:\Eclipse Latest\SpringJar\extra Jar\cglib-2.2.2.jar;E:\Eclipse Latest\SpringJar\extra Jar\commons-logging-1.1.1.jar;E:\Eclipse Latest\SpringJar\extra Jar\junit-4.8.2.jar;E:\Eclipse Latest\SpringJar\extra Jar\spring-aop-3.0.5.RELEASE.jar;E:\Eclipse Latest\SpringJar\extra Jar\spring-asm-3.0.5.RELEASE.jar;E:\Eclipse Latest\SpringJar\extra Jar\spring-beans-3.0.5.RELEASE.jar;E:\Eclipse Latest\SpringJar\extra Jar\spring-context-3.0.5.RELEASE.jar;E:\Eclipse Latest\SpringJar\extra Jar\spring-core-3.0.5.RELEASE.jar;E:\Eclipse Latest\SpringJar\extra Jar\spring-expression-3.0.5.RELEASE.jar;E:\Eclipse Latest\SpringJar\spring-aspects-4.1.6.RELEASE.jar;E:\TestJar\aspectjweaver-1.6.11.jar
user.name=sanju singh
java.vm.specification.version=1.8
sun.java.command=foo.ConfigureApp
java.home=C:\Program Files\Java\jdk1.8.0_45\jre
sun.arch.data.model=64
user.language=en
java.specification.vendor=Oracle Corporation
awt.toolkit=sun.awt.windows.WToolkit
java.vm.info=mixed mode
java.version=1.8.0_45
java.ext.dirs=C:\Program Files\Java\jdk1.8.0_45\jre\lib\ext;C:\Windows\Sun\Java\lib\ext
sun.boot.class.path=C:\Program Files\Java\jdk1.8.0_45\jre\lib\resources.jar;C:\Program Files\Java\jdk1.8.0_45\jre\lib\rt.jar;C:\Program Files\Java\jdk1.8.0_45\jre\lib\sunrsasign.jar;C:\Program Files\Java\jdk1.8.0_45\jre\lib\jsse.jar;C:\Program Files\Java\jdk1.8.0_45\jre\lib\jce.jar;C:\Program Files\Java\jdk1.8.0_45\jre\lib\charsets.jar;C:\Program Files\Java\jdk1.8.0_45\jre\lib\jfr.jar;C:\Program Files\Java\jdk1.8.0_45\jre\classes
java.vendor=Oracle Corporation
file.separator=\
java.vendor.url.bug=http://bugreport.sun.com/bugreport/
sun.io.unicode.encoding=UnicodeLittle
sun.cpu.endian=little
sun.desktop=windows
sun.cpu.isalist=amd64
---- Command Line ---
Empty
---- Full Classpath ---
Empty
---- Compiler Messages ---
Empty
