---- AspectJ Properties ---
AspectJ Compiler 1.6.11 built on Tuesday Mar 15, 2011 at 15:31:04 GMT
---- Dump Properties ---
Dump file: ajcore.20150913.181500.195.txt
Dump reason: org.aspectj.bridge.AbortException
Dump on exception: true
Dump at exit condition: abort
---- Exception Information ---
Message: abort trouble in: 
public class org.springframework.context.support.DelegatingMessageSource extends org.springframework.context.support.MessageSourceSupport implements org.springframework.context.HierarchicalMessageSource:
  private org.springframework.context.MessageSource parentMessageSource
  public void <init>():
                    ALOAD_0     // Lorg/springframework/context/support/DelegatingMessageSource; this   (line 37)
                    INVOKESPECIAL org.springframework.context.support.MessageSourceSupport.<init> ()V
    constructor-execution(void org.springframework.context.support.DelegatingMessageSource.<init>())
    |               RETURN
    constructor-execution(void org.springframework.context.support.DelegatingMessageSource.<init>())
  end public void <init>()

  public void setParentMessageSource(org.springframework.context.MessageSource):
                    ALOAD_0     // Lorg/springframework/context/support/DelegatingMessageSource; this   (line 43)
                    ALOAD_1     // Lorg/springframework/context/MessageSource; parent
                    PUTFIELD org.springframework.context.support.DelegatingMessageSource.parentMessageSource Lorg/springframework/context/MessageSource;
                    RETURN   (line 44)
  end public void setParentMessageSource(org.springframework.context.MessageSource)

  public org.springframework.context.MessageSource getParentMessageSource():
                    ALOAD_0     // Lorg/springframework/context/support/DelegatingMessageSource; this   (line 47)
                    GETFIELD org.springframework.context.support.DelegatingMessageSource.parentMessageSource Lorg/springframework/context/MessageSource;
                    ARETURN
  end public org.springframework.context.MessageSource getParentMessageSource()

  public String getMessage(String, Object[], String, java.util.Locale):
                    ALOAD_0     // Lorg/springframework/context/support/DelegatingMessageSource; this   (line 52)
                    GETFIELD org.springframework.context.support.DelegatingMessageSource.parentMessageSource Lorg/springframework/context/MessageSource;
                    IFNULL L0
                    ALOAD_0     // Lorg/springframework/context/support/DelegatingMessageSource; this   (line 53)
                    GETFIELD org.springframework.context.support.DelegatingMessageSource.parentMessageSource Lorg/springframework/context/MessageSource;
                    ALOAD_1     // Ljava/lang/String; code
                    ALOAD_2     // [Ljava/lang/Object; args
                    ALOAD_3     // Ljava/lang/String; defaultMessage
                    ALOAD 4     // Ljava/util/Locale; locale
                    INVOKEINTERFACE org.springframework.context.MessageSource.getMessage (Ljava/lang/String;[Ljava/lang/Object;Ljava/lang/String;Ljava/util/Locale;)Ljava/lang/String;
                    ARETURN
                L0: ALOAD_0     // Lorg/springframework/context/support/DelegatingMessageSource; this   (line 56)
                    ALOAD_3     // Ljava/lang/String; defaultMessage
                    ALOAD_2     // [Ljava/lang/Object; args
                    ALOAD 4     // Ljava/util/Locale; locale
                    INVOKEVIRTUAL org.springframework.context.support.DelegatingMessageSource.renderDefaultMessage (Ljava/lang/String;[Ljava/lang/Object;Ljava/util/Locale;)Ljava/lang/String;
                    ARETURN
  end public String getMessage(String, Object[], String, java.util.Locale)

  public String getMessage(String, Object[], java.util.Locale) throws org.springframework.context.NoSuchMessageException:
                    ALOAD_0     // Lorg/springframework/context/support/DelegatingMessageSource; this   (line 61)
                    GETFIELD org.springframework.context.support.DelegatingMessageSource.parentMessageSource Lorg/springframework/context/MessageSource;
                    IFNULL L0
                    ALOAD_0     // Lorg/springframework/context/support/DelegatingMessageSource; this   (line 62)
                    GETFIELD org.springframework.context.support.DelegatingMessageSource.parentMessageSource Lorg/springframework/context/MessageSource;
                    ALOAD_1     // Ljava/lang/String; code
                    ALOAD_2     // [Ljava/lang/Object; args
                    ALOAD_3     // Ljava/util/Locale; locale
                    INVOKEINTERFACE org.springframework.context.MessageSource.getMessage (Ljava/lang/String;[Ljava/lang/Object;Ljava/util/Locale;)Ljava/lang/String;
                    ARETURN
                L0: NEW org.springframework.context.NoSuchMessageException   (line 65)
                    DUP
                    ALOAD_1     // Ljava/lang/String; code
                    ALOAD_3     // Ljava/util/Locale; locale
                    INVOKESPECIAL org.springframework.context.NoSuchMessageException.<init> (Ljava/lang/String;Ljava/util/Locale;)V
                    ATHROW
  end public String getMessage(String, Object[], java.util.Locale) throws org.springframework.context.NoSuchMessageException

  public String getMessage(org.springframework.context.MessageSourceResolvable, java.util.Locale) throws org.springframework.context.NoSuchMessageException:
                    ALOAD_0     // Lorg/springframework/context/support/DelegatingMessageSource; this   (line 70)
                    GETFIELD org.springframework.context.support.DelegatingMessageSource.parentMessageSource Lorg/springframework/context/MessageSource;
                    IFNULL L0
                    ALOAD_0     // Lorg/springframework/context/support/DelegatingMessageSource; this   (line 71)
                    GETFIELD org.springframework.context.support.DelegatingMessageSource.parentMessageSource Lorg/springframework/context/MessageSource;
                    ALOAD_1     // Lorg/springframework/context/MessageSourceResolvable; resolvable
                    ALOAD_2     // Ljava/util/Locale; locale
                    INVOKEINTERFACE org.springframework.context.MessageSource.getMessage (Lorg/springframework/context/MessageSourceResolvable;Ljava/util/Locale;)Ljava/lang/String;
                    ARETURN
                L0: ALOAD_1     // Lorg/springframework/context/MessageSourceResolvable; resolvable   (line 74)
                    INVOKEINTERFACE org.springframework.context.MessageSourceResolvable.getDefaultMessage ()Ljava/lang/String;
                    IFNULL L1
                    ALOAD_0     // Lorg/springframework/context/support/DelegatingMessageSource; this   (line 75)
                    ALOAD_1     // Lorg/springframework/context/MessageSourceResolvable; resolvable
                    INVOKEINTERFACE org.springframework.context.MessageSourceResolvable.getDefaultMessage ()Ljava/lang/String;
                    ALOAD_1     // Lorg/springframework/context/MessageSourceResolvable; resolvable
                    INVOKEINTERFACE org.springframework.context.MessageSourceResolvable.getArguments ()[Ljava/lang/Object;
                    ALOAD_2     // Ljava/util/Locale; locale
                    INVOKEVIRTUAL org.springframework.context.support.DelegatingMessageSource.renderDefaultMessage (Ljava/lang/String;[Ljava/lang/Object;Ljava/util/Locale;)Ljava/lang/String;
                    ARETURN
                L1: ALOAD_1     // Lorg/springframework/context/MessageSourceResolvable; resolvable   (line 77)
                    INVOKEINTERFACE org.springframework.context.MessageSourceResolvable.getCodes ()[Ljava/lang/String;
                    ASTORE_3
                    ALOAD_3     // [Ljava/lang/String; codes   (line 78)
                    IFNULL L2
                    ALOAD_3     // [Ljava/lang/String; codes
                    ARRAYLENGTH
                    IFLE L2
                    ALOAD_3     // [Ljava/lang/String; codes
                    ICONST_0
                    AALOAD
                    GOTO L3
                L2: ACONST_NULL
                L3: ASTORE 4
                    NEW org.springframework.context.NoSuchMessageException   (line 79)
                    DUP
                    ALOAD 4     // Ljava/lang/String; code
                    ALOAD_2     // Ljava/util/Locale; locale
                    INVOKESPECIAL org.springframework.context.NoSuchMessageException.<init> (Ljava/lang/String;Ljava/util/Locale;)V
                    ATHROW
  end public String getMessage(org.springframework.context.MessageSourceResolvable, java.util.Locale) throws org.springframework.context.NoSuchMessageException

end public class org.springframework.context.support.DelegatingMessageSource
 -- (NullPointerException) null
null
java.lang.NullPointerException

org.aspectj.bridge.AbortException: trouble in: 
public class org.springframework.context.support.DelegatingMessageSource extends org.springframework.context.support.MessageSourceSupport implements org.springframework.context.HierarchicalMessageSource:
  private org.springframework.context.MessageSource parentMessageSource
  public void <init>():
                    ALOAD_0     // Lorg/springframework/context/support/DelegatingMessageSource; this   (line 37)
                    INVOKESPECIAL org.springframework.context.support.MessageSourceSupport.<init> ()V
    constructor-execution(void org.springframework.context.support.DelegatingMessageSource.<init>())
    |               RETURN
    constructor-execution(void org.springframework.context.support.DelegatingMessageSource.<init>())
  end public void <init>()

  public void setParentMessageSource(org.springframework.context.MessageSource):
                    ALOAD_0     // Lorg/springframework/context/support/DelegatingMessageSource; this   (line 43)
                    ALOAD_1     // Lorg/springframework/context/MessageSource; parent
                    PUTFIELD org.springframework.context.support.DelegatingMessageSource.parentMessageSource Lorg/springframework/context/MessageSource;
                    RETURN   (line 44)
  end public void setParentMessageSource(org.springframework.context.MessageSource)

  public org.springframework.context.MessageSource getParentMessageSource():
                    ALOAD_0     // Lorg/springframework/context/support/DelegatingMessageSource; this   (line 47)
                    GETFIELD org.springframework.context.support.DelegatingMessageSource.parentMessageSource Lorg/springframework/context/MessageSource;
                    ARETURN
  end public org.springframework.context.MessageSource getParentMessageSource()

  public String getMessage(String, Object[], String, java.util.Locale):
                    ALOAD_0     // Lorg/springframework/context/support/DelegatingMessageSource; this   (line 52)
                    GETFIELD org.springframework.context.support.DelegatingMessageSource.parentMessageSource Lorg/springframework/context/MessageSource;
                    IFNULL L0
                    ALOAD_0     // Lorg/springframework/context/support/DelegatingMessageSource; this   (line 53)
                    GETFIELD org.springframework.context.support.DelegatingMessageSource.parentMessageSource Lorg/springframework/context/MessageSource;
                    ALOAD_1     // Ljava/lang/String; code
                    ALOAD_2     // [Ljava/lang/Object; args
                    ALOAD_3     // Ljava/lang/String; defaultMessage
                    ALOAD 4     // Ljava/util/Locale; locale
                    INVOKEINTERFACE org.springframework.context.MessageSource.getMessage (Ljava/lang/String;[Ljava/lang/Object;Ljava/lang/String;Ljava/util/Locale;)Ljava/lang/String;
                    ARETURN
                L0: ALOAD_0     // Lorg/springframework/context/support/DelegatingMessageSource; this   (line 56)
                    ALOAD_3     // Ljava/lang/String; defaultMessage
                    ALOAD_2     // [Ljava/lang/Object; args
                    ALOAD 4     // Ljava/util/Locale; locale
                    INVOKEVIRTUAL org.springframework.context.support.DelegatingMessageSource.renderDefaultMessage (Ljava/lang/String;[Ljava/lang/Object;Ljava/util/Locale;)Ljava/lang/String;
                    ARETURN
  end public String getMessage(String, Object[], String, java.util.Locale)

  public String getMessage(String, Object[], java.util.Locale) throws org.springframework.context.NoSuchMessageException:
                    ALOAD_0     // Lorg/springframework/context/support/DelegatingMessageSource; this   (line 61)
                    GETFIELD org.springframework.context.support.DelegatingMessageSource.parentMessageSource Lorg/springframework/context/MessageSource;
                    IFNULL L0
                    ALOAD_0     // Lorg/springframework/context/support/DelegatingMessageSource; this   (line 62)
                    GETFIELD org.springframework.context.support.DelegatingMessageSource.parentMessageSource Lorg/springframework/context/MessageSource;
                    ALOAD_1     // Ljava/lang/String; code
                    ALOAD_2     // [Ljava/lang/Object; args
                    ALOAD_3     // Ljava/util/Locale; locale
                    INVOKEINTERFACE org.springframework.context.MessageSource.getMessage (Ljava/lang/String;[Ljava/lang/Object;Ljava/util/Locale;)Ljava/lang/String;
                    ARETURN
                L0: NEW org.springframework.context.NoSuchMessageException   (line 65)
                    DUP
                    ALOAD_1     // Ljava/lang/String; code
                    ALOAD_3     // Ljava/util/Locale; locale
                    INVOKESPECIAL org.springframework.context.NoSuchMessageException.<init> (Ljava/lang/String;Ljava/util/Locale;)V
                    ATHROW
  end public String getMessage(String, Object[], java.util.Locale) throws org.springframework.context.NoSuchMessageException

  public String getMessage(org.springframework.context.MessageSourceResolvable, java.util.Locale) throws org.springframework.context.NoSuchMessageException:
                    ALOAD_0     // Lorg/springframework/context/support/DelegatingMessageSource; this   (line 70)
                    GETFIELD org.springframework.context.support.DelegatingMessageSource.parentMessageSource Lorg/springframework/context/MessageSource;
                    IFNULL L0
                    ALOAD_0     // Lorg/springframework/context/support/DelegatingMessageSource; this   (line 71)
                    GETFIELD org.springframework.context.support.DelegatingMessageSource.parentMessageSource Lorg/springframework/context/MessageSource;
                    ALOAD_1     // Lorg/springframework/context/MessageSourceResolvable; resolvable
                    ALOAD_2     // Ljava/util/Locale; locale
                    INVOKEINTERFACE org.springframework.context.MessageSource.getMessage (Lorg/springframework/context/MessageSourceResolvable;Ljava/util/Locale;)Ljava/lang/String;
                    ARETURN
                L0: ALOAD_1     // Lorg/springframework/context/MessageSourceResolvable; resolvable   (line 74)
                    INVOKEINTERFACE org.springframework.context.MessageSourceResolvable.getDefaultMessage ()Ljava/lang/String;
                    IFNULL L1
                    ALOAD_0     // Lorg/springframework/context/support/DelegatingMessageSource; this   (line 75)
                    ALOAD_1     // Lorg/springframework/context/MessageSourceResolvable; resolvable
                    INVOKEINTERFACE org.springframework.context.MessageSourceResolvable.getDefaultMessage ()Ljava/lang/String;
                    ALOAD_1     // Lorg/springframework/context/MessageSourceResolvable; resolvable
                    INVOKEINTERFACE org.springframework.context.MessageSourceResolvable.getArguments ()[Ljava/lang/Object;
                    ALOAD_2     // Ljava/util/Locale; locale
                    INVOKEVIRTUAL org.springframework.context.support.DelegatingMessageSource.renderDefaultMessage (Ljava/lang/String;[Ljava/lang/Object;Ljava/util/Locale;)Ljava/lang/String;
                    ARETURN
                L1: ALOAD_1     // Lorg/springframework/context/MessageSourceResolvable; resolvable   (line 77)
                    INVOKEINTERFACE org.springframework.context.MessageSourceResolvable.getCodes ()[Ljava/lang/String;
                    ASTORE_3
                    ALOAD_3     // [Ljava/lang/String; codes   (line 78)
                    IFNULL L2
                    ALOAD_3     // [Ljava/lang/String; codes
                    ARRAYLENGTH
                    IFLE L2
                    ALOAD_3     // [Ljava/lang/String; codes
                    ICONST_0
                    AALOAD
                    GOTO L3
                L2: ACONST_NULL
                L3: ASTORE 4
                    NEW org.springframework.context.NoSuchMessageException   (line 79)
                    DUP
                    ALOAD 4     // Ljava/lang/String; code
                    ALOAD_2     // Ljava/util/Locale; locale
                    INVOKESPECIAL org.springframework.context.NoSuchMessageException.<init> (Ljava/lang/String;Ljava/util/Locale;)V
                    ATHROW
  end public String getMessage(org.springframework.context.MessageSourceResolvable, java.util.Locale) throws org.springframework.context.NoSuchMessageException

end public class org.springframework.context.support.DelegatingMessageSource

	at org.aspectj.bridge.MessageWriter.handleMessage(MessageWriter.java:47)
	at org.aspectj.weaver.tools.WeavingAdaptor$WeavingAdaptorMessageWriter.handleMessage(WeavingAdaptor.java:737)
	at org.aspectj.weaver.tools.WeavingAdaptor$WeavingAdaptorMessageHolder.handleMessage(WeavingAdaptor.java:682)
	at org.aspectj.weaver.bcel.BcelWeaver.weave(BcelWeaver.java:1712)
	at org.aspectj.weaver.bcel.BcelWeaver.weaveWithoutDump(BcelWeaver.java:1631)
	at org.aspectj.weaver.bcel.BcelWeaver.weaveAndNotify(BcelWeaver.java:1394)
	at org.aspectj.weaver.bcel.BcelWeaver.weave(BcelWeaver.java:1180)
	at org.aspectj.weaver.tools.WeavingAdaptor.getWovenBytes(WeavingAdaptor.java:467)
	at org.aspectj.weaver.tools.WeavingAdaptor.weaveClass(WeavingAdaptor.java:318)
	at org.aspectj.weaver.loadtime.Aj.preProcess(Aj.java:96)
	at org.aspectj.weaver.loadtime.ClassPreProcessorAgentAdapter.transform(ClassPreProcessorAgentAdapter.java:54)
	at sun.instrument.TransformerManager.transform(TransformerManager.java:188)
	at sun.instrument.InstrumentationImpl.transform(InstrumentationImpl.java:428)
	at java.lang.ClassLoader.defineClass1(Native Method)
	at java.lang.ClassLoader.defineClass(ClassLoader.java:760)
	at java.security.SecureClassLoader.defineClass(SecureClassLoader.java:142)
	at java.net.URLClassLoader.defineClass(URLClassLoader.java:467)
	at java.net.URLClassLoader.access$100(URLClassLoader.java:73)
	at java.net.URLClassLoader$1.run(URLClassLoader.java:368)
	at java.net.URLClassLoader$1.run(URLClassLoader.java:362)
	at java.security.AccessController.doPrivileged(Native Method)
	at java.net.URLClassLoader.findClass(URLClassLoader.java:361)
	at java.lang.ClassLoader.loadClass(ClassLoader.java:424)
	at sun.misc.Launcher$AppClassLoader.loadClass(Launcher.java:331)
	at java.lang.ClassLoader.loadClass(ClassLoader.java:357)
	at org.springframework.context.support.AbstractApplicationContext.initMessageSource(AbstractApplicationContext.java:771)
	at org.springframework.context.support.AbstractApplicationContext.refresh(AbstractApplicationContext.java:413)
	at org.springframework.context.support.ClassPathXmlApplicationContext.<init>(ClassPathXmlApplicationContext.java:139)
	at org.springframework.context.support.ClassPathXmlApplicationContext.<init>(ClassPathXmlApplicationContext.java:83)
	at foo.ConfigureApp.main(ConfigureApp.java:9)
---- System Properties ---
java.runtime.name=Java(TM) SE Runtime Environment
sun.boot.library.path=C:\Program Files\Java\jdk1.8.0_45\jre\bin
java.vm.version=25.45-b02
java.vm.vendor=Oracle Corporation
java.vendor.url=http://java.oracle.com/
path.separator=;
java.vm.name=Java HotSpot(TM) 64-Bit Server VM
file.encoding.pkg=sun.io
user.country=US
user.script=
sun.java.launcher=SUN_STANDARD
sun.os.patch.level=
java.vm.specification.name=Java Virtual Machine Specification
user.dir=E:\Eclipse Latest\SpringChap3.3
java.runtime.version=1.8.0_45-b15
java.awt.graphicsenv=sun.awt.Win32GraphicsEnvironment
java.endorsed.dirs=C:\Program Files\Java\jdk1.8.0_45\jre\lib\endorsed
os.arch=amd64
java.io.tmpdir=C:\Users\SANJUS~1\AppData\Local\Temp\
line.separator=

java.vm.specification.vendor=Oracle Corporation
user.variant=
os.name=Windows 7
sun.jnu.encoding=Cp1252
java.library.path=C:\Program Files\Java\jdk1.8.0_45\bin;C:\Windows\Sun\Java\bin;C:\Windows\system32;C:\Windows;C:/Program Files/Java/jdk1.8.0_45/bin/../jre/bin/server;C:/Program Files/Java/jdk1.8.0_45/bin/../jre/bin;C:/Program Files/Java/jdk1.8.0_45/bin/../jre/lib/amd64;C:\oraclexe\app\oracle\product\10.2.0\server\bin;C:\Program Files\Java\jdk1.8.0_45\bin;C:\Program Files (x86)\Java\jre1.8.0_45\bin;C:\ProgramData\Oracle\Java\javapath;C:\Windows\system32;C:\Windows;C:\Windows\System32\Wbem;C:\Windows\System32\WindowsPowerShell\v1.0\;C:\Python27;;E:\Eclipse Latest\eclipse-jee-luna-SR2-win32-x86_64\eclipse;;.
java.specification.name=Java Platform API Specification
java.class.version=52.0
sun.management.compiler=HotSpot 64-Bit Tiered Compilers
os.version=6.1
user.home=C:\Users\sanju singh
user.timezone=Asia/Calcutta
java.awt.printerjob=sun.awt.windows.WPrinterJob
file.encoding=Cp1252
java.specification.version=1.8
java.class.path=E:\Eclipse Latest\SpringChap3.3\bin;E:\Eclipse Latest\SpringJar\extra Jar\aopalliance-1.0.jar;E:\Eclipse Latest\SpringJar\extra Jar\asm-3.3.1.jar;E:\Eclipse Latest\SpringJar\extra Jar\aspectjrt-1.6.11.jar;E:\Eclipse Latest\SpringJar\extra Jar\aspectjweaver-1.6.11.jar;E:\Eclipse Latest\SpringJar\extra Jar\cglib-2.2.2.jar;E:\Eclipse Latest\SpringJar\extra Jar\commons-logging-1.1.1.jar;E:\Eclipse Latest\SpringJar\extra Jar\junit-4.8.2.jar;E:\Eclipse Latest\SpringJar\extra Jar\spring-aop-3.0.5.RELEASE.jar;E:\Eclipse Latest\SpringJar\extra Jar\spring-asm-3.0.5.RELEASE.jar;E:\Eclipse Latest\SpringJar\extra Jar\spring-beans-3.0.5.RELEASE.jar;E:\Eclipse Latest\SpringJar\extra Jar\spring-context-3.0.5.RELEASE.jar;E:\Eclipse Latest\SpringJar\extra Jar\spring-core-3.0.5.RELEASE.jar;E:\Eclipse Latest\SpringJar\extra Jar\spring-expression-3.0.5.RELEASE.jar;E:\Eclipse Latest\SpringJar\spring-aspects-4.1.6.RELEASE.jar;E:\TestJar\aspectjweaver-1.6.11.jar
user.name=sanju singh
java.vm.specification.version=1.8
sun.java.command=foo.ConfigureApp
java.home=C:\Program Files\Java\jdk1.8.0_45\jre
sun.arch.data.model=64
user.language=en
java.specification.vendor=Oracle Corporation
awt.toolkit=sun.awt.windows.WToolkit
java.vm.info=mixed mode
java.version=1.8.0_45
java.ext.dirs=C:\Program Files\Java\jdk1.8.0_45\jre\lib\ext;C:\Windows\Sun\Java\lib\ext
sun.boot.class.path=C:\Program Files\Java\jdk1.8.0_45\jre\lib\resources.jar;C:\Program Files\Java\jdk1.8.0_45\jre\lib\rt.jar;C:\Program Files\Java\jdk1.8.0_45\jre\lib\sunrsasign.jar;C:\Program Files\Java\jdk1.8.0_45\jre\lib\jsse.jar;C:\Program Files\Java\jdk1.8.0_45\jre\lib\jce.jar;C:\Program Files\Java\jdk1.8.0_45\jre\lib\charsets.jar;C:\Program Files\Java\jdk1.8.0_45\jre\lib\jfr.jar;C:\Program Files\Java\jdk1.8.0_45\jre\classes
java.vendor=Oracle Corporation
file.separator=\
java.vendor.url.bug=http://bugreport.sun.com/bugreport/
sun.io.unicode.encoding=UnicodeLittle
sun.cpu.endian=little
sun.desktop=windows
sun.cpu.isalist=amd64
---- Command Line ---
Empty
---- Full Classpath ---
Empty
---- Compiler Messages ---
Empty
