---- AspectJ Properties ---
AspectJ Compiler 1.6.11 built on Tuesday Mar 15, 2011 at 15:31:04 GMT
---- Dump Properties ---
Dump file: ajcore.20150913.181456.601.txt
Dump reason: abort
Dump on exception: true
Dump at exit condition: abort
---- System Properties ---
java.runtime.name=Java(TM) SE Runtime Environment
sun.boot.library.path=C:\Program Files\Java\jdk1.8.0_45\jre\bin
java.vm.version=25.45-b02
java.vm.vendor=Oracle Corporation
java.vendor.url=http://java.oracle.com/
path.separator=;
java.vm.name=Java HotSpot(TM) 64-Bit Server VM
file.encoding.pkg=sun.io
user.country=US
user.script=
sun.java.launcher=SUN_STANDARD
sun.os.patch.level=
java.vm.specification.name=Java Virtual Machine Specification
user.dir=E:\Eclipse Latest\SpringChap3.3
java.runtime.version=1.8.0_45-b15
java.awt.graphicsenv=sun.awt.Win32GraphicsEnvironment
java.endorsed.dirs=C:\Program Files\Java\jdk1.8.0_45\jre\lib\endorsed
os.arch=amd64
java.io.tmpdir=C:\Users\SANJUS~1\AppData\Local\Temp\
line.separator=

java.vm.specification.vendor=Oracle Corporation
user.variant=
os.name=Windows 7
sun.jnu.encoding=Cp1252
java.library.path=C:\Program Files\Java\jdk1.8.0_45\bin;C:\Windows\Sun\Java\bin;C:\Windows\system32;C:\Windows;C:/Program Files/Java/jdk1.8.0_45/bin/../jre/bin/server;C:/Program Files/Java/jdk1.8.0_45/bin/../jre/bin;C:/Program Files/Java/jdk1.8.0_45/bin/../jre/lib/amd64;C:\oraclexe\app\oracle\product\10.2.0\server\bin;C:\Program Files\Java\jdk1.8.0_45\bin;C:\Program Files (x86)\Java\jre1.8.0_45\bin;C:\ProgramData\Oracle\Java\javapath;C:\Windows\system32;C:\Windows;C:\Windows\System32\Wbem;C:\Windows\System32\WindowsPowerShell\v1.0\;C:\Python27;;E:\Eclipse Latest\eclipse-jee-luna-SR2-win32-x86_64\eclipse;;.
java.specification.name=Java Platform API Specification
java.class.version=52.0
sun.management.compiler=HotSpot 64-Bit Tiered Compilers
os.version=6.1
user.home=C:\Users\sanju singh
user.timezone=Asia/Calcutta
java.awt.printerjob=sun.awt.windows.WPrinterJob
file.encoding=Cp1252
java.specification.version=1.8
java.class.path=E:\Eclipse Latest\SpringChap3.3\bin;E:\Eclipse Latest\SpringJar\extra Jar\aopalliance-1.0.jar;E:\Eclipse Latest\SpringJar\extra Jar\asm-3.3.1.jar;E:\Eclipse Latest\SpringJar\extra Jar\aspectjrt-1.6.11.jar;E:\Eclipse Latest\SpringJar\extra Jar\aspectjweaver-1.6.11.jar;E:\Eclipse Latest\SpringJar\extra Jar\cglib-2.2.2.jar;E:\Eclipse Latest\SpringJar\extra Jar\commons-logging-1.1.1.jar;E:\Eclipse Latest\SpringJar\extra Jar\junit-4.8.2.jar;E:\Eclipse Latest\SpringJar\extra Jar\spring-aop-3.0.5.RELEASE.jar;E:\Eclipse Latest\SpringJar\extra Jar\spring-asm-3.0.5.RELEASE.jar;E:\Eclipse Latest\SpringJar\extra Jar\spring-beans-3.0.5.RELEASE.jar;E:\Eclipse Latest\SpringJar\extra Jar\spring-context-3.0.5.RELEASE.jar;E:\Eclipse Latest\SpringJar\extra Jar\spring-core-3.0.5.RELEASE.jar;E:\Eclipse Latest\SpringJar\extra Jar\spring-expression-3.0.5.RELEASE.jar;E:\Eclipse Latest\SpringJar\spring-aspects-4.1.6.RELEASE.jar;E:\TestJar\aspectjweaver-1.6.11.jar
user.name=sanju singh
java.vm.specification.version=1.8
sun.java.command=foo.ConfigureApp
java.home=C:\Program Files\Java\jdk1.8.0_45\jre
sun.arch.data.model=64
user.language=en
java.specification.vendor=Oracle Corporation
awt.toolkit=sun.awt.windows.WToolkit
java.vm.info=mixed mode
java.version=1.8.0_45
java.ext.dirs=C:\Program Files\Java\jdk1.8.0_45\jre\lib\ext;C:\Windows\Sun\Java\lib\ext
sun.boot.class.path=C:\Program Files\Java\jdk1.8.0_45\jre\lib\resources.jar;C:\Program Files\Java\jdk1.8.0_45\jre\lib\rt.jar;C:\Program Files\Java\jdk1.8.0_45\jre\lib\sunrsasign.jar;C:\Program Files\Java\jdk1.8.0_45\jre\lib\jsse.jar;C:\Program Files\Java\jdk1.8.0_45\jre\lib\jce.jar;C:\Program Files\Java\jdk1.8.0_45\jre\lib\charsets.jar;C:\Program Files\Java\jdk1.8.0_45\jre\lib\jfr.jar;C:\Program Files\Java\jdk1.8.0_45\jre\classes
java.vendor=Oracle Corporation
file.separator=\
java.vendor.url.bug=http://bugreport.sun.com/bugreport/
sun.io.unicode.encoding=UnicodeLittle
sun.cpu.endian=little
sun.desktop=windows
sun.cpu.isalist=amd64
---- Command Line ---
Empty
---- Full Classpath ---
Empty
---- Compiler Messages ---
info AspectJ Weaver Version 1.6.11 built on Tuesday Mar 15, 2011 at 15:31:04 GMT
info register classloader sun.misc.Launcher$AppClassLoader@14dad5dc
info using configuration file:/E:/Eclipse%20Latest/SpringJar/spring-aspects-4.1.6.RELEASE.jar!/META-INF/aop.xml
error can't determine annotations of missing type org.springframework.cache.annotation.CachePut
when weaving type org.springframework.beans.factory.xml.DelegatingEntityResolver
when weaving classes 
when weaving 
 [Xlint:cantFindType]
error can't determine annotations of missing type org.springframework.cache.annotation.Cacheable
when weaving type org.springframework.beans.factory.xml.DelegatingEntityResolver
when weaving classes 
when weaving 
 [Xlint:cantFindType]
error can't determine annotations of missing type org.springframework.cache.annotation.CacheEvict
when weaving type org.springframework.beans.factory.xml.DelegatingEntityResolver
when weaving classes 
when weaving 
 [Xlint:cantFindType]
error can't determine annotations of missing type org.springframework.cache.annotation.Caching
when weaving type org.springframework.beans.factory.xml.DelegatingEntityResolver
when weaving classes 
when weaving 
 [Xlint:cantFindType]
error can't determine annotations of missing type org.springframework.transaction.annotation.Transactional
when weaving type org.springframework.beans.factory.xml.DelegatingEntityResolver
when weaving classes 
when weaving 
 [Xlint:cantFindType]
abort trouble in: 
public class org.springframework.beans.factory.xml.DelegatingEntityResolver extends java.lang.Object implements org.xml.sax.EntityResolver:
  public static final String DTD_SUFFIX = ".dtd"
  public static final String XSD_SUFFIX = ".xsd"
  private final org.xml.sax.EntityResolver dtdResolver
  private final org.xml.sax.EntityResolver schemaResolver
  public void <init>(ClassLoader):
                    ALOAD_0     // Lorg/springframework/beans/factory/xml/DelegatingEntityResolver; this   (line 60)
                    INVOKESPECIAL java.lang.Object.<init> ()V
    constructor-execution(void org.springframework.beans.factory.xml.DelegatingEntityResolver.<init>(java.lang.ClassLoader))
    |               ALOAD_0     // Lorg/springframework/beans/factory/xml/DelegatingEntityResolver; this   (line 61)
    |               NEW org.springframework.beans.factory.xml.BeansDtdResolver
    |               DUP
    |               INVOKESPECIAL org.springframework.beans.factory.xml.BeansDtdResolver.<init> ()V
    |               PUTFIELD org.springframework.beans.factory.xml.DelegatingEntityResolver.dtdResolver Lorg/xml/sax/EntityResolver;
    |               ALOAD_0     // Lorg/springframework/beans/factory/xml/DelegatingEntityResolver; this   (line 62)
    |               NEW org.springframework.beans.factory.xml.PluggableSchemaResolver
    |               DUP
    |               ALOAD_1     // Ljava/lang/ClassLoader; classLoader
    |               INVOKESPECIAL org.springframework.beans.factory.xml.PluggableSchemaResolver.<init> (Ljava/lang/ClassLoader;)V
    |               PUTFIELD org.springframework.beans.factory.xml.DelegatingEntityResolver.schemaResolver Lorg/xml/sax/EntityResolver;
    |               RETURN   (line 63)
    constructor-execution(void org.springframework.beans.factory.xml.DelegatingEntityResolver.<init>(java.lang.ClassLoader))
  end public void <init>(ClassLoader)

  public void <init>(org.xml.sax.EntityResolver, org.xml.sax.EntityResolver):
                    ALOAD_0     // Lorg/springframework/beans/factory/xml/DelegatingEntityResolver; this   (line 71)
                    INVOKESPECIAL java.lang.Object.<init> ()V
    constructor-execution(void org.springframework.beans.factory.xml.DelegatingEntityResolver.<init>(org.xml.sax.EntityResolver, org.xml.sax.EntityResolver))
    |               ALOAD_1     // Lorg/xml/sax/EntityResolver; dtdResolver   (line 72)
    |               LDC "'dtdResolver' is required"
    |               INVOKESTATIC org.springframework.util.Assert.notNull (Ljava/lang/Object;Ljava/lang/String;)V
    |               ALOAD_2     // Lorg/xml/sax/EntityResolver; schemaResolver   (line 73)
    |               LDC "'schemaResolver' is required"
    |               INVOKESTATIC org.springframework.util.Assert.notNull (Ljava/lang/Object;Ljava/lang/String;)V
    |               ALOAD_0     // Lorg/springframework/beans/factory/xml/DelegatingEntityResolver; this   (line 74)
    |               ALOAD_1     // Lorg/xml/sax/EntityResolver; dtdResolver
    |               PUTFIELD org.springframework.beans.factory.xml.DelegatingEntityResolver.dtdResolver Lorg/xml/sax/EntityResolver;
    |               ALOAD_0     // Lorg/springframework/beans/factory/xml/DelegatingEntityResolver; this   (line 75)
    |               ALOAD_2     // Lorg/xml/sax/EntityResolver; schemaResolver
    |               PUTFIELD org.springframework.beans.factory.xml.DelegatingEntityResolver.schemaResolver Lorg/xml/sax/EntityResolver;
    |               RETURN   (line 76)
    constructor-execution(void org.springframework.beans.factory.xml.DelegatingEntityResolver.<init>(org.xml.sax.EntityResolver, org.xml.sax.EntityResolver))
  end public void <init>(org.xml.sax.EntityResolver, org.xml.sax.EntityResolver)

  public org.xml.sax.InputSource resolveEntity(String, String) throws org.xml.sax.SAXException, java.io.IOException:
                    ALOAD_2     // Ljava/lang/String; systemId   (line 80)
                    IFNULL L1
                    ALOAD_2     // Ljava/lang/String; systemId   (line 81)
                    LDC ".dtd"
                    INVOKEVIRTUAL java.lang.String.endsWith (Ljava/lang/String;)Z
                    IFEQ L0
                    ALOAD_0     // Lorg/springframework/beans/factory/xml/DelegatingEntityResolver; this   (line 82)
                    GETFIELD org.springframework.beans.factory.xml.DelegatingEntityResolver.dtdResolver Lorg/xml/sax/EntityResolver;
                    ALOAD_1     // Ljava/lang/String; publicId
                    ALOAD_2     // Ljava/lang/String; systemId
                    INVOKEINTERFACE org.xml.sax.EntityResolver.resolveEntity (Ljava/lang/String;Ljava/lang/String;)Lorg/xml/sax/InputSource;
                    ARETURN
                L0: ALOAD_2     // Ljava/lang/String; systemId   (line 84)
                    LDC ".xsd"
                    INVOKEVIRTUAL java.lang.String.endsWith (Ljava/lang/String;)Z
                    IFEQ L1
                    ALOAD_0     // Lorg/springframework/beans/factory/xml/DelegatingEntityResolver; this   (line 85)
                    GETFIELD org.springframework.beans.factory.xml.DelegatingEntityResolver.schemaResolver Lorg/xml/sax/EntityResolver;
                    ALOAD_1     // Ljava/lang/String; publicId
                    ALOAD_2     // Ljava/lang/String; systemId
                    INVOKEINTERFACE org.xml.sax.EntityResolver.resolveEntity (Ljava/lang/String;Ljava/lang/String;)Lorg/xml/sax/InputSource;
                    ARETURN
                L1: ACONST_NULL   (line 88)
                    ARETURN
  end public org.xml.sax.InputSource resolveEntity(String, String) throws org.xml.sax.SAXException, java.io.IOException

  public String toString():
                    NEW java.lang.StringBuilder   (line 94)
                    DUP
                    LDC "EntityResolver delegating .xsd to "
                    INVOKESPECIAL java.lang.StringBuilder.<init> (Ljava/lang/String;)V
                    ALOAD_0     // Lorg/springframework/beans/factory/xml/DelegatingEntityResolver; this
                    GETFIELD org.springframework.beans.factory.xml.DelegatingEntityResolver.schemaResolver Lorg/xml/sax/EntityResolver;
                    INVOKEVIRTUAL java.lang.StringBuilder.append (Ljava/lang/Object;)Ljava/lang/StringBuilder;
                    LDC " and "   (line 95)
                    INVOKEVIRTUAL java.lang.StringBuilder.append (Ljava/lang/String;)Ljava/lang/StringBuilder;
                    LDC ".dtd"
                    INVOKEVIRTUAL java.lang.StringBuilder.append (Ljava/lang/String;)Ljava/lang/StringBuilder;
                    LDC " to "
                    INVOKEVIRTUAL java.lang.StringBuilder.append (Ljava/lang/String;)Ljava/lang/StringBuilder;
                    ALOAD_0     // Lorg/springframework/beans/factory/xml/DelegatingEntityResolver; this
                    GETFIELD org.springframework.beans.factory.xml.DelegatingEntityResolver.dtdResolver Lorg/xml/sax/EntityResolver;
                    INVOKEVIRTUAL java.lang.StringBuilder.append (Ljava/lang/Object;)Ljava/lang/StringBuilder;
                    INVOKEVIRTUAL java.lang.StringBuilder.toString ()Ljava/lang/String;   (line 94)
                    ARETURN
  end public String toString()

end public class org.springframework.beans.factory.xml.DelegatingEntityResolver
 -- (NullPointerException) null
null
java.lang.NullPointerException
	at org.aspectj.weaver.UnresolvedType.forSignature(UnresolvedType.java:361)
	at org.aspectj.weaver.bcel.BcelObjectType.getDeclaredInterfaces(BcelObjectType.java:275)
	at org.aspectj.weaver.ReferenceType.getDeclaredInterfaces(ReferenceType.java:624)
	at org.aspectj.weaver.ResolvedType.getDirectSupertypes(ResolvedType.java:76)
	at org.aspectj.weaver.patterns.TypePattern.matchesSubtypes(TypePattern.java:178)
	at org.aspectj.weaver.patterns.ExactTypePattern.matchesSubtypes(ExactTypePattern.java:74)
	at org.aspectj.weaver.patterns.TypePattern.matchesStatically(TypePattern.java:130)
	at org.aspectj.weaver.patterns.OrTypePattern.matchesStatically(OrTypePattern.java:76)
	at org.aspectj.weaver.patterns.SignaturePattern.matchesExactlyMethod(SignaturePattern.java:505)
	at org.aspectj.weaver.patterns.SignaturePattern.matchesExactly(SignaturePattern.java:360)
	at org.aspectj.weaver.patterns.SignaturePattern.matches(SignaturePattern.java:320)
	at org.aspectj.weaver.patterns.KindedPointcut.matchInternal(KindedPointcut.java:202)
	at org.aspectj.weaver.patterns.Pointcut.match(Pointcut.java:137)
	at org.aspectj.weaver.patterns.AndPointcut.matchInternal(AndPointcut.java:51)
	at org.aspectj.weaver.patterns.Pointcut.match(Pointcut.java:137)
	at org.aspectj.weaver.patterns.OrPointcut.matchInternal(OrPointcut.java:54)
	at org.aspectj.weaver.patterns.Pointcut.match(Pointcut.java:137)
	at org.aspectj.weaver.ShadowMunger.match(ShadowMunger.java:113)
	at org.aspectj.weaver.Advice.match(Advice.java:109)
	at org.aspectj.weaver.bcel.BcelAdvice.match(BcelAdvice.java:149)
	at org.aspectj.weaver.bcel.BcelClassWeaver.match(BcelClassWeaver.java:3116)
	at org.aspectj.weaver.bcel.BcelClassWeaver.match(BcelClassWeaver.java:2550)
	at org.aspectj.weaver.bcel.BcelClassWeaver.weave(BcelClassWeaver.java:474)
	at org.aspectj.weaver.bcel.BcelClassWeaver.weave(BcelClassWeaver.java:100)
	at org.aspectj.weaver.bcel.BcelWeaver.weave(BcelWeaver.java:1687)
	at org.aspectj.weaver.bcel.BcelWeaver.weaveWithoutDump(BcelWeaver.java:1631)
	at org.aspectj.weaver.bcel.BcelWeaver.weaveAndNotify(BcelWeaver.java:1394)
	at org.aspectj.weaver.bcel.BcelWeaver.weave(BcelWeaver.java:1180)
	at org.aspectj.weaver.tools.WeavingAdaptor.getWovenBytes(WeavingAdaptor.java:467)
	at org.aspectj.weaver.tools.WeavingAdaptor.weaveClass(WeavingAdaptor.java:318)
	at org.aspectj.weaver.loadtime.Aj.preProcess(Aj.java:96)
	at org.aspectj.weaver.loadtime.ClassPreProcessorAgentAdapter.transform(ClassPreProcessorAgentAdapter.java:54)
	at sun.instrument.TransformerManager.transform(TransformerManager.java:188)
	at sun.instrument.InstrumentationImpl.transform(InstrumentationImpl.java:428)
	at java.lang.ClassLoader.defineClass1(Native Method)
	at java.lang.ClassLoader.defineClass(ClassLoader.java:760)
	at java.security.SecureClassLoader.defineClass(SecureClassLoader.java:142)
	at java.net.URLClassLoader.defineClass(URLClassLoader.java:467)
	at java.net.URLClassLoader.access$100(URLClassLoader.java:73)
	at java.net.URLClassLoader$1.run(URLClassLoader.java:368)
	at java.net.URLClassLoader$1.run(URLClassLoader.java:362)
	at java.security.AccessController.doPrivileged(Native Method)
	at java.net.URLClassLoader.findClass(URLClassLoader.java:361)
	at java.lang.ClassLoader.loadClass(ClassLoader.java:424)
	at sun.misc.Launcher$AppClassLoader.loadClass(Launcher.java:331)
	at java.lang.ClassLoader.loadClass(ClassLoader.java:357)
	at java.lang.ClassLoader.defineClass1(Native Method)
	at java.lang.ClassLoader.defineClass(ClassLoader.java:760)
	at java.security.SecureClassLoader.defineClass(SecureClassLoader.java:142)
	at java.net.URLClassLoader.defineClass(URLClassLoader.java:467)
	at java.net.URLClassLoader.access$100(URLClassLoader.java:73)
	at java.net.URLClassLoader$1.run(URLClassLoader.java:368)
	at java.net.URLClassLoader$1.run(URLClassLoader.java:362)
	at java.security.AccessController.doPrivileged(Native Method)
	at java.net.URLClassLoader.findClass(URLClassLoader.java:361)
	at java.lang.ClassLoader.loadClass(ClassLoader.java:424)
	at sun.misc.Launcher$AppClassLoader.loadClass(Launcher.java:331)
	at java.lang.ClassLoader.loadClass(ClassLoader.java:357)
	at org.springframework.context.support.AbstractXmlApplicationContext.loadBeanDefinitions(AbstractXmlApplicationContext.java:87)
	at org.springframework.context.support.AbstractRefreshableApplicationContext.refreshBeanFactory(AbstractRefreshableApplicationContext.java:130)
	at org.springframework.context.support.AbstractApplicationContext.obtainFreshBeanFactory(AbstractApplicationContext.java:467)
	at org.springframework.context.support.AbstractApplicationContext.refresh(AbstractApplicationContext.java:397)
	at org.springframework.context.support.ClassPathXmlApplicationContext.<init>(ClassPathXmlApplicationContext.java:139)
	at org.springframework.context.support.ClassPathXmlApplicationContext.<init>(ClassPathXmlApplicationContext.java:83)
	at foo.ConfigureApp.main(ConfigureApp.java:9)

error can't determine annotations of missing type org.springframework.cache.annotation.CachePut
when weaving type org.springframework.beans.factory.xml.BeansDtdResolver
when weaving classes 
when weaving 
 [Xlint:cantFindType]
error can't determine annotations of missing type org.springframework.cache.annotation.Cacheable
when weaving type org.springframework.beans.factory.xml.BeansDtdResolver
when weaving classes 
when weaving 
 [Xlint:cantFindType]
error can't determine annotations of missing type org.springframework.cache.annotation.CacheEvict
when weaving type org.springframework.beans.factory.xml.BeansDtdResolver
when weaving classes 
when weaving 
 [Xlint:cantFindType]
error can't determine annotations of missing type org.springframework.cache.annotation.Caching
when weaving type org.springframework.beans.factory.xml.BeansDtdResolver
when weaving classes 
when weaving 
 [Xlint:cantFindType]
error can't determine annotations of missing type org.springframework.transaction.annotation.Transactional
when weaving type org.springframework.beans.factory.xml.BeansDtdResolver
when weaving classes 
when weaving 
 [Xlint:cantFindType]
abort trouble in: 
public class org.springframework.beans.factory.xml.BeansDtdResolver extends java.lang.Object implements org.xml.sax.EntityResolver:
  private static final String DTD_EXTENSION = ".dtd"
  private static final String[] DTD_NAMES
  private static final org.apache.commons.logging.Log logger
  static void <clinit>():
    staticinitialization(void org.springframework.beans.factory.xml.BeansDtdResolver.<clinit>())
    |               ICONST_2   (line 48)
    |               ANEWARRAY java.lang.String
    |               DUP
    |               ICONST_0
    |               LDC "spring-beans-2.0"
    |               AASTORE
    |               DUP
    |               ICONST_1
    |               LDC "spring-beans"
    |               AASTORE
    |               PUTSTATIC org.springframework.beans.factory.xml.BeansDtdResolver.DTD_NAMES [Ljava/lang/String;
    |               LDC org.springframework.beans.factory.xml.BeansDtdResolver   (line 50)
    |               INVOKESTATIC org.apache.commons.logging.LogFactory.getLog (Ljava/lang/Class;)Lorg/apache/commons/logging/Log;
    |               PUTSTATIC org.springframework.beans.factory.xml.BeansDtdResolver.logger Lorg/apache/commons/logging/Log;
    |               RETURN   (line 44)
    staticinitialization(void org.springframework.beans.factory.xml.BeansDtdResolver.<clinit>())
  end static void <clinit>()

  public void <init>():
                    ALOAD_0     // Lorg/springframework/beans/factory/xml/BeansDtdResolver; this   (line 44)
                    INVOKESPECIAL java.lang.Object.<init> ()V
    constructor-execution(void org.springframework.beans.factory.xml.BeansDtdResolver.<init>())
    |               RETURN
    constructor-execution(void org.springframework.beans.factory.xml.BeansDtdResolver.<init>())
  end public void <init>()

  public org.xml.sax.InputSource resolveEntity(String, String) throws java.io.IOException:
                    GETSTATIC org.springframework.beans.factory.xml.BeansDtdResolver.logger Lorg/apache/commons/logging/Log;   (line 54)
                    INVOKEINTERFACE org.apache.commons.logging.Log.isTraceEnabled ()Z
                    IFEQ L0
                    GETSTATIC org.springframework.beans.factory.xml.BeansDtdResolver.logger Lorg/apache/commons/logging/Log;   (line 55)
                    NEW java.lang.StringBuilder
                    DUP
                    LDC "Trying to resolve XML entity with public ID ["
                    INVOKESPECIAL java.lang.StringBuilder.<init> (Ljava/lang/String;)V
                    ALOAD_1     // Ljava/lang/String; publicId
                    INVOKEVIRTUAL java.lang.StringBuilder.append (Ljava/lang/String;)Ljava/lang/StringBuilder;
                    LDC "] and system ID ["   (line 56)
                    INVOKEVIRTUAL java.lang.StringBuilder.append (Ljava/lang/String;)Ljava/lang/StringBuilder;
                    ALOAD_2     // Ljava/lang/String; systemId
                    INVOKEVIRTUAL java.lang.StringBuilder.append (Ljava/lang/String;)Ljava/lang/StringBuilder;
                    LDC "]"
                    INVOKEVIRTUAL java.lang.StringBuilder.append (Ljava/lang/String;)Ljava/lang/StringBuilder;
                    INVOKEVIRTUAL java.lang.StringBuilder.toString ()Ljava/lang/String;
                    INVOKEINTERFACE org.apache.commons.logging.Log.trace (Ljava/lang/Object;)V   (line 55)
                L0: ALOAD_2     // Ljava/lang/String; systemId   (line 58)
                    IFNULL L6
                    ALOAD_2     // Ljava/lang/String; systemId
                    LDC ".dtd"
                    INVOKEVIRTUAL java.lang.String.endsWith (Ljava/lang/String;)Z
                    IFEQ L6
                    ALOAD_2     // Ljava/lang/String; systemId   (line 59)
                    LDC "/"
                    INVOKEVIRTUAL java.lang.String.lastIndexOf (Ljava/lang/String;)I
                    ISTORE_3
                    GETSTATIC org.springframework.beans.factory.xml.BeansDtdResolver.DTD_NAMES [Ljava/lang/String;   (line 60)
                    DUP
                    ASTORE 7
                    ARRAYLENGTH
                    ISTORE 6
                    ICONST_0
                    ISTORE 5
                    GOTO L5
                L1: ALOAD 7
                    ILOAD 5
                    AALOAD
                    ASTORE 4
                    ALOAD_2     // Ljava/lang/String; systemId   (line 61)
                    ALOAD 4     // Ljava/lang/String; DTD_NAME
                    INVOKEVIRTUAL java.lang.String.indexOf (Ljava/lang/String;)I
                    ISTORE 8
                    ILOAD 8     // I dtdNameStart   (line 62)
                    ILOAD_3     // I lastPathSeparator
                    IF_ICMPLE L4
                    ALOAD_2     // Ljava/lang/String; systemId   (line 63)
                    ILOAD 8     // I dtdNameStart
                    INVOKEVIRTUAL java.lang.String.substring (I)Ljava/lang/String;
                    ASTORE 9
                    GETSTATIC org.springframework.beans.factory.xml.BeansDtdResolver.logger Lorg/apache/commons/logging/Log;   (line 64)
                    INVOKEINTERFACE org.apache.commons.logging.Log.isTraceEnabled ()Z
                    IFEQ L2
                    GETSTATIC org.springframework.beans.factory.xml.BeansDtdResolver.logger Lorg/apache/commons/logging/Log;   (line 65)
                    NEW java.lang.StringBuilder
                    DUP
                    LDC "Trying to locate ["
                    INVOKESPECIAL java.lang.StringBuilder.<init> (Ljava/lang/String;)V
                    ALOAD 9     // Ljava/lang/String; dtdFile
                    INVOKEVIRTUAL java.lang.StringBuilder.append (Ljava/lang/String;)Ljava/lang/StringBuilder;
                    LDC "] in Spring jar"
                    INVOKEVIRTUAL java.lang.StringBuilder.append (Ljava/lang/String;)Ljava/lang/StringBuilder;
                    INVOKEVIRTUAL java.lang.StringBuilder.toString ()Ljava/lang/String;
                    INVOKEINTERFACE org.apache.commons.logging.Log.trace (Ljava/lang/Object;)V
    catch java.io.IOException -> E0
    |           L2: NEW org.springframework.core.io.ClassPathResource   (line 68)
    |               DUP
    |               ALOAD 9     // Ljava/lang/String; dtdFile
    |               ALOAD_0     // Lorg/springframework/beans/factory/xml/BeansDtdResolver; this
    |               INVOKEVIRTUAL java.lang.Object.getClass ()Ljava/lang/Class;
    |               INVOKESPECIAL org.springframework.core.io.ClassPathResource.<init> (Ljava/lang/String;Ljava/lang/Class;)V
    |               ASTORE 10
    |               NEW org.xml.sax.InputSource   (line 69)
    |               DUP
    |               ALOAD 10     // Lorg/springframework/core/io/Resource; resource
    |               INVOKEINTERFACE org.springframework.core.io.Resource.getInputStream ()Ljava/io/InputStream;
    |               INVOKESPECIAL org.xml.sax.InputSource.<init> (Ljava/io/InputStream;)V
    |               ASTORE 11
    |               ALOAD 11     // Lorg/xml/sax/InputSource; source   (line 70)
    |               ALOAD_1     // Ljava/lang/String; publicId
    |               INVOKEVIRTUAL org.xml.sax.InputSource.setPublicId (Ljava/lang/String;)V
    |               ALOAD 11     // Lorg/xml/sax/InputSource; source   (line 71)
    |               ALOAD_2     // Ljava/lang/String; systemId
    |               INVOKEVIRTUAL org.xml.sax.InputSource.setSystemId (Ljava/lang/String;)V
    |               GETSTATIC org.springframework.beans.factory.xml.BeansDtdResolver.logger Lorg/apache/commons/logging/Log;   (line 72)
    |               INVOKEINTERFACE org.apache.commons.logging.Log.isDebugEnabled ()Z
    |               IFEQ L3
    |               GETSTATIC org.springframework.beans.factory.xml.BeansDtdResolver.logger Lorg/apache/commons/logging/Log;   (line 73)
    |               NEW java.lang.StringBuilder
    |               DUP
    |               LDC "Found beans DTD ["
    |               INVOKESPECIAL java.lang.StringBuilder.<init> (Ljava/lang/String;)V
    |               ALOAD_2     // Ljava/lang/String; systemId
    |               INVOKEVIRTUAL java.lang.StringBuilder.append (Ljava/lang/String;)Ljava/lang/StringBuilder;
    |               LDC "] in classpath: "
    |               INVOKEVIRTUAL java.lang.StringBuilder.append (Ljava/lang/String;)Ljava/lang/StringBuilder;
    |               ALOAD 9     // Ljava/lang/String; dtdFile
    |               INVOKEVIRTUAL java.lang.StringBuilder.append (Ljava/lang/String;)Ljava/lang/StringBuilder;
    |               INVOKEVIRTUAL java.lang.StringBuilder.toString ()Ljava/lang/String;
    |               INVOKEINTERFACE org.apache.commons.logging.Log.debug (Ljava/lang/Object;)V
    |           L3: ALOAD 11     // Lorg/xml/sax/InputSource; source   (line 75)
    catch java.io.IOException -> E0
                    ARETURN
                E0: ASTORE 10   (line 77)
                    GETSTATIC org.springframework.beans.factory.xml.BeansDtdResolver.logger Lorg/apache/commons/logging/Log;   (line 78)
                    INVOKEINTERFACE org.apache.commons.logging.Log.isDebugEnabled ()Z
                    IFEQ L4
                    GETSTATIC org.springframework.beans.factory.xml.BeansDtdResolver.logger Lorg/apache/commons/logging/Log;   (line 79)
                    NEW java.lang.StringBuilder
                    DUP
                    LDC "Could not resolve beans DTD ["
                    INVOKESPECIAL java.lang.StringBuilder.<init> (Ljava/lang/String;)V
                    ALOAD_2     // Ljava/lang/String; systemId
                    INVOKEVIRTUAL java.lang.StringBuilder.append (Ljava/lang/String;)Ljava/lang/StringBuilder;
                    LDC "]: not found in class path"
                    INVOKEVIRTUAL java.lang.StringBuilder.append (Ljava/lang/String;)Ljava/lang/StringBuilder;
                    INVOKEVIRTUAL java.lang.StringBuilder.toString ()Ljava/lang/String;
                    ALOAD 10     // Ljava/io/IOException; ex
                    INVOKEINTERFACE org.apache.commons.logging.Log.debug (Ljava/lang/Object;Ljava/lang/Throwable;)V
                L4: IINC 5 1   (line 60)
                L5: ILOAD 5
                    ILOAD 6
                    IF_ICMPLT L1
                L6: ACONST_NULL   (line 88)
                    ARETURN
  end public org.xml.sax.InputSource resolveEntity(String, String) throws java.io.IOException

  public String toString():
                    NEW java.lang.StringBuilder   (line 94)
                    DUP
                    LDC "EntityResolver for DTDs "
                    INVOKESPECIAL java.lang.StringBuilder.<init> (Ljava/lang/String;)V
                    GETSTATIC org.springframework.beans.factory.xml.BeansDtdResolver.DTD_NAMES [Ljava/lang/String;
                    INVOKESTATIC java.util.Arrays.toString ([Ljava/lang/Object;)Ljava/lang/String;
                    INVOKEVIRTUAL java.lang.StringBuilder.append (Ljava/lang/String;)Ljava/lang/StringBuilder;
                    INVOKEVIRTUAL java.lang.StringBuilder.toString ()Ljava/lang/String;
                    ARETURN
  end public String toString()
end public class org.springframework.beans.factory.xml.BeansDtdResolver
 -- (NullPointerException) null
null
java.lang.NullPointerException
	at org.aspectj.weaver.UnresolvedType.forSignature(UnresolvedType.java:361)
	at org.aspectj.weaver.bcel.BcelObjectType.getDeclaredInterfaces(BcelObjectType.java:275)
	at org.aspectj.weaver.ReferenceType.getDeclaredInterfaces(ReferenceType.java:624)
	at org.aspectj.weaver.ResolvedType.getDirectSupertypes(ResolvedType.java:76)
	at org.aspectj.weaver.patterns.TypePattern.matchesSubtypes(TypePattern.java:178)
	at org.aspectj.weaver.patterns.ExactTypePattern.matchesSubtypes(ExactTypePattern.java:74)
	at org.aspectj.weaver.patterns.TypePattern.matchesStatically(TypePattern.java:130)
	at org.aspectj.weaver.patterns.OrTypePattern.matchesStatically(OrTypePattern.java:76)
	at org.aspectj.weaver.patterns.SignaturePattern.matchesExactlyMethod(SignaturePattern.java:505)
	at org.aspectj.weaver.patterns.SignaturePattern.matchesExactly(SignaturePattern.java:360)
	at org.aspectj.weaver.patterns.SignaturePattern.matches(SignaturePattern.java:320)
	at org.aspectj.weaver.patterns.KindedPointcut.matchInternal(KindedPointcut.java:202)
	at org.aspectj.weaver.patterns.Pointcut.match(Pointcut.java:137)
	at org.aspectj.weaver.patterns.AndPointcut.matchInternal(AndPointcut.java:51)
	at org.aspectj.weaver.patterns.Pointcut.match(Pointcut.java:137)
	at org.aspectj.weaver.patterns.OrPointcut.matchInternal(OrPointcut.java:54)
	at org.aspectj.weaver.patterns.Pointcut.match(Pointcut.java:137)
	at org.aspectj.weaver.ShadowMunger.match(ShadowMunger.java:113)
	at org.aspectj.weaver.Advice.match(Advice.java:109)
	at org.aspectj.weaver.bcel.BcelAdvice.match(BcelAdvice.java:149)
	at org.aspectj.weaver.bcel.BcelClassWeaver.match(BcelClassWeaver.java:3116)
	at org.aspectj.weaver.bcel.BcelClassWeaver.match(BcelClassWeaver.java:2550)
	at org.aspectj.weaver.bcel.BcelClassWeaver.weave(BcelClassWeaver.java:474)
	at org.aspectj.weaver.bcel.BcelClassWeaver.weave(BcelClassWeaver.java:100)
	at org.aspectj.weaver.bcel.BcelWeaver.weave(BcelWeaver.java:1687)
	at org.aspectj.weaver.bcel.BcelWeaver.weaveWithoutDump(BcelWeaver.java:1631)
	at org.aspectj.weaver.bcel.BcelWeaver.weaveAndNotify(BcelWeaver.java:1394)
	at org.aspectj.weaver.bcel.BcelWeaver.weave(BcelWeaver.java:1180)
	at org.aspectj.weaver.tools.WeavingAdaptor.getWovenBytes(WeavingAdaptor.java:467)
	at org.aspectj.weaver.tools.WeavingAdaptor.weaveClass(WeavingAdaptor.java:318)
	at org.aspectj.weaver.loadtime.Aj.preProcess(Aj.java:96)
	at org.aspectj.weaver.loadtime.ClassPreProcessorAgentAdapter.transform(ClassPreProcessorAgentAdapter.java:54)
	at sun.instrument.TransformerManager.transform(TransformerManager.java:188)
	at sun.instrument.InstrumentationImpl.transform(InstrumentationImpl.java:428)
	at java.lang.ClassLoader.defineClass1(Native Method)
	at java.lang.ClassLoader.defineClass(ClassLoader.java:760)
	at java.security.SecureClassLoader.defineClass(SecureClassLoader.java:142)
	at java.net.URLClassLoader.defineClass(URLClassLoader.java:467)
	at java.net.URLClassLoader.access$100(URLClassLoader.java:73)
	at java.net.URLClassLoader$1.run(URLClassLoader.java:368)
	at java.net.URLClassLoader$1.run(URLClassLoader.java:362)
	at java.security.AccessController.doPrivileged(Native Method)
	at java.net.URLClassLoader.findClass(URLClassLoader.java:361)
	at java.lang.ClassLoader.loadClass(ClassLoader.java:424)
	at sun.misc.Launcher$AppClassLoader.loadClass(Launcher.java:331)
	at java.lang.ClassLoader.loadClass(ClassLoader.java:357)
	at org.springframework.beans.factory.xml.DelegatingEntityResolver.<init>(DelegatingEntityResolver.java:61)
	at org.springframework.beans.factory.xml.ResourceEntityResolver.<init>(ResourceEntityResolver.java:67)
	at org.springframework.context.support.AbstractXmlApplicationContext.loadBeanDefinitions(AbstractXmlApplicationContext.java:87)
	at org.springframework.context.support.AbstractRefreshableApplicationContext.refreshBeanFactory(AbstractRefreshableApplicationContext.java:130)
	at org.springframework.context.support.AbstractApplicationContext.obtainFreshBeanFactory(AbstractApplicationContext.java:467)
	at org.springframework.context.support.AbstractApplicationContext.refresh(AbstractApplicationContext.java:397)
	at org.springframework.context.support.ClassPathXmlApplicationContext.<init>(ClassPathXmlApplicationContext.java:139)
	at org.springframework.context.support.ClassPathXmlApplicationContext.<init>(ClassPathXmlApplicationContext.java:83)
	at foo.ConfigureApp.main(ConfigureApp.java:9)

error can't determine annotations of missing type org.springframework.cache.annotation.CachePut
when weaving type org.springframework.beans.factory.xml.PluggableSchemaResolver
when weaving classes 
when weaving 
 [Xlint:cantFindType]
error can't determine annotations of missing type org.springframework.cache.annotation.Cacheable
when weaving type org.springframework.beans.factory.xml.PluggableSchemaResolver
when weaving classes 
when weaving 
 [Xlint:cantFindType]
error can't determine annotations of missing type org.springframework.cache.annotation.CacheEvict
when weaving type org.springframework.beans.factory.xml.PluggableSchemaResolver
when weaving classes 
when weaving 
 [Xlint:cantFindType]
error can't determine annotations of missing type org.springframework.cache.annotation.Caching
when weaving type org.springframework.beans.factory.xml.PluggableSchemaResolver
when weaving classes 
when weaving 
 [Xlint:cantFindType]
error can't determine annotations of missing type org.springframework.transaction.annotation.Transactional
when weaving type org.springframework.beans.factory.xml.PluggableSchemaResolver
when weaving classes 
when weaving 
 [Xlint:cantFindType]
abort trouble in: 
public class org.springframework.beans.factory.xml.PluggableSchemaResolver extends java.lang.Object implements org.xml.sax.EntityResolver:
  public static final String DEFAULT_SCHEMA_MAPPINGS_LOCATION = "META-INF/spring.schemas"
  private static final org.apache.commons.logging.Log logger
  private final ClassLoader classLoader
  private final String schemaMappingsLocation
  private volatile java.util.Map schemaMappings [Signature(Ljava/util/Map<Ljava/lang/String;Ljava/lang/String;>;)]
  static void <clinit>():
    staticinitialization(void org.springframework.beans.factory.xml.PluggableSchemaResolver.<clinit>())
    |               LDC org.springframework.beans.factory.xml.PluggableSchemaResolver   (line 66)
    |               INVOKESTATIC org.apache.commons.logging.LogFactory.getLog (Ljava/lang/Class;)Lorg/apache/commons/logging/Log;
    |               PUTSTATIC org.springframework.beans.factory.xml.PluggableSchemaResolver.logger Lorg/apache/commons/logging/Log;
    |               RETURN   (line 57)
    staticinitialization(void org.springframework.beans.factory.xml.PluggableSchemaResolver.<clinit>())
  end static void <clinit>()

  public void <init>(ClassLoader):
                    ALOAD_0     // Lorg/springframework/beans/factory/xml/PluggableSchemaResolver; this   (line 83)
                    INVOKESPECIAL java.lang.Object.<init> ()V
    constructor-execution(void org.springframework.beans.factory.xml.PluggableSchemaResolver.<init>(java.lang.ClassLoader))
    |               ALOAD_0     // Lorg/springframework/beans/factory/xml/PluggableSchemaResolver; this   (line 84)
    |               ALOAD_1     // Ljava/lang/ClassLoader; classLoader
    |               PUTFIELD org.springframework.beans.factory.xml.PluggableSchemaResolver.classLoader Ljava/lang/ClassLoader;
    |               ALOAD_0     // Lorg/springframework/beans/factory/xml/PluggableSchemaResolver; this   (line 85)
    |               LDC "META-INF/spring.schemas"
    |               PUTFIELD org.springframework.beans.factory.xml.PluggableSchemaResolver.schemaMappingsLocation Ljava/lang/String;
    |               RETURN   (line 86)
    constructor-execution(void org.springframework.beans.factory.xml.PluggableSchemaResolver.<init>(java.lang.ClassLoader))
  end public void <init>(ClassLoader)

  public void <init>(ClassLoader, String):
                    ALOAD_0     // Lorg/springframework/beans/factory/xml/PluggableSchemaResolver; this   (line 97)
                    INVOKESPECIAL java.lang.Object.<init> ()V
    constructor-execution(void org.springframework.beans.factory.xml.PluggableSchemaResolver.<init>(java.lang.ClassLoader, java.lang.String))
    |               ALOAD_2     // Ljava/lang/String; schemaMappingsLocation   (line 98)
    |               LDC "'schemaMappingsLocation' must not be empty"
    |               INVOKESTATIC org.springframework.util.Assert.hasText (Ljava/lang/String;Ljava/lang/String;)V
    |               ALOAD_0     // Lorg/springframework/beans/factory/xml/PluggableSchemaResolver; this   (line 99)
    |               ALOAD_1     // Ljava/lang/ClassLoader; classLoader
    |               PUTFIELD org.springframework.beans.factory.xml.PluggableSchemaResolver.classLoader Ljava/lang/ClassLoader;
    |               ALOAD_0     // Lorg/springframework/beans/factory/xml/PluggableSchemaResolver; this   (line 100)
    |               ALOAD_2     // Ljava/lang/String; schemaMappingsLocation
    |               PUTFIELD org.springframework.beans.factory.xml.PluggableSchemaResolver.schemaMappingsLocation Ljava/lang/String;
    |               RETURN   (line 101)
    constructor-execution(void org.springframework.beans.factory.xml.PluggableSchemaResolver.<init>(java.lang.ClassLoader, java.lang.String))
  end public void <init>(ClassLoader, String)

  public org.xml.sax.InputSource resolveEntity(String, String) throws java.io.IOException:
                    GETSTATIC org.springframework.beans.factory.xml.PluggableSchemaResolver.logger Lorg/apache/commons/logging/Log;   (line 104)
                    INVOKEINTERFACE org.apache.commons.logging.Log.isTraceEnabled ()Z
                    IFEQ L0
                    GETSTATIC org.springframework.beans.factory.xml.PluggableSchemaResolver.logger Lorg/apache/commons/logging/Log;   (line 105)
                    NEW java.lang.StringBuilder
                    DUP
                    LDC "Trying to resolve XML entity with public id ["
                    INVOKESPECIAL java.lang.StringBuilder.<init> (Ljava/lang/String;)V
                    ALOAD_1     // Ljava/lang/String; publicId
                    INVOKEVIRTUAL java.lang.StringBuilder.append (Ljava/lang/String;)Ljava/lang/StringBuilder;
                    LDC "] and system id ["   (line 106)
                    INVOKEVIRTUAL java.lang.StringBuilder.append (Ljava/lang/String;)Ljava/lang/StringBuilder;
                    ALOAD_2     // Ljava/lang/String; systemId
                    INVOKEVIRTUAL java.lang.StringBuilder.append (Ljava/lang/String;)Ljava/lang/StringBuilder;
                    LDC "]"
                    INVOKEVIRTUAL java.lang.StringBuilder.append (Ljava/lang/String;)Ljava/lang/StringBuilder;
                    INVOKEVIRTUAL java.lang.StringBuilder.toString ()Ljava/lang/String;
                    INVOKEINTERFACE org.apache.commons.logging.Log.trace (Ljava/lang/Object;)V   (line 105)
                L0: ALOAD_2     // Ljava/lang/String; systemId   (line 109)
                    IFNULL L2
                    ALOAD_0     // Lorg/springframework/beans/factory/xml/PluggableSchemaResolver; this   (line 110)
                    INVOKESPECIAL org.springframework.beans.factory.xml.PluggableSchemaResolver.getSchemaMappings ()Ljava/util/Map;
                    ALOAD_2     // Ljava/lang/String; systemId
                    INVOKEINTERFACE java.util.Map.get (Ljava/lang/Object;)Ljava/lang/Object;
                    CHECKCAST java.lang.String
                    ASTORE_3
                    ALOAD_3     // Ljava/lang/String; resourceLocation   (line 111)
                    IFNULL L2
                    NEW org.springframework.core.io.ClassPathResource   (line 112)
                    DUP
                    ALOAD_3     // Ljava/lang/String; resourceLocation
                    ALOAD_0     // Lorg/springframework/beans/factory/xml/PluggableSchemaResolver; this
                    GETFIELD org.springframework.beans.factory.xml.PluggableSchemaResolver.classLoader Ljava/lang/ClassLoader;
                    INVOKESPECIAL org.springframework.core.io.ClassPathResource.<init> (Ljava/lang/String;Ljava/lang/ClassLoader;)V
                    ASTORE 4
    catch java.io.FileNotFoundException -> E0
    |               NEW org.xml.sax.InputSource   (line 114)
    |               DUP
    |               ALOAD 4     // Lorg/springframework/core/io/Resource; resource
    |               INVOKEINTERFACE org.springframework.core.io.Resource.getInputStream ()Ljava/io/InputStream;
    |               INVOKESPECIAL org.xml.sax.InputSource.<init> (Ljava/io/InputStream;)V
    |               ASTORE 5
    |               ALOAD 5     // Lorg/xml/sax/InputSource; source   (line 115)
    |               ALOAD_1     // Ljava/lang/String; publicId
    |               INVOKEVIRTUAL org.xml.sax.InputSource.setPublicId (Ljava/lang/String;)V
    |               ALOAD 5     // Lorg/xml/sax/InputSource; source   (line 116)
    |               ALOAD_2     // Ljava/lang/String; systemId
    |               INVOKEVIRTUAL org.xml.sax.InputSource.setSystemId (Ljava/lang/String;)V
    |               GETSTATIC org.springframework.beans.factory.xml.PluggableSchemaResolver.logger Lorg/apache/commons/logging/Log;   (line 117)
    |               INVOKEINTERFACE org.apache.commons.logging.Log.isDebugEnabled ()Z
    |               IFEQ L1
    |               GETSTATIC org.springframework.beans.factory.xml.PluggableSchemaResolver.logger Lorg/apache/commons/logging/Log;   (line 118)
    |               NEW java.lang.StringBuilder
    |               DUP
    |               LDC "Found XML schema ["
    |               INVOKESPECIAL java.lang.StringBuilder.<init> (Ljava/lang/String;)V
    |               ALOAD_2     // Ljava/lang/String; systemId
    |               INVOKEVIRTUAL java.lang.StringBuilder.append (Ljava/lang/String;)Ljava/lang/StringBuilder;
    |               LDC "] in classpath: "
    |               INVOKEVIRTUAL java.lang.StringBuilder.append (Ljava/lang/String;)Ljava/lang/StringBuilder;
    |               ALOAD_3     // Ljava/lang/String; resourceLocation
    |               INVOKEVIRTUAL java.lang.StringBuilder.append (Ljava/lang/String;)Ljava/lang/StringBuilder;
    |               INVOKEVIRTUAL java.lang.StringBuilder.toString ()Ljava/lang/String;
    |               INVOKEINTERFACE org.apache.commons.logging.Log.debug (Ljava/lang/Object;)V
    |           L1: ALOAD 5     // Lorg/xml/sax/InputSource; source   (line 120)
    catch java.io.FileNotFoundException -> E0
                    ARETURN
                E0: ASTORE 5   (line 122)
                    GETSTATIC org.springframework.beans.factory.xml.PluggableSchemaResolver.logger Lorg/apache/commons/logging/Log;   (line 123)
                    INVOKEINTERFACE org.apache.commons.logging.Log.isDebugEnabled ()Z
                    IFEQ L2
                    GETSTATIC org.springframework.beans.factory.xml.PluggableSchemaResolver.logger Lorg/apache/commons/logging/Log;   (line 124)
                    NEW java.lang.StringBuilder
                    DUP
                    LDC "Couldn't find XML schema ["
                    INVOKESPECIAL java.lang.StringBuilder.<init> (Ljava/lang/String;)V
                    ALOAD_2     // Ljava/lang/String; systemId
                    INVOKEVIRTUAL java.lang.StringBuilder.append (Ljava/lang/String;)Ljava/lang/StringBuilder;
                    LDC "]: "
                    INVOKEVIRTUAL java.lang.StringBuilder.append (Ljava/lang/String;)Ljava/lang/StringBuilder;
                    ALOAD 4     // Lorg/springframework/core/io/Resource; resource
                    INVOKEVIRTUAL java.lang.StringBuilder.append (Ljava/lang/Object;)Ljava/lang/StringBuilder;
                    INVOKEVIRTUAL java.lang.StringBuilder.toString ()Ljava/lang/String;
                    ALOAD 5     // Ljava/io/FileNotFoundException; ex
                    INVOKEINTERFACE org.apache.commons.logging.Log.debug (Ljava/lang/Object;Ljava/lang/Throwable;)V
                L2: ACONST_NULL   (line 129)
                    ARETURN
  end public org.xml.sax.InputSource resolveEntity(String, String) throws java.io.IOException

  private java.util.Map getSchemaMappings():
                    ALOAD_0     // Lorg/springframework/beans/factory/xml/PluggableSchemaResolver; this   (line 136)
                    GETFIELD org.springframework.beans.factory.xml.PluggableSchemaResolver.schemaMappings Ljava/util/Map;
                    IFNONNULL L3
                    ALOAD_0     // Lorg/springframework/beans/factory/xml/PluggableSchemaResolver; this   (line 137)
                    DUP
                    ASTORE_1
                    MONITORENTER
    finally -> E2
    |               ALOAD_0     // Lorg/springframework/beans/factory/xml/PluggableSchemaResolver; this   (line 138)
    |               GETFIELD org.springframework.beans.factory.xml.PluggableSchemaResolver.schemaMappings Ljava/util/Map;
    |               IFNONNULL L2
    |               GETSTATIC org.springframework.beans.factory.xml.PluggableSchemaResolver.logger Lorg/apache/commons/logging/Log;   (line 139)
    |               INVOKEINTERFACE org.apache.commons.logging.Log.isDebugEnabled ()Z
    |               IFEQ L0
    |               GETSTATIC org.springframework.beans.factory.xml.PluggableSchemaResolver.logger Lorg/apache/commons/logging/Log;   (line 140)
    |               NEW java.lang.StringBuilder
    |               DUP
    |               LDC "Loading schema mappings from ["
    |               INVOKESPECIAL java.lang.StringBuilder.<init> (Ljava/lang/String;)V
    |               ALOAD_0     // Lorg/springframework/beans/factory/xml/PluggableSchemaResolver; this
    |               GETFIELD org.springframework.beans.factory.xml.PluggableSchemaResolver.schemaMappingsLocation Ljava/lang/String;
    |               INVOKEVIRTUAL java.lang.StringBuilder.append (Ljava/lang/String;)Ljava/lang/StringBuilder;
    |               LDC "]"
    |               INVOKEVIRTUAL java.lang.StringBuilder.append (Ljava/lang/String;)Ljava/lang/StringBuilder;
    |               INVOKEVIRTUAL java.lang.StringBuilder.toString ()Ljava/lang/String;
    |               INVOKEINTERFACE org.apache.commons.logging.Log.debug (Ljava/lang/Object;)V
    | catch java.io.IOException -> E0
    | |         L0: ALOAD_0     // Lorg/springframework/beans/factory/xml/PluggableSchemaResolver; this   (line 144)
    | |             GETFIELD org.springframework.beans.factory.xml.PluggableSchemaResolver.schemaMappingsLocation Ljava/lang/String;
    | |             ALOAD_0     // Lorg/springframework/beans/factory/xml/PluggableSchemaResolver; this
    | |             GETFIELD org.springframework.beans.factory.xml.PluggableSchemaResolver.classLoader Ljava/lang/ClassLoader;
    | |             INVOKESTATIC org.springframework.core.io.support.PropertiesLoaderUtils.loadAllProperties (Ljava/lang/String;Ljava/lang/ClassLoader;)Ljava/util/Properties;
    | |             ASTORE_2   (line 143)
    | |             GETSTATIC org.springframework.beans.factory.xml.PluggableSchemaResolver.logger Lorg/apache/commons/logging/Log;   (line 145)
    | |             INVOKEINTERFACE org.apache.commons.logging.Log.isDebugEnabled ()Z
    | |             IFEQ L1
    | |             GETSTATIC org.springframework.beans.factory.xml.PluggableSchemaResolver.logger Lorg/apache/commons/logging/Log;   (line 146)
    | |             NEW java.lang.StringBuilder
    | |             DUP
    | |             LDC "Loaded schema mappings: "
    | |             INVOKESPECIAL java.lang.StringBuilder.<init> (Ljava/lang/String;)V
    | |             ALOAD_2     // Ljava/util/Properties; mappings
    | |             INVOKEVIRTUAL java.lang.StringBuilder.append (Ljava/lang/Object;)Ljava/lang/StringBuilder;
    | |             INVOKEVIRTUAL java.lang.StringBuilder.toString ()Ljava/lang/String;
    | |             INVOKEINTERFACE org.apache.commons.logging.Log.debug (Ljava/lang/Object;)V
    | |         L1: NEW java.util.concurrent.ConcurrentHashMap   (line 148)
    | |             DUP
    | |             INVOKESPECIAL java.util.concurrent.ConcurrentHashMap.<init> ()V
    | |             ASTORE_3
    | |             ALOAD_2     // Ljava/util/Properties; mappings   (line 149)
    | |             ALOAD_3     // Ljava/util/Map; schemaMappings
    | |             INVOKESTATIC org.springframework.util.CollectionUtils.mergePropertiesIntoMap (Ljava/util/Properties;Ljava/util/Map;)V
    | |             ALOAD_0     // Lorg/springframework/beans/factory/xml/PluggableSchemaResolver; this   (line 150)
    | |             ALOAD_3     // Ljava/util/Map; schemaMappings
    | |             PUTFIELD org.springframework.beans.factory.xml.PluggableSchemaResolver.schemaMappings Ljava/util/Map;
    | catch java.io.IOException -> E0
    |               GOTO L2
    |           E0: ASTORE_2   (line 152)
    |               NEW java.lang.IllegalStateException   (line 153)
    |               DUP
    |               NEW java.lang.StringBuilder   (line 154)
    |               DUP
    |               LDC "Unable to load schema mappings from location ["
    |               INVOKESPECIAL java.lang.StringBuilder.<init> (Ljava/lang/String;)V
    |               ALOAD_0     // Lorg/springframework/beans/factory/xml/PluggableSchemaResolver; this
    |               GETFIELD org.springframework.beans.factory.xml.PluggableSchemaResolver.schemaMappingsLocation Ljava/lang/String;
    |               INVOKEVIRTUAL java.lang.StringBuilder.append (Ljava/lang/String;)Ljava/lang/StringBuilder;
    |               LDC "]"
    |               INVOKEVIRTUAL java.lang.StringBuilder.append (Ljava/lang/String;)Ljava/lang/StringBuilder;
    |               INVOKEVIRTUAL java.lang.StringBuilder.toString ()Ljava/lang/String;
    |               ALOAD_2     // Ljava/io/IOException; ex
    |               INVOKESPECIAL java.lang.IllegalStateException.<init> (Ljava/lang/String;Ljava/lang/Throwable;)V   (line 153)
    |               ATHROW
    |           L2: ALOAD_1   (line 137)
    |               MONITOREXIT
    finally -> E2
                    GOTO L3
    finally -> E2
    |           E2: ALOAD_1
    |               MONITOREXIT
    finally -> E2
                    ATHROW
                L3: ALOAD_0     // Lorg/springframework/beans/factory/xml/PluggableSchemaResolver; this   (line 159)
                    GETFIELD org.springframework.beans.factory.xml.PluggableSchemaResolver.schemaMappings Ljava/util/Map;
                    ARETURN
  end private java.util.Map getSchemaMappings()

  public String toString():
                    NEW java.lang.StringBuilder   (line 165)
                    DUP
                    LDC "EntityResolver using mappings "
                    INVOKESPECIAL java.lang.StringBuilder.<init> (Ljava/lang/String;)V
                    ALOAD_0     // Lorg/springframework/beans/factory/xml/PluggableSchemaResolver; this
                    INVOKESPECIAL org.springframework.beans.factory.xml.PluggableSchemaResolver.getSchemaMappings ()Ljava/util/Map;
                    INVOKEVIRTUAL java.lang.StringBuilder.append (Ljava/lang/Object;)Ljava/lang/StringBuilder;
                    INVOKEVIRTUAL java.lang.StringBuilder.toString ()Ljava/lang/String;
                    ARETURN
  end public String toString()
end public class org.springframework.beans.factory.xml.PluggableSchemaResolver
 -- (NullPointerException) null
null
java.lang.NullPointerException
	at org.aspectj.weaver.UnresolvedType.forSignature(UnresolvedType.java:361)
	at org.aspectj.weaver.bcel.BcelObjectType.getDeclaredInterfaces(BcelObjectType.java:275)
	at org.aspectj.weaver.ReferenceType.getDeclaredInterfaces(ReferenceType.java:624)
	at org.aspectj.weaver.ResolvedType.getDirectSupertypes(ResolvedType.java:76)
	at org.aspectj.weaver.patterns.TypePattern.matchesSubtypes(TypePattern.java:178)
	at org.aspectj.weaver.patterns.ExactTypePattern.matchesSubtypes(ExactTypePattern.java:74)
	at org.aspectj.weaver.patterns.TypePattern.matchesStatically(TypePattern.java:130)
	at org.aspectj.weaver.patterns.OrTypePattern.matchesStatically(OrTypePattern.java:76)
	at org.aspectj.weaver.patterns.SignaturePattern.matchesExactlyMethod(SignaturePattern.java:505)
	at org.aspectj.weaver.patterns.SignaturePattern.matchesExactly(SignaturePattern.java:360)
	at org.aspectj.weaver.patterns.SignaturePattern.matches(SignaturePattern.java:320)
	at org.aspectj.weaver.patterns.KindedPointcut.matchInternal(KindedPointcut.java:202)
	at org.aspectj.weaver.patterns.Pointcut.match(Pointcut.java:137)
	at org.aspectj.weaver.patterns.AndPointcut.matchInternal(AndPointcut.java:51)
	at org.aspectj.weaver.patterns.Pointcut.match(Pointcut.java:137)
	at org.aspectj.weaver.patterns.OrPointcut.matchInternal(OrPointcut.java:54)
	at org.aspectj.weaver.patterns.Pointcut.match(Pointcut.java:137)
	at org.aspectj.weaver.ShadowMunger.match(ShadowMunger.java:113)
	at org.aspectj.weaver.Advice.match(Advice.java:109)
	at org.aspectj.weaver.bcel.BcelAdvice.match(BcelAdvice.java:149)
	at org.aspectj.weaver.bcel.BcelClassWeaver.match(BcelClassWeaver.java:3116)
	at org.aspectj.weaver.bcel.BcelClassWeaver.match(BcelClassWeaver.java:2550)
	at org.aspectj.weaver.bcel.BcelClassWeaver.weave(BcelClassWeaver.java:474)
	at org.aspectj.weaver.bcel.BcelClassWeaver.weave(BcelClassWeaver.java:100)
	at org.aspectj.weaver.bcel.BcelWeaver.weave(BcelWeaver.java:1687)
	at org.aspectj.weaver.bcel.BcelWeaver.weaveWithoutDump(BcelWeaver.java:1631)
	at org.aspectj.weaver.bcel.BcelWeaver.weaveAndNotify(BcelWeaver.java:1394)
	at org.aspectj.weaver.bcel.BcelWeaver.weave(BcelWeaver.java:1180)
	at org.aspectj.weaver.tools.WeavingAdaptor.getWovenBytes(WeavingAdaptor.java:467)
	at org.aspectj.weaver.tools.WeavingAdaptor.weaveClass(WeavingAdaptor.java:318)
	at org.aspectj.weaver.loadtime.Aj.preProcess(Aj.java:96)
	at org.aspectj.weaver.loadtime.ClassPreProcessorAgentAdapter.transform(ClassPreProcessorAgentAdapter.java:54)
	at sun.instrument.TransformerManager.transform(TransformerManager.java:188)
	at sun.instrument.InstrumentationImpl.transform(InstrumentationImpl.java:428)
	at java.lang.ClassLoader.defineClass1(Native Method)
	at java.lang.ClassLoader.defineClass(ClassLoader.java:760)
	at java.security.SecureClassLoader.defineClass(SecureClassLoader.java:142)
	at java.net.URLClassLoader.defineClass(URLClassLoader.java:467)
	at java.net.URLClassLoader.access$100(URLClassLoader.java:73)
	at java.net.URLClassLoader$1.run(URLClassLoader.java:368)
	at java.net.URLClassLoader$1.run(URLClassLoader.java:362)
	at java.security.AccessController.doPrivileged(Native Method)
	at java.net.URLClassLoader.findClass(URLClassLoader.java:361)
	at java.lang.ClassLoader.loadClass(ClassLoader.java:424)
	at sun.misc.Launcher$AppClassLoader.loadClass(Launcher.java:331)
	at java.lang.ClassLoader.loadClass(ClassLoader.java:357)
	at org.springframework.beans.factory.xml.DelegatingEntityResolver.<init>(DelegatingEntityResolver.java:62)
	at org.springframework.beans.factory.xml.ResourceEntityResolver.<init>(ResourceEntityResolver.java:67)
	at org.springframework.context.support.AbstractXmlApplicationContext.loadBeanDefinitions(AbstractXmlApplicationContext.java:87)
	at org.springframework.context.support.AbstractRefreshableApplicationContext.refreshBeanFactory(AbstractRefreshableApplicationContext.java:130)
	at org.springframework.context.support.AbstractApplicationContext.obtainFreshBeanFactory(AbstractApplicationContext.java:467)
	at org.springframework.context.support.AbstractApplicationContext.refresh(AbstractApplicationContext.java:397)
	at org.springframework.context.support.ClassPathXmlApplicationContext.<init>(ClassPathXmlApplicationContext.java:139)
	at org.springframework.context.support.ClassPathXmlApplicationContext.<init>(ClassPathXmlApplicationContext.java:83)
	at foo.ConfigureApp.main(ConfigureApp.java:9)

error can't determine annotations of missing type org.springframework.cache.annotation.CachePut
when weaving type org.springframework.core.io.DefaultResourceLoader$ClassPathContextResource
when weaving classes 
when weaving 
 [Xlint:cantFindType]
error can't determine annotations of missing type org.springframework.cache.annotation.Cacheable
when weaving type org.springframework.core.io.DefaultResourceLoader$ClassPathContextResource
when weaving classes 
when weaving 
 [Xlint:cantFindType]
error can't determine annotations of missing type org.springframework.cache.annotation.CacheEvict
when weaving type org.springframework.core.io.DefaultResourceLoader$ClassPathContextResource
when weaving classes 
when weaving 
 [Xlint:cantFindType]
error can't determine annotations of missing type org.springframework.cache.annotation.Caching
when weaving type org.springframework.core.io.DefaultResourceLoader$ClassPathContextResource
when weaving classes 
when weaving 
 [Xlint:cantFindType]
error can't determine annotations of missing type org.springframework.transaction.annotation.Transactional
when weaving type org.springframework.core.io.DefaultResourceLoader$ClassPathContextResource
when weaving classes 
when weaving 
 [Xlint:cantFindType]
abort trouble in: 
 class org.springframework.core.io.DefaultResourceLoader$ClassPathContextResource extends org.springframework.core.io.ClassPathResource implements org.springframework.core.io.ContextResource:
  public void <init>(String, ClassLoader):
                    ALOAD_0     // Lorg/springframework/core/io/DefaultResourceLoader$ClassPathContextResource; this   (line 128)
                    ALOAD_1     // Ljava/lang/String; path
                    ALOAD_2     // Ljava/lang/ClassLoader; classLoader
                    INVOKESPECIAL org.springframework.core.io.ClassPathResource.<init> (Ljava/lang/String;Ljava/lang/ClassLoader;)V
    constructor-execution(void org.springframework.core.io.DefaultResourceLoader$ClassPathContextResource.<init>(java.lang.String, java.lang.ClassLoader))
    |               RETURN   (line 129)
    constructor-execution(void org.springframework.core.io.DefaultResourceLoader$ClassPathContextResource.<init>(java.lang.String, java.lang.ClassLoader))
  end public void <init>(String, ClassLoader)

  public String getPathWithinContext():
                    ALOAD_0     // Lorg/springframework/core/io/DefaultResourceLoader$ClassPathContextResource; this   (line 132)
                    INVOKEVIRTUAL org.springframework.core.io.DefaultResourceLoader$ClassPathContextResource.getPath ()Ljava/lang/String;
                    ARETURN
  end public String getPathWithinContext()

  public org.springframework.core.io.Resource createRelative(String):
                    ALOAD_0     // Lorg/springframework/core/io/DefaultResourceLoader$ClassPathContextResource; this   (line 137)
                    INVOKEVIRTUAL org.springframework.core.io.DefaultResourceLoader$ClassPathContextResource.getPath ()Ljava/lang/String;
                    ALOAD_1     // Ljava/lang/String; relativePath
                    INVOKESTATIC org.springframework.util.StringUtils.applyRelativePath (Ljava/lang/String;Ljava/lang/String;)Ljava/lang/String;
                    ASTORE_2
                    NEW org.springframework.core.io.DefaultResourceLoader$ClassPathContextResource   (line 138)
                    DUP
                    ALOAD_2     // Ljava/lang/String; pathToUse
                    ALOAD_0     // Lorg/springframework/core/io/DefaultResourceLoader$ClassPathContextResource; this
                    INVOKEVIRTUAL org.springframework.core.io.DefaultResourceLoader$ClassPathContextResource.getClassLoader ()Ljava/lang/ClassLoader;
                    INVOKESPECIAL org.springframework.core.io.DefaultResourceLoader$ClassPathContextResource.<init> (Ljava/lang/String;Ljava/lang/ClassLoader;)V
                    ARETURN
  end public org.springframework.core.io.Resource createRelative(String)

end  class org.springframework.core.io.DefaultResourceLoader$ClassPathContextResource
 -- (NullPointerException) null
null
java.lang.NullPointerException
	at org.aspectj.weaver.UnresolvedType.forSignature(UnresolvedType.java:361)
	at org.aspectj.weaver.bcel.BcelObjectType.getDeclaredInterfaces(BcelObjectType.java:275)
	at org.aspectj.weaver.ReferenceType.getDeclaredInterfaces(ReferenceType.java:624)
	at org.aspectj.weaver.ResolvedType.getDirectSupertypes(ResolvedType.java:76)
	at org.aspectj.weaver.patterns.TypePattern.matchesSubtypes(TypePattern.java:178)
	at org.aspectj.weaver.patterns.ExactTypePattern.matchesSubtypes(ExactTypePattern.java:74)
	at org.aspectj.weaver.patterns.TypePattern.matchesStatically(TypePattern.java:130)
	at org.aspectj.weaver.patterns.OrTypePattern.matchesStatically(OrTypePattern.java:76)
	at org.aspectj.weaver.patterns.SignaturePattern.matchesExactlyMethod(SignaturePattern.java:505)
	at org.aspectj.weaver.patterns.SignaturePattern.matchesExactly(SignaturePattern.java:360)
	at org.aspectj.weaver.patterns.SignaturePattern.matches(SignaturePattern.java:320)
	at org.aspectj.weaver.patterns.KindedPointcut.matchInternal(KindedPointcut.java:202)
	at org.aspectj.weaver.patterns.Pointcut.match(Pointcut.java:137)
	at org.aspectj.weaver.patterns.AndPointcut.matchInternal(AndPointcut.java:51)
	at org.aspectj.weaver.patterns.Pointcut.match(Pointcut.java:137)
	at org.aspectj.weaver.patterns.OrPointcut.matchInternal(OrPointcut.java:54)
	at org.aspectj.weaver.patterns.Pointcut.match(Pointcut.java:137)
	at org.aspectj.weaver.ShadowMunger.match(ShadowMunger.java:113)
	at org.aspectj.weaver.Advice.match(Advice.java:109)
	at org.aspectj.weaver.bcel.BcelAdvice.match(BcelAdvice.java:149)
	at org.aspectj.weaver.bcel.BcelClassWeaver.match(BcelClassWeaver.java:3116)
	at org.aspectj.weaver.bcel.BcelClassWeaver.match(BcelClassWeaver.java:2550)
	at org.aspectj.weaver.bcel.BcelClassWeaver.weave(BcelClassWeaver.java:474)
	at org.aspectj.weaver.bcel.BcelClassWeaver.weave(BcelClassWeaver.java:100)
	at org.aspectj.weaver.bcel.BcelWeaver.weave(BcelWeaver.java:1687)
	at org.aspectj.weaver.bcel.BcelWeaver.weaveWithoutDump(BcelWeaver.java:1631)
	at org.aspectj.weaver.bcel.BcelWeaver.weaveAndNotify(BcelWeaver.java:1394)
	at org.aspectj.weaver.bcel.BcelWeaver.weave(BcelWeaver.java:1180)
	at org.aspectj.weaver.tools.WeavingAdaptor.getWovenBytes(WeavingAdaptor.java:467)
	at org.aspectj.weaver.tools.WeavingAdaptor.weaveClass(WeavingAdaptor.java:318)
	at org.aspectj.weaver.loadtime.Aj.preProcess(Aj.java:96)
	at org.aspectj.weaver.loadtime.ClassPreProcessorAgentAdapter.transform(ClassPreProcessorAgentAdapter.java:54)
	at sun.instrument.TransformerManager.transform(TransformerManager.java:188)
	at sun.instrument.InstrumentationImpl.transform(InstrumentationImpl.java:428)
	at java.lang.ClassLoader.defineClass1(Native Method)
	at java.lang.ClassLoader.defineClass(ClassLoader.java:760)
	at java.security.SecureClassLoader.defineClass(SecureClassLoader.java:142)
	at java.net.URLClassLoader.defineClass(URLClassLoader.java:467)
	at java.net.URLClassLoader.access$100(URLClassLoader.java:73)
	at java.net.URLClassLoader$1.run(URLClassLoader.java:368)
	at java.net.URLClassLoader$1.run(URLClassLoader.java:362)
	at java.security.AccessController.doPrivileged(Native Method)
	at java.net.URLClassLoader.findClass(URLClassLoader.java:361)
	at java.lang.ClassLoader.loadClass(ClassLoader.java:424)
	at sun.misc.Launcher$AppClassLoader.loadClass(Launcher.java:331)
	at java.lang.ClassLoader.loadClass(ClassLoader.java:357)
	at org.springframework.core.io.DefaultResourceLoader.getResourceByPath(DefaultResourceLoader.java:117)
	at org.springframework.core.io.DefaultResourceLoader.getResource(DefaultResourceLoader.java:100)
	at org.springframework.core.io.support.PathMatchingResourcePatternResolver.getResources(PathMatchingResourcePatternResolver.java:284)
	at org.springframework.context.support.AbstractApplicationContext.getResources(AbstractApplicationContext.java:1227)
	at org.springframework.beans.factory.support.AbstractBeanDefinitionReader.loadBeanDefinitions(AbstractBeanDefinitionReader.java:177)
	at org.springframework.beans.factory.support.AbstractBeanDefinitionReader.loadBeanDefinitions(AbstractBeanDefinitionReader.java:149)
	at org.springframework.beans.factory.support.AbstractBeanDefinitionReader.loadBeanDefinitions(AbstractBeanDefinitionReader.java:212)
	at org.springframework.context.support.AbstractXmlApplicationContext.loadBeanDefinitions(AbstractXmlApplicationContext.java:126)
	at org.springframework.context.support.AbstractXmlApplicationContext.loadBeanDefinitions(AbstractXmlApplicationContext.java:92)
	at org.springframework.context.support.AbstractRefreshableApplicationContext.refreshBeanFactory(AbstractRefreshableApplicationContext.java:130)
	at org.springframework.context.support.AbstractApplicationContext.obtainFreshBeanFactory(AbstractApplicationContext.java:467)
	at org.springframework.context.support.AbstractApplicationContext.refresh(AbstractApplicationContext.java:397)
	at org.springframework.context.support.ClassPathXmlApplicationContext.<init>(ClassPathXmlApplicationContext.java:139)
	at org.springframework.context.support.ClassPathXmlApplicationContext.<init>(ClassPathXmlApplicationContext.java:83)
	at foo.ConfigureApp.main(ConfigureApp.java:9)

error can't determine annotations of missing type org.springframework.cache.annotation.CachePut
when weaving type org.springframework.core.io.ContextResource
when weaving classes 
when weaving 
 [Xlint:cantFindType]
error can't determine annotations of missing type org.springframework.cache.annotation.Cacheable
when weaving type org.springframework.core.io.ContextResource
when weaving classes 
when weaving 
 [Xlint:cantFindType]
error can't determine annotations of missing type org.springframework.cache.annotation.CacheEvict
when weaving type org.springframework.core.io.ContextResource
when weaving classes 
when weaving 
 [Xlint:cantFindType]
error can't determine annotations of missing type org.springframework.cache.annotation.Caching
when weaving type org.springframework.core.io.ContextResource
when weaving classes 
when weaving 
 [Xlint:cantFindType]
error can't determine annotations of missing type org.springframework.transaction.annotation.Transactional
when weaving type org.springframework.core.io.ContextResource
when weaving classes 
when weaving 
 [Xlint:cantFindType]
