---- AspectJ Properties ---
AspectJ Compiler 1.6.11 built on Tuesday Mar 15, 2011 at 15:31:04 GMT
---- Dump Properties ---
Dump file: ajcore.20150913.181501.645.txt
Dump reason: org.aspectj.bridge.AbortException
Dump on exception: true
Dump at exit condition: abort
---- Exception Information ---
Message: abort trouble in: 
public class org.springframework.core.io.support.ResourceArrayPropertyEditor extends java.beans.PropertyEditorSupport:
  private static final org.apache.commons.logging.Log logger
  private final org.springframework.core.io.support.ResourcePatternResolver resourcePatternResolver
  private final boolean ignoreUnresolvablePlaceholders
  static void <clinit>():
    staticinitialization(void org.springframework.core.io.support.ResourceArrayPropertyEditor.<clinit>())
    |               LDC org.springframework.core.io.support.ResourceArrayPropertyEditor   (line 56)
    |               INVOKESTATIC org.apache.commons.logging.LogFactory.getLog (Ljava/lang/Class;)Lorg/apache/commons/logging/Log;
    |               PUTSTATIC org.springframework.core.io.support.ResourceArrayPropertyEditor.logger Lorg/apache/commons/logging/Log;
    |               RETURN   (line 54)
    staticinitialization(void org.springframework.core.io.support.ResourceArrayPropertyEditor.<clinit>())
  end static void <clinit>()

  public void <init>():
                    ALOAD_0     // Lorg/springframework/core/io/support/ResourceArrayPropertyEditor; this   (line 69)
                    NEW org.springframework.core.io.support.PathMatchingResourcePatternResolver
                    DUP
                    INVOKESPECIAL org.springframework.core.io.support.PathMatchingResourcePatternResolver.<init> ()V
                    INVOKESPECIAL org.springframework.core.io.support.ResourceArrayPropertyEditor.<init> (Lorg/springframework/core/io/support/ResourcePatternResolver;)V
    constructor-execution(void org.springframework.core.io.support.ResourceArrayPropertyEditor.<init>())
    |               RETURN   (line 70)
    constructor-execution(void org.springframework.core.io.support.ResourceArrayPropertyEditor.<init>())
  end public void <init>()

  public void <init>(org.springframework.core.io.support.ResourcePatternResolver):
                    ALOAD_0     // Lorg/springframework/core/io/support/ResourceArrayPropertyEditor; this   (line 77)
                    ALOAD_1     // Lorg/springframework/core/io/support/ResourcePatternResolver; resourcePatternResolver
                    ICONST_1
                    INVOKESPECIAL org.springframework.core.io.support.ResourceArrayPropertyEditor.<init> (Lorg/springframework/core/io/support/ResourcePatternResolver;Z)V
    constructor-execution(void org.springframework.core.io.support.ResourceArrayPropertyEditor.<init>(org.springframework.core.io.support.ResourcePatternResolver))
    |               RETURN   (line 78)
    constructor-execution(void org.springframework.core.io.support.ResourceArrayPropertyEditor.<init>(org.springframework.core.io.support.ResourcePatternResolver))
  end public void <init>(org.springframework.core.io.support.ResourcePatternResolver)

  public void <init>(org.springframework.core.io.support.ResourcePatternResolver, boolean):
                    ALOAD_0     // Lorg/springframework/core/io/support/ResourceArrayPropertyEditor; this   (line 86)
                    INVOKESPECIAL java.beans.PropertyEditorSupport.<init> ()V
    constructor-execution(void org.springframework.core.io.support.ResourceArrayPropertyEditor.<init>(org.springframework.core.io.support.ResourcePatternResolver, boolean))
    |               ALOAD_0     // Lorg/springframework/core/io/support/ResourceArrayPropertyEditor; this   (line 87)
    |               ALOAD_1     // Lorg/springframework/core/io/support/ResourcePatternResolver; resourcePatternResolver
    |               PUTFIELD org.springframework.core.io.support.ResourceArrayPropertyEditor.resourcePatternResolver Lorg/springframework/core/io/support/ResourcePatternResolver;
    |               ALOAD_0     // Lorg/springframework/core/io/support/ResourceArrayPropertyEditor; this   (line 88)
    |               ILOAD_2     // Z ignoreUnresolvablePlaceholders
    |               PUTFIELD org.springframework.core.io.support.ResourceArrayPropertyEditor.ignoreUnresolvablePlaceholders Z
    |               RETURN   (line 89)
    constructor-execution(void org.springframework.core.io.support.ResourceArrayPropertyEditor.<init>(org.springframework.core.io.support.ResourcePatternResolver, boolean))
  end public void <init>(org.springframework.core.io.support.ResourcePatternResolver, boolean)

  public void setAsText(String):
                    ALOAD_0     // Lorg/springframework/core/io/support/ResourceArrayPropertyEditor; this   (line 97)
                    ALOAD_1     // Ljava/lang/String; text
                    INVOKEVIRTUAL org.springframework.core.io.support.ResourceArrayPropertyEditor.resolvePath (Ljava/lang/String;)Ljava/lang/String;
                    INVOKEVIRTUAL java.lang.String.trim ()Ljava/lang/String;
                    ASTORE_2
    catch java.io.IOException -> E0
    |               ALOAD_0     // Lorg/springframework/core/io/support/ResourceArrayPropertyEditor; this   (line 99)
    |               ALOAD_0     // Lorg/springframework/core/io/support/ResourceArrayPropertyEditor; this
    |               GETFIELD org.springframework.core.io.support.ResourceArrayPropertyEditor.resourcePatternResolver Lorg/springframework/core/io/support/ResourcePatternResolver;
    |               ALOAD_2     // Ljava/lang/String; pattern
    |               INVOKEINTERFACE org.springframework.core.io.support.ResourcePatternResolver.getResources (Ljava/lang/String;)[Lorg/springframework/core/io/Resource;
    |               INVOKEVIRTUAL org.springframework.core.io.support.ResourceArrayPropertyEditor.setValue (Ljava/lang/Object;)V
    catch java.io.IOException -> E0
                    GOTO L0
                E0: ASTORE_3   (line 101)
                    NEW java.lang.IllegalArgumentException   (line 102)
                    DUP
                    NEW java.lang.StringBuilder   (line 103)
                    DUP
                    LDC "Could not resolve resource location pattern ["
                    INVOKESPECIAL java.lang.StringBuilder.<init> (Ljava/lang/String;)V
                    ALOAD_2     // Ljava/lang/String; pattern
                    INVOKEVIRTUAL java.lang.StringBuilder.append (Ljava/lang/String;)Ljava/lang/StringBuilder;
                    LDC "]: "
                    INVOKEVIRTUAL java.lang.StringBuilder.append (Ljava/lang/String;)Ljava/lang/StringBuilder;
                    ALOAD_3     // Ljava/io/IOException; ex
                    INVOKEVIRTUAL java.io.IOException.getMessage ()Ljava/lang/String;
                    INVOKEVIRTUAL java.lang.StringBuilder.append (Ljava/lang/String;)Ljava/lang/StringBuilder;
                    INVOKEVIRTUAL java.lang.StringBuilder.toString ()Ljava/lang/String;
                    INVOKESPECIAL java.lang.IllegalArgumentException.<init> (Ljava/lang/String;)V   (line 102)
                    ATHROW
                L0: RETURN   (line 105)
  end public void setAsText(String)

  public void setValue(Object) throws java.lang.IllegalArgumentException:
                    ALOAD_1     // Ljava/lang/Object; value   (line 113)
                    INSTANCEOF java.util.Collection
                    IFNE L0
                    ALOAD_1     // Ljava/lang/Object; value
                    INSTANCEOF [Ljava.lang.Object;
                    IFEQ L10
                    ALOAD_1     // Ljava/lang/Object; value
                    INSTANCEOF [Lorg.springframework.core.io.Resource;
                    IFNE L10
                L0: ALOAD_1     // Ljava/lang/Object; value   (line 114)
                    INSTANCEOF java.util.Collection
                    IFEQ L1
                    ALOAD_1     // Ljava/lang/Object; value
                    CHECKCAST java.util.Collection
                    GOTO L2
                L1: ALOAD_1     // Ljava/lang/Object; value
                    CHECKCAST [Ljava.lang.Object;
                    INVOKESTATIC java.util.Arrays.asList ([Ljava/lang/Object;)Ljava/util/List;
                    CHECKCAST java.util.Collection
                L2: ASTORE_2
                    NEW java.util.ArrayList   (line 115)
                    DUP
                    INVOKESPECIAL java.util.ArrayList.<init> ()V
                    ASTORE_3
                    ALOAD_2     // Ljava/util/Collection; input   (line 116)
                    INVOKEINTERFACE java.util.Collection.iterator ()Ljava/util/Iterator;
                    ASTORE 5
                    GOTO L9
                L3: ALOAD 5
                    INVOKEINTERFACE java.util.Iterator.next ()Ljava/lang/Object;
                    ASTORE 4
                    ALOAD 4     // Ljava/lang/Object; element   (line 117)
                    INSTANCEOF java.lang.String
                    IFEQ L7
                    ALOAD_0     // Lorg/springframework/core/io/support/ResourceArrayPropertyEditor; this   (line 120)
                    ALOAD 4     // Ljava/lang/Object; element
                    CHECKCAST java.lang.String
                    INVOKEVIRTUAL org.springframework.core.io.support.ResourceArrayPropertyEditor.resolvePath (Ljava/lang/String;)Ljava/lang/String;
                    INVOKEVIRTUAL java.lang.String.trim ()Ljava/lang/String;
                    ASTORE 6
    catch java.io.IOException -> E0
    |               ALOAD_0     // Lorg/springframework/core/io/support/ResourceArrayPropertyEditor; this   (line 122)
    |               GETFIELD org.springframework.core.io.support.ResourceArrayPropertyEditor.resourcePatternResolver Lorg/springframework/core/io/support/ResourcePatternResolver;
    |               ALOAD 6     // Ljava/lang/String; pattern
    |               INVOKEINTERFACE org.springframework.core.io.support.ResourcePatternResolver.getResources (Ljava/lang/String;)[Lorg/springframework/core/io/Resource;
    |               ASTORE 7
    |               ALOAD 7     // [Lorg/springframework/core/io/Resource; resources   (line 123)
    |               DUP
    |               ASTORE 11
    |               ARRAYLENGTH
    |               ISTORE 10
    |               ICONST_0
    |               ISTORE 9
    |               GOTO L6
    |           L4: ALOAD 11
    |               ILOAD 9
    |               AALOAD
    |               ASTORE 8
    |               ALOAD_3     // Ljava/util/List; merged   (line 124)
    |               ALOAD 8     // Lorg/springframework/core/io/Resource; resource
    |               INVOKEINTERFACE java.util.List.contains (Ljava/lang/Object;)Z
    |               IFNE L5
    |               ALOAD_3     // Ljava/util/List; merged   (line 125)
    |               ALOAD 8     // Lorg/springframework/core/io/Resource; resource
    |               INVOKEINTERFACE java.util.List.add (Ljava/lang/Object;)Z
    |               POP
    |           L5: IINC 9 1   (line 123)
    |           L6: ILOAD 9
    |               ILOAD 10
    |               IF_ICMPLT L4
    catch java.io.IOException -> E0
                    GOTO L9
                E0: ASTORE 7   (line 129)
                    GETSTATIC org.springframework.core.io.support.ResourceArrayPropertyEditor.logger Lorg/apache/commons/logging/Log;   (line 131)
                    INVOKEINTERFACE org.apache.commons.logging.Log.isDebugEnabled ()Z
                    IFEQ L9
                    GETSTATIC org.springframework.core.io.support.ResourceArrayPropertyEditor.logger Lorg/apache/commons/logging/Log;   (line 132)
                    NEW java.lang.StringBuilder
                    DUP
                    LDC "Could not retrieve resources for pattern '"
                    INVOKESPECIAL java.lang.StringBuilder.<init> (Ljava/lang/String;)V
                    ALOAD 6     // Ljava/lang/String; pattern
                    INVOKEVIRTUAL java.lang.StringBuilder.append (Ljava/lang/String;)Ljava/lang/StringBuilder;
                    LDC "': "
                    INVOKEVIRTUAL java.lang.StringBuilder.append (Ljava/lang/String;)Ljava/lang/StringBuilder;
                    ALOAD 7     // Ljava/io/IOException; ex
                    INVOKEVIRTUAL java.lang.StringBuilder.append (Ljava/lang/Object;)Ljava/lang/StringBuilder;
                    INVOKEVIRTUAL java.lang.StringBuilder.toString ()Ljava/lang/String;
                    INVOKEINTERFACE org.apache.commons.logging.Log.debug (Ljava/lang/Object;)V
                    GOTO L9
                L7: ALOAD 4     // Ljava/lang/Object; element   (line 136)
                    INSTANCEOF org.springframework.core.io.Resource
                    IFEQ L8
                    ALOAD 4     // Ljava/lang/Object; element   (line 138)
                    CHECKCAST org.springframework.core.io.Resource
                    ASTORE 6
                    ALOAD_3     // Ljava/util/List; merged   (line 139)
                    ALOAD 6     // Lorg/springframework/core/io/Resource; resource
                    INVOKEINTERFACE java.util.List.contains (Ljava/lang/Object;)Z
                    IFNE L9
                    ALOAD_3     // Ljava/util/List; merged   (line 140)
                    ALOAD 6     // Lorg/springframework/core/io/Resource; resource
                    INVOKEINTERFACE java.util.List.add (Ljava/lang/Object;)Z
                    POP
                    GOTO L9
                L8: NEW java.lang.IllegalArgumentException   (line 144)
                    DUP
                    NEW java.lang.StringBuilder
                    DUP
                    LDC "Cannot convert element ["
                    INVOKESPECIAL java.lang.StringBuilder.<init> (Ljava/lang/String;)V
                    ALOAD 4     // Ljava/lang/Object; element
                    INVOKEVIRTUAL java.lang.StringBuilder.append (Ljava/lang/Object;)Ljava/lang/StringBuilder;
                    LDC "] to ["
                    INVOKEVIRTUAL java.lang.StringBuilder.append (Ljava/lang/String;)Ljava/lang/StringBuilder;
                    LDC org.springframework.core.io.Resource   (line 145)
                    INVOKEVIRTUAL java.lang.Class.getName ()Ljava/lang/String;
                    INVOKEVIRTUAL java.lang.StringBuilder.append (Ljava/lang/String;)Ljava/lang/StringBuilder;
                    LDC "]: only location String and Resource object supported"
                    INVOKEVIRTUAL java.lang.StringBuilder.append (Ljava/lang/String;)Ljava/lang/StringBuilder;
                    INVOKEVIRTUAL java.lang.StringBuilder.toString ()Ljava/lang/String;
                    INVOKESPECIAL java.lang.IllegalArgumentException.<init> (Ljava/lang/String;)V   (line 144)
                    ATHROW
                L9: ALOAD 5   (line 116)
                    INVOKEINTERFACE java.util.Iterator.hasNext ()Z
                    IFNE L3
                    ALOAD_0     // Lorg/springframework/core/io/support/ResourceArrayPropertyEditor; this   (line 148)
                    ALOAD_3     // Ljava/util/List; merged
                    ALOAD_3     // Ljava/util/List; merged
                    INVOKEINTERFACE java.util.List.size ()I
                    ANEWARRAY org.springframework.core.io.Resource
                    INVOKEINTERFACE java.util.List.toArray ([Ljava/lang/Object;)[Ljava/lang/Object;
                    INVOKESPECIAL java.beans.PropertyEditorSupport.setValue (Ljava/lang/Object;)V
                    GOTO L11
               L10: ALOAD_0     // Lorg/springframework/core/io/support/ResourceArrayPropertyEditor; this   (line 154)
                    ALOAD_1     // Ljava/lang/Object; value
                    INVOKESPECIAL java.beans.PropertyEditorSupport.setValue (Ljava/lang/Object;)V
               L11: RETURN   (line 156)
  end public void setValue(Object) throws java.lang.IllegalArgumentException

  protected String resolvePath(String):
                    ALOAD_1     // Ljava/lang/String; path   (line 166)
                    ALOAD_0     // Lorg/springframework/core/io/support/ResourceArrayPropertyEditor; this
                    GETFIELD org.springframework.core.io.support.ResourceArrayPropertyEditor.ignoreUnresolvablePlaceholders Z
                    INVOKESTATIC org.springframework.util.SystemPropertyUtils.resolvePlaceholders (Ljava/lang/String;Z)Ljava/lang/String;
                    ARETURN
  end protected String resolvePath(String)
end public class org.springframework.core.io.support.ResourceArrayPropertyEditor
 -- (NullPointerException) null
null
java.lang.NullPointerException

org.aspectj.bridge.AbortException: trouble in: 
public class org.springframework.core.io.support.ResourceArrayPropertyEditor extends java.beans.PropertyEditorSupport:
  private static final org.apache.commons.logging.Log logger
  private final org.springframework.core.io.support.ResourcePatternResolver resourcePatternResolver
  private final boolean ignoreUnresolvablePlaceholders
  static void <clinit>():
    staticinitialization(void org.springframework.core.io.support.ResourceArrayPropertyEditor.<clinit>())
    |               LDC org.springframework.core.io.support.ResourceArrayPropertyEditor   (line 56)
    |               INVOKESTATIC org.apache.commons.logging.LogFactory.getLog (Ljava/lang/Class;)Lorg/apache/commons/logging/Log;
    |               PUTSTATIC org.springframework.core.io.support.ResourceArrayPropertyEditor.logger Lorg/apache/commons/logging/Log;
    |               RETURN   (line 54)
    staticinitialization(void org.springframework.core.io.support.ResourceArrayPropertyEditor.<clinit>())
  end static void <clinit>()

  public void <init>():
                    ALOAD_0     // Lorg/springframework/core/io/support/ResourceArrayPropertyEditor; this   (line 69)
                    NEW org.springframework.core.io.support.PathMatchingResourcePatternResolver
                    DUP
                    INVOKESPECIAL org.springframework.core.io.support.PathMatchingResourcePatternResolver.<init> ()V
                    INVOKESPECIAL org.springframework.core.io.support.ResourceArrayPropertyEditor.<init> (Lorg/springframework/core/io/support/ResourcePatternResolver;)V
    constructor-execution(void org.springframework.core.io.support.ResourceArrayPropertyEditor.<init>())
    |               RETURN   (line 70)
    constructor-execution(void org.springframework.core.io.support.ResourceArrayPropertyEditor.<init>())
  end public void <init>()

  public void <init>(org.springframework.core.io.support.ResourcePatternResolver):
                    ALOAD_0     // Lorg/springframework/core/io/support/ResourceArrayPropertyEditor; this   (line 77)
                    ALOAD_1     // Lorg/springframework/core/io/support/ResourcePatternResolver; resourcePatternResolver
                    ICONST_1
                    INVOKESPECIAL org.springframework.core.io.support.ResourceArrayPropertyEditor.<init> (Lorg/springframework/core/io/support/ResourcePatternResolver;Z)V
    constructor-execution(void org.springframework.core.io.support.ResourceArrayPropertyEditor.<init>(org.springframework.core.io.support.ResourcePatternResolver))
    |               RETURN   (line 78)
    constructor-execution(void org.springframework.core.io.support.ResourceArrayPropertyEditor.<init>(org.springframework.core.io.support.ResourcePatternResolver))
  end public void <init>(org.springframework.core.io.support.ResourcePatternResolver)

  public void <init>(org.springframework.core.io.support.ResourcePatternResolver, boolean):
                    ALOAD_0     // Lorg/springframework/core/io/support/ResourceArrayPropertyEditor; this   (line 86)
                    INVOKESPECIAL java.beans.PropertyEditorSupport.<init> ()V
    constructor-execution(void org.springframework.core.io.support.ResourceArrayPropertyEditor.<init>(org.springframework.core.io.support.ResourcePatternResolver, boolean))
    |               ALOAD_0     // Lorg/springframework/core/io/support/ResourceArrayPropertyEditor; this   (line 87)
    |               ALOAD_1     // Lorg/springframework/core/io/support/ResourcePatternResolver; resourcePatternResolver
    |               PUTFIELD org.springframework.core.io.support.ResourceArrayPropertyEditor.resourcePatternResolver Lorg/springframework/core/io/support/ResourcePatternResolver;
    |               ALOAD_0     // Lorg/springframework/core/io/support/ResourceArrayPropertyEditor; this   (line 88)
    |               ILOAD_2     // Z ignoreUnresolvablePlaceholders
    |               PUTFIELD org.springframework.core.io.support.ResourceArrayPropertyEditor.ignoreUnresolvablePlaceholders Z
    |               RETURN   (line 89)
    constructor-execution(void org.springframework.core.io.support.ResourceArrayPropertyEditor.<init>(org.springframework.core.io.support.ResourcePatternResolver, boolean))
  end public void <init>(org.springframework.core.io.support.ResourcePatternResolver, boolean)

  public void setAsText(String):
                    ALOAD_0     // Lorg/springframework/core/io/support/ResourceArrayPropertyEditor; this   (line 97)
                    ALOAD_1     // Ljava/lang/String; text
                    INVOKEVIRTUAL org.springframework.core.io.support.ResourceArrayPropertyEditor.resolvePath (Ljava/lang/String;)Ljava/lang/String;
                    INVOKEVIRTUAL java.lang.String.trim ()Ljava/lang/String;
                    ASTORE_2
    catch java.io.IOException -> E0
    |               ALOAD_0     // Lorg/springframework/core/io/support/ResourceArrayPropertyEditor; this   (line 99)
    |               ALOAD_0     // Lorg/springframework/core/io/support/ResourceArrayPropertyEditor; this
    |               GETFIELD org.springframework.core.io.support.ResourceArrayPropertyEditor.resourcePatternResolver Lorg/springframework/core/io/support/ResourcePatternResolver;
    |               ALOAD_2     // Ljava/lang/String; pattern
    |               INVOKEINTERFACE org.springframework.core.io.support.ResourcePatternResolver.getResources (Ljava/lang/String;)[Lorg/springframework/core/io/Resource;
    |               INVOKEVIRTUAL org.springframework.core.io.support.ResourceArrayPropertyEditor.setValue (Ljava/lang/Object;)V
    catch java.io.IOException -> E0
                    GOTO L0
                E0: ASTORE_3   (line 101)
                    NEW java.lang.IllegalArgumentException   (line 102)
                    DUP
                    NEW java.lang.StringBuilder   (line 103)
                    DUP
                    LDC "Could not resolve resource location pattern ["
                    INVOKESPECIAL java.lang.StringBuilder.<init> (Ljava/lang/String;)V
                    ALOAD_2     // Ljava/lang/String; pattern
                    INVOKEVIRTUAL java.lang.StringBuilder.append (Ljava/lang/String;)Ljava/lang/StringBuilder;
                    LDC "]: "
                    INVOKEVIRTUAL java.lang.StringBuilder.append (Ljava/lang/String;)Ljava/lang/StringBuilder;
                    ALOAD_3     // Ljava/io/IOException; ex
                    INVOKEVIRTUAL java.io.IOException.getMessage ()Ljava/lang/String;
                    INVOKEVIRTUAL java.lang.StringBuilder.append (Ljava/lang/String;)Ljava/lang/StringBuilder;
                    INVOKEVIRTUAL java.lang.StringBuilder.toString ()Ljava/lang/String;
                    INVOKESPECIAL java.lang.IllegalArgumentException.<init> (Ljava/lang/String;)V   (line 102)
                    ATHROW
                L0: RETURN   (line 105)
  end public void setAsText(String)

  public void setValue(Object) throws java.lang.IllegalArgumentException:
                    ALOAD_1     // Ljava/lang/Object; value   (line 113)
                    INSTANCEOF java.util.Collection
                    IFNE L0
                    ALOAD_1     // Ljava/lang/Object; value
                    INSTANCEOF [Ljava.lang.Object;
                    IFEQ L10
                    ALOAD_1     // Ljava/lang/Object; value
                    INSTANCEOF [Lorg.springframework.core.io.Resource;
                    IFNE L10
                L0: ALOAD_1     // Ljava/lang/Object; value   (line 114)
                    INSTANCEOF java.util.Collection
                    IFEQ L1
                    ALOAD_1     // Ljava/lang/Object; value
                    CHECKCAST java.util.Collection
                    GOTO L2
                L1: ALOAD_1     // Ljava/lang/Object; value
                    CHECKCAST [Ljava.lang.Object;
                    INVOKESTATIC java.util.Arrays.asList ([Ljava/lang/Object;)Ljava/util/List;
                    CHECKCAST java.util.Collection
                L2: ASTORE_2
                    NEW java.util.ArrayList   (line 115)
                    DUP
                    INVOKESPECIAL java.util.ArrayList.<init> ()V
                    ASTORE_3
                    ALOAD_2     // Ljava/util/Collection; input   (line 116)
                    INVOKEINTERFACE java.util.Collection.iterator ()Ljava/util/Iterator;
                    ASTORE 5
                    GOTO L9
                L3: ALOAD 5
                    INVOKEINTERFACE java.util.Iterator.next ()Ljava/lang/Object;
                    ASTORE 4
                    ALOAD 4     // Ljava/lang/Object; element   (line 117)
                    INSTANCEOF java.lang.String
                    IFEQ L7
                    ALOAD_0     // Lorg/springframework/core/io/support/ResourceArrayPropertyEditor; this   (line 120)
                    ALOAD 4     // Ljava/lang/Object; element
                    CHECKCAST java.lang.String
                    INVOKEVIRTUAL org.springframework.core.io.support.ResourceArrayPropertyEditor.resolvePath (Ljava/lang/String;)Ljava/lang/String;
                    INVOKEVIRTUAL java.lang.String.trim ()Ljava/lang/String;
                    ASTORE 6
    catch java.io.IOException -> E0
    |               ALOAD_0     // Lorg/springframework/core/io/support/ResourceArrayPropertyEditor; this   (line 122)
    |               GETFIELD org.springframework.core.io.support.ResourceArrayPropertyEditor.resourcePatternResolver Lorg/springframework/core/io/support/ResourcePatternResolver;
    |               ALOAD 6     // Ljava/lang/String; pattern
    |               INVOKEINTERFACE org.springframework.core.io.support.ResourcePatternResolver.getResources (Ljava/lang/String;)[Lorg/springframework/core/io/Resource;
    |               ASTORE 7
    |               ALOAD 7     // [Lorg/springframework/core/io/Resource; resources   (line 123)
    |               DUP
    |               ASTORE 11
    |               ARRAYLENGTH
    |               ISTORE 10
    |               ICONST_0
    |               ISTORE 9
    |               GOTO L6
    |           L4: ALOAD 11
    |               ILOAD 9
    |               AALOAD
    |               ASTORE 8
    |               ALOAD_3     // Ljava/util/List; merged   (line 124)
    |               ALOAD 8     // Lorg/springframework/core/io/Resource; resource
    |               INVOKEINTERFACE java.util.List.contains (Ljava/lang/Object;)Z
    |               IFNE L5
    |               ALOAD_3     // Ljava/util/List; merged   (line 125)
    |               ALOAD 8     // Lorg/springframework/core/io/Resource; resource
    |               INVOKEINTERFACE java.util.List.add (Ljava/lang/Object;)Z
    |               POP
    |           L5: IINC 9 1   (line 123)
    |           L6: ILOAD 9
    |               ILOAD 10
    |               IF_ICMPLT L4
    catch java.io.IOException -> E0
                    GOTO L9
                E0: ASTORE 7   (line 129)
                    GETSTATIC org.springframework.core.io.support.ResourceArrayPropertyEditor.logger Lorg/apache/commons/logging/Log;   (line 131)
                    INVOKEINTERFACE org.apache.commons.logging.Log.isDebugEnabled ()Z
                    IFEQ L9
                    GETSTATIC org.springframework.core.io.support.ResourceArrayPropertyEditor.logger Lorg/apache/commons/logging/Log;   (line 132)
                    NEW java.lang.StringBuilder
                    DUP
                    LDC "Could not retrieve resources for pattern '"
                    INVOKESPECIAL java.lang.StringBuilder.<init> (Ljava/lang/String;)V
                    ALOAD 6     // Ljava/lang/String; pattern
                    INVOKEVIRTUAL java.lang.StringBuilder.append (Ljava/lang/String;)Ljava/lang/StringBuilder;
                    LDC "': "
                    INVOKEVIRTUAL java.lang.StringBuilder.append (Ljava/lang/String;)Ljava/lang/StringBuilder;
                    ALOAD 7     // Ljava/io/IOException; ex
                    INVOKEVIRTUAL java.lang.StringBuilder.append (Ljava/lang/Object;)Ljava/lang/StringBuilder;
                    INVOKEVIRTUAL java.lang.StringBuilder.toString ()Ljava/lang/String;
                    INVOKEINTERFACE org.apache.commons.logging.Log.debug (Ljava/lang/Object;)V
                    GOTO L9
                L7: ALOAD 4     // Ljava/lang/Object; element   (line 136)
                    INSTANCEOF org.springframework.core.io.Resource
                    IFEQ L8
                    ALOAD 4     // Ljava/lang/Object; element   (line 138)
                    CHECKCAST org.springframework.core.io.Resource
                    ASTORE 6
                    ALOAD_3     // Ljava/util/List; merged   (line 139)
                    ALOAD 6     // Lorg/springframework/core/io/Resource; resource
                    INVOKEINTERFACE java.util.List.contains (Ljava/lang/Object;)Z
                    IFNE L9
                    ALOAD_3     // Ljava/util/List; merged   (line 140)
                    ALOAD 6     // Lorg/springframework/core/io/Resource; resource
                    INVOKEINTERFACE java.util.List.add (Ljava/lang/Object;)Z
                    POP
                    GOTO L9
                L8: NEW java.lang.IllegalArgumentException   (line 144)
                    DUP
                    NEW java.lang.StringBuilder
                    DUP
                    LDC "Cannot convert element ["
                    INVOKESPECIAL java.lang.StringBuilder.<init> (Ljava/lang/String;)V
                    ALOAD 4     // Ljava/lang/Object; element
                    INVOKEVIRTUAL java.lang.StringBuilder.append (Ljava/lang/Object;)Ljava/lang/StringBuilder;
                    LDC "] to ["
                    INVOKEVIRTUAL java.lang.StringBuilder.append (Ljava/lang/String;)Ljava/lang/StringBuilder;
                    LDC org.springframework.core.io.Resource   (line 145)
                    INVOKEVIRTUAL java.lang.Class.getName ()Ljava/lang/String;
                    INVOKEVIRTUAL java.lang.StringBuilder.append (Ljava/lang/String;)Ljava/lang/StringBuilder;
                    LDC "]: only location String and Resource object supported"
                    INVOKEVIRTUAL java.lang.StringBuilder.append (Ljava/lang/String;)Ljava/lang/StringBuilder;
                    INVOKEVIRTUAL java.lang.StringBuilder.toString ()Ljava/lang/String;
                    INVOKESPECIAL java.lang.IllegalArgumentException.<init> (Ljava/lang/String;)V   (line 144)
                    ATHROW
                L9: ALOAD 5   (line 116)
                    INVOKEINTERFACE java.util.Iterator.hasNext ()Z
                    IFNE L3
                    ALOAD_0     // Lorg/springframework/core/io/support/ResourceArrayPropertyEditor; this   (line 148)
                    ALOAD_3     // Ljava/util/List; merged
                    ALOAD_3     // Ljava/util/List; merged
                    INVOKEINTERFACE java.util.List.size ()I
                    ANEWARRAY org.springframework.core.io.Resource
                    INVOKEINTERFACE java.util.List.toArray ([Ljava/lang/Object;)[Ljava/lang/Object;
                    INVOKESPECIAL java.beans.PropertyEditorSupport.setValue (Ljava/lang/Object;)V
                    GOTO L11
               L10: ALOAD_0     // Lorg/springframework/core/io/support/ResourceArrayPropertyEditor; this   (line 154)
                    ALOAD_1     // Ljava/lang/Object; value
                    INVOKESPECIAL java.beans.PropertyEditorSupport.setValue (Ljava/lang/Object;)V
               L11: RETURN   (line 156)
  end public void setValue(Object) throws java.lang.IllegalArgumentException

  protected String resolvePath(String):
                    ALOAD_1     // Ljava/lang/String; path   (line 166)
                    ALOAD_0     // Lorg/springframework/core/io/support/ResourceArrayPropertyEditor; this
                    GETFIELD org.springframework.core.io.support.ResourceArrayPropertyEditor.ignoreUnresolvablePlaceholders Z
                    INVOKESTATIC org.springframework.util.SystemPropertyUtils.resolvePlaceholders (Ljava/lang/String;Z)Ljava/lang/String;
                    ARETURN
  end protected String resolvePath(String)
end public class org.springframework.core.io.support.ResourceArrayPropertyEditor

	at org.aspectj.bridge.MessageWriter.handleMessage(MessageWriter.java:47)
	at org.aspectj.weaver.tools.WeavingAdaptor$WeavingAdaptorMessageWriter.handleMessage(WeavingAdaptor.java:737)
	at org.aspectj.weaver.tools.WeavingAdaptor$WeavingAdaptorMessageHolder.handleMessage(WeavingAdaptor.java:682)
	at org.aspectj.weaver.bcel.BcelWeaver.weave(BcelWeaver.java:1712)
	at org.aspectj.weaver.bcel.BcelWeaver.weaveWithoutDump(BcelWeaver.java:1631)
	at org.aspectj.weaver.bcel.BcelWeaver.weaveAndNotify(BcelWeaver.java:1394)
	at org.aspectj.weaver.bcel.BcelWeaver.weave(BcelWeaver.java:1180)
	at org.aspectj.weaver.tools.WeavingAdaptor.getWovenBytes(WeavingAdaptor.java:467)
	at org.aspectj.weaver.tools.WeavingAdaptor.weaveClass(WeavingAdaptor.java:318)
	at org.aspectj.weaver.loadtime.Aj.preProcess(Aj.java:96)
	at org.aspectj.weaver.loadtime.ClassPreProcessorAgentAdapter.transform(ClassPreProcessorAgentAdapter.java:54)
	at sun.instrument.TransformerManager.transform(TransformerManager.java:188)
	at sun.instrument.InstrumentationImpl.transform(InstrumentationImpl.java:428)
	at java.lang.ClassLoader.defineClass1(Native Method)
	at java.lang.ClassLoader.defineClass(ClassLoader.java:760)
	at java.security.SecureClassLoader.defineClass(SecureClassLoader.java:142)
	at java.net.URLClassLoader.defineClass(URLClassLoader.java:467)
	at java.net.URLClassLoader.access$100(URLClassLoader.java:73)
	at java.net.URLClassLoader$1.run(URLClassLoader.java:368)
	at java.net.URLClassLoader$1.run(URLClassLoader.java:362)
	at java.security.AccessController.doPrivileged(Native Method)
	at java.net.URLClassLoader.findClass(URLClassLoader.java:361)
	at java.lang.ClassLoader.loadClass(ClassLoader.java:424)
	at sun.misc.Launcher$AppClassLoader.loadClass(Launcher.java:331)
	at java.lang.ClassLoader.loadClass(ClassLoader.java:357)
	at org.springframework.beans.support.ResourceEditorRegistrar.registerCustomEditors(ResourceEditorRegistrar.java:99)
	at org.springframework.beans.factory.support.AbstractBeanFactory.registerCustomEditors(AbstractBeanFactory.java:1039)
	at org.springframework.beans.factory.support.AbstractBeanFactory.initBeanWrapper(AbstractBeanFactory.java:1019)
	at org.springframework.beans.factory.support.ConstructorResolver.instantiateUsingFactoryMethod(ConstructorResolver.java:341)
	at org.springframework.beans.factory.support.AbstractAutowireCapableBeanFactory.instantiateUsingFactoryMethod(AbstractAutowireCapableBeanFactory.java:983)
	at org.springframework.beans.factory.support.AbstractAutowireCapableBeanFactory.createBeanInstance(AbstractAutowireCapableBeanFactory.java:879)
	at org.springframework.beans.factory.support.AbstractAutowireCapableBeanFactory.doCreateBean(AbstractAutowireCapableBeanFactory.java:485)
	at org.springframework.beans.factory.support.AbstractAutowireCapableBeanFactory.createBean(AbstractAutowireCapableBeanFactory.java:456)
	at org.springframework.beans.factory.support.AbstractBeanFactory$1.getObject(AbstractBeanFactory.java:291)
	at org.springframework.beans.factory.support.DefaultSingletonBeanRegistry.getSingleton(DefaultSingletonBeanRegistry.java:222)
	at org.springframework.beans.factory.support.AbstractBeanFactory.doGetBean(AbstractBeanFactory.java:288)
	at org.springframework.beans.factory.support.AbstractBeanFactory.getBean(AbstractBeanFactory.java:190)
	at org.springframework.beans.factory.support.DefaultListableBeanFactory.preInstantiateSingletons(DefaultListableBeanFactory.java:580)
	at org.springframework.context.support.AbstractApplicationContext.finishBeanFactoryInitialization(AbstractApplicationContext.java:895)
	at org.springframework.context.support.AbstractApplicationContext.refresh(AbstractApplicationContext.java:425)
	at org.springframework.context.support.ClassPathXmlApplicationContext.<init>(ClassPathXmlApplicationContext.java:139)
	at org.springframework.context.support.ClassPathXmlApplicationContext.<init>(ClassPathXmlApplicationContext.java:83)
	at foo.ConfigureApp.main(ConfigureApp.java:9)
---- System Properties ---
java.runtime.name=Java(TM) SE Runtime Environment
sun.boot.library.path=C:\Program Files\Java\jdk1.8.0_45\jre\bin
java.vm.version=25.45-b02
java.vm.vendor=Oracle Corporation
java.vendor.url=http://java.oracle.com/
path.separator=;
java.vm.name=Java HotSpot(TM) 64-Bit Server VM
file.encoding.pkg=sun.io
user.country=US
user.script=
sun.java.launcher=SUN_STANDARD
sun.os.patch.level=
java.vm.specification.name=Java Virtual Machine Specification
user.dir=E:\Eclipse Latest\SpringChap3.3
java.runtime.version=1.8.0_45-b15
java.awt.graphicsenv=sun.awt.Win32GraphicsEnvironment
java.endorsed.dirs=C:\Program Files\Java\jdk1.8.0_45\jre\lib\endorsed
os.arch=amd64
java.io.tmpdir=C:\Users\SANJUS~1\AppData\Local\Temp\
line.separator=

java.vm.specification.vendor=Oracle Corporation
user.variant=
os.name=Windows 7
sun.jnu.encoding=Cp1252
java.library.path=C:\Program Files\Java\jdk1.8.0_45\bin;C:\Windows\Sun\Java\bin;C:\Windows\system32;C:\Windows;C:/Program Files/Java/jdk1.8.0_45/bin/../jre/bin/server;C:/Program Files/Java/jdk1.8.0_45/bin/../jre/bin;C:/Program Files/Java/jdk1.8.0_45/bin/../jre/lib/amd64;C:\oraclexe\app\oracle\product\10.2.0\server\bin;C:\Program Files\Java\jdk1.8.0_45\bin;C:\Program Files (x86)\Java\jre1.8.0_45\bin;C:\ProgramData\Oracle\Java\javapath;C:\Windows\system32;C:\Windows;C:\Windows\System32\Wbem;C:\Windows\System32\WindowsPowerShell\v1.0\;C:\Python27;;E:\Eclipse Latest\eclipse-jee-luna-SR2-win32-x86_64\eclipse;;.
java.specification.name=Java Platform API Specification
java.class.version=52.0
sun.management.compiler=HotSpot 64-Bit Tiered Compilers
os.version=6.1
user.home=C:\Users\sanju singh
user.timezone=Asia/Calcutta
java.awt.printerjob=sun.awt.windows.WPrinterJob
file.encoding=Cp1252
java.specification.version=1.8
java.class.path=E:\Eclipse Latest\SpringChap3.3\bin;E:\Eclipse Latest\SpringJar\extra Jar\aopalliance-1.0.jar;E:\Eclipse Latest\SpringJar\extra Jar\asm-3.3.1.jar;E:\Eclipse Latest\SpringJar\extra Jar\aspectjrt-1.6.11.jar;E:\Eclipse Latest\SpringJar\extra Jar\aspectjweaver-1.6.11.jar;E:\Eclipse Latest\SpringJar\extra Jar\cglib-2.2.2.jar;E:\Eclipse Latest\SpringJar\extra Jar\commons-logging-1.1.1.jar;E:\Eclipse Latest\SpringJar\extra Jar\junit-4.8.2.jar;E:\Eclipse Latest\SpringJar\extra Jar\spring-aop-3.0.5.RELEASE.jar;E:\Eclipse Latest\SpringJar\extra Jar\spring-asm-3.0.5.RELEASE.jar;E:\Eclipse Latest\SpringJar\extra Jar\spring-beans-3.0.5.RELEASE.jar;E:\Eclipse Latest\SpringJar\extra Jar\spring-context-3.0.5.RELEASE.jar;E:\Eclipse Latest\SpringJar\extra Jar\spring-core-3.0.5.RELEASE.jar;E:\Eclipse Latest\SpringJar\extra Jar\spring-expression-3.0.5.RELEASE.jar;E:\Eclipse Latest\SpringJar\spring-aspects-4.1.6.RELEASE.jar;E:\TestJar\aspectjweaver-1.6.11.jar
user.name=sanju singh
java.vm.specification.version=1.8
sun.java.command=foo.ConfigureApp
java.home=C:\Program Files\Java\jdk1.8.0_45\jre
sun.arch.data.model=64
user.language=en
java.specification.vendor=Oracle Corporation
awt.toolkit=sun.awt.windows.WToolkit
java.vm.info=mixed mode
java.version=1.8.0_45
java.ext.dirs=C:\Program Files\Java\jdk1.8.0_45\jre\lib\ext;C:\Windows\Sun\Java\lib\ext
sun.boot.class.path=C:\Program Files\Java\jdk1.8.0_45\jre\lib\resources.jar;C:\Program Files\Java\jdk1.8.0_45\jre\lib\rt.jar;C:\Program Files\Java\jdk1.8.0_45\jre\lib\sunrsasign.jar;C:\Program Files\Java\jdk1.8.0_45\jre\lib\jsse.jar;C:\Program Files\Java\jdk1.8.0_45\jre\lib\jce.jar;C:\Program Files\Java\jdk1.8.0_45\jre\lib\charsets.jar;C:\Program Files\Java\jdk1.8.0_45\jre\lib\jfr.jar;C:\Program Files\Java\jdk1.8.0_45\jre\classes
java.vendor=Oracle Corporation
file.separator=\
java.vendor.url.bug=http://bugreport.sun.com/bugreport/
sun.io.unicode.encoding=UnicodeLittle
sun.cpu.endian=little
sun.desktop=windows
sun.cpu.isalist=amd64
---- Command Line ---
Empty
---- Full Classpath ---
Empty
---- Compiler Messages ---
Empty
