---- AspectJ Properties ---
AspectJ Compiler 1.6.11 built on Tuesday Mar 15, 2011 at 15:31:04 GMT
---- Dump Properties ---
Dump file: ajcore.20150913.185853.383.txt
Dump reason: org.aspectj.bridge.AbortException
Dump on exception: true
Dump at exit condition: abort
---- Exception Information ---
Message: abort trouble in: 
public class org.springframework.util.xml.XmlValidationModeDetector extends java.lang.Object:
  public static final int VALIDATION_NONE = 0
  public static final int VALIDATION_AUTO = 1
  public static final int VALIDATION_DTD = 2
  public static final int VALIDATION_XSD = 3
  private static final String DOCTYPE = "DOCTYPE"
  private static final String START_COMMENT = "<!--"
  private static final String END_COMMENT = "-->"
  private boolean inComment
  public void <init>():
                    ALOAD_0     // Lorg/springframework/util/xml/XmlValidationModeDetector; this   (line 34)
                    INVOKESPECIAL java.lang.Object.<init> ()V
    constructor-execution(void org.springframework.util.xml.XmlValidationModeDetector.<init>())
    |               RETURN
    constructor-execution(void org.springframework.util.xml.XmlValidationModeDetector.<init>())
  end public void <init>()

  public int detectValidationMode(java.io.InputStream) throws java.io.IOException:
                    NEW java.io.BufferedReader   (line 91)
                    DUP
                    NEW java.io.InputStreamReader
                    DUP
                    ALOAD_1     // Ljava/io/InputStream; inputStream
                    INVOKESPECIAL java.io.InputStreamReader.<init> (Ljava/io/InputStream;)V
                    INVOKESPECIAL java.io.BufferedReader.<init> (Ljava/io/Reader;)V
                    ASTORE_2
    finally -> E2
    | catch java.io.CharConversionException -> E0
    | |             ICONST_0   (line 93)
    | |             ISTORE_3
    | |             GOTO L3   (line 95)
    | |         L0: ALOAD_0     // Lorg/springframework/util/xml/XmlValidationModeDetector; this   (line 96)
    | |             ALOAD 4     // Ljava/lang/String; content
    | |             INVOKESPECIAL org.springframework.util.xml.XmlValidationModeDetector.consumeCommentTokens (Ljava/lang/String;)Ljava/lang/String;
    | |             ASTORE 4     // Ljava/lang/String; content
    | |             ALOAD_0     // Lorg/springframework/util/xml/XmlValidationModeDetector; this   (line 97)
    | |             GETFIELD org.springframework.util.xml.XmlValidationModeDetector.inComment Z
    | |             IFNE L3
    | |             ALOAD 4     // Ljava/lang/String; content
    | |             INVOKESTATIC org.springframework.util.StringUtils.hasText (Ljava/lang/String;)Z
    | |             IFNE L1
    | |             GOTO L3   (line 98)
    | |         L1: ALOAD_0     // Lorg/springframework/util/xml/XmlValidationModeDetector; this   (line 100)
    | |             ALOAD 4     // Ljava/lang/String; content
    | |             INVOKESPECIAL org.springframework.util.xml.XmlValidationModeDetector.hasDoctype (Ljava/lang/String;)Z
    | |             IFEQ L2
    | |             ICONST_1   (line 101)
    | |             ISTORE_3     // Z isDtdValidated
    | |             GOTO L4   (line 102)
    | |         L2: ALOAD_0     // Lorg/springframework/util/xml/XmlValidationModeDetector; this   (line 104)
    | |             ALOAD 4     // Ljava/lang/String; content
    | |             INVOKESPECIAL org.springframework.util.xml.XmlValidationModeDetector.hasOpeningTag (Ljava/lang/String;)Z
    | |             IFEQ L3
    | |             GOTO L4   (line 106)
    | |         L3: ALOAD_2     // Ljava/io/BufferedReader; reader   (line 95)
    | |             INVOKEVIRTUAL java.io.BufferedReader.readLine ()Ljava/lang/String;
    | |             DUP
    | |             ASTORE 4
    | |             IFNONNULL L0
    | |         L4: ILOAD_3     // Z isDtdValidated   (line 109)
    | |             IFEQ L5
    | |             ICONST_2
    | |             GOTO L6
    | |         L5: ICONST_3
    | |         L6: ISTORE 6
    | catch java.io.CharConversionException -> E0
    finally -> E2
                    ALOAD_2     // Ljava/io/BufferedReader; reader   (line 117)
                    INVOKEVIRTUAL java.io.BufferedReader.close ()V
                    ILOAD 6   (line 109)
                    IRETURN
    finally -> E2
    |           E0: POP   (line 111)
    finally -> E2
                    ALOAD_2     // Ljava/io/BufferedReader; reader   (line 117)
                    INVOKEVIRTUAL java.io.BufferedReader.close ()V
                    ICONST_1   (line 114)
                    IRETURN
                E2: ASTORE 5   (line 116)
                    ALOAD_2     // Ljava/io/BufferedReader; reader   (line 117)
                    INVOKEVIRTUAL java.io.BufferedReader.close ()V
                    ALOAD 5   (line 118)
                    ATHROW
  end public int detectValidationMode(java.io.InputStream) throws java.io.IOException

  private boolean hasDoctype(String):
                    ALOAD_1     // Ljava/lang/String; content   (line 126)
                    LDC "DOCTYPE"
                    INVOKEVIRTUAL java.lang.String.indexOf (Ljava/lang/String;)I
                    ICONST_M1
                    IF_ICMPLE L0
                    ICONST_1
                    IRETURN
                L0: ICONST_0
                    IRETURN
  end private boolean hasDoctype(String)

  private boolean hasOpeningTag(String):
                    ALOAD_0     // Lorg/springframework/util/xml/XmlValidationModeDetector; this   (line 135)
                    GETFIELD org.springframework.util.xml.XmlValidationModeDetector.inComment Z
                    IFEQ L0
                    ICONST_0   (line 136)
                    IRETURN
                L0: ALOAD_1     // Ljava/lang/String; content   (line 138)
                    BIPUSH 60
                    INVOKEVIRTUAL java.lang.String.indexOf (I)I
                    ISTORE_2
                    ILOAD_2     // I openTagIndex   (line 139)
                    ICONST_M1
                    IF_ICMPLE L1
                    ALOAD_1     // Ljava/lang/String; content
                    INVOKEVIRTUAL java.lang.String.length ()I
                    ILOAD_2     // I openTagIndex
                    IF_ICMPLE L1
                    ALOAD_1     // Ljava/lang/String; content
                    ILOAD_2     // I openTagIndex
                    ICONST_1
                    IADD
                    INVOKEVIRTUAL java.lang.String.charAt (I)C
                    INVOKESTATIC java.lang.Character.isLetter (C)Z
                    IFEQ L1
                    ICONST_1
                    IRETURN
                L1: ICONST_0
                    IRETURN
  end private boolean hasOpeningTag(String)

  private String consumeCommentTokens(String):
                    ALOAD_1     // Ljava/lang/String; line   (line 149)
                    LDC "<!--"
                    INVOKEVIRTUAL java.lang.String.indexOf (Ljava/lang/String;)I
                    ICONST_M1
                    IF_ICMPNE L1
                    ALOAD_1     // Ljava/lang/String; line
                    LDC "-->"
                    INVOKEVIRTUAL java.lang.String.indexOf (Ljava/lang/String;)I
                    ICONST_M1
                    IF_ICMPNE L1
                    ALOAD_1     // Ljava/lang/String; line   (line 150)
                    ARETURN
                L0: ALOAD_0     // Lorg/springframework/util/xml/XmlValidationModeDetector; this   (line 153)
                    GETFIELD org.springframework.util.xml.XmlValidationModeDetector.inComment Z
                    IFNE L1
                    ALOAD_1     // Ljava/lang/String; line
                    INVOKEVIRTUAL java.lang.String.trim ()Ljava/lang/String;
                    LDC "<!--"
                    INVOKEVIRTUAL java.lang.String.startsWith (Ljava/lang/String;)Z
                    IFNE L1
                    ALOAD_1     // Ljava/lang/String; line   (line 154)
                    ARETURN
                L1: ALOAD_0     // Lorg/springframework/util/xml/XmlValidationModeDetector; this   (line 152)
                    ALOAD_1     // Ljava/lang/String; line
                    INVOKESPECIAL org.springframework.util.xml.XmlValidationModeDetector.consume (Ljava/lang/String;)Ljava/lang/String;
                    DUP
                    ASTORE_1     // Ljava/lang/String; line
                    IFNONNULL L0
                    ALOAD_1     // Ljava/lang/String; line   (line 157)
                    ARETURN
  end private String consumeCommentTokens(String)

  private String consume(String):
                    ALOAD_0     // Lorg/springframework/util/xml/XmlValidationModeDetector; this   (line 165)
                    GETFIELD org.springframework.util.xml.XmlValidationModeDetector.inComment Z
                    IFEQ L0
                    ALOAD_0     // Lorg/springframework/util/xml/XmlValidationModeDetector; this
                    ALOAD_1     // Ljava/lang/String; line
                    INVOKESPECIAL org.springframework.util.xml.XmlValidationModeDetector.endComment (Ljava/lang/String;)I
                    GOTO L1
                L0: ALOAD_0     // Lorg/springframework/util/xml/XmlValidationModeDetector; this
                    ALOAD_1     // Ljava/lang/String; line
                    INVOKESPECIAL org.springframework.util.xml.XmlValidationModeDetector.startComment (Ljava/lang/String;)I
                L1: ISTORE_2
                    ILOAD_2     // I index   (line 166)
                    ICONST_M1
                    IF_ICMPNE L2
                    ACONST_NULL
                    GOTO L3
                L2: ALOAD_1     // Ljava/lang/String; line
                    ILOAD_2     // I index
                    INVOKEVIRTUAL java.lang.String.substring (I)Ljava/lang/String;
                L3: ARETURN
  end private String consume(String)

  private int startComment(String):
                    ALOAD_0     // Lorg/springframework/util/xml/XmlValidationModeDetector; this   (line 174)
                    ALOAD_1     // Ljava/lang/String; line
                    LDC "<!--"
                    ICONST_1
                    INVOKESPECIAL org.springframework.util.xml.XmlValidationModeDetector.commentToken (Ljava/lang/String;Ljava/lang/String;Z)I
                    IRETURN
  end private int startComment(String)

  private int endComment(String):
                    ALOAD_0     // Lorg/springframework/util/xml/XmlValidationModeDetector; this   (line 178)
                    ALOAD_1     // Ljava/lang/String; line
                    LDC "-->"
                    ICONST_0
                    INVOKESPECIAL org.springframework.util.xml.XmlValidationModeDetector.commentToken (Ljava/lang/String;Ljava/lang/String;Z)I
                    IRETURN
  end private int endComment(String)

  private int commentToken(String, String, boolean):
                    ALOAD_1     // Ljava/lang/String; line   (line 187)
                    ALOAD_2     // Ljava/lang/String; token
                    INVOKEVIRTUAL java.lang.String.indexOf (Ljava/lang/String;)I
                    ISTORE 4
                    ILOAD 4     // I index   (line 188)
                    ICONST_M1
                    IF_ICMPLE L0
                    ALOAD_0     // Lorg/springframework/util/xml/XmlValidationModeDetector; this   (line 189)
                    ILOAD_3     // Z inCommentIfPresent
                    PUTFIELD org.springframework.util.xml.XmlValidationModeDetector.inComment Z
                L0: ILOAD 4     // I index   (line 191)
                    ICONST_M1
                    IF_ICMPNE L1
                    ILOAD 4     // I index
                    GOTO L2
                L1: ILOAD 4     // I index
                    ALOAD_2     // Ljava/lang/String; token
                    INVOKEVIRTUAL java.lang.String.length ()I
                    IADD
                L2: IRETURN
  end private int commentToken(String, String, boolean)

end public class org.springframework.util.xml.XmlValidationModeDetector
 -- (NullPointerException) null
null
java.lang.NullPointerException
	at org.aspectj.weaver.UnresolvedType.forSignature(UnresolvedType.java:361)
	at org.aspectj.weaver.bcel.BcelObjectType.getDeclaredInterfaces(BcelObjectType.java:275)
	at org.aspectj.weaver.ReferenceType.getDeclaredInterfaces(ReferenceType.java:624)
	at org.aspectj.weaver.ResolvedType.getDirectSupertypes(ResolvedType.java:76)
	at org.aspectj.weaver.patterns.TypePattern.matchesSubtypes(TypePattern.java:178)
	at org.aspectj.weaver.patterns.ExactTypePattern.matchesSubtypes(ExactTypePattern.java:74)
	at org.aspectj.weaver.patterns.TypePattern.matchesStatically(TypePattern.java:130)
	at org.aspectj.weaver.patterns.OrTypePattern.matchesStatically(OrTypePattern.java:76)
	at org.aspectj.weaver.patterns.SignaturePattern.matchesExactlyMethod(SignaturePattern.java:505)
	at org.aspectj.weaver.patterns.SignaturePattern.matchesExactly(SignaturePattern.java:360)
	at org.aspectj.weaver.patterns.SignaturePattern.matches(SignaturePattern.java:320)
	at org.aspectj.weaver.patterns.KindedPointcut.matchInternal(KindedPointcut.java:202)
	at org.aspectj.weaver.patterns.Pointcut.match(Pointcut.java:137)
	at org.aspectj.weaver.patterns.AndPointcut.matchInternal(AndPointcut.java:51)
	at org.aspectj.weaver.patterns.Pointcut.match(Pointcut.java:137)
	at org.aspectj.weaver.patterns.OrPointcut.matchInternal(OrPointcut.java:54)
	at org.aspectj.weaver.patterns.Pointcut.match(Pointcut.java:137)
	at org.aspectj.weaver.ShadowMunger.match(ShadowMunger.java:113)
	at org.aspectj.weaver.Advice.match(Advice.java:109)
	at org.aspectj.weaver.bcel.BcelAdvice.match(BcelAdvice.java:149)
	at org.aspectj.weaver.bcel.BcelClassWeaver.match(BcelClassWeaver.java:3116)
	at org.aspectj.weaver.bcel.BcelClassWeaver.match(BcelClassWeaver.java:2550)
	at org.aspectj.weaver.bcel.BcelClassWeaver.weave(BcelClassWeaver.java:474)
	at org.aspectj.weaver.bcel.BcelClassWeaver.weave(BcelClassWeaver.java:100)
	at org.aspectj.weaver.bcel.BcelWeaver.weave(BcelWeaver.java:1687)
	at org.aspectj.weaver.bcel.BcelWeaver.weaveWithoutDump(BcelWeaver.java:1631)
	at org.aspectj.weaver.bcel.BcelWeaver.weaveAndNotify(BcelWeaver.java:1394)
	at org.aspectj.weaver.bcel.BcelWeaver.weave(BcelWeaver.java:1180)
	at org.aspectj.weaver.tools.WeavingAdaptor.getWovenBytes(WeavingAdaptor.java:467)
	at org.aspectj.weaver.tools.WeavingAdaptor.weaveClass(WeavingAdaptor.java:318)
	at org.aspectj.weaver.loadtime.Aj.preProcess(Aj.java:96)
	at org.aspectj.weaver.loadtime.ClassPreProcessorAgentAdapter.transform(ClassPreProcessorAgentAdapter.java:54)
	at sun.instrument.TransformerManager.transform(TransformerManager.java:188)
	at sun.instrument.InstrumentationImpl.transform(InstrumentationImpl.java:428)
	at java.lang.ClassLoader.defineClass1(Native Method)
	at java.lang.ClassLoader.defineClass(ClassLoader.java:760)
	at java.security.SecureClassLoader.defineClass(SecureClassLoader.java:142)
	at java.net.URLClassLoader.defineClass(URLClassLoader.java:467)
	at java.net.URLClassLoader.access$100(URLClassLoader.java:73)
	at java.net.URLClassLoader$1.run(URLClassLoader.java:368)
	at java.net.URLClassLoader$1.run(URLClassLoader.java:362)
	at java.security.AccessController.doPrivileged(Native Method)
	at java.net.URLClassLoader.findClass(URLClassLoader.java:361)
	at java.lang.ClassLoader.loadClass(ClassLoader.java:424)
	at sun.misc.Launcher$AppClassLoader.loadClass(Launcher.java:331)
	at java.lang.ClassLoader.loadClass(ClassLoader.java:357)
	at org.springframework.beans.factory.xml.XmlBeanDefinitionReader.<init>(XmlBeanDefinitionReader.java:122)
	at org.springframework.context.support.AbstractXmlApplicationContext.loadBeanDefinitions(AbstractXmlApplicationContext.java:82)
	at org.springframework.context.support.AbstractRefreshableApplicationContext.refreshBeanFactory(AbstractRefreshableApplicationContext.java:130)
	at org.springframework.context.support.AbstractApplicationContext.obtainFreshBeanFactory(AbstractApplicationContext.java:467)
	at org.springframework.context.support.AbstractApplicationContext.refresh(AbstractApplicationContext.java:397)
	at org.springframework.context.support.ClassPathXmlApplicationContext.<init>(ClassPathXmlApplicationContext.java:139)
	at org.springframework.context.support.ClassPathXmlApplicationContext.<init>(ClassPathXmlApplicationContext.java:83)
	at foo.ConfigureApp.main(ConfigureApp.java:9)

org.aspectj.bridge.AbortException: trouble in: 
public class org.springframework.util.xml.XmlValidationModeDetector extends java.lang.Object:
  public static final int VALIDATION_NONE = 0
  public static final int VALIDATION_AUTO = 1
  public static final int VALIDATION_DTD = 2
  public static final int VALIDATION_XSD = 3
  private static final String DOCTYPE = "DOCTYPE"
  private static final String START_COMMENT = "<!--"
  private static final String END_COMMENT = "-->"
  private boolean inComment
  public void <init>():
                    ALOAD_0     // Lorg/springframework/util/xml/XmlValidationModeDetector; this   (line 34)
                    INVOKESPECIAL java.lang.Object.<init> ()V
    constructor-execution(void org.springframework.util.xml.XmlValidationModeDetector.<init>())
    |               RETURN
    constructor-execution(void org.springframework.util.xml.XmlValidationModeDetector.<init>())
  end public void <init>()

  public int detectValidationMode(java.io.InputStream) throws java.io.IOException:
                    NEW java.io.BufferedReader   (line 91)
                    DUP
                    NEW java.io.InputStreamReader
                    DUP
                    ALOAD_1     // Ljava/io/InputStream; inputStream
                    INVOKESPECIAL java.io.InputStreamReader.<init> (Ljava/io/InputStream;)V
                    INVOKESPECIAL java.io.BufferedReader.<init> (Ljava/io/Reader;)V
                    ASTORE_2
    finally -> E2
    | catch java.io.CharConversionException -> E0
    | |             ICONST_0   (line 93)
    | |             ISTORE_3
    | |             GOTO L3   (line 95)
    | |         L0: ALOAD_0     // Lorg/springframework/util/xml/XmlValidationModeDetector; this   (line 96)
    | |             ALOAD 4     // Ljava/lang/String; content
    | |             INVOKESPECIAL org.springframework.util.xml.XmlValidationModeDetector.consumeCommentTokens (Ljava/lang/String;)Ljava/lang/String;
    | |             ASTORE 4     // Ljava/lang/String; content
    | |             ALOAD_0     // Lorg/springframework/util/xml/XmlValidationModeDetector; this   (line 97)
    | |             GETFIELD org.springframework.util.xml.XmlValidationModeDetector.inComment Z
    | |             IFNE L3
    | |             ALOAD 4     // Ljava/lang/String; content
    | |             INVOKESTATIC org.springframework.util.StringUtils.hasText (Ljava/lang/String;)Z
    | |             IFNE L1
    | |             GOTO L3   (line 98)
    | |         L1: ALOAD_0     // Lorg/springframework/util/xml/XmlValidationModeDetector; this   (line 100)
    | |             ALOAD 4     // Ljava/lang/String; content
    | |             INVOKESPECIAL org.springframework.util.xml.XmlValidationModeDetector.hasDoctype (Ljava/lang/String;)Z
    | |             IFEQ L2
    | |             ICONST_1   (line 101)
    | |             ISTORE_3     // Z isDtdValidated
    | |             GOTO L4   (line 102)
    | |         L2: ALOAD_0     // Lorg/springframework/util/xml/XmlValidationModeDetector; this   (line 104)
    | |             ALOAD 4     // Ljava/lang/String; content
    | |             INVOKESPECIAL org.springframework.util.xml.XmlValidationModeDetector.hasOpeningTag (Ljava/lang/String;)Z
    | |             IFEQ L3
    | |             GOTO L4   (line 106)
    | |         L3: ALOAD_2     // Ljava/io/BufferedReader; reader   (line 95)
    | |             INVOKEVIRTUAL java.io.BufferedReader.readLine ()Ljava/lang/String;
    | |             DUP
    | |             ASTORE 4
    | |             IFNONNULL L0
    | |         L4: ILOAD_3     // Z isDtdValidated   (line 109)
    | |             IFEQ L5
    | |             ICONST_2
    | |             GOTO L6
    | |         L5: ICONST_3
    | |         L6: ISTORE 6
    | catch java.io.CharConversionException -> E0
    finally -> E2
                    ALOAD_2     // Ljava/io/BufferedReader; reader   (line 117)
                    INVOKEVIRTUAL java.io.BufferedReader.close ()V
                    ILOAD 6   (line 109)
                    IRETURN
    finally -> E2
    |           E0: POP   (line 111)
    finally -> E2
                    ALOAD_2     // Ljava/io/BufferedReader; reader   (line 117)
                    INVOKEVIRTUAL java.io.BufferedReader.close ()V
                    ICONST_1   (line 114)
                    IRETURN
                E2: ASTORE 5   (line 116)
                    ALOAD_2     // Ljava/io/BufferedReader; reader   (line 117)
                    INVOKEVIRTUAL java.io.BufferedReader.close ()V
                    ALOAD 5   (line 118)
                    ATHROW
  end public int detectValidationMode(java.io.InputStream) throws java.io.IOException

  private boolean hasDoctype(String):
                    ALOAD_1     // Ljava/lang/String; content   (line 126)
                    LDC "DOCTYPE"
                    INVOKEVIRTUAL java.lang.String.indexOf (Ljava/lang/String;)I
                    ICONST_M1
                    IF_ICMPLE L0
                    ICONST_1
                    IRETURN
                L0: ICONST_0
                    IRETURN
  end private boolean hasDoctype(String)

  private boolean hasOpeningTag(String):
                    ALOAD_0     // Lorg/springframework/util/xml/XmlValidationModeDetector; this   (line 135)
                    GETFIELD org.springframework.util.xml.XmlValidationModeDetector.inComment Z
                    IFEQ L0
                    ICONST_0   (line 136)
                    IRETURN
                L0: ALOAD_1     // Ljava/lang/String; content   (line 138)
                    BIPUSH 60
                    INVOKEVIRTUAL java.lang.String.indexOf (I)I
                    ISTORE_2
                    ILOAD_2     // I openTagIndex   (line 139)
                    ICONST_M1
                    IF_ICMPLE L1
                    ALOAD_1     // Ljava/lang/String; content
                    INVOKEVIRTUAL java.lang.String.length ()I
                    ILOAD_2     // I openTagIndex
                    IF_ICMPLE L1
                    ALOAD_1     // Ljava/lang/String; content
                    ILOAD_2     // I openTagIndex
                    ICONST_1
                    IADD
                    INVOKEVIRTUAL java.lang.String.charAt (I)C
                    INVOKESTATIC java.lang.Character.isLetter (C)Z
                    IFEQ L1
                    ICONST_1
                    IRETURN
                L1: ICONST_0
                    IRETURN
  end private boolean hasOpeningTag(String)

  private String consumeCommentTokens(String):
                    ALOAD_1     // Ljava/lang/String; line   (line 149)
                    LDC "<!--"
                    INVOKEVIRTUAL java.lang.String.indexOf (Ljava/lang/String;)I
                    ICONST_M1
                    IF_ICMPNE L1
                    ALOAD_1     // Ljava/lang/String; line
                    LDC "-->"
                    INVOKEVIRTUAL java.lang.String.indexOf (Ljava/lang/String;)I
                    ICONST_M1
                    IF_ICMPNE L1
                    ALOAD_1     // Ljava/lang/String; line   (line 150)
                    ARETURN
                L0: ALOAD_0     // Lorg/springframework/util/xml/XmlValidationModeDetector; this   (line 153)
                    GETFIELD org.springframework.util.xml.XmlValidationModeDetector.inComment Z
                    IFNE L1
                    ALOAD_1     // Ljava/lang/String; line
                    INVOKEVIRTUAL java.lang.String.trim ()Ljava/lang/String;
                    LDC "<!--"
                    INVOKEVIRTUAL java.lang.String.startsWith (Ljava/lang/String;)Z
                    IFNE L1
                    ALOAD_1     // Ljava/lang/String; line   (line 154)
                    ARETURN
                L1: ALOAD_0     // Lorg/springframework/util/xml/XmlValidationModeDetector; this   (line 152)
                    ALOAD_1     // Ljava/lang/String; line
                    INVOKESPECIAL org.springframework.util.xml.XmlValidationModeDetector.consume (Ljava/lang/String;)Ljava/lang/String;
                    DUP
                    ASTORE_1     // Ljava/lang/String; line
                    IFNONNULL L0
                    ALOAD_1     // Ljava/lang/String; line   (line 157)
                    ARETURN
  end private String consumeCommentTokens(String)

  private String consume(String):
                    ALOAD_0     // Lorg/springframework/util/xml/XmlValidationModeDetector; this   (line 165)
                    GETFIELD org.springframework.util.xml.XmlValidationModeDetector.inComment Z
                    IFEQ L0
                    ALOAD_0     // Lorg/springframework/util/xml/XmlValidationModeDetector; this
                    ALOAD_1     // Ljava/lang/String; line
                    INVOKESPECIAL org.springframework.util.xml.XmlValidationModeDetector.endComment (Ljava/lang/String;)I
                    GOTO L1
                L0: ALOAD_0     // Lorg/springframework/util/xml/XmlValidationModeDetector; this
                    ALOAD_1     // Ljava/lang/String; line
                    INVOKESPECIAL org.springframework.util.xml.XmlValidationModeDetector.startComment (Ljava/lang/String;)I
                L1: ISTORE_2
                    ILOAD_2     // I index   (line 166)
                    ICONST_M1
                    IF_ICMPNE L2
                    ACONST_NULL
                    GOTO L3
                L2: ALOAD_1     // Ljava/lang/String; line
                    ILOAD_2     // I index
                    INVOKEVIRTUAL java.lang.String.substring (I)Ljava/lang/String;
                L3: ARETURN
  end private String consume(String)

  private int startComment(String):
                    ALOAD_0     // Lorg/springframework/util/xml/XmlValidationModeDetector; this   (line 174)
                    ALOAD_1     // Ljava/lang/String; line
                    LDC "<!--"
                    ICONST_1
                    INVOKESPECIAL org.springframework.util.xml.XmlValidationModeDetector.commentToken (Ljava/lang/String;Ljava/lang/String;Z)I
                    IRETURN
  end private int startComment(String)

  private int endComment(String):
                    ALOAD_0     // Lorg/springframework/util/xml/XmlValidationModeDetector; this   (line 178)
                    ALOAD_1     // Ljava/lang/String; line
                    LDC "-->"
                    ICONST_0
                    INVOKESPECIAL org.springframework.util.xml.XmlValidationModeDetector.commentToken (Ljava/lang/String;Ljava/lang/String;Z)I
                    IRETURN
  end private int endComment(String)

  private int commentToken(String, String, boolean):
                    ALOAD_1     // Ljava/lang/String; line   (line 187)
                    ALOAD_2     // Ljava/lang/String; token
                    INVOKEVIRTUAL java.lang.String.indexOf (Ljava/lang/String;)I
                    ISTORE 4
                    ILOAD 4     // I index   (line 188)
                    ICONST_M1
                    IF_ICMPLE L0
                    ALOAD_0     // Lorg/springframework/util/xml/XmlValidationModeDetector; this   (line 189)
                    ILOAD_3     // Z inCommentIfPresent
                    PUTFIELD org.springframework.util.xml.XmlValidationModeDetector.inComment Z
                L0: ILOAD 4     // I index   (line 191)
                    ICONST_M1
                    IF_ICMPNE L1
                    ILOAD 4     // I index
                    GOTO L2
                L1: ILOAD 4     // I index
                    ALOAD_2     // Ljava/lang/String; token
                    INVOKEVIRTUAL java.lang.String.length ()I
                    IADD
                L2: IRETURN
  end private int commentToken(String, String, boolean)

end public class org.springframework.util.xml.XmlValidationModeDetector

	at org.aspectj.bridge.MessageWriter.handleMessage(MessageWriter.java:47)
	at org.aspectj.weaver.tools.WeavingAdaptor$WeavingAdaptorMessageWriter.handleMessage(WeavingAdaptor.java:737)
	at org.aspectj.weaver.tools.WeavingAdaptor$WeavingAdaptorMessageHolder.handleMessage(WeavingAdaptor.java:682)
	at org.aspectj.weaver.bcel.BcelWeaver.weave(BcelWeaver.java:1712)
	at org.aspectj.weaver.bcel.BcelWeaver.weaveWithoutDump(BcelWeaver.java:1631)
	at org.aspectj.weaver.bcel.BcelWeaver.weaveAndNotify(BcelWeaver.java:1394)
	at org.aspectj.weaver.bcel.BcelWeaver.weave(BcelWeaver.java:1180)
	at org.aspectj.weaver.tools.WeavingAdaptor.getWovenBytes(WeavingAdaptor.java:467)
	at org.aspectj.weaver.tools.WeavingAdaptor.weaveClass(WeavingAdaptor.java:318)
	at org.aspectj.weaver.loadtime.Aj.preProcess(Aj.java:96)
	at org.aspectj.weaver.loadtime.ClassPreProcessorAgentAdapter.transform(ClassPreProcessorAgentAdapter.java:54)
	at sun.instrument.TransformerManager.transform(TransformerManager.java:188)
	at sun.instrument.InstrumentationImpl.transform(InstrumentationImpl.java:428)
	at java.lang.ClassLoader.defineClass1(Native Method)
	at java.lang.ClassLoader.defineClass(ClassLoader.java:760)
	at java.security.SecureClassLoader.defineClass(SecureClassLoader.java:142)
	at java.net.URLClassLoader.defineClass(URLClassLoader.java:467)
	at java.net.URLClassLoader.access$100(URLClassLoader.java:73)
	at java.net.URLClassLoader$1.run(URLClassLoader.java:368)
	at java.net.URLClassLoader$1.run(URLClassLoader.java:362)
	at java.security.AccessController.doPrivileged(Native Method)
	at java.net.URLClassLoader.findClass(URLClassLoader.java:361)
	at java.lang.ClassLoader.loadClass(ClassLoader.java:424)
	at sun.misc.Launcher$AppClassLoader.loadClass(Launcher.java:331)
	at java.lang.ClassLoader.loadClass(ClassLoader.java:357)
	at org.springframework.beans.factory.xml.XmlBeanDefinitionReader.<init>(XmlBeanDefinitionReader.java:122)
	at org.springframework.context.support.AbstractXmlApplicationContext.loadBeanDefinitions(AbstractXmlApplicationContext.java:82)
	at org.springframework.context.support.AbstractRefreshableApplicationContext.refreshBeanFactory(AbstractRefreshableApplicationContext.java:130)
	at org.springframework.context.support.AbstractApplicationContext.obtainFreshBeanFactory(AbstractApplicationContext.java:467)
	at org.springframework.context.support.AbstractApplicationContext.refresh(AbstractApplicationContext.java:397)
	at org.springframework.context.support.ClassPathXmlApplicationContext.<init>(ClassPathXmlApplicationContext.java:139)
	at org.springframework.context.support.ClassPathXmlApplicationContext.<init>(ClassPathXmlApplicationContext.java:83)
	at foo.ConfigureApp.main(ConfigureApp.java:9)
---- System Properties ---
java.runtime.name=Java(TM) SE Runtime Environment
sun.boot.library.path=C:\Program Files\Java\jdk1.8.0_45\jre\bin
java.vm.version=25.45-b02
java.vm.vendor=Oracle Corporation
java.vendor.url=http://java.oracle.com/
path.separator=;
java.vm.name=Java HotSpot(TM) 64-Bit Server VM
file.encoding.pkg=sun.io
user.country=US
user.script=
sun.java.launcher=SUN_STANDARD
sun.os.patch.level=
java.vm.specification.name=Java Virtual Machine Specification
user.dir=E:\Eclipse Latest\SpringChap3.3
java.runtime.version=1.8.0_45-b15
java.awt.graphicsenv=sun.awt.Win32GraphicsEnvironment
java.endorsed.dirs=C:\Program Files\Java\jdk1.8.0_45\jre\lib\endorsed
os.arch=amd64
java.io.tmpdir=C:\Users\SANJUS~1\AppData\Local\Temp\
line.separator=

java.vm.specification.vendor=Oracle Corporation
user.variant=
os.name=Windows 7
sun.jnu.encoding=Cp1252
java.library.path=C:\Program Files\Java\jdk1.8.0_45\bin;C:\Windows\Sun\Java\bin;C:\Windows\system32;C:\Windows;C:/Program Files/Java/jdk1.8.0_45/bin/../jre/bin/server;C:/Program Files/Java/jdk1.8.0_45/bin/../jre/bin;C:/Program Files/Java/jdk1.8.0_45/bin/../jre/lib/amd64;C:\oraclexe\app\oracle\product\10.2.0\server\bin;C:\Program Files\Java\jdk1.8.0_45\bin;C:\Program Files (x86)\Java\jre1.8.0_45\bin;C:\ProgramData\Oracle\Java\javapath;C:\Windows\system32;C:\Windows;C:\Windows\System32\Wbem;C:\Windows\System32\WindowsPowerShell\v1.0\;C:\Python27;;E:\Eclipse Latest\eclipse-jee-luna-SR2-win32-x86_64\eclipse;;.
java.specification.name=Java Platform API Specification
java.class.version=52.0
sun.management.compiler=HotSpot 64-Bit Tiered Compilers
os.version=6.1
user.home=C:\Users\sanju singh
user.timezone=Asia/Calcutta
java.awt.printerjob=sun.awt.windows.WPrinterJob
file.encoding=Cp1252
java.specification.version=1.8
java.class.path=E:\Eclipse Latest\SpringChap3.3\bin;E:\Eclipse Latest\SpringJar\extra Jar\aopalliance-1.0.jar;E:\Eclipse Latest\SpringJar\extra Jar\asm-3.3.1.jar;E:\Eclipse Latest\SpringJar\extra Jar\aspectjrt-1.6.11.jar;E:\Eclipse Latest\SpringJar\extra Jar\aspectjweaver-1.6.11.jar;E:\Eclipse Latest\SpringJar\extra Jar\cglib-2.2.2.jar;E:\Eclipse Latest\SpringJar\extra Jar\commons-logging-1.1.1.jar;E:\Eclipse Latest\SpringJar\extra Jar\junit-4.8.2.jar;E:\Eclipse Latest\SpringJar\extra Jar\spring-aop-3.0.5.RELEASE.jar;E:\Eclipse Latest\SpringJar\extra Jar\spring-asm-3.0.5.RELEASE.jar;E:\Eclipse Latest\SpringJar\extra Jar\spring-beans-3.0.5.RELEASE.jar;E:\Eclipse Latest\SpringJar\extra Jar\spring-context-3.0.5.RELEASE.jar;E:\Eclipse Latest\SpringJar\extra Jar\spring-core-3.0.5.RELEASE.jar;E:\Eclipse Latest\SpringJar\extra Jar\spring-expression-3.0.5.RELEASE.jar;E:\Eclipse Latest\SpringJar\spring-aspects-4.1.6.RELEASE.jar;E:\TestJar\aspectjweaver-1.6.11.jar
user.name=sanju singh
java.vm.specification.version=1.8
sun.java.command=foo.ConfigureApp
java.home=C:\Program Files\Java\jdk1.8.0_45\jre
sun.arch.data.model=64
user.language=en
java.specification.vendor=Oracle Corporation
awt.toolkit=sun.awt.windows.WToolkit
java.vm.info=mixed mode
java.version=1.8.0_45
java.ext.dirs=C:\Program Files\Java\jdk1.8.0_45\jre\lib\ext;C:\Windows\Sun\Java\lib\ext
sun.boot.class.path=C:\Program Files\Java\jdk1.8.0_45\jre\lib\resources.jar;C:\Program Files\Java\jdk1.8.0_45\jre\lib\rt.jar;C:\Program Files\Java\jdk1.8.0_45\jre\lib\sunrsasign.jar;C:\Program Files\Java\jdk1.8.0_45\jre\lib\jsse.jar;C:\Program Files\Java\jdk1.8.0_45\jre\lib\jce.jar;C:\Program Files\Java\jdk1.8.0_45\jre\lib\charsets.jar;C:\Program Files\Java\jdk1.8.0_45\jre\lib\jfr.jar;C:\Program Files\Java\jdk1.8.0_45\jre\classes
java.vendor=Oracle Corporation
file.separator=\
java.vendor.url.bug=http://bugreport.sun.com/bugreport/
sun.io.unicode.encoding=UnicodeLittle
sun.cpu.endian=little
sun.desktop=windows
sun.cpu.isalist=amd64
---- Command Line ---
Empty
---- Full Classpath ---
Empty
---- Compiler Messages ---
Empty
