---- AspectJ Properties ---
AspectJ Compiler 1.6.11 built on Tuesday Mar 15, 2011 at 15:31:04 GMT
---- Dump Properties ---
Dump file: ajcore.20150913.185847.142.txt
Dump reason: org.aspectj.bridge.AbortException
Dump on exception: true
Dump at exit condition: abort
---- Exception Information ---
Message: abort trouble in: 
public abstract class org.springframework.core.NestedRuntimeException extends java.lang.RuntimeException:
  private static final long serialVersionUID = 5439915454935047936
  static void <clinit>():
    staticinitialization(void org.springframework.core.NestedRuntimeException.<clinit>())
    |               LDC org.springframework.core.NestedExceptionUtils   (line 45)
    |               INVOKEVIRTUAL java.lang.Class.getName ()Ljava/lang/String;
    |               POP
    |               RETURN   (line 37)
    staticinitialization(void org.springframework.core.NestedRuntimeException.<clinit>())
  end static void <clinit>()

  public void <init>(String):
                    ALOAD_0     // Lorg/springframework/core/NestedRuntimeException; this   (line 54)
                    ALOAD_1     // Ljava/lang/String; msg
                    INVOKESPECIAL java.lang.RuntimeException.<init> (Ljava/lang/String;)V
    constructor-execution(void org.springframework.core.NestedRuntimeException.<init>(java.lang.String))
    |               RETURN   (line 55)
    constructor-execution(void org.springframework.core.NestedRuntimeException.<init>(java.lang.String))
  end public void <init>(String)

  public void <init>(String, Throwable):
                    ALOAD_0     // Lorg/springframework/core/NestedRuntimeException; this   (line 64)
                    ALOAD_1     // Ljava/lang/String; msg
                    ALOAD_2     // Ljava/lang/Throwable; cause
                    INVOKESPECIAL java.lang.RuntimeException.<init> (Ljava/lang/String;Ljava/lang/Throwable;)V
    constructor-execution(void org.springframework.core.NestedRuntimeException.<init>(java.lang.String, java.lang.Throwable))
    |               RETURN   (line 65)
    constructor-execution(void org.springframework.core.NestedRuntimeException.<init>(java.lang.String, java.lang.Throwable))
  end public void <init>(String, Throwable)

  public String getMessage():
                    ALOAD_0     // Lorg/springframework/core/NestedRuntimeException; this   (line 74)
                    INVOKESPECIAL java.lang.RuntimeException.getMessage ()Ljava/lang/String;
                    ALOAD_0     // Lorg/springframework/core/NestedRuntimeException; this
                    INVOKEVIRTUAL org.springframework.core.NestedRuntimeException.getCause ()Ljava/lang/Throwable;
                    INVOKESTATIC org.springframework.core.NestedExceptionUtils.buildMessage (Ljava/lang/String;Ljava/lang/Throwable;)Ljava/lang/String;
                    ARETURN
  end public String getMessage()

  public Throwable getRootCause():
                    ACONST_NULL   (line 84)
                    ASTORE_1
                    ALOAD_0     // Lorg/springframework/core/NestedRuntimeException; this   (line 85)
                    INVOKEVIRTUAL org.springframework.core.NestedRuntimeException.getCause ()Ljava/lang/Throwable;
                    ASTORE_2
                    GOTO L1   (line 86)
                L0: ALOAD_2     // Ljava/lang/Throwable; cause   (line 87)
                    ASTORE_1     // Ljava/lang/Throwable; rootCause
                    ALOAD_2     // Ljava/lang/Throwable; cause   (line 88)
                    INVOKEVIRTUAL java.lang.Throwable.getCause ()Ljava/lang/Throwable;
                    ASTORE_2     // Ljava/lang/Throwable; cause
                L1: ALOAD_2     // Ljava/lang/Throwable; cause   (line 86)
                    IFNULL L2
                    ALOAD_2     // Ljava/lang/Throwable; cause
                    ALOAD_1     // Ljava/lang/Throwable; rootCause
                    IF_ACMPNE L0
                L2: ALOAD_1     // Ljava/lang/Throwable; rootCause   (line 90)
                    ARETURN
  end public Throwable getRootCause()

  public Throwable getMostSpecificCause():
                    ALOAD_0     // Lorg/springframework/core/NestedRuntimeException; this   (line 102)
                    INVOKEVIRTUAL org.springframework.core.NestedRuntimeException.getRootCause ()Ljava/lang/Throwable;
                    ASTORE_1
                    ALOAD_1     // Ljava/lang/Throwable; rootCause   (line 103)
                    IFNULL L0
                    ALOAD_1     // Ljava/lang/Throwable; rootCause
                    GOTO L1
                L0: ALOAD_0     // Lorg/springframework/core/NestedRuntimeException; this
                L1: ARETURN
  end public Throwable getMostSpecificCause()

  public boolean contains(Class):
                    ALOAD_1     // Ljava/lang/Class; exType   (line 114)
                    IFNONNULL L0
                    ICONST_0   (line 115)
                    IRETURN
                L0: ALOAD_1     // Ljava/lang/Class; exType   (line 117)
                    ALOAD_0     // Lorg/springframework/core/NestedRuntimeException; this
                    INVOKEVIRTUAL java.lang.Class.isInstance (Ljava/lang/Object;)Z
                    IFEQ L1
                    ICONST_1   (line 118)
                    IRETURN
                L1: ALOAD_0     // Lorg/springframework/core/NestedRuntimeException; this   (line 120)
                    INVOKEVIRTUAL org.springframework.core.NestedRuntimeException.getCause ()Ljava/lang/Throwable;
                    ASTORE_2
                    ALOAD_2     // Ljava/lang/Throwable; cause   (line 121)
                    ALOAD_0     // Lorg/springframework/core/NestedRuntimeException; this
                    IF_ACMPNE L2
                    ICONST_0   (line 122)
                    IRETURN
                L2: ALOAD_2     // Ljava/lang/Throwable; cause   (line 124)
                    INSTANCEOF org.springframework.core.NestedRuntimeException
                    IFEQ L6
                    ALOAD_2     // Ljava/lang/Throwable; cause   (line 125)
                    CHECKCAST org.springframework.core.NestedRuntimeException
                    ALOAD_1     // Ljava/lang/Class; exType
                    INVOKEVIRTUAL org.springframework.core.NestedRuntimeException.contains (Ljava/lang/Class;)Z
                    IRETURN
                L3: ALOAD_1     // Ljava/lang/Class; exType   (line 129)
                    ALOAD_2     // Ljava/lang/Throwable; cause
                    INVOKEVIRTUAL java.lang.Class.isInstance (Ljava/lang/Object;)Z
                    IFEQ L4
                    ICONST_1   (line 130)
                    IRETURN
                L4: ALOAD_2     // Ljava/lang/Throwable; cause   (line 132)
                    INVOKEVIRTUAL java.lang.Throwable.getCause ()Ljava/lang/Throwable;
                    ALOAD_2     // Ljava/lang/Throwable; cause
                    IF_ACMPNE L5
                    GOTO L7   (line 133)
                L5: ALOAD_2     // Ljava/lang/Throwable; cause   (line 135)
                    INVOKEVIRTUAL java.lang.Throwable.getCause ()Ljava/lang/Throwable;
                    ASTORE_2     // Ljava/lang/Throwable; cause
                L6: ALOAD_2     // Ljava/lang/Throwable; cause   (line 128)
                    IFNONNULL L3
                L7: ICONST_0   (line 137)
                    IRETURN
  end public boolean contains(Class)
end public abstract class org.springframework.core.NestedRuntimeException
 -- (NullPointerException) null
null
java.lang.NullPointerException
	at org.aspectj.weaver.UnresolvedType.forSignature(UnresolvedType.java:361)
	at org.aspectj.weaver.bcel.BcelObjectType.getDeclaredInterfaces(BcelObjectType.java:275)
	at org.aspectj.weaver.ReferenceType.getDeclaredInterfaces(ReferenceType.java:624)
	at org.aspectj.weaver.ResolvedType.getDirectSupertypes(ResolvedType.java:76)
	at org.aspectj.weaver.patterns.TypePattern.matchesSubtypes(TypePattern.java:178)
	at org.aspectj.weaver.patterns.ExactTypePattern.matchesSubtypes(ExactTypePattern.java:74)
	at org.aspectj.weaver.patterns.TypePattern.matchesStatically(TypePattern.java:130)
	at org.aspectj.weaver.patterns.OrTypePattern.matchesStatically(OrTypePattern.java:76)
	at org.aspectj.weaver.patterns.SignaturePattern.matchesExactlyMethod(SignaturePattern.java:505)
	at org.aspectj.weaver.patterns.SignaturePattern.matchesExactly(SignaturePattern.java:360)
	at org.aspectj.weaver.patterns.SignaturePattern.matches(SignaturePattern.java:320)
	at org.aspectj.weaver.patterns.KindedPointcut.matchInternal(KindedPointcut.java:202)
	at org.aspectj.weaver.patterns.Pointcut.match(Pointcut.java:137)
	at org.aspectj.weaver.patterns.AndPointcut.matchInternal(AndPointcut.java:51)
	at org.aspectj.weaver.patterns.Pointcut.match(Pointcut.java:137)
	at org.aspectj.weaver.patterns.OrPointcut.matchInternal(OrPointcut.java:54)
	at org.aspectj.weaver.patterns.Pointcut.match(Pointcut.java:137)
	at org.aspectj.weaver.ShadowMunger.match(ShadowMunger.java:113)
	at org.aspectj.weaver.Advice.match(Advice.java:109)
	at org.aspectj.weaver.bcel.BcelAdvice.match(BcelAdvice.java:149)
	at org.aspectj.weaver.bcel.BcelClassWeaver.match(BcelClassWeaver.java:3116)
	at org.aspectj.weaver.bcel.BcelClassWeaver.match(BcelClassWeaver.java:2550)
	at org.aspectj.weaver.bcel.BcelClassWeaver.weave(BcelClassWeaver.java:474)
	at org.aspectj.weaver.bcel.BcelClassWeaver.weave(BcelClassWeaver.java:100)
	at org.aspectj.weaver.bcel.BcelWeaver.weave(BcelWeaver.java:1687)
	at org.aspectj.weaver.bcel.BcelWeaver.weaveWithoutDump(BcelWeaver.java:1631)
	at org.aspectj.weaver.bcel.BcelWeaver.weaveAndNotify(BcelWeaver.java:1394)
	at org.aspectj.weaver.bcel.BcelWeaver.weave(BcelWeaver.java:1180)
	at org.aspectj.weaver.tools.WeavingAdaptor.getWovenBytes(WeavingAdaptor.java:467)
	at org.aspectj.weaver.tools.WeavingAdaptor.weaveClass(WeavingAdaptor.java:318)
	at org.aspectj.weaver.loadtime.Aj.preProcess(Aj.java:96)
	at org.aspectj.weaver.loadtime.ClassPreProcessorAgentAdapter.transform(ClassPreProcessorAgentAdapter.java:54)
	at sun.instrument.TransformerManager.transform(TransformerManager.java:188)
	at sun.instrument.InstrumentationImpl.transform(InstrumentationImpl.java:428)
	at java.lang.ClassLoader.defineClass1(Native Method)
	at java.lang.ClassLoader.defineClass(ClassLoader.java:760)
	at java.security.SecureClassLoader.defineClass(SecureClassLoader.java:142)
	at java.net.URLClassLoader.defineClass(URLClassLoader.java:467)
	at java.net.URLClassLoader.access$100(URLClassLoader.java:73)
	at java.net.URLClassLoader$1.run(URLClassLoader.java:368)
	at java.net.URLClassLoader$1.run(URLClassLoader.java:362)
	at java.security.AccessController.doPrivileged(Native Method)
	at java.net.URLClassLoader.findClass(URLClassLoader.java:361)
	at java.lang.ClassLoader.loadClass(ClassLoader.java:424)
	at sun.misc.Launcher$AppClassLoader.loadClass(Launcher.java:331)
	at java.lang.ClassLoader.loadClass(ClassLoader.java:357)
	at java.lang.ClassLoader.defineClass1(Native Method)
	at java.lang.ClassLoader.defineClass(ClassLoader.java:760)
	at java.security.SecureClassLoader.defineClass(SecureClassLoader.java:142)
	at java.net.URLClassLoader.defineClass(URLClassLoader.java:467)
	at java.net.URLClassLoader.access$100(URLClassLoader.java:73)
	at java.net.URLClassLoader$1.run(URLClassLoader.java:368)
	at java.net.URLClassLoader$1.run(URLClassLoader.java:362)
	at java.security.AccessController.doPrivileged(Native Method)
	at java.net.URLClassLoader.findClass(URLClassLoader.java:361)
	at java.lang.ClassLoader.loadClass(ClassLoader.java:424)
	at sun.misc.Launcher$AppClassLoader.loadClass(Launcher.java:331)
	at java.lang.ClassLoader.loadClass(ClassLoader.java:357)
	at foo.ConfigureApp.main(ConfigureApp.java:9)

org.aspectj.bridge.AbortException: trouble in: 
public abstract class org.springframework.core.NestedRuntimeException extends java.lang.RuntimeException:
  private static final long serialVersionUID = 5439915454935047936
  static void <clinit>():
    staticinitialization(void org.springframework.core.NestedRuntimeException.<clinit>())
    |               LDC org.springframework.core.NestedExceptionUtils   (line 45)
    |               INVOKEVIRTUAL java.lang.Class.getName ()Ljava/lang/String;
    |               POP
    |               RETURN   (line 37)
    staticinitialization(void org.springframework.core.NestedRuntimeException.<clinit>())
  end static void <clinit>()

  public void <init>(String):
                    ALOAD_0     // Lorg/springframework/core/NestedRuntimeException; this   (line 54)
                    ALOAD_1     // Ljava/lang/String; msg
                    INVOKESPECIAL java.lang.RuntimeException.<init> (Ljava/lang/String;)V
    constructor-execution(void org.springframework.core.NestedRuntimeException.<init>(java.lang.String))
    |               RETURN   (line 55)
    constructor-execution(void org.springframework.core.NestedRuntimeException.<init>(java.lang.String))
  end public void <init>(String)

  public void <init>(String, Throwable):
                    ALOAD_0     // Lorg/springframework/core/NestedRuntimeException; this   (line 64)
                    ALOAD_1     // Ljava/lang/String; msg
                    ALOAD_2     // Ljava/lang/Throwable; cause
                    INVOKESPECIAL java.lang.RuntimeException.<init> (Ljava/lang/String;Ljava/lang/Throwable;)V
    constructor-execution(void org.springframework.core.NestedRuntimeException.<init>(java.lang.String, java.lang.Throwable))
    |               RETURN   (line 65)
    constructor-execution(void org.springframework.core.NestedRuntimeException.<init>(java.lang.String, java.lang.Throwable))
  end public void <init>(String, Throwable)

  public String getMessage():
                    ALOAD_0     // Lorg/springframework/core/NestedRuntimeException; this   (line 74)
                    INVOKESPECIAL java.lang.RuntimeException.getMessage ()Ljava/lang/String;
                    ALOAD_0     // Lorg/springframework/core/NestedRuntimeException; this
                    INVOKEVIRTUAL org.springframework.core.NestedRuntimeException.getCause ()Ljava/lang/Throwable;
                    INVOKESTATIC org.springframework.core.NestedExceptionUtils.buildMessage (Ljava/lang/String;Ljava/lang/Throwable;)Ljava/lang/String;
                    ARETURN
  end public String getMessage()

  public Throwable getRootCause():
                    ACONST_NULL   (line 84)
                    ASTORE_1
                    ALOAD_0     // Lorg/springframework/core/NestedRuntimeException; this   (line 85)
                    INVOKEVIRTUAL org.springframework.core.NestedRuntimeException.getCause ()Ljava/lang/Throwable;
                    ASTORE_2
                    GOTO L1   (line 86)
                L0: ALOAD_2     // Ljava/lang/Throwable; cause   (line 87)
                    ASTORE_1     // Ljava/lang/Throwable; rootCause
                    ALOAD_2     // Ljava/lang/Throwable; cause   (line 88)
                    INVOKEVIRTUAL java.lang.Throwable.getCause ()Ljava/lang/Throwable;
                    ASTORE_2     // Ljava/lang/Throwable; cause
                L1: ALOAD_2     // Ljava/lang/Throwable; cause   (line 86)
                    IFNULL L2
                    ALOAD_2     // Ljava/lang/Throwable; cause
                    ALOAD_1     // Ljava/lang/Throwable; rootCause
                    IF_ACMPNE L0
                L2: ALOAD_1     // Ljava/lang/Throwable; rootCause   (line 90)
                    ARETURN
  end public Throwable getRootCause()

  public Throwable getMostSpecificCause():
                    ALOAD_0     // Lorg/springframework/core/NestedRuntimeException; this   (line 102)
                    INVOKEVIRTUAL org.springframework.core.NestedRuntimeException.getRootCause ()Ljava/lang/Throwable;
                    ASTORE_1
                    ALOAD_1     // Ljava/lang/Throwable; rootCause   (line 103)
                    IFNULL L0
                    ALOAD_1     // Ljava/lang/Throwable; rootCause
                    GOTO L1
                L0: ALOAD_0     // Lorg/springframework/core/NestedRuntimeException; this
                L1: ARETURN
  end public Throwable getMostSpecificCause()

  public boolean contains(Class):
                    ALOAD_1     // Ljava/lang/Class; exType   (line 114)
                    IFNONNULL L0
                    ICONST_0   (line 115)
                    IRETURN
                L0: ALOAD_1     // Ljava/lang/Class; exType   (line 117)
                    ALOAD_0     // Lorg/springframework/core/NestedRuntimeException; this
                    INVOKEVIRTUAL java.lang.Class.isInstance (Ljava/lang/Object;)Z
                    IFEQ L1
                    ICONST_1   (line 118)
                    IRETURN
                L1: ALOAD_0     // Lorg/springframework/core/NestedRuntimeException; this   (line 120)
                    INVOKEVIRTUAL org.springframework.core.NestedRuntimeException.getCause ()Ljava/lang/Throwable;
                    ASTORE_2
                    ALOAD_2     // Ljava/lang/Throwable; cause   (line 121)
                    ALOAD_0     // Lorg/springframework/core/NestedRuntimeException; this
                    IF_ACMPNE L2
                    ICONST_0   (line 122)
                    IRETURN
                L2: ALOAD_2     // Ljava/lang/Throwable; cause   (line 124)
                    INSTANCEOF org.springframework.core.NestedRuntimeException
                    IFEQ L6
                    ALOAD_2     // Ljava/lang/Throwable; cause   (line 125)
                    CHECKCAST org.springframework.core.NestedRuntimeException
                    ALOAD_1     // Ljava/lang/Class; exType
                    INVOKEVIRTUAL org.springframework.core.NestedRuntimeException.contains (Ljava/lang/Class;)Z
                    IRETURN
                L3: ALOAD_1     // Ljava/lang/Class; exType   (line 129)
                    ALOAD_2     // Ljava/lang/Throwable; cause
                    INVOKEVIRTUAL java.lang.Class.isInstance (Ljava/lang/Object;)Z
                    IFEQ L4
                    ICONST_1   (line 130)
                    IRETURN
                L4: ALOAD_2     // Ljava/lang/Throwable; cause   (line 132)
                    INVOKEVIRTUAL java.lang.Throwable.getCause ()Ljava/lang/Throwable;
                    ALOAD_2     // Ljava/lang/Throwable; cause
                    IF_ACMPNE L5
                    GOTO L7   (line 133)
                L5: ALOAD_2     // Ljava/lang/Throwable; cause   (line 135)
                    INVOKEVIRTUAL java.lang.Throwable.getCause ()Ljava/lang/Throwable;
                    ASTORE_2     // Ljava/lang/Throwable; cause
                L6: ALOAD_2     // Ljava/lang/Throwable; cause   (line 128)
                    IFNONNULL L3
                L7: ICONST_0   (line 137)
                    IRETURN
  end public boolean contains(Class)
end public abstract class org.springframework.core.NestedRuntimeException

	at org.aspectj.bridge.MessageWriter.handleMessage(MessageWriter.java:47)
	at org.aspectj.weaver.tools.WeavingAdaptor$WeavingAdaptorMessageWriter.handleMessage(WeavingAdaptor.java:737)
	at org.aspectj.weaver.tools.WeavingAdaptor$WeavingAdaptorMessageHolder.handleMessage(WeavingAdaptor.java:682)
	at org.aspectj.weaver.bcel.BcelWeaver.weave(BcelWeaver.java:1712)
	at org.aspectj.weaver.bcel.BcelWeaver.weaveWithoutDump(BcelWeaver.java:1631)
	at org.aspectj.weaver.bcel.BcelWeaver.weaveAndNotify(BcelWeaver.java:1394)
	at org.aspectj.weaver.bcel.BcelWeaver.weave(BcelWeaver.java:1180)
	at org.aspectj.weaver.tools.WeavingAdaptor.getWovenBytes(WeavingAdaptor.java:467)
	at org.aspectj.weaver.tools.WeavingAdaptor.weaveClass(WeavingAdaptor.java:318)
	at org.aspectj.weaver.loadtime.Aj.preProcess(Aj.java:96)
	at org.aspectj.weaver.loadtime.ClassPreProcessorAgentAdapter.transform(ClassPreProcessorAgentAdapter.java:54)
	at sun.instrument.TransformerManager.transform(TransformerManager.java:188)
	at sun.instrument.InstrumentationImpl.transform(InstrumentationImpl.java:428)
	at java.lang.ClassLoader.defineClass1(Native Method)
	at java.lang.ClassLoader.defineClass(ClassLoader.java:760)
	at java.security.SecureClassLoader.defineClass(SecureClassLoader.java:142)
	at java.net.URLClassLoader.defineClass(URLClassLoader.java:467)
	at java.net.URLClassLoader.access$100(URLClassLoader.java:73)
	at java.net.URLClassLoader$1.run(URLClassLoader.java:368)
	at java.net.URLClassLoader$1.run(URLClassLoader.java:362)
	at java.security.AccessController.doPrivileged(Native Method)
	at java.net.URLClassLoader.findClass(URLClassLoader.java:361)
	at java.lang.ClassLoader.loadClass(ClassLoader.java:424)
	at sun.misc.Launcher$AppClassLoader.loadClass(Launcher.java:331)
	at java.lang.ClassLoader.loadClass(ClassLoader.java:357)
	at java.lang.ClassLoader.defineClass1(Native Method)
	at java.lang.ClassLoader.defineClass(ClassLoader.java:760)
	at java.security.SecureClassLoader.defineClass(SecureClassLoader.java:142)
	at java.net.URLClassLoader.defineClass(URLClassLoader.java:467)
	at java.net.URLClassLoader.access$100(URLClassLoader.java:73)
	at java.net.URLClassLoader$1.run(URLClassLoader.java:368)
	at java.net.URLClassLoader$1.run(URLClassLoader.java:362)
	at java.security.AccessController.doPrivileged(Native Method)
	at java.net.URLClassLoader.findClass(URLClassLoader.java:361)
	at java.lang.ClassLoader.loadClass(ClassLoader.java:424)
	at sun.misc.Launcher$AppClassLoader.loadClass(Launcher.java:331)
	at java.lang.ClassLoader.loadClass(ClassLoader.java:357)
	at foo.ConfigureApp.main(ConfigureApp.java:9)
---- System Properties ---
java.runtime.name=Java(TM) SE Runtime Environment
sun.boot.library.path=C:\Program Files\Java\jdk1.8.0_45\jre\bin
java.vm.version=25.45-b02
java.vm.vendor=Oracle Corporation
java.vendor.url=http://java.oracle.com/
path.separator=;
java.vm.name=Java HotSpot(TM) 64-Bit Server VM
file.encoding.pkg=sun.io
user.country=US
user.script=
sun.java.launcher=SUN_STANDARD
sun.os.patch.level=
java.vm.specification.name=Java Virtual Machine Specification
user.dir=E:\Eclipse Latest\SpringChap3.3
java.runtime.version=1.8.0_45-b15
java.awt.graphicsenv=sun.awt.Win32GraphicsEnvironment
java.endorsed.dirs=C:\Program Files\Java\jdk1.8.0_45\jre\lib\endorsed
os.arch=amd64
java.io.tmpdir=C:\Users\SANJUS~1\AppData\Local\Temp\
line.separator=

java.vm.specification.vendor=Oracle Corporation
user.variant=
os.name=Windows 7
sun.jnu.encoding=Cp1252
java.library.path=C:\Program Files\Java\jdk1.8.0_45\bin;C:\Windows\Sun\Java\bin;C:\Windows\system32;C:\Windows;C:/Program Files/Java/jdk1.8.0_45/bin/../jre/bin/server;C:/Program Files/Java/jdk1.8.0_45/bin/../jre/bin;C:/Program Files/Java/jdk1.8.0_45/bin/../jre/lib/amd64;C:\oraclexe\app\oracle\product\10.2.0\server\bin;C:\Program Files\Java\jdk1.8.0_45\bin;C:\Program Files (x86)\Java\jre1.8.0_45\bin;C:\ProgramData\Oracle\Java\javapath;C:\Windows\system32;C:\Windows;C:\Windows\System32\Wbem;C:\Windows\System32\WindowsPowerShell\v1.0\;C:\Python27;;E:\Eclipse Latest\eclipse-jee-luna-SR2-win32-x86_64\eclipse;;.
java.specification.name=Java Platform API Specification
java.class.version=52.0
sun.management.compiler=HotSpot 64-Bit Tiered Compilers
os.version=6.1
user.home=C:\Users\sanju singh
user.timezone=Asia/Calcutta
java.awt.printerjob=sun.awt.windows.WPrinterJob
file.encoding=Cp1252
java.specification.version=1.8
java.class.path=E:\Eclipse Latest\SpringChap3.3\bin;E:\Eclipse Latest\SpringJar\extra Jar\aopalliance-1.0.jar;E:\Eclipse Latest\SpringJar\extra Jar\asm-3.3.1.jar;E:\Eclipse Latest\SpringJar\extra Jar\aspectjrt-1.6.11.jar;E:\Eclipse Latest\SpringJar\extra Jar\aspectjweaver-1.6.11.jar;E:\Eclipse Latest\SpringJar\extra Jar\cglib-2.2.2.jar;E:\Eclipse Latest\SpringJar\extra Jar\commons-logging-1.1.1.jar;E:\Eclipse Latest\SpringJar\extra Jar\junit-4.8.2.jar;E:\Eclipse Latest\SpringJar\extra Jar\spring-aop-3.0.5.RELEASE.jar;E:\Eclipse Latest\SpringJar\extra Jar\spring-asm-3.0.5.RELEASE.jar;E:\Eclipse Latest\SpringJar\extra Jar\spring-beans-3.0.5.RELEASE.jar;E:\Eclipse Latest\SpringJar\extra Jar\spring-context-3.0.5.RELEASE.jar;E:\Eclipse Latest\SpringJar\extra Jar\spring-core-3.0.5.RELEASE.jar;E:\Eclipse Latest\SpringJar\extra Jar\spring-expression-3.0.5.RELEASE.jar;E:\Eclipse Latest\SpringJar\spring-aspects-4.1.6.RELEASE.jar;E:\TestJar\aspectjweaver-1.6.11.jar
user.name=sanju singh
java.vm.specification.version=1.8
sun.java.command=foo.ConfigureApp
java.home=C:\Program Files\Java\jdk1.8.0_45\jre
sun.arch.data.model=64
user.language=en
java.specification.vendor=Oracle Corporation
awt.toolkit=sun.awt.windows.WToolkit
java.vm.info=mixed mode
java.version=1.8.0_45
java.ext.dirs=C:\Program Files\Java\jdk1.8.0_45\jre\lib\ext;C:\Windows\Sun\Java\lib\ext
sun.boot.class.path=C:\Program Files\Java\jdk1.8.0_45\jre\lib\resources.jar;C:\Program Files\Java\jdk1.8.0_45\jre\lib\rt.jar;C:\Program Files\Java\jdk1.8.0_45\jre\lib\sunrsasign.jar;C:\Program Files\Java\jdk1.8.0_45\jre\lib\jsse.jar;C:\Program Files\Java\jdk1.8.0_45\jre\lib\jce.jar;C:\Program Files\Java\jdk1.8.0_45\jre\lib\charsets.jar;C:\Program Files\Java\jdk1.8.0_45\jre\lib\jfr.jar;C:\Program Files\Java\jdk1.8.0_45\jre\classes
java.vendor=Oracle Corporation
file.separator=\
java.vendor.url.bug=http://bugreport.sun.com/bugreport/
sun.io.unicode.encoding=UnicodeLittle
sun.cpu.endian=little
sun.desktop=windows
sun.cpu.isalist=amd64
---- Command Line ---
Empty
---- Full Classpath ---
Empty
---- Compiler Messages ---
Empty
