---- AspectJ Properties ---
AspectJ Compiler 1.6.11 built on Tuesday Mar 15, 2011 at 15:31:04 GMT
---- Dump Properties ---
Dump file: ajcore.20150913.185847.003.txt
Dump reason: abort
Dump on exception: true
Dump at exit condition: abort
---- System Properties ---
java.runtime.name=Java(TM) SE Runtime Environment
sun.boot.library.path=C:\Program Files\Java\jdk1.8.0_45\jre\bin
java.vm.version=25.45-b02
java.vm.vendor=Oracle Corporation
java.vendor.url=http://java.oracle.com/
path.separator=;
java.vm.name=Java HotSpot(TM) 64-Bit Server VM
file.encoding.pkg=sun.io
user.country=US
user.script=
sun.java.launcher=SUN_STANDARD
sun.os.patch.level=
java.vm.specification.name=Java Virtual Machine Specification
user.dir=E:\Eclipse Latest\SpringChap3.3
java.runtime.version=1.8.0_45-b15
java.awt.graphicsenv=sun.awt.Win32GraphicsEnvironment
java.endorsed.dirs=C:\Program Files\Java\jdk1.8.0_45\jre\lib\endorsed
os.arch=amd64
java.io.tmpdir=C:\Users\SANJUS~1\AppData\Local\Temp\
line.separator=

java.vm.specification.vendor=Oracle Corporation
user.variant=
os.name=Windows 7
sun.jnu.encoding=Cp1252
java.library.path=C:\Program Files\Java\jdk1.8.0_45\bin;C:\Windows\Sun\Java\bin;C:\Windows\system32;C:\Windows;C:/Program Files/Java/jdk1.8.0_45/bin/../jre/bin/server;C:/Program Files/Java/jdk1.8.0_45/bin/../jre/bin;C:/Program Files/Java/jdk1.8.0_45/bin/../jre/lib/amd64;C:\oraclexe\app\oracle\product\10.2.0\server\bin;C:\Program Files\Java\jdk1.8.0_45\bin;C:\Program Files (x86)\Java\jre1.8.0_45\bin;C:\ProgramData\Oracle\Java\javapath;C:\Windows\system32;C:\Windows;C:\Windows\System32\Wbem;C:\Windows\System32\WindowsPowerShell\v1.0\;C:\Python27;;E:\Eclipse Latest\eclipse-jee-luna-SR2-win32-x86_64\eclipse;;.
java.specification.name=Java Platform API Specification
java.class.version=52.0
sun.management.compiler=HotSpot 64-Bit Tiered Compilers
os.version=6.1
user.home=C:\Users\sanju singh
user.timezone=Asia/Calcutta
java.awt.printerjob=sun.awt.windows.WPrinterJob
file.encoding=Cp1252
java.specification.version=1.8
java.class.path=E:\Eclipse Latest\SpringChap3.3\bin;E:\Eclipse Latest\SpringJar\extra Jar\aopalliance-1.0.jar;E:\Eclipse Latest\SpringJar\extra Jar\asm-3.3.1.jar;E:\Eclipse Latest\SpringJar\extra Jar\aspectjrt-1.6.11.jar;E:\Eclipse Latest\SpringJar\extra Jar\aspectjweaver-1.6.11.jar;E:\Eclipse Latest\SpringJar\extra Jar\cglib-2.2.2.jar;E:\Eclipse Latest\SpringJar\extra Jar\commons-logging-1.1.1.jar;E:\Eclipse Latest\SpringJar\extra Jar\junit-4.8.2.jar;E:\Eclipse Latest\SpringJar\extra Jar\spring-aop-3.0.5.RELEASE.jar;E:\Eclipse Latest\SpringJar\extra Jar\spring-asm-3.0.5.RELEASE.jar;E:\Eclipse Latest\SpringJar\extra Jar\spring-beans-3.0.5.RELEASE.jar;E:\Eclipse Latest\SpringJar\extra Jar\spring-context-3.0.5.RELEASE.jar;E:\Eclipse Latest\SpringJar\extra Jar\spring-core-3.0.5.RELEASE.jar;E:\Eclipse Latest\SpringJar\extra Jar\spring-expression-3.0.5.RELEASE.jar;E:\Eclipse Latest\SpringJar\spring-aspects-4.1.6.RELEASE.jar;E:\TestJar\aspectjweaver-1.6.11.jar
user.name=sanju singh
java.vm.specification.version=1.8
sun.java.command=foo.ConfigureApp
java.home=C:\Program Files\Java\jdk1.8.0_45\jre
sun.arch.data.model=64
user.language=en
java.specification.vendor=Oracle Corporation
awt.toolkit=sun.awt.windows.WToolkit
java.vm.info=mixed mode
java.version=1.8.0_45
java.ext.dirs=C:\Program Files\Java\jdk1.8.0_45\jre\lib\ext;C:\Windows\Sun\Java\lib\ext
sun.boot.class.path=C:\Program Files\Java\jdk1.8.0_45\jre\lib\resources.jar;C:\Program Files\Java\jdk1.8.0_45\jre\lib\rt.jar;C:\Program Files\Java\jdk1.8.0_45\jre\lib\sunrsasign.jar;C:\Program Files\Java\jdk1.8.0_45\jre\lib\jsse.jar;C:\Program Files\Java\jdk1.8.0_45\jre\lib\jce.jar;C:\Program Files\Java\jdk1.8.0_45\jre\lib\charsets.jar;C:\Program Files\Java\jdk1.8.0_45\jre\lib\jfr.jar;C:\Program Files\Java\jdk1.8.0_45\jre\classes
java.vendor=Oracle Corporation
file.separator=\
java.vendor.url.bug=http://bugreport.sun.com/bugreport/
sun.io.unicode.encoding=UnicodeLittle
sun.cpu.endian=little
sun.desktop=windows
sun.cpu.isalist=amd64
---- Command Line ---
Empty
---- Full Classpath ---
Empty
---- Compiler Messages ---
info AspectJ Weaver Version 1.6.11 built on Tuesday Mar 15, 2011 at 15:31:04 GMT
info register classloader sun.misc.Launcher$AppClassLoader@14dad5dc
info using configuration file:/E:/Eclipse%20Latest/SpringJar/spring-aspects-4.1.6.RELEASE.jar!/META-INF/aop.xml
error can't determine annotations of missing type org.springframework.cache.annotation.CachePut
when weaving type org.springframework.context.support.AbstractApplicationContext$1
when weaving classes 
when weaving 
 [Xlint:cantFindType]
error can't determine annotations of missing type org.springframework.cache.annotation.Cacheable
when weaving type org.springframework.context.support.AbstractApplicationContext$1
when weaving classes 
when weaving 
 [Xlint:cantFindType]
error can't determine annotations of missing type org.springframework.cache.annotation.CacheEvict
when weaving type org.springframework.context.support.AbstractApplicationContext$1
when weaving classes 
when weaving 
 [Xlint:cantFindType]
error can't determine annotations of missing type org.springframework.cache.annotation.Caching
when weaving type org.springframework.context.support.AbstractApplicationContext$1
when weaving classes 
when weaving 
 [Xlint:cantFindType]
error can't determine annotations of missing type org.springframework.transaction.annotation.Transactional
when weaving type org.springframework.context.support.AbstractApplicationContext$1
when weaving classes 
when weaving 
 [Xlint:cantFindType]
abort trouble in: 
final class org.springframework.context.support.AbstractApplicationContext$1 extends org.springframework.context.support.ReadOnlySystemAttributesMap:
  final org.springframework.context.support.AbstractApplicationContext this$0
  void <init>(org.springframework.context.support.AbstractApplicationContext):
                    ALOAD_0     // Lorg/springframework/context/support/AbstractApplicationContext$1; this   (line 1)
                    ALOAD_1
                    PUTFIELD org.springframework.context.support.AbstractApplicationContext$1.this$0 Lorg/springframework/context/support/AbstractApplicationContext;
                    ALOAD_0     // Lorg/springframework/context/support/AbstractApplicationContext$1; this   (line 514)
                    INVOKESPECIAL org.springframework.context.support.ReadOnlySystemAttributesMap.<init> ()V
    constructor-execution(void org.springframework.context.support.AbstractApplicationContext$1.<init>(org.springframework.context.support.AbstractApplicationContext))
    |               RETURN
    constructor-execution(void org.springframework.context.support.AbstractApplicationContext$1.<init>(org.springframework.context.support.AbstractApplicationContext))
  end void <init>(org.springframework.context.support.AbstractApplicationContext)

  protected String getSystemAttribute(String):
    catch java.security.AccessControlException -> E0
    |               ALOAD_1     // Ljava/lang/String; propertyName   (line 518)
    |               INVOKESTATIC java.lang.System.getProperty (Ljava/lang/String;)Ljava/lang/String;
    catch java.security.AccessControlException -> E0
                    ARETURN
                E0: ASTORE_2   (line 520)
                    ALOAD_0     // Lorg/springframework/context/support/AbstractApplicationContext$1; this   (line 521)
                    GETFIELD org.springframework.context.support.AbstractApplicationContext$1.this$0 Lorg/springframework/context/support/AbstractApplicationContext;
                    GETFIELD org.springframework.context.support.AbstractApplicationContext.logger Lorg/apache/commons/logging/Log;
                    INVOKEINTERFACE org.apache.commons.logging.Log.isInfoEnabled ()Z
                    IFEQ L0
                    ALOAD_0     // Lorg/springframework/context/support/AbstractApplicationContext$1; this   (line 522)
                    GETFIELD org.springframework.context.support.AbstractApplicationContext$1.this$0 Lorg/springframework/context/support/AbstractApplicationContext;
                    GETFIELD org.springframework.context.support.AbstractApplicationContext.logger Lorg/apache/commons/logging/Log;
                    NEW java.lang.StringBuilder
                    DUP
                    LDC "Not allowed to obtain system property ["
                    INVOKESPECIAL java.lang.StringBuilder.<init> (Ljava/lang/String;)V
                    ALOAD_1     // Ljava/lang/String; propertyName
                    INVOKEVIRTUAL java.lang.StringBuilder.append (Ljava/lang/String;)Ljava/lang/StringBuilder;
                    LDC "]: "
                    INVOKEVIRTUAL java.lang.StringBuilder.append (Ljava/lang/String;)Ljava/lang/StringBuilder;
                    ALOAD_2     // Ljava/security/AccessControlException; ex   (line 523)
                    INVOKEVIRTUAL java.security.AccessControlException.getMessage ()Ljava/lang/String;
                    INVOKEVIRTUAL java.lang.StringBuilder.append (Ljava/lang/String;)Ljava/lang/StringBuilder;
                    INVOKEVIRTUAL java.lang.StringBuilder.toString ()Ljava/lang/String;
                    INVOKEINTERFACE org.apache.commons.logging.Log.info (Ljava/lang/Object;)V   (line 522)
                L0: ACONST_NULL   (line 525)
                    ARETURN
  end protected String getSystemAttribute(String)

end final class org.springframework.context.support.AbstractApplicationContext$1
 -- (ClassFormatException) File: 'java.util.Map$Entry': Invalid byte tag in constant pool: 15
File: 'java.util.Map$Entry': Invalid byte tag in constant pool: 15
org.aspectj.apache.bcel.classfile.ClassFormatException: File: 'java.util.Map$Entry': Invalid byte tag in constant pool: 15
	at org.aspectj.apache.bcel.classfile.ClassParser.readConstantPool(ClassParser.java:192)
	at org.aspectj.apache.bcel.classfile.ClassParser.parse(ClassParser.java:131)
	at org.aspectj.apache.bcel.util.ClassLoaderRepository.loadClass(ClassLoaderRepository.java:323)
	at org.aspectj.weaver.bcel.BcelWorld.lookupJavaClass(BcelWorld.java:402)
	at org.aspectj.weaver.bcel.BcelWorld.resolveDelegate(BcelWorld.java:376)
	at org.aspectj.weaver.ltw.LTWWorld.resolveDelegate(LTWWorld.java:111)
	at org.aspectj.weaver.World.resolveToReferenceType(World.java:467)
	at org.aspectj.weaver.World.resolve(World.java:308)
	at org.aspectj.weaver.World.resolve(World.java:218)
	at org.aspectj.weaver.UnresolvedType.resolve(UnresolvedType.java:593)
	at org.aspectj.weaver.bcel.BcelGenericSignatureToTypeXConverter.classTypeSignature2TypeX(BcelGenericSignatureToTypeXConverter.java:72)
	at org.aspectj.weaver.bcel.BcelGenericSignatureToTypeXConverter.fieldTypeSignature2TypeX(BcelGenericSignatureToTypeXConverter.java:114)
	at org.aspectj.weaver.bcel.BcelGenericSignatureToTypeXConverter.typeArgument2TypeX(BcelGenericSignatureToTypeXConverter.java:182)
	at org.aspectj.weaver.bcel.BcelGenericSignatureToTypeXConverter.classTypeSignature2TypeX(BcelGenericSignatureToTypeXConverter.java:87)
	at org.aspectj.weaver.bcel.BcelGenericSignatureToTypeXConverter.fieldTypeSignature2TypeX(BcelGenericSignatureToTypeXConverter.java:114)
	at org.aspectj.weaver.bcel.BcelGenericSignatureToTypeXConverter.typeSignature2TypeX(BcelGenericSignatureToTypeXConverter.java:201)
	at org.aspectj.weaver.bcel.BcelGenericSignatureToTypeXConverter.typeSignature2TypeX(BcelGenericSignatureToTypeXConverter.java:189)
	at org.aspectj.weaver.bcel.BcelMethod.unpackGenericSignature(BcelMethod.java:596)
	at org.aspectj.weaver.bcel.BcelMethod.getGenericReturnType(BcelMethod.java:544)
	at org.aspectj.weaver.ResolvedMemberImpl.parameterizedWith(ResolvedMemberImpl.java:757)
	at org.aspectj.weaver.ResolvedMemberImpl.parameterizedWith(ResolvedMemberImpl.java:710)
	at org.aspectj.weaver.ReferenceType.getDeclaredMethods(ReferenceType.java:766)
	at org.aspectj.weaver.ResolvedType$MethodGetterIncludingItds.get(ResolvedType.java:246)
	at org.aspectj.weaver.ResolvedType$MethodGetterIncludingItds.get(ResolvedType.java:244)
	at org.aspectj.weaver.Iterators$4$1.hasNext(Iterators.java:213)
	at org.aspectj.weaver.Iterators$4.hasNext(Iterators.java:230)
	at org.aspectj.weaver.ResolvedType.lookupResolvedMember(ResolvedType.java:611)
	at org.aspectj.weaver.JoinPointSignatureIterator.findSignaturesFromSupertypes(JoinPointSignatureIterator.java:192)
	at org.aspectj.weaver.JoinPointSignatureIterator.findSignaturesFromSupertypes(JoinPointSignatureIterator.java:238)
	at org.aspectj.weaver.JoinPointSignatureIterator.hasNext(JoinPointSignatureIterator.java:68)
	at org.aspectj.weaver.patterns.SignaturePattern.matches(SignaturePattern.java:317)
	at org.aspectj.weaver.patterns.KindedPointcut.matchInternal(KindedPointcut.java:202)
	at org.aspectj.weaver.patterns.Pointcut.match(Pointcut.java:137)
	at org.aspectj.weaver.patterns.AndPointcut.matchInternal(AndPointcut.java:51)
	at org.aspectj.weaver.patterns.Pointcut.match(Pointcut.java:137)
	at org.aspectj.weaver.patterns.OrPointcut.matchInternal(OrPointcut.java:50)
	at org.aspectj.weaver.patterns.Pointcut.match(Pointcut.java:137)
	at org.aspectj.weaver.ShadowMunger.match(ShadowMunger.java:113)
	at org.aspectj.weaver.Advice.match(Advice.java:109)
	at org.aspectj.weaver.bcel.BcelAdvice.match(BcelAdvice.java:149)
	at org.aspectj.weaver.bcel.BcelClassWeaver.match(BcelClassWeaver.java:3116)
	at org.aspectj.weaver.bcel.BcelClassWeaver.match(BcelClassWeaver.java:2550)
	at org.aspectj.weaver.bcel.BcelClassWeaver.weave(BcelClassWeaver.java:474)
	at org.aspectj.weaver.bcel.BcelClassWeaver.weave(BcelClassWeaver.java:100)
	at org.aspectj.weaver.bcel.BcelWeaver.weave(BcelWeaver.java:1687)
	at org.aspectj.weaver.bcel.BcelWeaver.weaveWithoutDump(BcelWeaver.java:1631)
	at org.aspectj.weaver.bcel.BcelWeaver.weaveAndNotify(BcelWeaver.java:1394)
	at org.aspectj.weaver.bcel.BcelWeaver.weave(BcelWeaver.java:1180)
	at org.aspectj.weaver.tools.WeavingAdaptor.getWovenBytes(WeavingAdaptor.java:467)
	at org.aspectj.weaver.tools.WeavingAdaptor.weaveClass(WeavingAdaptor.java:318)
	at org.aspectj.weaver.loadtime.Aj.preProcess(Aj.java:96)
	at org.aspectj.weaver.loadtime.ClassPreProcessorAgentAdapter.transform(ClassPreProcessorAgentAdapter.java:54)
	at sun.instrument.TransformerManager.transform(TransformerManager.java:188)
	at sun.instrument.InstrumentationImpl.transform(InstrumentationImpl.java:428)
	at java.lang.ClassLoader.defineClass1(Native Method)
	at java.lang.ClassLoader.defineClass(ClassLoader.java:760)
	at java.security.SecureClassLoader.defineClass(SecureClassLoader.java:142)
	at java.net.URLClassLoader.defineClass(URLClassLoader.java:467)
	at java.net.URLClassLoader.access$100(URLClassLoader.java:73)
	at java.net.URLClassLoader$1.run(URLClassLoader.java:368)
	at java.net.URLClassLoader$1.run(URLClassLoader.java:362)
	at java.security.AccessController.doPrivileged(Native Method)
	at java.net.URLClassLoader.findClass(URLClassLoader.java:361)
	at java.lang.ClassLoader.loadClass(ClassLoader.java:424)
	at sun.misc.Launcher$AppClassLoader.loadClass(Launcher.java:331)
	at java.lang.ClassLoader.loadClass(ClassLoader.java:357)
	at foo.ConfigureApp.main(ConfigureApp.java:9)

error can't determine annotations of missing type org.springframework.cache.annotation.CachePut
when weaving type org.springframework.context.support.ReadOnlySystemAttributesMap
when weaving classes 
when weaving 
 [Xlint:cantFindType]
error can't determine annotations of missing type org.springframework.cache.annotation.Cacheable
when weaving type org.springframework.context.support.ReadOnlySystemAttributesMap
when weaving classes 
when weaving 
 [Xlint:cantFindType]
error can't determine annotations of missing type org.springframework.cache.annotation.CacheEvict
when weaving type org.springframework.context.support.ReadOnlySystemAttributesMap
when weaving classes 
when weaving 
 [Xlint:cantFindType]
error can't determine annotations of missing type org.springframework.cache.annotation.Caching
when weaving type org.springframework.context.support.ReadOnlySystemAttributesMap
when weaving classes 
when weaving 
 [Xlint:cantFindType]
error can't determine annotations of missing type org.springframework.transaction.annotation.Transactional
when weaving type org.springframework.context.support.ReadOnlySystemAttributesMap
when weaving classes 
when weaving 
 [Xlint:cantFindType]
abort trouble in: 
abstract class org.springframework.context.support.ReadOnlySystemAttributesMap extends java.lang.Object implements java.util.Map:
  void <init>():
                    ALOAD_0     // Lorg/springframework/context/support/ReadOnlySystemAttributesMap; this   (line 33)
                    INVOKESPECIAL java.lang.Object.<init> ()V
    constructor-execution(void org.springframework.context.support.ReadOnlySystemAttributesMap.<init>())
    |               RETURN
    constructor-execution(void org.springframework.context.support.ReadOnlySystemAttributesMap.<init>())
  end void <init>()

  public boolean containsKey(Object):
                    ALOAD_0     // Lorg/springframework/context/support/ReadOnlySystemAttributesMap; this   (line 36)
                    ALOAD_1     // Ljava/lang/Object; key
                    INVOKEVIRTUAL org.springframework.context.support.ReadOnlySystemAttributesMap.get (Ljava/lang/Object;)Ljava/lang/String;
                    IFNULL L0
                    ICONST_1
                    IRETURN
                L0: ICONST_0
                    IRETURN
  end public boolean containsKey(Object)

  public String get(Object):
                    ALOAD_1     // Ljava/lang/Object; key   (line 40)
                    INSTANCEOF java.lang.String
                    IFEQ L0
                    ALOAD_1     // Ljava/lang/Object; key   (line 41)
                    CHECKCAST java.lang.String
                    ASTORE_2
                    ALOAD_0     // Lorg/springframework/context/support/ReadOnlySystemAttributesMap; this   (line 42)
                    ALOAD_2     // Ljava/lang/String; attributeName
                    INVOKEVIRTUAL org.springframework.context.support.ReadOnlySystemAttributesMap.getSystemAttribute (Ljava/lang/String;)Ljava/lang/String;
                    ARETURN
                L0: ACONST_NULL   (line 45)
                    ARETURN
  end public String get(Object)

  public boolean isEmpty():
                    ICONST_0   (line 50)
                    IRETURN
  end public boolean isEmpty()

  protected abstract String getSystemAttribute(String);

  public int size():
                    NEW java.lang.UnsupportedOperationException   (line 63)
                    DUP
                    INVOKESPECIAL java.lang.UnsupportedOperationException.<init> ()V
                    ATHROW
  end public int size()

  public String put(String, String):
                    NEW java.lang.UnsupportedOperationException   (line 67)
                    DUP
                    INVOKESPECIAL java.lang.UnsupportedOperationException.<init> ()V
                    ATHROW
  end public String put(String, String)

  public boolean containsValue(Object):
                    NEW java.lang.UnsupportedOperationException   (line 71)
                    DUP
                    INVOKESPECIAL java.lang.UnsupportedOperationException.<init> ()V
                    ATHROW
  end public boolean containsValue(Object)

  public String remove(Object):
                    NEW java.lang.UnsupportedOperationException   (line 75)
                    DUP
                    INVOKESPECIAL java.lang.UnsupportedOperationException.<init> ()V
                    ATHROW
  end public String remove(Object)

  public void clear():
                    NEW java.lang.UnsupportedOperationException   (line 79)
                    DUP
                    INVOKESPECIAL java.lang.UnsupportedOperationException.<init> ()V
                    ATHROW
  end public void clear()

  public java.util.Set keySet():
                    NEW java.lang.UnsupportedOperationException   (line 83)
                    DUP
                    INVOKESPECIAL java.lang.UnsupportedOperationException.<init> ()V
                    ATHROW
  end public java.util.Set keySet()

  public void putAll(java.util.Map):
                    NEW java.lang.UnsupportedOperationException   (line 87)
                    DUP
                    INVOKESPECIAL java.lang.UnsupportedOperationException.<init> ()V
                    ATHROW
  end public void putAll(java.util.Map)

  public java.util.Collection values():
                    NEW java.lang.UnsupportedOperationException   (line 91)
                    DUP
                    INVOKESPECIAL java.lang.UnsupportedOperationException.<init> ()V
                    ATHROW
  end public java.util.Collection values()

  public java.util.Set entrySet():
                    NEW java.lang.UnsupportedOperationException   (line 95)
                    DUP
                    INVOKESPECIAL java.lang.UnsupportedOperationException.<init> ()V
                    ATHROW
  end public java.util.Set entrySet()

  public volatile Object get(Object):
                    ALOAD_0   (line 1)
                    ALOAD_1
                    INVOKEVIRTUAL org.springframework.context.support.ReadOnlySystemAttributesMap.get (Ljava/lang/Object;)Ljava/lang/String;
                    ARETURN
  end public volatile Object get(Object)

  public volatile Object remove(Object):
                    ALOAD_0   (line 1)
                    ALOAD_1
                    INVOKEVIRTUAL org.springframework.context.support.ReadOnlySystemAttributesMap.remove (Ljava/lang/Object;)Ljava/lang/String;
                    ARETURN
  end public volatile Object remove(Object)

  public volatile Object put(Object, Object):
                    ALOAD_0   (line 1)
                    ALOAD_1
                    CHECKCAST java.lang.String
                    ALOAD_2
                    CHECKCAST java.lang.String
                    INVOKEVIRTUAL org.springframework.context.support.ReadOnlySystemAttributesMap.put (Ljava/lang/String;Ljava/lang/String;)Ljava/lang/String;
                    ARETURN
  end public volatile Object put(Object, Object)

end abstract class org.springframework.context.support.ReadOnlySystemAttributesMap
 -- (ClassFormatException) File: 'java.lang.CharSequence': Invalid byte tag in constant pool: 15
File: 'java.lang.CharSequence': Invalid byte tag in constant pool: 15
org.aspectj.apache.bcel.classfile.ClassFormatException: File: 'java.lang.CharSequence': Invalid byte tag in constant pool: 15
	at org.aspectj.apache.bcel.classfile.ClassParser.readConstantPool(ClassParser.java:192)
	at org.aspectj.apache.bcel.classfile.ClassParser.parse(ClassParser.java:131)
	at org.aspectj.apache.bcel.util.ClassLoaderRepository.loadClass(ClassLoaderRepository.java:323)
	at org.aspectj.weaver.bcel.BcelWorld.lookupJavaClass(BcelWorld.java:402)
	at org.aspectj.weaver.bcel.BcelWorld.resolveDelegate(BcelWorld.java:376)
	at org.aspectj.weaver.ltw.LTWWorld.resolveDelegate(LTWWorld.java:111)
	at org.aspectj.weaver.World.resolveToReferenceType(World.java:467)
	at org.aspectj.weaver.World.resolve(World.java:308)
	at org.aspectj.weaver.World.resolve(World.java:218)
	at org.aspectj.weaver.bcel.BcelGenericSignatureToTypeXConverter.classTypeSignature2TypeX(BcelGenericSignatureToTypeXConverter.java:97)
	at org.aspectj.weaver.bcel.BcelGenericSignatureToTypeXConverter.classTypeSignature2TypeX(BcelGenericSignatureToTypeXConverter.java:41)
	at org.aspectj.weaver.bcel.BcelObjectType.ensureGenericSignatureUnpacked(BcelObjectType.java:810)
	at org.aspectj.weaver.bcel.BcelObjectType.getDeclaredInterfaces(BcelObjectType.java:257)
	at org.aspectj.weaver.ReferenceType.getDeclaredInterfaces(ReferenceType.java:624)
	at org.aspectj.weaver.ResolvedType.getDirectSupertypes(ResolvedType.java:76)
	at org.aspectj.weaver.patterns.TypePattern.matchesSubtypes(TypePattern.java:178)
	at org.aspectj.weaver.patterns.ExactTypePattern.matchesSubtypes(ExactTypePattern.java:74)
	at org.aspectj.weaver.patterns.TypePattern.matchesStatically(TypePattern.java:130)
	at org.aspectj.weaver.patterns.OrTypePattern.matchesStatically(OrTypePattern.java:76)
	at org.aspectj.weaver.patterns.SignaturePattern.matchesExactlyMethod(SignaturePattern.java:505)
	at org.aspectj.weaver.patterns.SignaturePattern.matchesExactly(SignaturePattern.java:360)
	at org.aspectj.weaver.patterns.SignaturePattern.matches(SignaturePattern.java:320)
	at org.aspectj.weaver.patterns.KindedPointcut.matchInternal(KindedPointcut.java:202)
	at org.aspectj.weaver.patterns.Pointcut.match(Pointcut.java:137)
	at org.aspectj.weaver.patterns.AndPointcut.matchInternal(AndPointcut.java:51)
	at org.aspectj.weaver.patterns.Pointcut.match(Pointcut.java:137)
	at org.aspectj.weaver.patterns.OrPointcut.matchInternal(OrPointcut.java:54)
	at org.aspectj.weaver.patterns.Pointcut.match(Pointcut.java:137)
	at org.aspectj.weaver.ShadowMunger.match(ShadowMunger.java:113)
	at org.aspectj.weaver.Advice.match(Advice.java:109)
	at org.aspectj.weaver.bcel.BcelAdvice.match(BcelAdvice.java:149)
	at org.aspectj.weaver.bcel.BcelClassWeaver.match(BcelClassWeaver.java:3116)
	at org.aspectj.weaver.bcel.BcelClassWeaver.match(BcelClassWeaver.java:2550)
	at org.aspectj.weaver.bcel.BcelClassWeaver.weave(BcelClassWeaver.java:474)
	at org.aspectj.weaver.bcel.BcelClassWeaver.weave(BcelClassWeaver.java:100)
	at org.aspectj.weaver.bcel.BcelWeaver.weave(BcelWeaver.java:1687)
	at org.aspectj.weaver.bcel.BcelWeaver.weaveWithoutDump(BcelWeaver.java:1631)
	at org.aspectj.weaver.bcel.BcelWeaver.weaveAndNotify(BcelWeaver.java:1394)
	at org.aspectj.weaver.bcel.BcelWeaver.weave(BcelWeaver.java:1180)
	at org.aspectj.weaver.tools.WeavingAdaptor.getWovenBytes(WeavingAdaptor.java:467)
	at org.aspectj.weaver.tools.WeavingAdaptor.weaveClass(WeavingAdaptor.java:318)
	at org.aspectj.weaver.loadtime.Aj.preProcess(Aj.java:96)
	at org.aspectj.weaver.loadtime.ClassPreProcessorAgentAdapter.transform(ClassPreProcessorAgentAdapter.java:54)
	at sun.instrument.TransformerManager.transform(TransformerManager.java:188)
	at sun.instrument.InstrumentationImpl.transform(InstrumentationImpl.java:428)
	at java.lang.ClassLoader.defineClass1(Native Method)
	at java.lang.ClassLoader.defineClass(ClassLoader.java:760)
	at java.security.SecureClassLoader.defineClass(SecureClassLoader.java:142)
	at java.net.URLClassLoader.defineClass(URLClassLoader.java:467)
	at java.net.URLClassLoader.access$100(URLClassLoader.java:73)
	at java.net.URLClassLoader$1.run(URLClassLoader.java:368)
	at java.net.URLClassLoader$1.run(URLClassLoader.java:362)
	at java.security.AccessController.doPrivileged(Native Method)
	at java.net.URLClassLoader.findClass(URLClassLoader.java:361)
	at java.lang.ClassLoader.loadClass(ClassLoader.java:424)
	at sun.misc.Launcher$AppClassLoader.loadClass(Launcher.java:331)
	at java.lang.ClassLoader.loadClass(ClassLoader.java:357)
	at java.lang.ClassLoader.defineClass1(Native Method)
	at java.lang.ClassLoader.defineClass(ClassLoader.java:760)
	at java.security.SecureClassLoader.defineClass(SecureClassLoader.java:142)
	at java.net.URLClassLoader.defineClass(URLClassLoader.java:467)
	at java.net.URLClassLoader.access$100(URLClassLoader.java:73)
	at java.net.URLClassLoader$1.run(URLClassLoader.java:368)
	at java.net.URLClassLoader$1.run(URLClassLoader.java:362)
	at java.security.AccessController.doPrivileged(Native Method)
	at java.net.URLClassLoader.findClass(URLClassLoader.java:361)
	at java.lang.ClassLoader.loadClass(ClassLoader.java:424)
	at sun.misc.Launcher$AppClassLoader.loadClass(Launcher.java:331)
	at java.lang.ClassLoader.loadClass(ClassLoader.java:357)
	at foo.ConfigureApp.main(ConfigureApp.java:9)

error can't determine annotations of missing type org.springframework.cache.annotation.CachePut
when weaving type org.springframework.beans.factory.config.ConfigurableListableBeanFactory
when weaving classes 
when weaving 
 [Xlint:cantFindType]
error can't determine annotations of missing type org.springframework.cache.annotation.Cacheable
when weaving type org.springframework.beans.factory.config.ConfigurableListableBeanFactory
when weaving classes 
when weaving 
 [Xlint:cantFindType]
error can't determine annotations of missing type org.springframework.cache.annotation.CacheEvict
when weaving type org.springframework.beans.factory.config.ConfigurableListableBeanFactory
when weaving classes 
when weaving 
 [Xlint:cantFindType]
error can't determine annotations of missing type org.springframework.cache.annotation.Caching
when weaving type org.springframework.beans.factory.config.ConfigurableListableBeanFactory
when weaving classes 
when weaving 
 [Xlint:cantFindType]
error can't determine annotations of missing type org.springframework.transaction.annotation.Transactional
when weaving type org.springframework.beans.factory.config.ConfigurableListableBeanFactory
when weaving classes 
when weaving 
 [Xlint:cantFindType]
