---- AspectJ Properties ---
AspectJ Compiler 1.6.11 built on Tuesday Mar 15, 2011 at 15:31:04 GMT
---- Dump Properties ---
Dump file: ajcore.20150913.181455.377.txt
Dump reason: abort
Dump on exception: true
Dump at exit condition: abort
---- System Properties ---
java.runtime.name=Java(TM) SE Runtime Environment
sun.boot.library.path=C:\Program Files\Java\jdk1.8.0_45\jre\bin
java.vm.version=25.45-b02
java.vm.vendor=Oracle Corporation
java.vendor.url=http://java.oracle.com/
path.separator=;
java.vm.name=Java HotSpot(TM) 64-Bit Server VM
file.encoding.pkg=sun.io
user.country=US
user.script=
sun.java.launcher=SUN_STANDARD
sun.os.patch.level=
java.vm.specification.name=Java Virtual Machine Specification
user.dir=E:\Eclipse Latest\SpringChap3.3
java.runtime.version=1.8.0_45-b15
java.awt.graphicsenv=sun.awt.Win32GraphicsEnvironment
java.endorsed.dirs=C:\Program Files\Java\jdk1.8.0_45\jre\lib\endorsed
os.arch=amd64
java.io.tmpdir=C:\Users\SANJUS~1\AppData\Local\Temp\
line.separator=

java.vm.specification.vendor=Oracle Corporation
user.variant=
os.name=Windows 7
sun.jnu.encoding=Cp1252
java.library.path=C:\Program Files\Java\jdk1.8.0_45\bin;C:\Windows\Sun\Java\bin;C:\Windows\system32;C:\Windows;C:/Program Files/Java/jdk1.8.0_45/bin/../jre/bin/server;C:/Program Files/Java/jdk1.8.0_45/bin/../jre/bin;C:/Program Files/Java/jdk1.8.0_45/bin/../jre/lib/amd64;C:\oraclexe\app\oracle\product\10.2.0\server\bin;C:\Program Files\Java\jdk1.8.0_45\bin;C:\Program Files (x86)\Java\jre1.8.0_45\bin;C:\ProgramData\Oracle\Java\javapath;C:\Windows\system32;C:\Windows;C:\Windows\System32\Wbem;C:\Windows\System32\WindowsPowerShell\v1.0\;C:\Python27;;E:\Eclipse Latest\eclipse-jee-luna-SR2-win32-x86_64\eclipse;;.
java.specification.name=Java Platform API Specification
java.class.version=52.0
sun.management.compiler=HotSpot 64-Bit Tiered Compilers
os.version=6.1
user.home=C:\Users\sanju singh
user.timezone=Asia/Calcutta
java.awt.printerjob=sun.awt.windows.WPrinterJob
file.encoding=Cp1252
java.specification.version=1.8
java.class.path=E:\Eclipse Latest\SpringChap3.3\bin;E:\Eclipse Latest\SpringJar\extra Jar\aopalliance-1.0.jar;E:\Eclipse Latest\SpringJar\extra Jar\asm-3.3.1.jar;E:\Eclipse Latest\SpringJar\extra Jar\aspectjrt-1.6.11.jar;E:\Eclipse Latest\SpringJar\extra Jar\aspectjweaver-1.6.11.jar;E:\Eclipse Latest\SpringJar\extra Jar\cglib-2.2.2.jar;E:\Eclipse Latest\SpringJar\extra Jar\commons-logging-1.1.1.jar;E:\Eclipse Latest\SpringJar\extra Jar\junit-4.8.2.jar;E:\Eclipse Latest\SpringJar\extra Jar\spring-aop-3.0.5.RELEASE.jar;E:\Eclipse Latest\SpringJar\extra Jar\spring-asm-3.0.5.RELEASE.jar;E:\Eclipse Latest\SpringJar\extra Jar\spring-beans-3.0.5.RELEASE.jar;E:\Eclipse Latest\SpringJar\extra Jar\spring-context-3.0.5.RELEASE.jar;E:\Eclipse Latest\SpringJar\extra Jar\spring-core-3.0.5.RELEASE.jar;E:\Eclipse Latest\SpringJar\extra Jar\spring-expression-3.0.5.RELEASE.jar;E:\Eclipse Latest\SpringJar\spring-aspects-4.1.6.RELEASE.jar;E:\TestJar\aspectjweaver-1.6.11.jar
user.name=sanju singh
java.vm.specification.version=1.8
sun.java.command=foo.ConfigureApp
java.home=C:\Program Files\Java\jdk1.8.0_45\jre
sun.arch.data.model=64
user.language=en
java.specification.vendor=Oracle Corporation
awt.toolkit=sun.awt.windows.WToolkit
java.vm.info=mixed mode
java.version=1.8.0_45
java.ext.dirs=C:\Program Files\Java\jdk1.8.0_45\jre\lib\ext;C:\Windows\Sun\Java\lib\ext
sun.boot.class.path=C:\Program Files\Java\jdk1.8.0_45\jre\lib\resources.jar;C:\Program Files\Java\jdk1.8.0_45\jre\lib\rt.jar;C:\Program Files\Java\jdk1.8.0_45\jre\lib\sunrsasign.jar;C:\Program Files\Java\jdk1.8.0_45\jre\lib\jsse.jar;C:\Program Files\Java\jdk1.8.0_45\jre\lib\jce.jar;C:\Program Files\Java\jdk1.8.0_45\jre\lib\charsets.jar;C:\Program Files\Java\jdk1.8.0_45\jre\lib\jfr.jar;C:\Program Files\Java\jdk1.8.0_45\jre\classes
java.vendor=Oracle Corporation
file.separator=\
java.vendor.url.bug=http://bugreport.sun.com/bugreport/
sun.io.unicode.encoding=UnicodeLittle
sun.cpu.endian=little
sun.desktop=windows
sun.cpu.isalist=amd64
---- Command Line ---
Empty
---- Full Classpath ---
Empty
---- Compiler Messages ---
info AspectJ Weaver Version 1.6.11 built on Tuesday Mar 15, 2011 at 15:31:04 GMT
info register classloader sun.misc.Launcher$AppClassLoader@14dad5dc
info using configuration file:/E:/Eclipse%20Latest/SpringJar/spring-aspects-4.1.6.RELEASE.jar!/META-INF/aop.xml
error can't determine annotations of missing type org.springframework.cache.annotation.CachePut
when weaving type org.springframework.beans.factory.support.AbstractBeanDefinition
when weaving classes 
when weaving 
 [Xlint:cantFindType]
error can't determine annotations of missing type org.springframework.cache.annotation.Cacheable
when weaving type org.springframework.beans.factory.support.AbstractBeanDefinition
when weaving classes 
when weaving 
 [Xlint:cantFindType]
error can't determine annotations of missing type org.springframework.cache.annotation.CacheEvict
when weaving type org.springframework.beans.factory.support.AbstractBeanDefinition
when weaving classes 
when weaving 
 [Xlint:cantFindType]
error can't determine annotations of missing type org.springframework.cache.annotation.Caching
when weaving type org.springframework.beans.factory.support.AbstractBeanDefinition
when weaving classes 
when weaving 
 [Xlint:cantFindType]
error can't determine annotations of missing type org.springframework.transaction.annotation.Transactional
when weaving type org.springframework.beans.factory.support.AbstractBeanDefinition
when weaving classes 
when weaving 
 [Xlint:cantFindType]
abort trouble in: 
public abstract class org.springframework.beans.factory.support.AbstractBeanDefinition extends org.springframework.beans.BeanMetadataAttributeAccessor implements org.springframework.beans.factory.config.BeanDefinition, java.lang.Cloneable:
  public static final String SCOPE_DEFAULT = ""
  public static final int AUTOWIRE_NO = 0
  public static final int AUTOWIRE_BY_NAME = 1
  public static final int AUTOWIRE_BY_TYPE = 2
  public static final int AUTOWIRE_CONSTRUCTOR = 3
  public static final int AUTOWIRE_AUTODETECT = 4 [Deprecated] [RuntimeVisibleAnnotations]
  public static final int DEPENDENCY_CHECK_NONE = 0
  public static final int DEPENDENCY_CHECK_OBJECTS = 1
  public static final int DEPENDENCY_CHECK_SIMPLE = 2
  public static final int DEPENDENCY_CHECK_ALL = 3
  private volatile Object beanClass
  private String scope
  private boolean singleton
  private boolean prototype
  private boolean abstractFlag
  private boolean lazyInit
  private int autowireMode
  private int dependencyCheck
  private String[] dependsOn
  private boolean autowireCandidate
  private boolean primary
  private final java.util.Map qualifiers [Signature(Ljava/util/Map<Ljava/lang/String;Lorg/springframework/beans/factory/support/AutowireCandidateQualifier;>;)]
  private boolean nonPublicAccessAllowed
  private boolean lenientConstructorResolution
  private org.springframework.beans.factory.config.ConstructorArgumentValues constructorArgumentValues
  private org.springframework.beans.MutablePropertyValues propertyValues
  private org.springframework.beans.factory.support.MethodOverrides methodOverrides
  private String factoryBeanName
  private String factoryMethodName
  private String initMethodName
  private String destroyMethodName
  private boolean enforceInitMethod
  private boolean enforceDestroyMethod
  private boolean synthetic
  private int role
  private String description
  private org.springframework.core.io.Resource resource
  protected void <init>():
                    ALOAD_0     // Lorg/springframework/beans/factory/support/AbstractBeanDefinition; this   (line 187)
                    ACONST_NULL
                    ACONST_NULL
                    INVOKESPECIAL org.springframework.beans.factory.support.AbstractBeanDefinition.<init> (Lorg/springframework/beans/factory/config/ConstructorArgumentValues;Lorg/springframework/beans/MutablePropertyValues;)V
    constructor-execution(void org.springframework.beans.factory.support.AbstractBeanDefinition.<init>())
    |               RETURN   (line 188)
    constructor-execution(void org.springframework.beans.factory.support.AbstractBeanDefinition.<init>())
  end protected void <init>()

  protected void <init>(org.springframework.beans.factory.config.ConstructorArgumentValues, org.springframework.beans.MutablePropertyValues):
                    ALOAD_0     // Lorg/springframework/beans/factory/support/AbstractBeanDefinition; this   (line 194)
                    INVOKESPECIAL org.springframework.beans.BeanMetadataAttributeAccessor.<init> ()V
    constructor-execution(void org.springframework.beans.factory.support.AbstractBeanDefinition.<init>(org.springframework.beans.factory.config.ConstructorArgumentValues, org.springframework.beans.MutablePropertyValues))
    |               ALOAD_0     // Lorg/springframework/beans/factory/support/AbstractBeanDefinition; this   (line 129)
    |               LDC ""
    |               PUTFIELD org.springframework.beans.factory.support.AbstractBeanDefinition.scope Ljava/lang/String;
    |               ALOAD_0     // Lorg/springframework/beans/factory/support/AbstractBeanDefinition; this   (line 131)
    |               ICONST_1
    |               PUTFIELD org.springframework.beans.factory.support.AbstractBeanDefinition.singleton Z
    |               ALOAD_0     // Lorg/springframework/beans/factory/support/AbstractBeanDefinition; this   (line 133)
    |               ICONST_0
    |               PUTFIELD org.springframework.beans.factory.support.AbstractBeanDefinition.prototype Z
    |               ALOAD_0     // Lorg/springframework/beans/factory/support/AbstractBeanDefinition; this   (line 135)
    |               ICONST_0
    |               PUTFIELD org.springframework.beans.factory.support.AbstractBeanDefinition.abstractFlag Z
    |               ALOAD_0     // Lorg/springframework/beans/factory/support/AbstractBeanDefinition; this   (line 137)
    |               ICONST_0
    |               PUTFIELD org.springframework.beans.factory.support.AbstractBeanDefinition.lazyInit Z
    |               ALOAD_0     // Lorg/springframework/beans/factory/support/AbstractBeanDefinition; this   (line 139)
    |               ICONST_0
    |               PUTFIELD org.springframework.beans.factory.support.AbstractBeanDefinition.autowireMode I
    |               ALOAD_0     // Lorg/springframework/beans/factory/support/AbstractBeanDefinition; this   (line 141)
    |               ICONST_0
    |               PUTFIELD org.springframework.beans.factory.support.AbstractBeanDefinition.dependencyCheck I
    |               ALOAD_0     // Lorg/springframework/beans/factory/support/AbstractBeanDefinition; this   (line 145)
    |               ICONST_1
    |               PUTFIELD org.springframework.beans.factory.support.AbstractBeanDefinition.autowireCandidate Z
    |               ALOAD_0     // Lorg/springframework/beans/factory/support/AbstractBeanDefinition; this   (line 147)
    |               ICONST_0
    |               PUTFIELD org.springframework.beans.factory.support.AbstractBeanDefinition.primary Z
    |               ALOAD_0     // Lorg/springframework/beans/factory/support/AbstractBeanDefinition; this   (line 149)
    |               NEW java.util.LinkedHashMap   (line 150)
    |               DUP
    |               ICONST_0
    |               INVOKESPECIAL java.util.LinkedHashMap.<init> (I)V
    |               PUTFIELD org.springframework.beans.factory.support.AbstractBeanDefinition.qualifiers Ljava/util/Map;
    |               ALOAD_0     // Lorg/springframework/beans/factory/support/AbstractBeanDefinition; this   (line 152)
    |               ICONST_1
    |               PUTFIELD org.springframework.beans.factory.support.AbstractBeanDefinition.nonPublicAccessAllowed Z
    |               ALOAD_0     // Lorg/springframework/beans/factory/support/AbstractBeanDefinition; this   (line 154)
    |               ICONST_1
    |               PUTFIELD org.springframework.beans.factory.support.AbstractBeanDefinition.lenientConstructorResolution Z
    |               ALOAD_0     // Lorg/springframework/beans/factory/support/AbstractBeanDefinition; this   (line 160)
    |               NEW org.springframework.beans.factory.support.MethodOverrides
    |               DUP
    |               INVOKESPECIAL org.springframework.beans.factory.support.MethodOverrides.<init> ()V
    |               PUTFIELD org.springframework.beans.factory.support.AbstractBeanDefinition.methodOverrides Lorg/springframework/beans/factory/support/MethodOverrides;
    |               ALOAD_0     // Lorg/springframework/beans/factory/support/AbstractBeanDefinition; this   (line 170)
    |               ICONST_1
    |               PUTFIELD org.springframework.beans.factory.support.AbstractBeanDefinition.enforceInitMethod Z
    |               ALOAD_0     // Lorg/springframework/beans/factory/support/AbstractBeanDefinition; this   (line 172)
    |               ICONST_1
    |               PUTFIELD org.springframework.beans.factory.support.AbstractBeanDefinition.enforceDestroyMethod Z
    |               ALOAD_0     // Lorg/springframework/beans/factory/support/AbstractBeanDefinition; this   (line 174)
    |               ICONST_0
    |               PUTFIELD org.springframework.beans.factory.support.AbstractBeanDefinition.synthetic Z
    |               ALOAD_0     // Lorg/springframework/beans/factory/support/AbstractBeanDefinition; this   (line 176)
    |               ICONST_0
    |               PUTFIELD org.springframework.beans.factory.support.AbstractBeanDefinition.role I
    |               ALOAD_0     // Lorg/springframework/beans/factory/support/AbstractBeanDefinition; this   (line 195)
    |               ALOAD_1     // Lorg/springframework/beans/factory/config/ConstructorArgumentValues; cargs
    |               INVOKEVIRTUAL org.springframework.beans.factory.support.AbstractBeanDefinition.setConstructorArgumentValues (Lorg/springframework/beans/factory/config/ConstructorArgumentValues;)V
    |               ALOAD_0     // Lorg/springframework/beans/factory/support/AbstractBeanDefinition; this   (line 196)
    |               ALOAD_2     // Lorg/springframework/beans/MutablePropertyValues; pvs
    |               INVOKEVIRTUAL org.springframework.beans.factory.support.AbstractBeanDefinition.setPropertyValues (Lorg/springframework/beans/MutablePropertyValues;)V
    |               RETURN   (line 197)
    constructor-execution(void org.springframework.beans.factory.support.AbstractBeanDefinition.<init>(org.springframework.beans.factory.config.ConstructorArgumentValues, org.springframework.beans.MutablePropertyValues))
  end protected void <init>(org.springframework.beans.factory.config.ConstructorArgumentValues, org.springframework.beans.MutablePropertyValues)

  protected void <init>(org.springframework.beans.factory.support.AbstractBeanDefinition):
                    ALOAD_0     // Lorg/springframework/beans/factory/support/AbstractBeanDefinition; this   (line 207)
                    ALOAD_1     // Lorg/springframework/beans/factory/support/AbstractBeanDefinition; original
                    INVOKESPECIAL org.springframework.beans.factory.support.AbstractBeanDefinition.<init> (Lorg/springframework/beans/factory/config/BeanDefinition;)V
    constructor-execution(void org.springframework.beans.factory.support.AbstractBeanDefinition.<init>(org.springframework.beans.factory.support.AbstractBeanDefinition))
    |               RETURN   (line 208)
    constructor-execution(void org.springframework.beans.factory.support.AbstractBeanDefinition.<init>(org.springframework.beans.factory.support.AbstractBeanDefinition))
  end protected void <init>(org.springframework.beans.factory.support.AbstractBeanDefinition)

  protected void <init>(org.springframework.beans.factory.config.BeanDefinition):
                    ALOAD_0     // Lorg/springframework/beans/factory/support/AbstractBeanDefinition; this   (line 215)
                    INVOKESPECIAL org.springframework.beans.BeanMetadataAttributeAccessor.<init> ()V
    constructor-execution(void org.springframework.beans.factory.support.AbstractBeanDefinition.<init>(org.springframework.beans.factory.config.BeanDefinition))
    |               ALOAD_0     // Lorg/springframework/beans/factory/support/AbstractBeanDefinition; this   (line 129)
    |               LDC ""
    |               PUTFIELD org.springframework.beans.factory.support.AbstractBeanDefinition.scope Ljava/lang/String;
    |               ALOAD_0     // Lorg/springframework/beans/factory/support/AbstractBeanDefinition; this   (line 131)
    |               ICONST_1
    |               PUTFIELD org.springframework.beans.factory.support.AbstractBeanDefinition.singleton Z
    |               ALOAD_0     // Lorg/springframework/beans/factory/support/AbstractBeanDefinition; this   (line 133)
    |               ICONST_0
    |               PUTFIELD org.springframework.beans.factory.support.AbstractBeanDefinition.prototype Z
    |               ALOAD_0     // Lorg/springframework/beans/factory/support/AbstractBeanDefinition; this   (line 135)
    |               ICONST_0
    |               PUTFIELD org.springframework.beans.factory.support.AbstractBeanDefinition.abstractFlag Z
    |               ALOAD_0     // Lorg/springframework/beans/factory/support/AbstractBeanDefinition; this   (line 137)
    |               ICONST_0
    |               PUTFIELD org.springframework.beans.factory.support.AbstractBeanDefinition.lazyInit Z
    |               ALOAD_0     // Lorg/springframework/beans/factory/support/AbstractBeanDefinition; this   (line 139)
    |               ICONST_0
    |               PUTFIELD org.springframework.beans.factory.support.AbstractBeanDefinition.autowireMode I
    |               ALOAD_0     // Lorg/springframework/beans/factory/support/AbstractBeanDefinition; this   (line 141)
    |               ICONST_0
    |               PUTFIELD org.springframework.beans.factory.support.AbstractBeanDefinition.dependencyCheck I
    |               ALOAD_0     // Lorg/springframework/beans/factory/support/AbstractBeanDefinition; this   (line 145)
    |               ICONST_1
    |               PUTFIELD org.springframework.beans.factory.support.AbstractBeanDefinition.autowireCandidate Z
    |               ALOAD_0     // Lorg/springframework/beans/factory/support/AbstractBeanDefinition; this   (line 147)
    |               ICONST_0
    |               PUTFIELD org.springframework.beans.factory.support.AbstractBeanDefinition.primary Z
    |               ALOAD_0     // Lorg/springframework/beans/factory/support/AbstractBeanDefinition; this   (line 149)
    |               NEW java.util.LinkedHashMap   (line 150)
    |               DUP
    |               ICONST_0
    |               INVOKESPECIAL java.util.LinkedHashMap.<init> (I)V
    |               PUTFIELD org.springframework.beans.factory.support.AbstractBeanDefinition.qualifiers Ljava/util/Map;
    |               ALOAD_0     // Lorg/springframework/beans/factory/support/AbstractBeanDefinition; this   (line 152)
    |               ICONST_1
    |               PUTFIELD org.springframework.beans.factory.support.AbstractBeanDefinition.nonPublicAccessAllowed Z
    |               ALOAD_0     // Lorg/springframework/beans/factory/support/AbstractBeanDefinition; this   (line 154)
    |               ICONST_1
    |               PUTFIELD org.springframework.beans.factory.support.AbstractBeanDefinition.lenientConstructorResolution Z
    |               ALOAD_0     // Lorg/springframework/beans/factory/support/AbstractBeanDefinition; this   (line 160)
    |               NEW org.springframework.beans.factory.support.MethodOverrides
    |               DUP
    |               INVOKESPECIAL org.springframework.beans.factory.support.MethodOverrides.<init> ()V
    |               PUTFIELD org.springframework.beans.factory.support.AbstractBeanDefinition.methodOverrides Lorg/springframework/beans/factory/support/MethodOverrides;
    |               ALOAD_0     // Lorg/springframework/beans/factory/support/AbstractBeanDefinition; this   (line 170)
    |               ICONST_1
    |               PUTFIELD org.springframework.beans.factory.support.AbstractBeanDefinition.enforceInitMethod Z
    |               ALOAD_0     // Lorg/springframework/beans/factory/support/AbstractBeanDefinition; this   (line 172)
    |               ICONST_1
    |               PUTFIELD org.springframework.beans.factory.support.AbstractBeanDefinition.enforceDestroyMethod Z
    |               ALOAD_0     // Lorg/springframework/beans/factory/support/AbstractBeanDefinition; this   (line 174)
    |               ICONST_0
    |               PUTFIELD org.springframework.beans.factory.support.AbstractBeanDefinition.synthetic Z
    |               ALOAD_0     // Lorg/springframework/beans/factory/support/AbstractBeanDefinition; this   (line 176)
    |               ICONST_0
    |               PUTFIELD org.springframework.beans.factory.support.AbstractBeanDefinition.role I
    |               ALOAD_0     // Lorg/springframework/beans/factory/support/AbstractBeanDefinition; this   (line 216)
    |               ALOAD_1     // Lorg/springframework/beans/factory/config/BeanDefinition; original
    |               INVOKEINTERFACE org.springframework.beans.factory.config.BeanDefinition.getParentName ()Ljava/lang/String;
    |               INVOKEVIRTUAL org.springframework.beans.factory.support.AbstractBeanDefinition.setParentName (Ljava/lang/String;)V
    |               ALOAD_0     // Lorg/springframework/beans/factory/support/AbstractBeanDefinition; this   (line 217)
    |               ALOAD_1     // Lorg/springframework/beans/factory/config/BeanDefinition; original
    |               INVOKEINTERFACE org.springframework.beans.factory.config.BeanDefinition.getBeanClassName ()Ljava/lang/String;
    |               INVOKEVIRTUAL org.springframework.beans.factory.support.AbstractBeanDefinition.setBeanClassName (Ljava/lang/String;)V
    |               ALOAD_0     // Lorg/springframework/beans/factory/support/AbstractBeanDefinition; this   (line 218)
    |               ALOAD_1     // Lorg/springframework/beans/factory/config/BeanDefinition; original
    |               INVOKEINTERFACE org.springframework.beans.factory.config.BeanDefinition.getFactoryBeanName ()Ljava/lang/String;
    |               INVOKEVIRTUAL org.springframework.beans.factory.support.AbstractBeanDefinition.setFactoryBeanName (Ljava/lang/String;)V
    |               ALOAD_0     // Lorg/springframework/beans/factory/support/AbstractBeanDefinition; this   (line 219)
    |               ALOAD_1     // Lorg/springframework/beans/factory/config/BeanDefinition; original
    |               INVOKEINTERFACE org.springframework.beans.factory.config.BeanDefinition.getFactoryMethodName ()Ljava/lang/String;
    |               INVOKEVIRTUAL org.springframework.beans.factory.support.AbstractBeanDefinition.setFactoryMethodName (Ljava/lang/String;)V
    |               ALOAD_0     // Lorg/springframework/beans/factory/support/AbstractBeanDefinition; this   (line 220)
    |               ALOAD_1     // Lorg/springframework/beans/factory/config/BeanDefinition; original
    |               INVOKEINTERFACE org.springframework.beans.factory.config.BeanDefinition.getScope ()Ljava/lang/String;
    |               INVOKEVIRTUAL org.springframework.beans.factory.support.AbstractBeanDefinition.setScope (Ljava/lang/String;)V
    |               ALOAD_0     // Lorg/springframework/beans/factory/support/AbstractBeanDefinition; this   (line 221)
    |               ALOAD_1     // Lorg/springframework/beans/factory/config/BeanDefinition; original
    |               INVOKEINTERFACE org.springframework.beans.factory.config.BeanDefinition.isAbstract ()Z
    |               INVOKEVIRTUAL org.springframework.beans.factory.support.AbstractBeanDefinition.setAbstract (Z)V
    |               ALOAD_0     // Lorg/springframework/beans/factory/support/AbstractBeanDefinition; this   (line 222)
    |               ALOAD_1     // Lorg/springframework/beans/factory/config/BeanDefinition; original
    |               INVOKEINTERFACE org.springframework.beans.factory.config.BeanDefinition.isLazyInit ()Z
    |               INVOKEVIRTUAL org.springframework.beans.factory.support.AbstractBeanDefinition.setLazyInit (Z)V
    |               ALOAD_0     // Lorg/springframework/beans/factory/support/AbstractBeanDefinition; this   (line 223)
    |               ALOAD_1     // Lorg/springframework/beans/factory/config/BeanDefinition; original
    |               INVOKEINTERFACE org.springframework.beans.factory.config.BeanDefinition.getRole ()I
    |               INVOKEVIRTUAL org.springframework.beans.factory.support.AbstractBeanDefinition.setRole (I)V
    |               ALOAD_0     // Lorg/springframework/beans/factory/support/AbstractBeanDefinition; this   (line 224)
    |               NEW org.springframework.beans.factory.config.ConstructorArgumentValues
    |               DUP
    |               ALOAD_1     // Lorg/springframework/beans/factory/config/BeanDefinition; original
    |               INVOKEINTERFACE org.springframework.beans.factory.config.BeanDefinition.getConstructorArgumentValues ()Lorg/springframework/beans/factory/config/ConstructorArgumentValues;
    |               INVOKESPECIAL org.springframework.beans.factory.config.ConstructorArgumentValues.<init> (Lorg/springframework/beans/factory/config/ConstructorArgumentValues;)V
    |               INVOKEVIRTUAL org.springframework.beans.factory.support.AbstractBeanDefinition.setConstructorArgumentValues (Lorg/springframework/beans/factory/config/ConstructorArgumentValues;)V
    |               ALOAD_0     // Lorg/springframework/beans/factory/support/AbstractBeanDefinition; this   (line 225)
    |               NEW org.springframework.beans.MutablePropertyValues
    |               DUP
    |               ALOAD_1     // Lorg/springframework/beans/factory/config/BeanDefinition; original
    |               INVOKEINTERFACE org.springframework.beans.factory.config.BeanDefinition.getPropertyValues ()Lorg/springframework/beans/MutablePropertyValues;
    |               INVOKESPECIAL org.springframework.beans.MutablePropertyValues.<init> (Lorg/springframework/beans/PropertyValues;)V
    |               INVOKEVIRTUAL org.springframework.beans.factory.support.AbstractBeanDefinition.setPropertyValues (Lorg/springframework/beans/MutablePropertyValues;)V
    |               ALOAD_0     // Lorg/springframework/beans/factory/support/AbstractBeanDefinition; this   (line 226)
    |               ALOAD_1     // Lorg/springframework/beans/factory/config/BeanDefinition; original
    |               INVOKEINTERFACE org.springframework.beans.factory.config.BeanDefinition.getSource ()Ljava/lang/Object;
    |               INVOKEVIRTUAL org.springframework.beans.factory.support.AbstractBeanDefinition.setSource (Ljava/lang/Object;)V
    |               ALOAD_0     // Lorg/springframework/beans/factory/support/AbstractBeanDefinition; this   (line 227)
    |               ALOAD_1     // Lorg/springframework/beans/factory/config/BeanDefinition; original
    |               INVOKEVIRTUAL org.springframework.beans.factory.support.AbstractBeanDefinition.copyAttributesFrom (Lorg/springframework/core/AttributeAccessor;)V
    |               ALOAD_1     // Lorg/springframework/beans/factory/config/BeanDefinition; original   (line 229)
    |               INSTANCEOF org.springframework.beans.factory.support.AbstractBeanDefinition
    |               IFEQ L1
    |               ALOAD_1     // Lorg/springframework/beans/factory/config/BeanDefinition; original   (line 230)
    |               CHECKCAST org.springframework.beans.factory.support.AbstractBeanDefinition
    |               ASTORE_2
    |               ALOAD_2     // Lorg/springframework/beans/factory/support/AbstractBeanDefinition; originalAbd   (line 231)
    |               INVOKEVIRTUAL org.springframework.beans.factory.support.AbstractBeanDefinition.hasBeanClass ()Z
    |               IFEQ L0
    |               ALOAD_0     // Lorg/springframework/beans/factory/support/AbstractBeanDefinition; this   (line 232)
    |               ALOAD_2     // Lorg/springframework/beans/factory/support/AbstractBeanDefinition; originalAbd
    |               INVOKEVIRTUAL org.springframework.beans.factory.support.AbstractBeanDefinition.getBeanClass ()Ljava/lang/Class;
    |               INVOKEVIRTUAL org.springframework.beans.factory.support.AbstractBeanDefinition.setBeanClass (Ljava/lang/Class;)V
    |           L0: ALOAD_0     // Lorg/springframework/beans/factory/support/AbstractBeanDefinition; this   (line 234)
    |               ALOAD_2     // Lorg/springframework/beans/factory/support/AbstractBeanDefinition; originalAbd
    |               INVOKEVIRTUAL org.springframework.beans.factory.support.AbstractBeanDefinition.getAutowireMode ()I
    |               INVOKEVIRTUAL org.springframework.beans.factory.support.AbstractBeanDefinition.setAutowireMode (I)V
    |               ALOAD_0     // Lorg/springframework/beans/factory/support/AbstractBeanDefinition; this   (line 235)
    |               ALOAD_2     // Lorg/springframework/beans/factory/support/AbstractBeanDefinition; originalAbd
    |               INVOKEVIRTUAL org.springframework.beans.factory.support.AbstractBeanDefinition.getDependencyCheck ()I
    |               INVOKEVIRTUAL org.springframework.beans.factory.support.AbstractBeanDefinition.setDependencyCheck (I)V
    |               ALOAD_0     // Lorg/springframework/beans/factory/support/AbstractBeanDefinition; this   (line 236)
    |               ALOAD_2     // Lorg/springframework/beans/factory/support/AbstractBeanDefinition; originalAbd
    |               INVOKEVIRTUAL org.springframework.beans.factory.support.AbstractBeanDefinition.getDependsOn ()[Ljava/lang/String;
    |               INVOKEVIRTUAL org.springframework.beans.factory.support.AbstractBeanDefinition.setDependsOn ([Ljava/lang/String;)V
    |               ALOAD_0     // Lorg/springframework/beans/factory/support/AbstractBeanDefinition; this   (line 237)
    |               ALOAD_2     // Lorg/springframework/beans/factory/support/AbstractBeanDefinition; originalAbd
    |               INVOKEVIRTUAL org.springframework.beans.factory.support.AbstractBeanDefinition.isAutowireCandidate ()Z
    |               INVOKEVIRTUAL org.springframework.beans.factory.support.AbstractBeanDefinition.setAutowireCandidate (Z)V
    |               ALOAD_0     // Lorg/springframework/beans/factory/support/AbstractBeanDefinition; this   (line 238)
    |               ALOAD_2     // Lorg/springframework/beans/factory/support/AbstractBeanDefinition; originalAbd
    |               INVOKEVIRTUAL org.springframework.beans.factory.support.AbstractBeanDefinition.copyQualifiersFrom (Lorg/springframework/beans/factory/support/AbstractBeanDefinition;)V
    |               ALOAD_0     // Lorg/springframework/beans/factory/support/AbstractBeanDefinition; this   (line 239)
    |               ALOAD_2     // Lorg/springframework/beans/factory/support/AbstractBeanDefinition; originalAbd
    |               INVOKEVIRTUAL org.springframework.beans.factory.support.AbstractBeanDefinition.isPrimary ()Z
    |               INVOKEVIRTUAL org.springframework.beans.factory.support.AbstractBeanDefinition.setPrimary (Z)V
    |               ALOAD_0     // Lorg/springframework/beans/factory/support/AbstractBeanDefinition; this   (line 240)
    |               ALOAD_2     // Lorg/springframework/beans/factory/support/AbstractBeanDefinition; originalAbd
    |               INVOKEVIRTUAL org.springframework.beans.factory.support.AbstractBeanDefinition.isNonPublicAccessAllowed ()Z
    |               INVOKEVIRTUAL org.springframework.beans.factory.support.AbstractBeanDefinition.setNonPublicAccessAllowed (Z)V
    |               ALOAD_0     // Lorg/springframework/beans/factory/support/AbstractBeanDefinition; this   (line 241)
    |               ALOAD_2     // Lorg/springframework/beans/factory/support/AbstractBeanDefinition; originalAbd
    |               INVOKEVIRTUAL org.springframework.beans.factory.support.AbstractBeanDefinition.isLenientConstructorResolution ()Z
    |               INVOKEVIRTUAL org.springframework.beans.factory.support.AbstractBeanDefinition.setLenientConstructorResolution (Z)V
    |               ALOAD_0     // Lorg/springframework/beans/factory/support/AbstractBeanDefinition; this   (line 242)
    |               ALOAD_2     // Lorg/springframework/beans/factory/support/AbstractBeanDefinition; originalAbd
    |               INVOKEVIRTUAL org.springframework.beans.factory.support.AbstractBeanDefinition.getInitMethodName ()Ljava/lang/String;
    |               INVOKEVIRTUAL org.springframework.beans.factory.support.AbstractBeanDefinition.setInitMethodName (Ljava/lang/String;)V
    |               ALOAD_0     // Lorg/springframework/beans/factory/support/AbstractBeanDefinition; this   (line 243)
    |               ALOAD_2     // Lorg/springframework/beans/factory/support/AbstractBeanDefinition; originalAbd
    |               INVOKEVIRTUAL org.springframework.beans.factory.support.AbstractBeanDefinition.isEnforceInitMethod ()Z
    |               INVOKEVIRTUAL org.springframework.beans.factory.support.AbstractBeanDefinition.setEnforceInitMethod (Z)V
    |               ALOAD_0     // Lorg/springframework/beans/factory/support/AbstractBeanDefinition; this   (line 244)
    |               ALOAD_2     // Lorg/springframework/beans/factory/support/AbstractBeanDefinition; originalAbd
    |               INVOKEVIRTUAL org.springframework.beans.factory.support.AbstractBeanDefinition.getDestroyMethodName ()Ljava/lang/String;
    |               INVOKEVIRTUAL org.springframework.beans.factory.support.AbstractBeanDefinition.setDestroyMethodName (Ljava/lang/String;)V
    |               ALOAD_0     // Lorg/springframework/beans/factory/support/AbstractBeanDefinition; this   (line 245)
    |               ALOAD_2     // Lorg/springframework/beans/factory/support/AbstractBeanDefinition; originalAbd
    |               INVOKEVIRTUAL org.springframework.beans.factory.support.AbstractBeanDefinition.isEnforceDestroyMethod ()Z
    |               INVOKEVIRTUAL org.springframework.beans.factory.support.AbstractBeanDefinition.setEnforceDestroyMethod (Z)V
    |               ALOAD_0     // Lorg/springframework/beans/factory/support/AbstractBeanDefinition; this   (line 246)
    |               NEW org.springframework.beans.factory.support.MethodOverrides
    |               DUP
    |               ALOAD_2     // Lorg/springframework/beans/factory/support/AbstractBeanDefinition; originalAbd
    |               INVOKEVIRTUAL org.springframework.beans.factory.support.AbstractBeanDefinition.getMethodOverrides ()Lorg/springframework/beans/factory/support/MethodOverrides;
    |               INVOKESPECIAL org.springframework.beans.factory.support.MethodOverrides.<init> (Lorg/springframework/beans/factory/support/MethodOverrides;)V
    |               INVOKEVIRTUAL org.springframework.beans.factory.support.AbstractBeanDefinition.setMethodOverrides (Lorg/springframework/beans/factory/support/MethodOverrides;)V
    |               ALOAD_0     // Lorg/springframework/beans/factory/support/AbstractBeanDefinition; this   (line 247)
    |               ALOAD_2     // Lorg/springframework/beans/factory/support/AbstractBeanDefinition; originalAbd
    |               INVOKEVIRTUAL org.springframework.beans.factory.support.AbstractBeanDefinition.isSynthetic ()Z
    |               INVOKEVIRTUAL org.springframework.beans.factory.support.AbstractBeanDefinition.setSynthetic (Z)V
    |               ALOAD_0     // Lorg/springframework/beans/factory/support/AbstractBeanDefinition; this   (line 248)
    |               ALOAD_2     // Lorg/springframework/beans/factory/support/AbstractBeanDefinition; originalAbd
    |               INVOKEVIRTUAL org.springframework.beans.factory.support.AbstractBeanDefinition.getResource ()Lorg/springframework/core/io/Resource;
    |               INVOKEVIRTUAL org.springframework.beans.factory.support.AbstractBeanDefinition.setResource (Lorg/springframework/core/io/Resource;)V
    |               GOTO L2
    |           L1: ALOAD_0     // Lorg/springframework/beans/factory/support/AbstractBeanDefinition; this   (line 251)
    |               ALOAD_1     // Lorg/springframework/beans/factory/config/BeanDefinition; original
    |               INVOKEINTERFACE org.springframework.beans.factory.config.BeanDefinition.getResourceDescription ()Ljava/lang/String;
    |               INVOKEVIRTUAL org.springframework.beans.factory.support.AbstractBeanDefinition.setResourceDescription (Ljava/lang/String;)V
    |           L2: RETURN   (line 253)
    constructor-execution(void org.springframework.beans.factory.support.AbstractBeanDefinition.<init>(org.springframework.beans.factory.config.BeanDefinition))
  end protected void <init>(org.springframework.beans.factory.config.BeanDefinition)

  public void overrideFrom(org.springframework.beans.factory.support.AbstractBeanDefinition):
                    ALOAD_0     // Lorg/springframework/beans/factory/support/AbstractBeanDefinition; this   (line 264)
                    ALOAD_1     // Lorg/springframework/beans/factory/support/AbstractBeanDefinition; other
                    INVOKEVIRTUAL org.springframework.beans.factory.support.AbstractBeanDefinition.overrideFrom (Lorg/springframework/beans/factory/config/BeanDefinition;)V
                    RETURN   (line 265)
  end public void overrideFrom(org.springframework.beans.factory.support.AbstractBeanDefinition)

  public void overrideFrom(org.springframework.beans.factory.config.BeanDefinition):
                    ALOAD_1     // Lorg/springframework/beans/factory/config/BeanDefinition; other   (line 284)
                    INVOKEINTERFACE org.springframework.beans.factory.config.BeanDefinition.getBeanClassName ()Ljava/lang/String;
                    INVOKESTATIC org.springframework.util.StringUtils.hasLength (Ljava/lang/String;)Z
                    IFEQ L0
                    ALOAD_0     // Lorg/springframework/beans/factory/support/AbstractBeanDefinition; this   (line 285)
                    ALOAD_1     // Lorg/springframework/beans/factory/config/BeanDefinition; other
                    INVOKEINTERFACE org.springframework.beans.factory.config.BeanDefinition.getBeanClassName ()Ljava/lang/String;
                    INVOKEVIRTUAL org.springframework.beans.factory.support.AbstractBeanDefinition.setBeanClassName (Ljava/lang/String;)V
                L0: ALOAD_1     // Lorg/springframework/beans/factory/config/BeanDefinition; other   (line 287)
                    INVOKEINTERFACE org.springframework.beans.factory.config.BeanDefinition.getFactoryBeanName ()Ljava/lang/String;
                    INVOKESTATIC org.springframework.util.StringUtils.hasLength (Ljava/lang/String;)Z
                    IFEQ L1
                    ALOAD_0     // Lorg/springframework/beans/factory/support/AbstractBeanDefinition; this   (line 288)
                    ALOAD_1     // Lorg/springframework/beans/factory/config/BeanDefinition; other
                    INVOKEINTERFACE org.springframework.beans.factory.config.BeanDefinition.getFactoryBeanName ()Ljava/lang/String;
                    INVOKEVIRTUAL org.springframework.beans.factory.support.AbstractBeanDefinition.setFactoryBeanName (Ljava/lang/String;)V
                L1: ALOAD_1     // Lorg/springframework/beans/factory/config/BeanDefinition; other   (line 290)
                    INVOKEINTERFACE org.springframework.beans.factory.config.BeanDefinition.getFactoryMethodName ()Ljava/lang/String;
                    INVOKESTATIC org.springframework.util.StringUtils.hasLength (Ljava/lang/String;)Z
                    IFEQ L2
                    ALOAD_0     // Lorg/springframework/beans/factory/support/AbstractBeanDefinition; this   (line 291)
                    ALOAD_1     // Lorg/springframework/beans/factory/config/BeanDefinition; other
                    INVOKEINTERFACE org.springframework.beans.factory.config.BeanDefinition.getFactoryMethodName ()Ljava/lang/String;
                    INVOKEVIRTUAL org.springframework.beans.factory.support.AbstractBeanDefinition.setFactoryMethodName (Ljava/lang/String;)V
                L2: ALOAD_1     // Lorg/springframework/beans/factory/config/BeanDefinition; other   (line 293)
                    INVOKEINTERFACE org.springframework.beans.factory.config.BeanDefinition.getScope ()Ljava/lang/String;
                    INVOKESTATIC org.springframework.util.StringUtils.hasLength (Ljava/lang/String;)Z
                    IFEQ L3
                    ALOAD_0     // Lorg/springframework/beans/factory/support/AbstractBeanDefinition; this   (line 294)
                    ALOAD_1     // Lorg/springframework/beans/factory/config/BeanDefinition; other
                    INVOKEINTERFACE org.springframework.beans.factory.config.BeanDefinition.getScope ()Ljava/lang/String;
                    INVOKEVIRTUAL org.springframework.beans.factory.support.AbstractBeanDefinition.setScope (Ljava/lang/String;)V
                L3: ALOAD_0     // Lorg/springframework/beans/factory/support/AbstractBeanDefinition; this   (line 296)
                    ALOAD_1     // Lorg/springframework/beans/factory/config/BeanDefinition; other
                    INVOKEINTERFACE org.springframework.beans.factory.config.BeanDefinition.isAbstract ()Z
                    INVOKEVIRTUAL org.springframework.beans.factory.support.AbstractBeanDefinition.setAbstract (Z)V
                    ALOAD_0     // Lorg/springframework/beans/factory/support/AbstractBeanDefinition; this   (line 297)
                    ALOAD_1     // Lorg/springframework/beans/factory/config/BeanDefinition; other
                    INVOKEINTERFACE org.springframework.beans.factory.config.BeanDefinition.isLazyInit ()Z
                    INVOKEVIRTUAL org.springframework.beans.factory.support.AbstractBeanDefinition.setLazyInit (Z)V
                    ALOAD_0     // Lorg/springframework/beans/factory/support/AbstractBeanDefinition; this   (line 298)
                    ALOAD_1     // Lorg/springframework/beans/factory/config/BeanDefinition; other
                    INVOKEINTERFACE org.springframework.beans.factory.config.BeanDefinition.getRole ()I
                    INVOKEVIRTUAL org.springframework.beans.factory.support.AbstractBeanDefinition.setRole (I)V
                    ALOAD_0     // Lorg/springframework/beans/factory/support/AbstractBeanDefinition; this   (line 299)
                    INVOKEVIRTUAL org.springframework.beans.factory.support.AbstractBeanDefinition.getConstructorArgumentValues ()Lorg/springframework/beans/factory/config/ConstructorArgumentValues;
                    ALOAD_1     // Lorg/springframework/beans/factory/config/BeanDefinition; other
                    INVOKEINTERFACE org.springframework.beans.factory.config.BeanDefinition.getConstructorArgumentValues ()Lorg/springframework/beans/factory/config/ConstructorArgumentValues;
                    INVOKEVIRTUAL org.springframework.beans.factory.config.ConstructorArgumentValues.addArgumentValues (Lorg/springframework/beans/factory/config/ConstructorArgumentValues;)V
                    ALOAD_0     // Lorg/springframework/beans/factory/support/AbstractBeanDefinition; this   (line 300)
                    INVOKEVIRTUAL org.springframework.beans.factory.support.AbstractBeanDefinition.getPropertyValues ()Lorg/springframework/beans/MutablePropertyValues;
                    ALOAD_1     // Lorg/springframework/beans/factory/config/BeanDefinition; other
                    INVOKEINTERFACE org.springframework.beans.factory.config.BeanDefinition.getPropertyValues ()Lorg/springframework/beans/MutablePropertyValues;
                    INVOKEVIRTUAL org.springframework.beans.MutablePropertyValues.addPropertyValues (Lorg/springframework/beans/PropertyValues;)Lorg/springframework/beans/MutablePropertyValues;
                    POP
                    ALOAD_0     // Lorg/springframework/beans/factory/support/AbstractBeanDefinition; this   (line 301)
                    ALOAD_1     // Lorg/springframework/beans/factory/config/BeanDefinition; other
                    INVOKEINTERFACE org.springframework.beans.factory.config.BeanDefinition.getSource ()Ljava/lang/Object;
                    INVOKEVIRTUAL org.springframework.beans.factory.support.AbstractBeanDefinition.setSource (Ljava/lang/Object;)V
                    ALOAD_0     // Lorg/springframework/beans/factory/support/AbstractBeanDefinition; this   (line 302)
                    ALOAD_1     // Lorg/springframework/beans/factory/config/BeanDefinition; other
                    INVOKEVIRTUAL org.springframework.beans.factory.support.AbstractBeanDefinition.copyAttributesFrom (Lorg/springframework/core/AttributeAccessor;)V
                    ALOAD_1     // Lorg/springframework/beans/factory/config/BeanDefinition; other   (line 304)
                    INSTANCEOF org.springframework.beans.factory.support.AbstractBeanDefinition
                    IFEQ L7
                    ALOAD_1     // Lorg/springframework/beans/factory/config/BeanDefinition; other   (line 305)
                    CHECKCAST org.springframework.beans.factory.support.AbstractBeanDefinition
                    ASTORE_2
                    ALOAD_2     // Lorg/springframework/beans/factory/support/AbstractBeanDefinition; otherAbd   (line 306)
                    INVOKEVIRTUAL org.springframework.beans.factory.support.AbstractBeanDefinition.hasBeanClass ()Z
                    IFEQ L4
                    ALOAD_0     // Lorg/springframework/beans/factory/support/AbstractBeanDefinition; this   (line 307)
                    ALOAD_2     // Lorg/springframework/beans/factory/support/AbstractBeanDefinition; otherAbd
                    INVOKEVIRTUAL org.springframework.beans.factory.support.AbstractBeanDefinition.getBeanClass ()Ljava/lang/Class;
                    INVOKEVIRTUAL org.springframework.beans.factory.support.AbstractBeanDefinition.setBeanClass (Ljava/lang/Class;)V
                L4: ALOAD_0     // Lorg/springframework/beans/factory/support/AbstractBeanDefinition; this   (line 309)
                    ALOAD_2     // Lorg/springframework/beans/factory/support/AbstractBeanDefinition; otherAbd
                    INVOKEVIRTUAL org.springframework.beans.factory.support.AbstractBeanDefinition.isAutowireCandidate ()Z
                    INVOKEVIRTUAL org.springframework.beans.factory.support.AbstractBeanDefinition.setAutowireCandidate (Z)V
                    ALOAD_0     // Lorg/springframework/beans/factory/support/AbstractBeanDefinition; this   (line 310)
                    ALOAD_2     // Lorg/springframework/beans/factory/support/AbstractBeanDefinition; otherAbd
                    INVOKEVIRTUAL org.springframework.beans.factory.support.AbstractBeanDefinition.getAutowireMode ()I
                    INVOKEVIRTUAL org.springframework.beans.factory.support.AbstractBeanDefinition.setAutowireMode (I)V
                    ALOAD_0     // Lorg/springframework/beans/factory/support/AbstractBeanDefinition; this   (line 311)
                    ALOAD_2     // Lorg/springframework/beans/factory/support/AbstractBeanDefinition; otherAbd
                    INVOKEVIRTUAL org.springframework.beans.factory.support.AbstractBeanDefinition.copyQualifiersFrom (Lorg/springframework/beans/factory/support/AbstractBeanDefinition;)V
                    ALOAD_0     // Lorg/springframework/beans/factory/support/AbstractBeanDefinition; this   (line 312)
                    ALOAD_2     // Lorg/springframework/beans/factory/support/AbstractBeanDefinition; otherAbd
                    INVOKEVIRTUAL org.springframework.beans.factory.support.AbstractBeanDefinition.isPrimary ()Z
                    INVOKEVIRTUAL org.springframework.beans.factory.support.AbstractBeanDefinition.setPrimary (Z)V
                    ALOAD_0     // Lorg/springframework/beans/factory/support/AbstractBeanDefinition; this   (line 313)
                    ALOAD_2     // Lorg/springframework/beans/factory/support/AbstractBeanDefinition; otherAbd
                    INVOKEVIRTUAL org.springframework.beans.factory.support.AbstractBeanDefinition.getDependencyCheck ()I
                    INVOKEVIRTUAL org.springframework.beans.factory.support.AbstractBeanDefinition.setDependencyCheck (I)V
                    ALOAD_0     // Lorg/springframework/beans/factory/support/AbstractBeanDefinition; this   (line 314)
                    ALOAD_2     // Lorg/springframework/beans/factory/support/AbstractBeanDefinition; otherAbd
                    INVOKEVIRTUAL org.springframework.beans.factory.support.AbstractBeanDefinition.getDependsOn ()[Ljava/lang/String;
                    INVOKEVIRTUAL org.springframework.beans.factory.support.AbstractBeanDefinition.setDependsOn ([Ljava/lang/String;)V
                    ALOAD_0     // Lorg/springframework/beans/factory/support/AbstractBeanDefinition; this   (line 315)
                    ALOAD_2     // Lorg/springframework/beans/factory/support/AbstractBeanDefinition; otherAbd
                    INVOKEVIRTUAL org.springframework.beans.factory.support.AbstractBeanDefinition.isNonPublicAccessAllowed ()Z
                    INVOKEVIRTUAL org.springframework.beans.factory.support.AbstractBeanDefinition.setNonPublicAccessAllowed (Z)V
                    ALOAD_0     // Lorg/springframework/beans/factory/support/AbstractBeanDefinition; this   (line 316)
                    ALOAD_2     // Lorg/springframework/beans/factory/support/AbstractBeanDefinition; otherAbd
                    INVOKEVIRTUAL org.springframework.beans.factory.support.AbstractBeanDefinition.isLenientConstructorResolution ()Z
                    INVOKEVIRTUAL org.springframework.beans.factory.support.AbstractBeanDefinition.setLenientConstructorResolution (Z)V
                    ALOAD_2     // Lorg/springframework/beans/factory/support/AbstractBeanDefinition; otherAbd   (line 317)
                    INVOKEVIRTUAL org.springframework.beans.factory.support.AbstractBeanDefinition.getInitMethodName ()Ljava/lang/String;
                    INVOKESTATIC org.springframework.util.StringUtils.hasLength (Ljava/lang/String;)Z
                    IFEQ L5
                    ALOAD_0     // Lorg/springframework/beans/factory/support/AbstractBeanDefinition; this   (line 318)
                    ALOAD_2     // Lorg/springframework/beans/factory/support/AbstractBeanDefinition; otherAbd
                    INVOKEVIRTUAL org.springframework.beans.factory.support.AbstractBeanDefinition.getInitMethodName ()Ljava/lang/String;
                    INVOKEVIRTUAL org.springframework.beans.factory.support.AbstractBeanDefinition.setInitMethodName (Ljava/lang/String;)V
                    ALOAD_0     // Lorg/springframework/beans/factory/support/AbstractBeanDefinition; this   (line 319)
                    ALOAD_2     // Lorg/springframework/beans/factory/support/AbstractBeanDefinition; otherAbd
                    INVOKEVIRTUAL org.springframework.beans.factory.support.AbstractBeanDefinition.isEnforceInitMethod ()Z
                    INVOKEVIRTUAL org.springframework.beans.factory.support.AbstractBeanDefinition.setEnforceInitMethod (Z)V
                L5: ALOAD_2     // Lorg/springframework/beans/factory/support/AbstractBeanDefinition; otherAbd   (line 321)
                    INVOKEVIRTUAL org.springframework.beans.factory.support.AbstractBeanDefinition.getDestroyMethodName ()Ljava/lang/String;
                    INVOKESTATIC org.springframework.util.StringUtils.hasLength (Ljava/lang/String;)Z
                    IFEQ L6
                    ALOAD_0     // Lorg/springframework/beans/factory/support/AbstractBeanDefinition; this   (line 322)
                    ALOAD_2     // Lorg/springframework/beans/factory/support/AbstractBeanDefinition; otherAbd
                    INVOKEVIRTUAL org.springframework.beans.factory.support.AbstractBeanDefinition.getDestroyMethodName ()Ljava/lang/String;
                    INVOKEVIRTUAL org.springframework.beans.factory.support.AbstractBeanDefinition.setDestroyMethodName (Ljava/lang/String;)V
                    ALOAD_0     // Lorg/springframework/beans/factory/support/AbstractBeanDefinition; this   (line 323)
                    ALOAD_2     // Lorg/springframework/beans/factory/support/AbstractBeanDefinition; otherAbd
                    INVOKEVIRTUAL org.springframework.beans.factory.support.AbstractBeanDefinition.isEnforceDestroyMethod ()Z
                    INVOKEVIRTUAL org.springframework.beans.factory.support.AbstractBeanDefinition.setEnforceDestroyMethod (Z)V
                L6: ALOAD_0     // Lorg/springframework/beans/factory/support/AbstractBeanDefinition; this   (line 325)
                    INVOKEVIRTUAL org.springframework.beans.factory.support.AbstractBeanDefinition.getMethodOverrides ()Lorg/springframework/beans/factory/support/MethodOverrides;
                    ALOAD_2     // Lorg/springframework/beans/factory/support/AbstractBeanDefinition; otherAbd
                    INVOKEVIRTUAL org.springframework.beans.factory.support.AbstractBeanDefinition.getMethodOverrides ()Lorg/springframework/beans/factory/support/MethodOverrides;
                    INVOKEVIRTUAL org.springframework.beans.factory.support.MethodOverrides.addOverrides (Lorg/springframework/beans/factory/support/MethodOverrides;)V
                    ALOAD_0     // Lorg/springframework/beans/factory/support/AbstractBeanDefinition; this   (line 326)
                    ALOAD_2     // Lorg/springframework/beans/factory/support/AbstractBeanDefinition; otherAbd
                    INVOKEVIRTUAL org.springframework.beans.factory.support.AbstractBeanDefinition.isSynthetic ()Z
                    INVOKEVIRTUAL org.springframework.beans.factory.support.AbstractBeanDefinition.setSynthetic (Z)V
                    ALOAD_0     // Lorg/springframework/beans/factory/support/AbstractBeanDefinition; this   (line 327)
                    ALOAD_2     // Lorg/springframework/beans/factory/support/AbstractBeanDefinition; otherAbd
                    INVOKEVIRTUAL org.springframework.beans.factory.support.AbstractBeanDefinition.getResource ()Lorg/springframework/core/io/Resource;
                    INVOKEVIRTUAL org.springframework.beans.factory.support.AbstractBeanDefinition.setResource (Lorg/springframework/core/io/Resource;)V
                    GOTO L8
                L7: ALOAD_0     // Lorg/springframework/beans/factory/support/AbstractBeanDefinition; this   (line 330)
                    ALOAD_1     // Lorg/springframework/beans/factory/config/BeanDefinition; other
                    INVOKEINTERFACE org.springframework.beans.factory.config.BeanDefinition.getResourceDescription ()Ljava/lang/String;
                    INVOKEVIRTUAL org.springframework.beans.factory.support.AbstractBeanDefinition.setResourceDescription (Ljava/lang/String;)V
                L8: RETURN   (line 332)
  end public void overrideFrom(org.springframework.beans.factory.config.BeanDefinition)

  public void applyDefaults(org.springframework.beans.factory.support.BeanDefinitionDefaults):
                    ALOAD_0     // Lorg/springframework/beans/factory/support/AbstractBeanDefinition; this   (line 339)
                    ALOAD_1     // Lorg/springframework/beans/factory/support/BeanDefinitionDefaults; defaults
                    INVOKEVIRTUAL org.springframework.beans.factory.support.BeanDefinitionDefaults.isLazyInit ()Z
                    INVOKEVIRTUAL org.springframework.beans.factory.support.AbstractBeanDefinition.setLazyInit (Z)V
                    ALOAD_0     // Lorg/springframework/beans/factory/support/AbstractBeanDefinition; this   (line 340)
                    ALOAD_1     // Lorg/springframework/beans/factory/support/BeanDefinitionDefaults; defaults
                    INVOKEVIRTUAL org.springframework.beans.factory.support.BeanDefinitionDefaults.getAutowireMode ()I
                    INVOKEVIRTUAL org.springframework.beans.factory.support.AbstractBeanDefinition.setAutowireMode (I)V
                    ALOAD_0     // Lorg/springframework/beans/factory/support/AbstractBeanDefinition; this   (line 341)
                    ALOAD_1     // Lorg/springframework/beans/factory/support/BeanDefinitionDefaults; defaults
                    INVOKEVIRTUAL org.springframework.beans.factory.support.BeanDefinitionDefaults.getDependencyCheck ()I
                    INVOKEVIRTUAL org.springframework.beans.factory.support.AbstractBeanDefinition.setDependencyCheck (I)V
                    ALOAD_0     // Lorg/springframework/beans/factory/support/AbstractBeanDefinition; this   (line 342)
                    ALOAD_1     // Lorg/springframework/beans/factory/support/BeanDefinitionDefaults; defaults
                    INVOKEVIRTUAL org.springframework.beans.factory.support.BeanDefinitionDefaults.getInitMethodName ()Ljava/lang/String;
                    INVOKEVIRTUAL org.springframework.beans.factory.support.AbstractBeanDefinition.setInitMethodName (Ljava/lang/String;)V
                    ALOAD_0     // Lorg/springframework/beans/factory/support/AbstractBeanDefinition; this   (line 343)
                    ICONST_0
                    INVOKEVIRTUAL org.springframework.beans.factory.support.AbstractBeanDefinition.setEnforceInitMethod (Z)V
                    ALOAD_0     // Lorg/springframework/beans/factory/support/AbstractBeanDefinition; this   (line 344)
                    ALOAD_1     // Lorg/springframework/beans/factory/support/BeanDefinitionDefaults; defaults
                    INVOKEVIRTUAL org.springframework.beans.factory.support.BeanDefinitionDefaults.getDestroyMethodName ()Ljava/lang/String;
                    INVOKEVIRTUAL org.springframework.beans.factory.support.AbstractBeanDefinition.setDestroyMethodName (Ljava/lang/String;)V
                    ALOAD_0     // Lorg/springframework/beans/factory/support/AbstractBeanDefinition; this   (line 345)
                    ICONST_0
                    INVOKEVIRTUAL org.springframework.beans.factory.support.AbstractBeanDefinition.setEnforceDestroyMethod (Z)V
                    RETURN   (line 346)
  end public void applyDefaults(org.springframework.beans.factory.support.BeanDefinitionDefaults)

  public boolean hasBeanClass():
                    ALOAD_0     // Lorg/springframework/beans/factory/support/AbstractBeanDefinition; this   (line 353)
                    GETFIELD org.springframework.beans.factory.support.AbstractBeanDefinition.beanClass Ljava/lang/Object;
                    INSTANCEOF java.lang.Class
                    IRETURN
  end public boolean hasBeanClass()

  public void setBeanClass(Class):
                    ALOAD_0     // Lorg/springframework/beans/factory/support/AbstractBeanDefinition; this   (line 360)
                    ALOAD_1     // Ljava/lang/Class; beanClass
                    PUTFIELD org.springframework.beans.factory.support.AbstractBeanDefinition.beanClass Ljava/lang/Object;
                    RETURN   (line 361)
  end public void setBeanClass(Class)

  public Class getBeanClass() throws java.lang.IllegalStateException:
                    ALOAD_0     // Lorg/springframework/beans/factory/support/AbstractBeanDefinition; this   (line 370)
                    GETFIELD org.springframework.beans.factory.support.AbstractBeanDefinition.beanClass Ljava/lang/Object;
                    ASTORE_1
                    ALOAD_1     // Ljava/lang/Object; beanClassObject   (line 371)
                    IFNONNULL L0
                    NEW java.lang.IllegalStateException   (line 372)
                    DUP
                    LDC_W "No bean class specified on bean definition"
                    INVOKESPECIAL java.lang.IllegalStateException.<init> (Ljava/lang/String;)V
                    ATHROW
                L0: ALOAD_1     // Ljava/lang/Object; beanClassObject   (line 374)
                    INSTANCEOF java.lang.Class
                    IFNE L1
                    NEW java.lang.IllegalStateException   (line 375)
                    DUP
                    NEW java.lang.StringBuilder   (line 376)
                    DUP
                    LDC_W "Bean class name ["
                    INVOKESPECIAL java.lang.StringBuilder.<init> (Ljava/lang/String;)V
                    ALOAD_1     // Ljava/lang/Object; beanClassObject
                    INVOKEVIRTUAL java.lang.StringBuilder.append (Ljava/lang/Object;)Ljava/lang/StringBuilder;
                    LDC_W "] has not been resolved into an actual Class"
                    INVOKEVIRTUAL java.lang.StringBuilder.append (Ljava/lang/String;)Ljava/lang/StringBuilder;
                    INVOKEVIRTUAL java.lang.StringBuilder.toString ()Ljava/lang/String;
                    INVOKESPECIAL java.lang.IllegalStateException.<init> (Ljava/lang/String;)V   (line 375)
                    ATHROW
                L1: ALOAD_1     // Ljava/lang/Object; beanClassObject   (line 378)
                    CHECKCAST java.lang.Class
                    ARETURN
  end public Class getBeanClass() throws java.lang.IllegalStateException

  public void setBeanClassName(String):
                    ALOAD_0     // Lorg/springframework/beans/factory/support/AbstractBeanDefinition; this   (line 382)
                    ALOAD_1     // Ljava/lang/String; beanClassName
                    PUTFIELD org.springframework.beans.factory.support.AbstractBeanDefinition.beanClass Ljava/lang/Object;
                    RETURN   (line 383)
  end public void setBeanClassName(String)

  public String getBeanClassName():
                    ALOAD_0     // Lorg/springframework/beans/factory/support/AbstractBeanDefinition; this   (line 386)
                    GETFIELD org.springframework.beans.factory.support.AbstractBeanDefinition.beanClass Ljava/lang/Object;
                    ASTORE_1
                    ALOAD_1     // Ljava/lang/Object; beanClassObject   (line 387)
                    INSTANCEOF java.lang.Class
                    IFEQ L0
                    ALOAD_1     // Ljava/lang/Object; beanClassObject   (line 388)
                    CHECKCAST java.lang.Class
                    INVOKEVIRTUAL java.lang.Class.getName ()Ljava/lang/String;
                    ARETURN
                L0: ALOAD_1     // Ljava/lang/Object; beanClassObject   (line 391)
                    CHECKCAST java.lang.String
                    ARETURN
  end public String getBeanClassName()

  public Class resolveBeanClass(ClassLoader) throws java.lang.ClassNotFoundException:
                    ALOAD_0     // Lorg/springframework/beans/factory/support/AbstractBeanDefinition; this   (line 404)
                    INVOKEVIRTUAL org.springframework.beans.factory.support.AbstractBeanDefinition.getBeanClassName ()Ljava/lang/String;
                    ASTORE_2
                    ALOAD_2     // Ljava/lang/String; className   (line 405)
                    IFNONNULL L0
                    ACONST_NULL   (line 406)
                    ARETURN
                L0: ALOAD_2     // Ljava/lang/String; className   (line 408)
                    ALOAD_1     // Ljava/lang/ClassLoader; classLoader
                    INVOKESTATIC org.springframework.util.ClassUtils.forName (Ljava/lang/String;Ljava/lang/ClassLoader;)Ljava/lang/Class;
                    ASTORE_3
                    ALOAD_0     // Lorg/springframework/beans/factory/support/AbstractBeanDefinition; this   (line 409)
                    ALOAD_3     // Ljava/lang/Class; resolvedClass
                    PUTFIELD org.springframework.beans.factory.support.AbstractBeanDefinition.beanClass Ljava/lang/Object;
                    ALOAD_3     // Ljava/lang/Class; resolvedClass   (line 410)
                    ARETURN
  end public Class resolveBeanClass(ClassLoader) throws java.lang.ClassNotFoundException

  public void setScope(String):
                    ALOAD_0     // Lorg/springframework/beans/factory/support/AbstractBeanDefinition; this   (line 425)
                    ALOAD_1     // Ljava/lang/String; scope
                    PUTFIELD org.springframework.beans.factory.support.AbstractBeanDefinition.scope Ljava/lang/String;
                    ALOAD_0     // Lorg/springframework/beans/factory/support/AbstractBeanDefinition; this   (line 426)
                    LDC_W "singleton"
                    ALOAD_1     // Ljava/lang/String; scope
                    INVOKEVIRTUAL java.lang.String.equals (Ljava/lang/Object;)Z
                    IFNE L0
                    LDC ""
                    ALOAD_1     // Ljava/lang/String; scope
                    INVOKEVIRTUAL java.lang.String.equals (Ljava/lang/Object;)Z
                    IFNE L0
                    ICONST_0
                    GOTO L1
                L0: ICONST_1
                L1: PUTFIELD org.springframework.beans.factory.support.AbstractBeanDefinition.singleton Z
                    ALOAD_0     // Lorg/springframework/beans/factory/support/AbstractBeanDefinition; this   (line 427)
                    LDC_W "prototype"
                    ALOAD_1     // Ljava/lang/String; scope
                    INVOKEVIRTUAL java.lang.String.equals (Ljava/lang/Object;)Z
                    PUTFIELD org.springframework.beans.factory.support.AbstractBeanDefinition.prototype Z
                    RETURN   (line 428)
  end public void setScope(String)

  public String getScope():
                    ALOAD_0     // Lorg/springframework/beans/factory/support/AbstractBeanDefinition; this   (line 434)
                    GETFIELD org.springframework.beans.factory.support.AbstractBeanDefinition.scope Ljava/lang/String;
                    ARETURN
  end public String getScope()

  public void setSingleton(boolean):
                    ALOAD_0     // Lorg/springframework/beans/factory/support/AbstractBeanDefinition; this   (line 452)
                    ILOAD_1     // Z singleton
                    IFEQ L0
                    LDC_W "singleton"
                    GOTO L1
                L0: LDC_W "prototype"
                L1: PUTFIELD org.springframework.beans.factory.support.AbstractBeanDefinition.scope Ljava/lang/String;
                    ALOAD_0     // Lorg/springframework/beans/factory/support/AbstractBeanDefinition; this   (line 453)
                    ILOAD_1     // Z singleton
                    PUTFIELD org.springframework.beans.factory.support.AbstractBeanDefinition.singleton Z
                    ALOAD_0     // Lorg/springframework/beans/factory/support/AbstractBeanDefinition; this   (line 454)
                    ILOAD_1     // Z singleton
                    IFEQ L2
                    ICONST_0
                    GOTO L3
                L2: ICONST_1
                L3: PUTFIELD org.springframework.beans.factory.support.AbstractBeanDefinition.prototype Z
                    RETURN   (line 455)
  end public void setSingleton(boolean)

  public boolean isSingleton():
                    ALOAD_0     // Lorg/springframework/beans/factory/support/AbstractBeanDefinition; this   (line 463)
                    GETFIELD org.springframework.beans.factory.support.AbstractBeanDefinition.singleton Z
                    IRETURN
  end public boolean isSingleton()

  public boolean isPrototype():
                    ALOAD_0     // Lorg/springframework/beans/factory/support/AbstractBeanDefinition; this   (line 472)
                    GETFIELD org.springframework.beans.factory.support.AbstractBeanDefinition.prototype Z
                    IRETURN
  end public boolean isPrototype()

  public void setAbstract(boolean):
                    ALOAD_0     // Lorg/springframework/beans/factory/support/AbstractBeanDefinition; this   (line 482)
                    ILOAD_1     // Z abstractFlag
                    PUTFIELD org.springframework.beans.factory.support.AbstractBeanDefinition.abstractFlag Z
                    RETURN   (line 483)
  end public void setAbstract(boolean)

  public boolean isAbstract():
                    ALOAD_0     // Lorg/springframework/beans/factory/support/AbstractBeanDefinition; this   (line 490)
                    GETFIELD org.springframework.beans.factory.support.AbstractBeanDefinition.abstractFlag Z
                    IRETURN
  end public boolean isAbstract()

  public void setLazyInit(boolean):
                    ALOAD_0     // Lorg/springframework/beans/factory/support/AbstractBeanDefinition; this   (line 499)
                    ILOAD_1     // Z lazyInit
                    PUTFIELD org.springframework.beans.factory.support.AbstractBeanDefinition.lazyInit Z
                    RETURN   (line 500)
  end public void setLazyInit(boolean)

  public boolean isLazyInit():
                    ALOAD_0     // Lorg/springframework/beans/factory/support/AbstractBeanDefinition; this   (line 507)
                    GETFIELD org.springframework.beans.factory.support.AbstractBeanDefinition.lazyInit Z
                    IRETURN
  end public boolean isLazyInit()

  public void setAutowireMode(int):
                    ALOAD_0     // Lorg/springframework/beans/factory/support/AbstractBeanDefinition; this   (line 524)
                    ILOAD_1     // I autowireMode
                    PUTFIELD org.springframework.beans.factory.support.AbstractBeanDefinition.autowireMode I
                    RETURN   (line 525)
  end public void setAutowireMode(int)

  public int getAutowireMode():
                    ALOAD_0     // Lorg/springframework/beans/factory/support/AbstractBeanDefinition; this   (line 531)
                    GETFIELD org.springframework.beans.factory.support.AbstractBeanDefinition.autowireMode I
                    IRETURN
  end public int getAutowireMode()

  public int getResolvedAutowireMode():
                    ALOAD_0     // Lorg/springframework/beans/factory/support/AbstractBeanDefinition; this   (line 542)
                    GETFIELD org.springframework.beans.factory.support.AbstractBeanDefinition.autowireMode I
                    ICONST_4
                    IF_ICMPNE L3
                    ALOAD_0     // Lorg/springframework/beans/factory/support/AbstractBeanDefinition; this   (line 546)
                    INVOKEVIRTUAL org.springframework.beans.factory.support.AbstractBeanDefinition.getBeanClass ()Ljava/lang/Class;
                    INVOKEVIRTUAL java.lang.Class.getConstructors ()[Ljava/lang/reflect/Constructor;
                    ASTORE_1
                    ALOAD_1     // [Ljava/lang/reflect/Constructor; constructors   (line 547)
                    DUP
                    ASTORE 5
                    ARRAYLENGTH
                    ISTORE 4
                    ICONST_0
                    ISTORE_3
                    GOTO L2
                L0: ALOAD 5
                    ILOAD_3
                    AALOAD
                    ASTORE_2
                    ALOAD_2     // Ljava/lang/reflect/Constructor; constructor   (line 548)
                    INVOKEVIRTUAL java.lang.reflect.Constructor.getParameterTypes ()[Ljava/lang/Class;
                    ARRAYLENGTH
                    IFNE L1
                    ICONST_2   (line 549)
                    IRETURN
                L1: IINC_3 1   (line 547)
                L2: ILOAD_3
                    ILOAD 4
                    IF_ICMPLT L0
                    ICONST_3   (line 552)
                    IRETURN
                L3: ALOAD_0     // Lorg/springframework/beans/factory/support/AbstractBeanDefinition; this   (line 555)
                    GETFIELD org.springframework.beans.factory.support.AbstractBeanDefinition.autowireMode I
                    IRETURN
  end public int getResolvedAutowireMode()

  public void setDependencyCheck(int):
                    ALOAD_0     // Lorg/springframework/beans/factory/support/AbstractBeanDefinition; this   (line 569)
                    ILOAD_1     // I dependencyCheck
                    PUTFIELD org.springframework.beans.factory.support.AbstractBeanDefinition.dependencyCheck I
                    RETURN   (line 570)
  end public void setDependencyCheck(int)

  public int getDependencyCheck():
                    ALOAD_0     // Lorg/springframework/beans/factory/support/AbstractBeanDefinition; this   (line 576)
                    GETFIELD org.springframework.beans.factory.support.AbstractBeanDefinition.dependencyCheck I
                    IRETURN
  end public int getDependencyCheck()

  public void setDependsOn(String[]):
                    ALOAD_0     // Lorg/springframework/beans/factory/support/AbstractBeanDefinition; this   (line 587)
                    ALOAD_1     // [Ljava/lang/String; dependsOn
                    PUTFIELD org.springframework.beans.factory.support.AbstractBeanDefinition.dependsOn [Ljava/lang/String;
                    RETURN   (line 588)
  end public void setDependsOn(String[])

  public String[] getDependsOn():
                    ALOAD_0     // Lorg/springframework/beans/factory/support/AbstractBeanDefinition; this   (line 594)
                    GETFIELD org.springframework.beans.factory.support.AbstractBeanDefinition.dependsOn [Ljava/lang/String;
                    ARETURN
  end public String[] getDependsOn()

  public void setAutowireCandidate(boolean):
                    ALOAD_0     // Lorg/springframework/beans/factory/support/AbstractBeanDefinition; this   (line 601)
                    ILOAD_1     // Z autowireCandidate
                    PUTFIELD org.springframework.beans.factory.support.AbstractBeanDefinition.autowireCandidate Z
                    RETURN   (line 602)
  end public void setAutowireCandidate(boolean)

  public boolean isAutowireCandidate():
                    ALOAD_0     // Lorg/springframework/beans/factory/support/AbstractBeanDefinition; this   (line 608)
                    GETFIELD org.springframework.beans.factory.support.AbstractBeanDefinition.autowireCandidate Z
                    IRETURN
  end public boolean isAutowireCandidate()

  public void setPrimary(boolean):
                    ALOAD_0     // Lorg/springframework/beans/factory/support/AbstractBeanDefinition; this   (line 617)
                    ILOAD_1     // Z primary
                    PUTFIELD org.springframework.beans.factory.support.AbstractBeanDefinition.primary Z
                    RETURN   (line 618)
  end public void setPrimary(boolean)

  public boolean isPrimary():
                    ALOAD_0     // Lorg/springframework/beans/factory/support/AbstractBeanDefinition; this   (line 626)
                    GETFIELD org.springframework.beans.factory.support.AbstractBeanDefinition.primary Z
                    IRETURN
  end public boolean isPrimary()

  public void addQualifier(org.springframework.beans.factory.support.AutowireCandidateQualifier):
                    ALOAD_0     // Lorg/springframework/beans/factory/support/AbstractBeanDefinition; this   (line 635)
                    GETFIELD org.springframework.beans.factory.support.AbstractBeanDefinition.qualifiers Ljava/util/Map;
                    ALOAD_1     // Lorg/springframework/beans/factory/support/AutowireCandidateQualifier; qualifier
                    INVOKEVIRTUAL org.springframework.beans.factory.support.AutowireCandidateQualifier.getTypeName ()Ljava/lang/String;
                    ALOAD_1     // Lorg/springframework/beans/factory/support/AutowireCandidateQualifier; qualifier
                    INVOKEINTERFACE java.util.Map.put (Ljava/lang/Object;Ljava/lang/Object;)Ljava/lang/Object;
                    POP
                    RETURN   (line 636)
  end public void addQualifier(org.springframework.beans.factory.support.AutowireCandidateQualifier)

  public boolean hasQualifier(String):
                    ALOAD_0     // Lorg/springframework/beans/factory/support/AbstractBeanDefinition; this   (line 642)
                    GETFIELD org.springframework.beans.factory.support.AbstractBeanDefinition.qualifiers Ljava/util/Map;
                    INVOKEINTERFACE java.util.Map.keySet ()Ljava/util/Set;
                    ALOAD_1     // Ljava/lang/String; typeName
                    INVOKEINTERFACE java.util.Set.contains (Ljava/lang/Object;)Z
                    IRETURN
  end public boolean hasQualifier(String)

  public org.springframework.beans.factory.support.AutowireCandidateQualifier getQualifier(String):
                    ALOAD_0     // Lorg/springframework/beans/factory/support/AbstractBeanDefinition; this   (line 649)
                    GETFIELD org.springframework.beans.factory.support.AbstractBeanDefinition.qualifiers Ljava/util/Map;
                    ALOAD_1     // Ljava/lang/String; typeName
                    INVOKEINTERFACE java.util.Map.get (Ljava/lang/Object;)Ljava/lang/Object;
                    CHECKCAST org.springframework.beans.factory.support.AutowireCandidateQualifier
                    ARETURN
  end public org.springframework.beans.factory.support.AutowireCandidateQualifier getQualifier(String)

  public java.util.Set getQualifiers():
                    NEW java.util.LinkedHashSet   (line 657)
                    DUP
                    ALOAD_0     // Lorg/springframework/beans/factory/support/AbstractBeanDefinition; this
                    GETFIELD org.springframework.beans.factory.support.AbstractBeanDefinition.qualifiers Ljava/util/Map;
                    INVOKEINTERFACE java.util.Map.values ()Ljava/util/Collection;
                    INVOKESPECIAL java.util.LinkedHashSet.<init> (Ljava/util/Collection;)V
                    ARETURN
  end public java.util.Set getQualifiers()

  public void copyQualifiersFrom(org.springframework.beans.factory.support.AbstractBeanDefinition):
                    ALOAD_1     // Lorg/springframework/beans/factory/support/AbstractBeanDefinition; source   (line 665)
                    LDC_W "Source must not be null"
                    INVOKESTATIC org.springframework.util.Assert.notNull (Ljava/lang/Object;Ljava/lang/String;)V
                    ALOAD_0     // Lorg/springframework/beans/factory/support/AbstractBeanDefinition; this   (line 666)
                    GETFIELD org.springframework.beans.factory.support.AbstractBeanDefinition.qualifiers Ljava/util/Map;
                    ALOAD_1     // Lorg/springframework/beans/factory/support/AbstractBeanDefinition; source
                    GETFIELD org.springframework.beans.factory.support.AbstractBeanDefinition.qualifiers Ljava/util/Map;
                    INVOKEINTERFACE java.util.Map.putAll (Ljava/util/Map;)V
                    RETURN   (line 667)
  end public void copyQualifiersFrom(org.springframework.beans.factory.support.AbstractBeanDefinition)

  public void setNonPublicAccessAllowed(boolean):
                    ALOAD_0     // Lorg/springframework/beans/factory/support/AbstractBeanDefinition; this   (line 681)
                    ILOAD_1     // Z nonPublicAccessAllowed
                    PUTFIELD org.springframework.beans.factory.support.AbstractBeanDefinition.nonPublicAccessAllowed Z
                    RETURN   (line 682)
  end public void setNonPublicAccessAllowed(boolean)

  public boolean isNonPublicAccessAllowed():
                    ALOAD_0     // Lorg/springframework/beans/factory/support/AbstractBeanDefinition; this   (line 688)
                    GETFIELD org.springframework.beans.factory.support.AbstractBeanDefinition.nonPublicAccessAllowed Z
                    IRETURN
  end public boolean isNonPublicAccessAllowed()

  public void setLenientConstructorResolution(boolean):
                    ALOAD_0     // Lorg/springframework/beans/factory/support/AbstractBeanDefinition; this   (line 698)
                    ILOAD_1     // Z lenientConstructorResolution
                    PUTFIELD org.springframework.beans.factory.support.AbstractBeanDefinition.lenientConstructorResolution Z
                    RETURN   (line 699)
  end public void setLenientConstructorResolution(boolean)

  public boolean isLenientConstructorResolution():
                    ALOAD_0     // Lorg/springframework/beans/factory/support/AbstractBeanDefinition; this   (line 705)
                    GETFIELD org.springframework.beans.factory.support.AbstractBeanDefinition.lenientConstructorResolution Z
                    IRETURN
  end public boolean isLenientConstructorResolution()

  public void setConstructorArgumentValues(org.springframework.beans.factory.config.ConstructorArgumentValues):
                    ALOAD_0     // Lorg/springframework/beans/factory/support/AbstractBeanDefinition; this   (line 712)
                    ALOAD_1     // Lorg/springframework/beans/factory/config/ConstructorArgumentValues; constructorArgumentValues   (line 713)
                    IFNULL L0
                    ALOAD_1     // Lorg/springframework/beans/factory/config/ConstructorArgumentValues; constructorArgumentValues
                    GOTO L1
                L0: NEW org.springframework.beans.factory.config.ConstructorArgumentValues
                    DUP
                    INVOKESPECIAL org.springframework.beans.factory.config.ConstructorArgumentValues.<init> ()V
                L1: PUTFIELD org.springframework.beans.factory.support.AbstractBeanDefinition.constructorArgumentValues Lorg/springframework/beans/factory/config/ConstructorArgumentValues;   (line 712)
                    RETURN   (line 714)
  end public void setConstructorArgumentValues(org.springframework.beans.factory.config.ConstructorArgumentValues)

  public org.springframework.beans.factory.config.ConstructorArgumentValues getConstructorArgumentValues():
                    ALOAD_0     // Lorg/springframework/beans/factory/support/AbstractBeanDefinition; this   (line 720)
                    GETFIELD org.springframework.beans.factory.support.AbstractBeanDefinition.constructorArgumentValues Lorg/springframework/beans/factory/config/ConstructorArgumentValues;
                    ARETURN
  end public org.springframework.beans.factory.config.ConstructorArgumentValues getConstructorArgumentValues()

  public boolean hasConstructorArgumentValues():
                    ALOAD_0     // Lorg/springframework/beans/factory/support/AbstractBeanDefinition; this   (line 727)
                    GETFIELD org.springframework.beans.factory.support.AbstractBeanDefinition.constructorArgumentValues Lorg/springframework/beans/factory/config/ConstructorArgumentValues;
                    INVOKEVIRTUAL org.springframework.beans.factory.config.ConstructorArgumentValues.isEmpty ()Z
                    IFEQ L0
                    ICONST_0
                    GOTO L1
                L0: ICONST_1
                L1: IRETURN
  end public boolean hasConstructorArgumentValues()

  public void setPropertyValues(org.springframework.beans.MutablePropertyValues):
                    ALOAD_0     // Lorg/springframework/beans/factory/support/AbstractBeanDefinition; this   (line 734)
                    ALOAD_1     // Lorg/springframework/beans/MutablePropertyValues; propertyValues
                    IFNULL L0
                    ALOAD_1     // Lorg/springframework/beans/MutablePropertyValues; propertyValues
                    GOTO L1
                L0: NEW org.springframework.beans.MutablePropertyValues
                    DUP
                    INVOKESPECIAL org.springframework.beans.MutablePropertyValues.<init> ()V
                L1: PUTFIELD org.springframework.beans.factory.support.AbstractBeanDefinition.propertyValues Lorg/springframework/beans/MutablePropertyValues;
                    RETURN   (line 735)
  end public void setPropertyValues(org.springframework.beans.MutablePropertyValues)

  public org.springframework.beans.MutablePropertyValues getPropertyValues():
                    ALOAD_0     // Lorg/springframework/beans/factory/support/AbstractBeanDefinition; this   (line 741)
                    GETFIELD org.springframework.beans.factory.support.AbstractBeanDefinition.propertyValues Lorg/springframework/beans/MutablePropertyValues;
                    ARETURN
  end public org.springframework.beans.MutablePropertyValues getPropertyValues()

  public void setMethodOverrides(org.springframework.beans.factory.support.MethodOverrides):
                    ALOAD_0     // Lorg/springframework/beans/factory/support/AbstractBeanDefinition; this   (line 748)
                    ALOAD_1     // Lorg/springframework/beans/factory/support/MethodOverrides; methodOverrides
                    IFNULL L0
                    ALOAD_1     // Lorg/springframework/beans/factory/support/MethodOverrides; methodOverrides
                    GOTO L1
                L0: NEW org.springframework.beans.factory.support.MethodOverrides
                    DUP
                    INVOKESPECIAL org.springframework.beans.factory.support.MethodOverrides.<init> ()V
                L1: PUTFIELD org.springframework.beans.factory.support.AbstractBeanDefinition.methodOverrides Lorg/springframework/beans/factory/support/MethodOverrides;
                    RETURN   (line 749)
  end public void setMethodOverrides(org.springframework.beans.factory.support.MethodOverrides)

  public org.springframework.beans.factory.support.MethodOverrides getMethodOverrides():
                    ALOAD_0     // Lorg/springframework/beans/factory/support/AbstractBeanDefinition; this   (line 757)
                    GETFIELD org.springframework.beans.factory.support.AbstractBeanDefinition.methodOverrides Lorg/springframework/beans/factory/support/MethodOverrides;
                    ARETURN
  end public org.springframework.beans.factory.support.MethodOverrides getMethodOverrides()

  public void setFactoryBeanName(String):
                    ALOAD_0     // Lorg/springframework/beans/factory/support/AbstractBeanDefinition; this   (line 762)
                    ALOAD_1     // Ljava/lang/String; factoryBeanName
                    PUTFIELD org.springframework.beans.factory.support.AbstractBeanDefinition.factoryBeanName Ljava/lang/String;
                    RETURN   (line 763)
  end public void setFactoryBeanName(String)

  public String getFactoryBeanName():
                    ALOAD_0     // Lorg/springframework/beans/factory/support/AbstractBeanDefinition; this   (line 766)
                    GETFIELD org.springframework.beans.factory.support.AbstractBeanDefinition.factoryBeanName Ljava/lang/String;
                    ARETURN
  end public String getFactoryBeanName()

  public void setFactoryMethodName(String):
                    ALOAD_0     // Lorg/springframework/beans/factory/support/AbstractBeanDefinition; this   (line 770)
                    ALOAD_1     // Ljava/lang/String; factoryMethodName
                    PUTFIELD org.springframework.beans.factory.support.AbstractBeanDefinition.factoryMethodName Ljava/lang/String;
                    RETURN   (line 771)
  end public void setFactoryMethodName(String)

  public String getFactoryMethodName():
                    ALOAD_0     // Lorg/springframework/beans/factory/support/AbstractBeanDefinition; this   (line 774)
                    GETFIELD org.springframework.beans.factory.support.AbstractBeanDefinition.factoryMethodName Ljava/lang/String;
                    ARETURN
  end public String getFactoryMethodName()

  public void setInitMethodName(String):
                    ALOAD_0     // Lorg/springframework/beans/factory/support/AbstractBeanDefinition; this   (line 782)
                    ALOAD_1     // Ljava/lang/String; initMethodName
                    PUTFIELD org.springframework.beans.factory.support.AbstractBeanDefinition.initMethodName Ljava/lang/String;
                    RETURN   (line 783)
  end public void setInitMethodName(String)

  public String getInitMethodName():
                    ALOAD_0     // Lorg/springframework/beans/factory/support/AbstractBeanDefinition; this   (line 789)
                    GETFIELD org.springframework.beans.factory.support.AbstractBeanDefinition.initMethodName Ljava/lang/String;
                    ARETURN
  end public String getInitMethodName()

  public void setEnforceInitMethod(boolean):
                    ALOAD_0     // Lorg/springframework/beans/factory/support/AbstractBeanDefinition; this   (line 798)
                    ILOAD_1     // Z enforceInitMethod
                    PUTFIELD org.springframework.beans.factory.support.AbstractBeanDefinition.enforceInitMethod Z
                    RETURN   (line 799)
  end public void setEnforceInitMethod(boolean)

  public boolean isEnforceInitMethod():
                    ALOAD_0     // Lorg/springframework/beans/factory/support/AbstractBeanDefinition; this   (line 806)
                    GETFIELD org.springframework.beans.factory.support.AbstractBeanDefinition.enforceInitMethod Z
                    IRETURN
  end public boolean isEnforceInitMethod()

  public void setDestroyMethodName(String):
                    ALOAD_0     // Lorg/springframework/beans/factory/support/AbstractBeanDefinition; this   (line 814)
                    ALOAD_1     // Ljava/lang/String; destroyMethodName
                    PUTFIELD org.springframework.beans.factory.support.AbstractBeanDefinition.destroyMethodName Ljava/lang/String;
                    RETURN   (line 815)
  end public void setDestroyMethodName(String)

  public String getDestroyMethodName():
                    ALOAD_0     // Lorg/springframework/beans/factory/support/AbstractBeanDefinition; this   (line 821)
                    GETFIELD org.springframework.beans.factory.support.AbstractBeanDefinition.destroyMethodName Ljava/lang/String;
                    ARETURN
  end public String getDestroyMethodName()

  public void setEnforceDestroyMethod(boolean):
                    ALOAD_0     // Lorg/springframework/beans/factory/support/AbstractBeanDefinition; this   (line 830)
                    ILOAD_1     // Z enforceDestroyMethod
                    PUTFIELD org.springframework.beans.factory.support.AbstractBeanDefinition.enforceDestroyMethod Z
                    RETURN   (line 831)
  end public void setEnforceDestroyMethod(boolean)

  public boolean isEnforceDestroyMethod():
                    ALOAD_0     // Lorg/springframework/beans/factory/support/AbstractBeanDefinition; this   (line 838)
                    GETFIELD org.springframework.beans.factory.support.AbstractBeanDefinition.enforceDestroyMethod Z
                    IRETURN
  end public boolean isEnforceDestroyMethod()

  public void setSynthetic(boolean):
                    ALOAD_0     // Lorg/springframework/beans/factory/support/AbstractBeanDefinition; this   (line 848)
                    ILOAD_1     // Z synthetic
                    PUTFIELD org.springframework.beans.factory.support.AbstractBeanDefinition.synthetic Z
                    RETURN   (line 849)
  end public void setSynthetic(boolean)

  public boolean isSynthetic():
                    ALOAD_0     // Lorg/springframework/beans/factory/support/AbstractBeanDefinition; this   (line 856)
                    GETFIELD org.springframework.beans.factory.support.AbstractBeanDefinition.synthetic Z
                    IRETURN
  end public boolean isSynthetic()

  public void setRole(int):
                    ALOAD_0     // Lorg/springframework/beans/factory/support/AbstractBeanDefinition; this   (line 863)
                    ILOAD_1     // I role
                    PUTFIELD org.springframework.beans.factory.support.AbstractBeanDefinition.role I
                    RETURN   (line 864)
  end public void setRole(int)

  public int getRole():
                    ALOAD_0     // Lorg/springframework/beans/factory/support/AbstractBeanDefinition; this   (line 870)
                    GETFIELD org.springframework.beans.factory.support.AbstractBeanDefinition.role I
                    IRETURN
  end public int getRole()

  public void setDescription(String):
                    ALOAD_0     // Lorg/springframework/beans/factory/support/AbstractBeanDefinition; this   (line 878)
                    ALOAD_1     // Ljava/lang/String; description
                    PUTFIELD org.springframework.beans.factory.support.AbstractBeanDefinition.description Ljava/lang/String;
                    RETURN   (line 879)
  end public void setDescription(String)

  public String getDescription():
                    ALOAD_0     // Lorg/springframework/beans/factory/support/AbstractBeanDefinition; this   (line 882)
                    GETFIELD org.springframework.beans.factory.support.AbstractBeanDefinition.description Ljava/lang/String;
                    ARETURN
  end public String getDescription()

  public void setResource(org.springframework.core.io.Resource):
                    ALOAD_0     // Lorg/springframework/beans/factory/support/AbstractBeanDefinition; this   (line 890)
                    ALOAD_1     // Lorg/springframework/core/io/Resource; resource
                    PUTFIELD org.springframework.beans.factory.support.AbstractBeanDefinition.resource Lorg/springframework/core/io/Resource;
                    RETURN   (line 891)
  end public void setResource(org.springframework.core.io.Resource)

  public org.springframework.core.io.Resource getResource():
                    ALOAD_0     // Lorg/springframework/beans/factory/support/AbstractBeanDefinition; this   (line 897)
                    GETFIELD org.springframework.beans.factory.support.AbstractBeanDefinition.resource Lorg/springframework/core/io/Resource;
                    ARETURN
  end public org.springframework.core.io.Resource getResource()

  public void setResourceDescription(String):
                    ALOAD_0     // Lorg/springframework/beans/factory/support/AbstractBeanDefinition; this   (line 905)
                    NEW org.springframework.core.io.DescriptiveResource
                    DUP
                    ALOAD_1     // Ljava/lang/String; resourceDescription
                    INVOKESPECIAL org.springframework.core.io.DescriptiveResource.<init> (Ljava/lang/String;)V
                    PUTFIELD org.springframework.beans.factory.support.AbstractBeanDefinition.resource Lorg/springframework/core/io/Resource;
                    RETURN   (line 906)
  end public void setResourceDescription(String)

  public String getResourceDescription():
                    ALOAD_0     // Lorg/springframework/beans/factory/support/AbstractBeanDefinition; this   (line 909)
                    GETFIELD org.springframework.beans.factory.support.AbstractBeanDefinition.resource Lorg/springframework/core/io/Resource;
                    IFNULL L0
                    ALOAD_0     // Lorg/springframework/beans/factory/support/AbstractBeanDefinition; this
                    GETFIELD org.springframework.beans.factory.support.AbstractBeanDefinition.resource Lorg/springframework/core/io/Resource;
                    INVOKEINTERFACE org.springframework.core.io.Resource.getDescription ()Ljava/lang/String;
                    GOTO L1
                L0: ACONST_NULL
                L1: ARETURN
  end public String getResourceDescription()

  public void setOriginatingBeanDefinition(org.springframework.beans.factory.config.BeanDefinition):
                    ALOAD_0     // Lorg/springframework/beans/factory/support/AbstractBeanDefinition; this   (line 916)
                    NEW org.springframework.beans.factory.support.BeanDefinitionResource
                    DUP
                    ALOAD_1     // Lorg/springframework/beans/factory/config/BeanDefinition; originatingBd
                    INVOKESPECIAL org.springframework.beans.factory.support.BeanDefinitionResource.<init> (Lorg/springframework/beans/factory/config/BeanDefinition;)V
                    PUTFIELD org.springframework.beans.factory.support.AbstractBeanDefinition.resource Lorg/springframework/core/io/Resource;
                    RETURN   (line 917)
  end public void setOriginatingBeanDefinition(org.springframework.beans.factory.config.BeanDefinition)

  public org.springframework.beans.factory.config.BeanDefinition getOriginatingBeanDefinition():
                    ALOAD_0     // Lorg/springframework/beans/factory/support/AbstractBeanDefinition; this   (line 920)
                    GETFIELD org.springframework.beans.factory.support.AbstractBeanDefinition.resource Lorg/springframework/core/io/Resource;
                    INSTANCEOF org.springframework.beans.factory.support.BeanDefinitionResource
                    IFEQ L0
                    ALOAD_0     // Lorg/springframework/beans/factory/support/AbstractBeanDefinition; this   (line 921)
                    GETFIELD org.springframework.beans.factory.support.AbstractBeanDefinition.resource Lorg/springframework/core/io/Resource;
                    CHECKCAST org.springframework.beans.factory.support.BeanDefinitionResource
                    INVOKEVIRTUAL org.springframework.beans.factory.support.BeanDefinitionResource.getBeanDefinition ()Lorg/springframework/beans/factory/config/BeanDefinition;
                    GOTO L1
                L0: ACONST_NULL
                L1: ARETURN   (line 920)
  end public org.springframework.beans.factory.config.BeanDefinition getOriginatingBeanDefinition()

  public void validate() throws org.springframework.beans.factory.support.BeanDefinitionValidationException:
                    ALOAD_0     // Lorg/springframework/beans/factory/support/AbstractBeanDefinition; this   (line 929)
                    INVOKEVIRTUAL org.springframework.beans.factory.support.AbstractBeanDefinition.getMethodOverrides ()Lorg/springframework/beans/factory/support/MethodOverrides;
                    INVOKEVIRTUAL org.springframework.beans.factory.support.MethodOverrides.isEmpty ()Z
                    IFNE L0
                    ALOAD_0     // Lorg/springframework/beans/factory/support/AbstractBeanDefinition; this
                    INVOKEVIRTUAL org.springframework.beans.factory.support.AbstractBeanDefinition.getFactoryMethodName ()Ljava/lang/String;
                    IFNULL L0
                    NEW org.springframework.beans.factory.support.BeanDefinitionValidationException   (line 930)
                    DUP
                    LDC_W "Cannot combine static factory method with method overrides: the static factory method must create the instance"   (line 931)
                    INVOKESPECIAL org.springframework.beans.factory.support.BeanDefinitionValidationException.<init> (Ljava/lang/String;)V   (line 930)
                    ATHROW
                L0: ALOAD_0     // Lorg/springframework/beans/factory/support/AbstractBeanDefinition; this   (line 935)
                    INVOKEVIRTUAL org.springframework.beans.factory.support.AbstractBeanDefinition.hasBeanClass ()Z
                    IFEQ L1
                    ALOAD_0     // Lorg/springframework/beans/factory/support/AbstractBeanDefinition; this   (line 936)
                    INVOKEVIRTUAL org.springframework.beans.factory.support.AbstractBeanDefinition.prepareMethodOverrides ()V
                L1: RETURN   (line 938)
  end public void validate() throws org.springframework.beans.factory.support.BeanDefinitionValidationException

  public void prepareMethodOverrides() throws org.springframework.beans.factory.support.BeanDefinitionValidationException:
                    ALOAD_0     // Lorg/springframework/beans/factory/support/AbstractBeanDefinition; this   (line 947)
                    INVOKEVIRTUAL org.springframework.beans.factory.support.AbstractBeanDefinition.getMethodOverrides ()Lorg/springframework/beans/factory/support/MethodOverrides;
                    ASTORE_1
                    ALOAD_1     // Lorg/springframework/beans/factory/support/MethodOverrides; methodOverrides   (line 948)
                    INVOKEVIRTUAL org.springframework.beans.factory.support.MethodOverrides.isEmpty ()Z
                    IFNE L2
                    ALOAD_1     // Lorg/springframework/beans/factory/support/MethodOverrides; methodOverrides   (line 949)
                    INVOKEVIRTUAL org.springframework.beans.factory.support.MethodOverrides.getOverrides ()Ljava/util/Set;
                    INVOKEINTERFACE java.util.Set.iterator ()Ljava/util/Iterator;
                    ASTORE_3
                    GOTO L1
                L0: ALOAD_3
                    INVOKEINTERFACE java.util.Iterator.next ()Ljava/lang/Object;
                    CHECKCAST org.springframework.beans.factory.support.MethodOverride
                    ASTORE_2
                    ALOAD_0     // Lorg/springframework/beans/factory/support/AbstractBeanDefinition; this   (line 950)
                    ALOAD_2     // Lorg/springframework/beans/factory/support/MethodOverride; mo
                    INVOKEVIRTUAL org.springframework.beans.factory.support.AbstractBeanDefinition.prepareMethodOverride (Lorg/springframework/beans/factory/support/MethodOverride;)V
                L1: ALOAD_3   (line 949)
                    INVOKEINTERFACE java.util.Iterator.hasNext ()Z
                    IFNE L0
                L2: RETURN   (line 953)
  end public void prepareMethodOverrides() throws org.springframework.beans.factory.support.BeanDefinitionValidationException

  protected void prepareMethodOverride(org.springframework.beans.factory.support.MethodOverride) throws org.springframework.beans.factory.support.BeanDefinitionValidationException:
                    ALOAD_0     // Lorg/springframework/beans/factory/support/AbstractBeanDefinition; this   (line 963)
                    INVOKEVIRTUAL org.springframework.beans.factory.support.AbstractBeanDefinition.getBeanClass ()Ljava/lang/Class;
                    ALOAD_1     // Lorg/springframework/beans/factory/support/MethodOverride; mo
                    INVOKEVIRTUAL org.springframework.beans.factory.support.MethodOverride.getMethodName ()Ljava/lang/String;
                    INVOKESTATIC org.springframework.util.ClassUtils.getMethodCountForName (Ljava/lang/Class;Ljava/lang/String;)I
                    ISTORE_2
                    ILOAD_2     // I count   (line 964)
                    IFNE L0
                    NEW org.springframework.beans.factory.support.BeanDefinitionValidationException   (line 965)
                    DUP
                    NEW java.lang.StringBuilder   (line 966)
                    DUP
                    LDC_W "Invalid method override: no method with name '"
                    INVOKESPECIAL java.lang.StringBuilder.<init> (Ljava/lang/String;)V
                    ALOAD_1     // Lorg/springframework/beans/factory/support/MethodOverride; mo
                    INVOKEVIRTUAL org.springframework.beans.factory.support.MethodOverride.getMethodName ()Ljava/lang/String;
                    INVOKEVIRTUAL java.lang.StringBuilder.append (Ljava/lang/String;)Ljava/lang/StringBuilder;
                    LDC_W "' on class ["   (line 967)
                    INVOKEVIRTUAL java.lang.StringBuilder.append (Ljava/lang/String;)Ljava/lang/StringBuilder;
                    ALOAD_0     // Lorg/springframework/beans/factory/support/AbstractBeanDefinition; this
                    INVOKEVIRTUAL org.springframework.beans.factory.support.AbstractBeanDefinition.getBeanClassName ()Ljava/lang/String;
                    INVOKEVIRTUAL java.lang.StringBuilder.append (Ljava/lang/String;)Ljava/lang/StringBuilder;
                    LDC_W "]"
                    INVOKEVIRTUAL java.lang.StringBuilder.append (Ljava/lang/String;)Ljava/lang/StringBuilder;
                    INVOKEVIRTUAL java.lang.StringBuilder.toString ()Ljava/lang/String;   (line 966)
                    INVOKESPECIAL org.springframework.beans.factory.support.BeanDefinitionValidationException.<init> (Ljava/lang/String;)V   (line 965)
                    ATHROW
                L0: ILOAD_2     // I count   (line 969)
                    ICONST_1
                    IF_ICMPNE L1
                    ALOAD_1     // Lorg/springframework/beans/factory/support/MethodOverride; mo   (line 971)
                    ICONST_0
                    INVOKEVIRTUAL org.springframework.beans.factory.support.MethodOverride.setOverloaded (Z)V
                L1: RETURN   (line 973)
  end protected void prepareMethodOverride(org.springframework.beans.factory.support.MethodOverride) throws org.springframework.beans.factory.support.BeanDefinitionValidationException

  public Object clone():
                    ALOAD_0     // Lorg/springframework/beans/factory/support/AbstractBeanDefinition; this   (line 983)
                    INVOKEVIRTUAL org.springframework.beans.factory.support.AbstractBeanDefinition.cloneBeanDefinition ()Lorg/springframework/beans/factory/support/AbstractBeanDefinition;
                    ARETURN
  end public Object clone()

  public abstract org.springframework.beans.factory.support.AbstractBeanDefinition cloneBeanDefinition();

  public boolean equals(Object):
                    ALOAD_0     // Lorg/springframework/beans/factory/support/AbstractBeanDefinition; this   (line 996)
                    ALOAD_1     // Ljava/lang/Object; other
                    IF_ACMPNE L0
                    ICONST_1   (line 997)
                    IRETURN
                L0: ALOAD_1     // Ljava/lang/Object; other   (line 999)
                    INSTANCEOF org.springframework.beans.factory.support.AbstractBeanDefinition
                    IFNE L1
                    ICONST_0   (line 1000)
                    IRETURN
                L1: ALOAD_1     // Ljava/lang/Object; other   (line 1003)
                    CHECKCAST org.springframework.beans.factory.support.AbstractBeanDefinition
                    ASTORE_2
                    ALOAD_0     // Lorg/springframework/beans/factory/support/AbstractBeanDefinition; this   (line 1005)
                    INVOKEVIRTUAL org.springframework.beans.factory.support.AbstractBeanDefinition.getBeanClassName ()Ljava/lang/String;
                    ALOAD_2     // Lorg/springframework/beans/factory/support/AbstractBeanDefinition; that
                    INVOKEVIRTUAL org.springframework.beans.factory.support.AbstractBeanDefinition.getBeanClassName ()Ljava/lang/String;
                    INVOKESTATIC org.springframework.util.ObjectUtils.nullSafeEquals (Ljava/lang/Object;Ljava/lang/Object;)Z
                    IFNE L2
                    ICONST_0
                    IRETURN
                L2: ALOAD_0     // Lorg/springframework/beans/factory/support/AbstractBeanDefinition; this   (line 1006)
                    GETFIELD org.springframework.beans.factory.support.AbstractBeanDefinition.scope Ljava/lang/String;
                    ALOAD_2     // Lorg/springframework/beans/factory/support/AbstractBeanDefinition; that
                    GETFIELD org.springframework.beans.factory.support.AbstractBeanDefinition.scope Ljava/lang/String;
                    INVOKESTATIC org.springframework.util.ObjectUtils.nullSafeEquals (Ljava/lang/Object;Ljava/lang/Object;)Z
                    IFNE L3
                    ICONST_0
                    IRETURN
                L3: ALOAD_0     // Lorg/springframework/beans/factory/support/AbstractBeanDefinition; this   (line 1007)
                    GETFIELD org.springframework.beans.factory.support.AbstractBeanDefinition.abstractFlag Z
                    ALOAD_2     // Lorg/springframework/beans/factory/support/AbstractBeanDefinition; that
                    GETFIELD org.springframework.beans.factory.support.AbstractBeanDefinition.abstractFlag Z
                    IF_ICMPEQ L4
                    ICONST_0
                    IRETURN
                L4: ALOAD_0     // Lorg/springframework/beans/factory/support/AbstractBeanDefinition; this   (line 1008)
                    GETFIELD org.springframework.beans.factory.support.AbstractBeanDefinition.lazyInit Z
                    ALOAD_2     // Lorg/springframework/beans/factory/support/AbstractBeanDefinition; that
                    GETFIELD org.springframework.beans.factory.support.AbstractBeanDefinition.lazyInit Z
                    IF_ICMPEQ L5
                    ICONST_0
                    IRETURN
                L5: ALOAD_0     // Lorg/springframework/beans/factory/support/AbstractBeanDefinition; this   (line 1010)
                    GETFIELD org.springframework.beans.factory.support.AbstractBeanDefinition.autowireMode I
                    ALOAD_2     // Lorg/springframework/beans/factory/support/AbstractBeanDefinition; that
                    GETFIELD org.springframework.beans.factory.support.AbstractBeanDefinition.autowireMode I
                    IF_ICMPEQ L6
                    ICONST_0
                    IRETURN
                L6: ALOAD_0     // Lorg/springframework/beans/factory/support/AbstractBeanDefinition; this   (line 1011)
                    GETFIELD org.springframework.beans.factory.support.AbstractBeanDefinition.dependencyCheck I
                    ALOAD_2     // Lorg/springframework/beans/factory/support/AbstractBeanDefinition; that
                    GETFIELD org.springframework.beans.factory.support.AbstractBeanDefinition.dependencyCheck I
                    IF_ICMPEQ L7
                    ICONST_0
                    IRETURN
                L7: ALOAD_0     // Lorg/springframework/beans/factory/support/AbstractBeanDefinition; this   (line 1012)
                    GETFIELD org.springframework.beans.factory.support.AbstractBeanDefinition.dependsOn [Ljava/lang/String;
                    ALOAD_2     // Lorg/springframework/beans/factory/support/AbstractBeanDefinition; that
                    GETFIELD org.springframework.beans.factory.support.AbstractBeanDefinition.dependsOn [Ljava/lang/String;
                    INVOKESTATIC java.util.Arrays.equals ([Ljava/lang/Object;[Ljava/lang/Object;)Z
                    IFNE L8
                    ICONST_0
                    IRETURN
                L8: ALOAD_0     // Lorg/springframework/beans/factory/support/AbstractBeanDefinition; this   (line 1013)
                    GETFIELD org.springframework.beans.factory.support.AbstractBeanDefinition.autowireCandidate Z
                    ALOAD_2     // Lorg/springframework/beans/factory/support/AbstractBeanDefinition; that
                    GETFIELD org.springframework.beans.factory.support.AbstractBeanDefinition.autowireCandidate Z
                    IF_ICMPEQ L9
                    ICONST_0
                    IRETURN
                L9: ALOAD_0     // Lorg/springframework/beans/factory/support/AbstractBeanDefinition; this   (line 1014)
                    GETFIELD org.springframework.beans.factory.support.AbstractBeanDefinition.qualifiers Ljava/util/Map;
                    ALOAD_2     // Lorg/springframework/beans/factory/support/AbstractBeanDefinition; that
                    GETFIELD org.springframework.beans.factory.support.AbstractBeanDefinition.qualifiers Ljava/util/Map;
                    INVOKESTATIC org.springframework.util.ObjectUtils.nullSafeEquals (Ljava/lang/Object;Ljava/lang/Object;)Z
                    IFNE L10
                    ICONST_0
                    IRETURN
               L10: ALOAD_0     // Lorg/springframework/beans/factory/support/AbstractBeanDefinition; this   (line 1015)
                    GETFIELD org.springframework.beans.factory.support.AbstractBeanDefinition.primary Z
                    ALOAD_2     // Lorg/springframework/beans/factory/support/AbstractBeanDefinition; that
                    GETFIELD org.springframework.beans.factory.support.AbstractBeanDefinition.primary Z
                    IF_ICMPEQ L11
                    ICONST_0
                    IRETURN
               L11: ALOAD_0     // Lorg/springframework/beans/factory/support/AbstractBeanDefinition; this   (line 1017)
                    GETFIELD org.springframework.beans.factory.support.AbstractBeanDefinition.nonPublicAccessAllowed Z
                    ALOAD_2     // Lorg/springframework/beans/factory/support/AbstractBeanDefinition; that
                    GETFIELD org.springframework.beans.factory.support.AbstractBeanDefinition.nonPublicAccessAllowed Z
                    IF_ICMPEQ L12
                    ICONST_0
                    IRETURN
               L12: ALOAD_0     // Lorg/springframework/beans/factory/support/AbstractBeanDefinition; this   (line 1018)
                    GETFIELD org.springframework.beans.factory.support.AbstractBeanDefinition.lenientConstructorResolution Z
                    ALOAD_2     // Lorg/springframework/beans/factory/support/AbstractBeanDefinition; that
                    GETFIELD org.springframework.beans.factory.support.AbstractBeanDefinition.lenientConstructorResolution Z
                    IF_ICMPEQ L13
                    ICONST_0
                    IRETURN
               L13: ALOAD_0     // Lorg/springframework/beans/factory/support/AbstractBeanDefinition; this   (line 1019)
                    GETFIELD org.springframework.beans.factory.support.AbstractBeanDefinition.constructorArgumentValues Lorg/springframework/beans/factory/config/ConstructorArgumentValues;
                    ALOAD_2     // Lorg/springframework/beans/factory/support/AbstractBeanDefinition; that
                    GETFIELD org.springframework.beans.factory.support.AbstractBeanDefinition.constructorArgumentValues Lorg/springframework/beans/factory/config/ConstructorArgumentValues;
                    INVOKESTATIC org.springframework.util.ObjectUtils.nullSafeEquals (Ljava/lang/Object;Ljava/lang/Object;)Z
                    IFNE L14
                    ICONST_0
                    IRETURN
               L14: ALOAD_0     // Lorg/springframework/beans/factory/support/AbstractBeanDefinition; this   (line 1020)
                    GETFIELD org.springframework.beans.factory.support.AbstractBeanDefinition.propertyValues Lorg/springframework/beans/MutablePropertyValues;
                    ALOAD_2     // Lorg/springframework/beans/factory/support/AbstractBeanDefinition; that
                    GETFIELD org.springframework.beans.factory.support.AbstractBeanDefinition.propertyValues Lorg/springframework/beans/MutablePropertyValues;
                    INVOKESTATIC org.springframework.util.ObjectUtils.nullSafeEquals (Ljava/lang/Object;Ljava/lang/Object;)Z
                    IFNE L15
                    ICONST_0
                    IRETURN
               L15: ALOAD_0     // Lorg/springframework/beans/factory/support/AbstractBeanDefinition; this   (line 1021)
                    GETFIELD org.springframework.beans.factory.support.AbstractBeanDefinition.methodOverrides Lorg/springframework/beans/factory/support/MethodOverrides;
                    ALOAD_2     // Lorg/springframework/beans/factory/support/AbstractBeanDefinition; that
                    GETFIELD org.springframework.beans.factory.support.AbstractBeanDefinition.methodOverrides Lorg/springframework/beans/factory/support/MethodOverrides;
                    INVOKESTATIC org.springframework.util.ObjectUtils.nullSafeEquals (Ljava/lang/Object;Ljava/lang/Object;)Z
                    IFNE L16
                    ICONST_0
                    IRETURN
               L16: ALOAD_0     // Lorg/springframework/beans/factory/support/AbstractBeanDefinition; this   (line 1023)
                    GETFIELD org.springframework.beans.factory.support.AbstractBeanDefinition.factoryBeanName Ljava/lang/String;
                    ALOAD_2     // Lorg/springframework/beans/factory/support/AbstractBeanDefinition; that
                    GETFIELD org.springframework.beans.factory.support.AbstractBeanDefinition.factoryBeanName Ljava/lang/String;
                    INVOKESTATIC org.springframework.util.ObjectUtils.nullSafeEquals (Ljava/lang/Object;Ljava/lang/Object;)Z
                    IFNE L17
                    ICONST_0
                    IRETURN
               L17: ALOAD_0     // Lorg/springframework/beans/factory/support/AbstractBeanDefinition; this   (line 1024)
                    GETFIELD org.springframework.beans.factory.support.AbstractBeanDefinition.factoryMethodName Ljava/lang/String;
                    ALOAD_2     // Lorg/springframework/beans/factory/support/AbstractBeanDefinition; that
                    GETFIELD org.springframework.beans.factory.support.AbstractBeanDefinition.factoryMethodName Ljava/lang/String;
                    INVOKESTATIC org.springframework.util.ObjectUtils.nullSafeEquals (Ljava/lang/Object;Ljava/lang/Object;)Z
                    IFNE L18
                    ICONST_0
                    IRETURN
               L18: ALOAD_0     // Lorg/springframework/beans/factory/support/AbstractBeanDefinition; this   (line 1025)
                    GETFIELD org.springframework.beans.factory.support.AbstractBeanDefinition.initMethodName Ljava/lang/String;
                    ALOAD_2     // Lorg/springframework/beans/factory/support/AbstractBeanDefinition; that
                    GETFIELD org.springframework.beans.factory.support.AbstractBeanDefinition.initMethodName Ljava/lang/String;
                    INVOKESTATIC org.springframework.util.ObjectUtils.nullSafeEquals (Ljava/lang/Object;Ljava/lang/Object;)Z
                    IFNE L19
                    ICONST_0
                    IRETURN
               L19: ALOAD_0     // Lorg/springframework/beans/factory/support/AbstractBeanDefinition; this   (line 1026)
                    GETFIELD org.springframework.beans.factory.support.AbstractBeanDefinition.enforceInitMethod Z
                    ALOAD_2     // Lorg/springframework/beans/factory/support/AbstractBeanDefinition; that
                    GETFIELD org.springframework.beans.factory.support.AbstractBeanDefinition.enforceInitMethod Z
                    IF_ICMPEQ L20
                    ICONST_0
                    IRETURN
               L20: ALOAD_0     // Lorg/springframework/beans/factory/support/AbstractBeanDefinition; this   (line 1027)
                    GETFIELD org.springframework.beans.factory.support.AbstractBeanDefinition.destroyMethodName Ljava/lang/String;
                    ALOAD_2     // Lorg/springframework/beans/factory/support/AbstractBeanDefinition; that
                    GETFIELD org.springframework.beans.factory.support.AbstractBeanDefinition.destroyMethodName Ljava/lang/String;
                    INVOKESTATIC org.springframework.util.ObjectUtils.nullSafeEquals (Ljava/lang/Object;Ljava/lang/Object;)Z
                    IFNE L21
                    ICONST_0
                    IRETURN
               L21: ALOAD_0     // Lorg/springframework/beans/factory/support/AbstractBeanDefinition; this   (line 1028)
                    GETFIELD org.springframework.beans.factory.support.AbstractBeanDefinition.enforceDestroyMethod Z
                    ALOAD_2     // Lorg/springframework/beans/factory/support/AbstractBeanDefinition; that
                    GETFIELD org.springframework.beans.factory.support.AbstractBeanDefinition.enforceDestroyMethod Z
                    IF_ICMPEQ L22
                    ICONST_0
                    IRETURN
               L22: ALOAD_0     // Lorg/springframework/beans/factory/support/AbstractBeanDefinition; this   (line 1030)
                    GETFIELD org.springframework.beans.factory.support.AbstractBeanDefinition.synthetic Z
                    ALOAD_2     // Lorg/springframework/beans/factory/support/AbstractBeanDefinition; that
                    GETFIELD org.springframework.beans.factory.support.AbstractBeanDefinition.synthetic Z
                    IF_ICMPEQ L23
                    ICONST_0
                    IRETURN
               L23: ALOAD_0     // Lorg/springframework/beans/factory/support/AbstractBeanDefinition; this   (line 1031)
                    GETFIELD org.springframework.beans.factory.support.AbstractBeanDefinition.role I
                    ALOAD_2     // Lorg/springframework/beans/factory/support/AbstractBeanDefinition; that
                    GETFIELD org.springframework.beans.factory.support.AbstractBeanDefinition.role I
                    IF_ICMPEQ L24
                    ICONST_0
                    IRETURN
               L24: ALOAD_0     // Lorg/springframework/beans/factory/support/AbstractBeanDefinition; this   (line 1033)
                    ALOAD_1     // Ljava/lang/Object; other
                    INVOKESPECIAL org.springframework.beans.BeanMetadataAttributeAccessor.equals (Ljava/lang/Object;)Z
                    IRETURN
  end public boolean equals(Object)

  public int hashCode():
                    ALOAD_0     // Lorg/springframework/beans/factory/support/AbstractBeanDefinition; this   (line 1038)
                    INVOKEVIRTUAL org.springframework.beans.factory.support.AbstractBeanDefinition.getBeanClassName ()Ljava/lang/String;
                    INVOKESTATIC org.springframework.util.ObjectUtils.nullSafeHashCode (Ljava/lang/Object;)I
                    ISTORE_1
                    BIPUSH 29   (line 1039)
                    ILOAD_1     // I hashCode
                    IMUL
                    ALOAD_0     // Lorg/springframework/beans/factory/support/AbstractBeanDefinition; this
                    GETFIELD org.springframework.beans.factory.support.AbstractBeanDefinition.scope Ljava/lang/String;
                    INVOKESTATIC org.springframework.util.ObjectUtils.nullSafeHashCode (Ljava/lang/Object;)I
                    IADD
                    ISTORE_1     // I hashCode
                    BIPUSH 29   (line 1040)
                    ILOAD_1     // I hashCode
                    IMUL
                    ALOAD_0     // Lorg/springframework/beans/factory/support/AbstractBeanDefinition; this
                    GETFIELD org.springframework.beans.factory.support.AbstractBeanDefinition.constructorArgumentValues Lorg/springframework/beans/factory/config/ConstructorArgumentValues;
                    INVOKESTATIC org.springframework.util.ObjectUtils.nullSafeHashCode (Ljava/lang/Object;)I
                    IADD
                    ISTORE_1     // I hashCode
                    BIPUSH 29   (line 1041)
                    ILOAD_1     // I hashCode
                    IMUL
                    ALOAD_0     // Lorg/springframework/beans/factory/support/AbstractBeanDefinition; this
                    GETFIELD org.springframework.beans.factory.support.AbstractBeanDefinition.propertyValues Lorg/springframework/beans/MutablePropertyValues;
                    INVOKESTATIC org.springframework.util.ObjectUtils.nullSafeHashCode (Ljava/lang/Object;)I
                    IADD
                    ISTORE_1     // I hashCode
                    BIPUSH 29   (line 1042)
                    ILOAD_1     // I hashCode
                    IMUL
                    ALOAD_0     // Lorg/springframework/beans/factory/support/AbstractBeanDefinition; this
                    GETFIELD org.springframework.beans.factory.support.AbstractBeanDefinition.factoryBeanName Ljava/lang/String;
                    INVOKESTATIC org.springframework.util.ObjectUtils.nullSafeHashCode (Ljava/lang/Object;)I
                    IADD
                    ISTORE_1     // I hashCode
                    BIPUSH 29   (line 1043)
                    ILOAD_1     // I hashCode
                    IMUL
                    ALOAD_0     // Lorg/springframework/beans/factory/support/AbstractBeanDefinition; this
                    GETFIELD org.springframework.beans.factory.support.AbstractBeanDefinition.factoryMethodName Ljava/lang/String;
                    INVOKESTATIC org.springframework.util.ObjectUtils.nullSafeHashCode (Ljava/lang/Object;)I
                    IADD
                    ISTORE_1     // I hashCode
                    BIPUSH 29   (line 1044)
                    ILOAD_1     // I hashCode
                    IMUL
                    ALOAD_0     // Lorg/springframework/beans/factory/support/AbstractBeanDefinition; this
                    INVOKESPECIAL org.springframework.beans.BeanMetadataAttributeAccessor.hashCode ()I
                    IADD
                    ISTORE_1     // I hashCode
                    ILOAD_1     // I hashCode   (line 1045)
                    IRETURN
  end public int hashCode()

  public String toString():
                    NEW java.lang.StringBuilder   (line 1050)
                    DUP
                    LDC_W "class ["
                    INVOKESPECIAL java.lang.StringBuilder.<init> (Ljava/lang/String;)V
                    ASTORE_1
                    ALOAD_1     // Ljava/lang/StringBuilder; sb   (line 1051)
                    ALOAD_0     // Lorg/springframework/beans/factory/support/AbstractBeanDefinition; this
                    INVOKEVIRTUAL org.springframework.beans.factory.support.AbstractBeanDefinition.getBeanClassName ()Ljava/lang/String;
                    INVOKEVIRTUAL java.lang.StringBuilder.append (Ljava/lang/String;)Ljava/lang/StringBuilder;
                    LDC_W "]"
                    INVOKEVIRTUAL java.lang.StringBuilder.append (Ljava/lang/String;)Ljava/lang/StringBuilder;
                    POP
                    ALOAD_1     // Ljava/lang/StringBuilder; sb   (line 1052)
                    LDC_W "; scope="
                    INVOKEVIRTUAL java.lang.StringBuilder.append (Ljava/lang/String;)Ljava/lang/StringBuilder;
                    ALOAD_0     // Lorg/springframework/beans/factory/support/AbstractBeanDefinition; this
                    GETFIELD org.springframework.beans.factory.support.AbstractBeanDefinition.scope Ljava/lang/String;
                    INVOKEVIRTUAL java.lang.StringBuilder.append (Ljava/lang/String;)Ljava/lang/StringBuilder;
                    POP
                    ALOAD_1     // Ljava/lang/StringBuilder; sb   (line 1053)
                    LDC_W "; abstract="
                    INVOKEVIRTUAL java.lang.StringBuilder.append (Ljava/lang/String;)Ljava/lang/StringBuilder;
                    ALOAD_0     // Lorg/springframework/beans/factory/support/AbstractBeanDefinition; this
                    GETFIELD org.springframework.beans.factory.support.AbstractBeanDefinition.abstractFlag Z
                    INVOKEVIRTUAL java.lang.StringBuilder.append (Z)Ljava/lang/StringBuilder;
                    POP
                    ALOAD_1     // Ljava/lang/StringBuilder; sb   (line 1054)
                    LDC_W "; lazyInit="
                    INVOKEVIRTUAL java.lang.StringBuilder.append (Ljava/lang/String;)Ljava/lang/StringBuilder;
                    ALOAD_0     // Lorg/springframework/beans/factory/support/AbstractBeanDefinition; this
                    GETFIELD org.springframework.beans.factory.support.AbstractBeanDefinition.lazyInit Z
                    INVOKEVIRTUAL java.lang.StringBuilder.append (Z)Ljava/lang/StringBuilder;
                    POP
                    ALOAD_1     // Ljava/lang/StringBuilder; sb   (line 1055)
                    LDC_W "; autowireMode="
                    INVOKEVIRTUAL java.lang.StringBuilder.append (Ljava/lang/String;)Ljava/lang/StringBuilder;
                    ALOAD_0     // Lorg/springframework/beans/factory/support/AbstractBeanDefinition; this
                    GETFIELD org.springframework.beans.factory.support.AbstractBeanDefinition.autowireMode I
                    INVOKEVIRTUAL java.lang.StringBuilder.append (I)Ljava/lang/StringBuilder;
                    POP
                    ALOAD_1     // Ljava/lang/StringBuilder; sb   (line 1056)
                    LDC_W "; dependencyCheck="
                    INVOKEVIRTUAL java.lang.StringBuilder.append (Ljava/lang/String;)Ljava/lang/StringBuilder;
                    ALOAD_0     // Lorg/springframework/beans/factory/support/AbstractBeanDefinition; this
                    GETFIELD org.springframework.beans.factory.support.AbstractBeanDefinition.dependencyCheck I
                    INVOKEVIRTUAL java.lang.StringBuilder.append (I)Ljava/lang/StringBuilder;
                    POP
                    ALOAD_1     // Ljava/lang/StringBuilder; sb   (line 1057)
                    LDC_W "; autowireCandidate="
                    INVOKEVIRTUAL java.lang.StringBuilder.append (Ljava/lang/String;)Ljava/lang/StringBuilder;
                    ALOAD_0     // Lorg/springframework/beans/factory/support/AbstractBeanDefinition; this
                    GETFIELD org.springframework.beans.factory.support.AbstractBeanDefinition.autowireCandidate Z
                    INVOKEVIRTUAL java.lang.StringBuilder.append (Z)Ljava/lang/StringBuilder;
                    POP
                    ALOAD_1     // Ljava/lang/StringBuilder; sb   (line 1058)
                    LDC_W "; primary="
                    INVOKEVIRTUAL java.lang.StringBuilder.append (Ljava/lang/String;)Ljava/lang/StringBuilder;
                    ALOAD_0     // Lorg/springframework/beans/factory/support/AbstractBeanDefinition; this
                    GETFIELD org.springframework.beans.factory.support.AbstractBeanDefinition.primary Z
                    INVOKEVIRTUAL java.lang.StringBuilder.append (Z)Ljava/lang/StringBuilder;
                    POP
                    ALOAD_1     // Ljava/lang/StringBuilder; sb   (line 1059)
                    LDC_W "; factoryBeanName="
                    INVOKEVIRTUAL java.lang.StringBuilder.append (Ljava/lang/String;)Ljava/lang/StringBuilder;
                    ALOAD_0     // Lorg/springframework/beans/factory/support/AbstractBeanDefinition; this
                    GETFIELD org.springframework.beans.factory.support.AbstractBeanDefinition.factoryBeanName Ljava/lang/String;
                    INVOKEVIRTUAL java.lang.StringBuilder.append (Ljava/lang/String;)Ljava/lang/StringBuilder;
                    POP
                    ALOAD_1     // Ljava/lang/StringBuilder; sb   (line 1060)
                    LDC_W "; factoryMethodName="
                    INVOKEVIRTUAL java.lang.StringBuilder.append (Ljava/lang/String;)Ljava/lang/StringBuilder;
                    ALOAD_0     // Lorg/springframework/beans/factory/support/AbstractBeanDefinition; this
                    GETFIELD org.springframework.beans.factory.support.AbstractBeanDefinition.factoryMethodName Ljava/lang/String;
                    INVOKEVIRTUAL java.lang.StringBuilder.append (Ljava/lang/String;)Ljava/lang/StringBuilder;
                    POP
                    ALOAD_1     // Ljava/lang/StringBuilder; sb   (line 1061)
                    LDC_W "; initMethodName="
                    INVOKEVIRTUAL java.lang.StringBuilder.append (Ljava/lang/String;)Ljava/lang/StringBuilder;
                    ALOAD_0     // Lorg/springframework/beans/factory/support/AbstractBeanDefinition; this
                    GETFIELD org.springframework.beans.factory.support.AbstractBeanDefinition.initMethodName Ljava/lang/String;
                    INVOKEVIRTUAL java.lang.StringBuilder.append (Ljava/lang/String;)Ljava/lang/StringBuilder;
                    POP
                    ALOAD_1     // Ljava/lang/StringBuilder; sb   (line 1062)
                    LDC_W "; destroyMethodName="
                    INVOKEVIRTUAL java.lang.StringBuilder.append (Ljava/lang/String;)Ljava/lang/StringBuilder;
                    ALOAD_0     // Lorg/springframework/beans/factory/support/AbstractBeanDefinition; this
                    GETFIELD org.springframework.beans.factory.support.AbstractBeanDefinition.destroyMethodName Ljava/lang/String;
                    INVOKEVIRTUAL java.lang.StringBuilder.append (Ljava/lang/String;)Ljava/lang/StringBuilder;
                    POP
                    ALOAD_0     // Lorg/springframework/beans/factory/support/AbstractBeanDefinition; this   (line 1063)
                    GETFIELD org.springframework.beans.factory.support.AbstractBeanDefinition.resource Lorg/springframework/core/io/Resource;
                    IFNULL L0
                    ALOAD_1     // Ljava/lang/StringBuilder; sb   (line 1064)
                    LDC_W "; defined in "
                    INVOKEVIRTUAL java.lang.StringBuilder.append (Ljava/lang/String;)Ljava/lang/StringBuilder;
                    ALOAD_0     // Lorg/springframework/beans/factory/support/AbstractBeanDefinition; this
                    GETFIELD org.springframework.beans.factory.support.AbstractBeanDefinition.resource Lorg/springframework/core/io/Resource;
                    INVOKEINTERFACE org.springframework.core.io.Resource.getDescription ()Ljava/lang/String;
                    INVOKEVIRTUAL java.lang.StringBuilder.append (Ljava/lang/String;)Ljava/lang/StringBuilder;
                    POP
                L0: ALOAD_1     // Ljava/lang/StringBuilder; sb   (line 1066)
                    INVOKEVIRTUAL java.lang.StringBuilder.toString ()Ljava/lang/String;
                    ARETURN
  end public String toString()

end public abstract class org.springframework.beans.factory.support.AbstractBeanDefinition
 -- (NullPointerException) null
null
java.lang.NullPointerException
	at org.aspectj.weaver.UnresolvedType.forSignature(UnresolvedType.java:361)
	at org.aspectj.weaver.bcel.BcelObjectType.getDeclaredInterfaces(BcelObjectType.java:275)
	at org.aspectj.weaver.ReferenceType.getDeclaredInterfaces(ReferenceType.java:624)
	at org.aspectj.weaver.ResolvedType.getDirectSupertypes(ResolvedType.java:76)
	at org.aspectj.weaver.patterns.TypePattern.matchesSubtypes(TypePattern.java:178)
	at org.aspectj.weaver.patterns.ExactTypePattern.matchesSubtypes(ExactTypePattern.java:74)
	at org.aspectj.weaver.patterns.TypePattern.matchesStatically(TypePattern.java:130)
	at org.aspectj.weaver.patterns.OrTypePattern.matchesStatically(OrTypePattern.java:76)
	at org.aspectj.weaver.patterns.SignaturePattern.matchesExactlyMethod(SignaturePattern.java:505)
	at org.aspectj.weaver.patterns.SignaturePattern.matchesExactly(SignaturePattern.java:360)
	at org.aspectj.weaver.patterns.SignaturePattern.matches(SignaturePattern.java:320)
	at org.aspectj.weaver.patterns.KindedPointcut.matchInternal(KindedPointcut.java:202)
	at org.aspectj.weaver.patterns.Pointcut.match(Pointcut.java:137)
	at org.aspectj.weaver.patterns.AndPointcut.matchInternal(AndPointcut.java:51)
	at org.aspectj.weaver.patterns.Pointcut.match(Pointcut.java:137)
	at org.aspectj.weaver.patterns.OrPointcut.matchInternal(OrPointcut.java:54)
	at org.aspectj.weaver.patterns.Pointcut.match(Pointcut.java:137)
	at org.aspectj.weaver.ShadowMunger.match(ShadowMunger.java:113)
	at org.aspectj.weaver.Advice.match(Advice.java:109)
	at org.aspectj.weaver.bcel.BcelAdvice.match(BcelAdvice.java:149)
	at org.aspectj.weaver.bcel.BcelClassWeaver.match(BcelClassWeaver.java:3116)
	at org.aspectj.weaver.bcel.BcelClassWeaver.match(BcelClassWeaver.java:2550)
	at org.aspectj.weaver.bcel.BcelClassWeaver.weave(BcelClassWeaver.java:474)
	at org.aspectj.weaver.bcel.BcelClassWeaver.weave(BcelClassWeaver.java:100)
	at org.aspectj.weaver.bcel.BcelWeaver.weave(BcelWeaver.java:1687)
	at org.aspectj.weaver.bcel.BcelWeaver.weaveWithoutDump(BcelWeaver.java:1631)
	at org.aspectj.weaver.bcel.BcelWeaver.weaveAndNotify(BcelWeaver.java:1394)
	at org.aspectj.weaver.bcel.BcelWeaver.weave(BcelWeaver.java:1180)
	at org.aspectj.weaver.tools.WeavingAdaptor.getWovenBytes(WeavingAdaptor.java:467)
	at org.aspectj.weaver.tools.WeavingAdaptor.weaveClass(WeavingAdaptor.java:318)
	at org.aspectj.weaver.loadtime.Aj.preProcess(Aj.java:96)
	at org.aspectj.weaver.loadtime.ClassPreProcessorAgentAdapter.transform(ClassPreProcessorAgentAdapter.java:54)
	at sun.instrument.TransformerManager.transform(TransformerManager.java:188)
	at sun.instrument.InstrumentationImpl.transform(InstrumentationImpl.java:428)
	at java.lang.ClassLoader.defineClass1(Native Method)
	at java.lang.ClassLoader.defineClass(ClassLoader.java:760)
	at java.security.SecureClassLoader.defineClass(SecureClassLoader.java:142)
	at java.net.URLClassLoader.defineClass(URLClassLoader.java:467)
	at java.net.URLClassLoader.access$100(URLClassLoader.java:73)
	at java.net.URLClassLoader$1.run(URLClassLoader.java:368)
	at java.net.URLClassLoader$1.run(URLClassLoader.java:362)
	at java.security.AccessController.doPrivileged(Native Method)
	at java.net.URLClassLoader.findClass(URLClassLoader.java:361)
	at java.lang.ClassLoader.loadClass(ClassLoader.java:424)
	at sun.misc.Launcher$AppClassLoader.loadClass(Launcher.java:331)
	at java.lang.ClassLoader.loadClass(ClassLoader.java:357)
	at org.springframework.context.support.AbstractRefreshableApplicationContext.createBeanFactory(AbstractRefreshableApplicationContext.java:194)
	at org.springframework.context.support.AbstractRefreshableApplicationContext.refreshBeanFactory(AbstractRefreshableApplicationContext.java:127)
	at org.springframework.context.support.AbstractApplicationContext.obtainFreshBeanFactory(AbstractApplicationContext.java:467)
	at org.springframework.context.support.AbstractApplicationContext.refresh(AbstractApplicationContext.java:397)
	at org.springframework.context.support.ClassPathXmlApplicationContext.<init>(ClassPathXmlApplicationContext.java:139)
	at org.springframework.context.support.ClassPathXmlApplicationContext.<init>(ClassPathXmlApplicationContext.java:83)
	at foo.ConfigureApp.main(ConfigureApp.java:9)

error can't determine annotations of missing type org.springframework.cache.annotation.CachePut
when weaving type org.springframework.beans.BeanMetadataAttributeAccessor
when weaving classes 
when weaving 
 [Xlint:cantFindType]
error can't determine annotations of missing type org.springframework.cache.annotation.Cacheable
when weaving type org.springframework.beans.BeanMetadataAttributeAccessor
when weaving classes 
when weaving 
 [Xlint:cantFindType]
error can't determine annotations of missing type org.springframework.cache.annotation.CacheEvict
when weaving type org.springframework.beans.BeanMetadataAttributeAccessor
when weaving classes 
when weaving 
 [Xlint:cantFindType]
error can't determine annotations of missing type org.springframework.cache.annotation.Caching
when weaving type org.springframework.beans.BeanMetadataAttributeAccessor
when weaving classes 
when weaving 
 [Xlint:cantFindType]
error can't determine annotations of missing type org.springframework.transaction.annotation.Transactional
when weaving type org.springframework.beans.BeanMetadataAttributeAccessor
when weaving classes 
when weaving 
 [Xlint:cantFindType]
