---- AspectJ Properties ---
AspectJ Compiler 1.6.11 built on Tuesday Mar 15, 2011 at 15:31:04 GMT
---- Dump Properties ---
Dump file: ajcore.20150913.181454.916.txt
Dump reason: abort
Dump on exception: true
Dump at exit condition: abort
---- System Properties ---
java.runtime.name=Java(TM) SE Runtime Environment
sun.boot.library.path=C:\Program Files\Java\jdk1.8.0_45\jre\bin
java.vm.version=25.45-b02
java.vm.vendor=Oracle Corporation
java.vendor.url=http://java.oracle.com/
path.separator=;
java.vm.name=Java HotSpot(TM) 64-Bit Server VM
file.encoding.pkg=sun.io
user.country=US
user.script=
sun.java.launcher=SUN_STANDARD
sun.os.patch.level=
java.vm.specification.name=Java Virtual Machine Specification
user.dir=E:\Eclipse Latest\SpringChap3.3
java.runtime.version=1.8.0_45-b15
java.awt.graphicsenv=sun.awt.Win32GraphicsEnvironment
java.endorsed.dirs=C:\Program Files\Java\jdk1.8.0_45\jre\lib\endorsed
os.arch=amd64
java.io.tmpdir=C:\Users\SANJUS~1\AppData\Local\Temp\
line.separator=

java.vm.specification.vendor=Oracle Corporation
user.variant=
os.name=Windows 7
sun.jnu.encoding=Cp1252
java.library.path=C:\Program Files\Java\jdk1.8.0_45\bin;C:\Windows\Sun\Java\bin;C:\Windows\system32;C:\Windows;C:/Program Files/Java/jdk1.8.0_45/bin/../jre/bin/server;C:/Program Files/Java/jdk1.8.0_45/bin/../jre/bin;C:/Program Files/Java/jdk1.8.0_45/bin/../jre/lib/amd64;C:\oraclexe\app\oracle\product\10.2.0\server\bin;C:\Program Files\Java\jdk1.8.0_45\bin;C:\Program Files (x86)\Java\jre1.8.0_45\bin;C:\ProgramData\Oracle\Java\javapath;C:\Windows\system32;C:\Windows;C:\Windows\System32\Wbem;C:\Windows\System32\WindowsPowerShell\v1.0\;C:\Python27;;E:\Eclipse Latest\eclipse-jee-luna-SR2-win32-x86_64\eclipse;;.
java.specification.name=Java Platform API Specification
java.class.version=52.0
sun.management.compiler=HotSpot 64-Bit Tiered Compilers
os.version=6.1
user.home=C:\Users\sanju singh
user.timezone=Asia/Calcutta
java.awt.printerjob=sun.awt.windows.WPrinterJob
file.encoding=Cp1252
java.specification.version=1.8
java.class.path=E:\Eclipse Latest\SpringChap3.3\bin;E:\Eclipse Latest\SpringJar\extra Jar\aopalliance-1.0.jar;E:\Eclipse Latest\SpringJar\extra Jar\asm-3.3.1.jar;E:\Eclipse Latest\SpringJar\extra Jar\aspectjrt-1.6.11.jar;E:\Eclipse Latest\SpringJar\extra Jar\aspectjweaver-1.6.11.jar;E:\Eclipse Latest\SpringJar\extra Jar\cglib-2.2.2.jar;E:\Eclipse Latest\SpringJar\extra Jar\commons-logging-1.1.1.jar;E:\Eclipse Latest\SpringJar\extra Jar\junit-4.8.2.jar;E:\Eclipse Latest\SpringJar\extra Jar\spring-aop-3.0.5.RELEASE.jar;E:\Eclipse Latest\SpringJar\extra Jar\spring-asm-3.0.5.RELEASE.jar;E:\Eclipse Latest\SpringJar\extra Jar\spring-beans-3.0.5.RELEASE.jar;E:\Eclipse Latest\SpringJar\extra Jar\spring-context-3.0.5.RELEASE.jar;E:\Eclipse Latest\SpringJar\extra Jar\spring-core-3.0.5.RELEASE.jar;E:\Eclipse Latest\SpringJar\extra Jar\spring-expression-3.0.5.RELEASE.jar;E:\Eclipse Latest\SpringJar\spring-aspects-4.1.6.RELEASE.jar;E:\TestJar\aspectjweaver-1.6.11.jar
user.name=sanju singh
java.vm.specification.version=1.8
sun.java.command=foo.ConfigureApp
java.home=C:\Program Files\Java\jdk1.8.0_45\jre
sun.arch.data.model=64
user.language=en
java.specification.vendor=Oracle Corporation
awt.toolkit=sun.awt.windows.WToolkit
java.vm.info=mixed mode
java.version=1.8.0_45
java.ext.dirs=C:\Program Files\Java\jdk1.8.0_45\jre\lib\ext;C:\Windows\Sun\Java\lib\ext
sun.boot.class.path=C:\Program Files\Java\jdk1.8.0_45\jre\lib\resources.jar;C:\Program Files\Java\jdk1.8.0_45\jre\lib\rt.jar;C:\Program Files\Java\jdk1.8.0_45\jre\lib\sunrsasign.jar;C:\Program Files\Java\jdk1.8.0_45\jre\lib\jsse.jar;C:\Program Files\Java\jdk1.8.0_45\jre\lib\jce.jar;C:\Program Files\Java\jdk1.8.0_45\jre\lib\charsets.jar;C:\Program Files\Java\jdk1.8.0_45\jre\lib\jfr.jar;C:\Program Files\Java\jdk1.8.0_45\jre\classes
java.vendor=Oracle Corporation
file.separator=\
java.vendor.url.bug=http://bugreport.sun.com/bugreport/
sun.io.unicode.encoding=UnicodeLittle
sun.cpu.endian=little
sun.desktop=windows
sun.cpu.isalist=amd64
---- Command Line ---
Empty
---- Full Classpath ---
Empty
---- Compiler Messages ---
info AspectJ Weaver Version 1.6.11 built on Tuesday Mar 15, 2011 at 15:31:04 GMT
info register classloader sun.misc.Launcher$AppClassLoader@14dad5dc
info using configuration file:/E:/Eclipse%20Latest/SpringJar/spring-aspects-4.1.6.RELEASE.jar!/META-INF/aop.xml
error can't determine annotations of missing type org.springframework.cache.annotation.CachePut
when weaving type org.springframework.beans.factory.BeanCreationException
when weaving classes 
when weaving 
 [Xlint:cantFindType]
error can't determine annotations of missing type org.springframework.cache.annotation.Cacheable
when weaving type org.springframework.beans.factory.BeanCreationException
when weaving classes 
when weaving 
 [Xlint:cantFindType]
error can't determine annotations of missing type org.springframework.cache.annotation.CacheEvict
when weaving type org.springframework.beans.factory.BeanCreationException
when weaving classes 
when weaving 
 [Xlint:cantFindType]
error can't determine annotations of missing type org.springframework.cache.annotation.Caching
when weaving type org.springframework.beans.factory.BeanCreationException
when weaving classes 
when weaving 
 [Xlint:cantFindType]
error can't determine annotations of missing type org.springframework.transaction.annotation.Transactional
when weaving type org.springframework.beans.factory.BeanCreationException
when weaving classes 
when weaving 
 [Xlint:cantFindType]
abort trouble in: 
public class org.springframework.beans.factory.BeanCreationException extends org.springframework.beans.FatalBeanException:
  private String beanName
  private String resourceDescription
  private java.util.List relatedCauses [Signature(Ljava/util/List<Ljava/lang/Throwable;>;)]
  public void <init>(String):
                    ALOAD_0     // Lorg/springframework/beans/factory/BeanCreationException; this   (line 47)
                    ALOAD_1     // Ljava/lang/String; msg
                    INVOKESPECIAL org.springframework.beans.FatalBeanException.<init> (Ljava/lang/String;)V
    constructor-execution(void org.springframework.beans.factory.BeanCreationException.<init>(java.lang.String))
    |               RETURN   (line 48)
    constructor-execution(void org.springframework.beans.factory.BeanCreationException.<init>(java.lang.String))
  end public void <init>(String)

  public void <init>(String, Throwable):
                    ALOAD_0     // Lorg/springframework/beans/factory/BeanCreationException; this   (line 56)
                    ALOAD_1     // Ljava/lang/String; msg
                    ALOAD_2     // Ljava/lang/Throwable; cause
                    INVOKESPECIAL org.springframework.beans.FatalBeanException.<init> (Ljava/lang/String;Ljava/lang/Throwable;)V
    constructor-execution(void org.springframework.beans.factory.BeanCreationException.<init>(java.lang.String, java.lang.Throwable))
    |               RETURN   (line 57)
    constructor-execution(void org.springframework.beans.factory.BeanCreationException.<init>(java.lang.String, java.lang.Throwable))
  end public void <init>(String, Throwable)

  public void <init>(String, String):
                    ALOAD_0     // Lorg/springframework/beans/factory/BeanCreationException; this   (line 65)
                    NEW java.lang.StringBuilder
                    DUP
                    LDC "Error creating bean with name '"
                    INVOKESPECIAL java.lang.StringBuilder.<init> (Ljava/lang/String;)V
                    ALOAD_1     // Ljava/lang/String; beanName
                    INVOKEVIRTUAL java.lang.StringBuilder.append (Ljava/lang/String;)Ljava/lang/StringBuilder;
                    LDC "': "
                    INVOKEVIRTUAL java.lang.StringBuilder.append (Ljava/lang/String;)Ljava/lang/StringBuilder;
                    ALOAD_2     // Ljava/lang/String; msg
                    INVOKEVIRTUAL java.lang.StringBuilder.append (Ljava/lang/String;)Ljava/lang/StringBuilder;
                    INVOKEVIRTUAL java.lang.StringBuilder.toString ()Ljava/lang/String;
                    INVOKESPECIAL org.springframework.beans.FatalBeanException.<init> (Ljava/lang/String;)V
    constructor-execution(void org.springframework.beans.factory.BeanCreationException.<init>(java.lang.String, java.lang.String))
    |               ALOAD_0     // Lorg/springframework/beans/factory/BeanCreationException; this   (line 66)
    |               ALOAD_1     // Ljava/lang/String; beanName
    |               PUTFIELD org.springframework.beans.factory.BeanCreationException.beanName Ljava/lang/String;
    |               RETURN   (line 67)
    constructor-execution(void org.springframework.beans.factory.BeanCreationException.<init>(java.lang.String, java.lang.String))
  end public void <init>(String, String)

  public void <init>(String, String, Throwable):
                    ALOAD_0     // Lorg/springframework/beans/factory/BeanCreationException; this   (line 76)
                    ALOAD_1     // Ljava/lang/String; beanName
                    ALOAD_2     // Ljava/lang/String; msg
                    INVOKESPECIAL org.springframework.beans.factory.BeanCreationException.<init> (Ljava/lang/String;Ljava/lang/String;)V
    constructor-execution(void org.springframework.beans.factory.BeanCreationException.<init>(java.lang.String, java.lang.String, java.lang.Throwable))
    |               ALOAD_0     // Lorg/springframework/beans/factory/BeanCreationException; this   (line 77)
    |               ALOAD_3     // Ljava/lang/Throwable; cause
    |               INVOKEVIRTUAL org.springframework.beans.factory.BeanCreationException.initCause (Ljava/lang/Throwable;)Ljava/lang/Throwable;
    |               POP
    |               RETURN   (line 78)
    constructor-execution(void org.springframework.beans.factory.BeanCreationException.<init>(java.lang.String, java.lang.String, java.lang.Throwable))
  end public void <init>(String, String, Throwable)

  public void <init>(String, String, String):
                    ALOAD_0     // Lorg/springframework/beans/factory/BeanCreationException; this   (line 88)
                    NEW java.lang.StringBuilder
                    DUP
                    LDC "Error creating bean with name '"
                    INVOKESPECIAL java.lang.StringBuilder.<init> (Ljava/lang/String;)V
                    ALOAD_2     // Ljava/lang/String; beanName
                    INVOKEVIRTUAL java.lang.StringBuilder.append (Ljava/lang/String;)Ljava/lang/StringBuilder;
                    LDC "'"
                    INVOKEVIRTUAL java.lang.StringBuilder.append (Ljava/lang/String;)Ljava/lang/StringBuilder;
                    ALOAD_1     // Ljava/lang/String; resourceDescription   (line 89)
                    IFNULL L0
                    NEW java.lang.StringBuilder
                    DUP
                    LDC " defined in "
                    INVOKESPECIAL java.lang.StringBuilder.<init> (Ljava/lang/String;)V
                    ALOAD_1     // Ljava/lang/String; resourceDescription
                    INVOKEVIRTUAL java.lang.StringBuilder.append (Ljava/lang/String;)Ljava/lang/StringBuilder;
                    INVOKEVIRTUAL java.lang.StringBuilder.toString ()Ljava/lang/String;
                    GOTO L1
                L0: LDC ""
                L1: INVOKEVIRTUAL java.lang.StringBuilder.append (Ljava/lang/String;)Ljava/lang/StringBuilder;
                    LDC ": "
                    INVOKEVIRTUAL java.lang.StringBuilder.append (Ljava/lang/String;)Ljava/lang/StringBuilder;
                    ALOAD_3     // Ljava/lang/String; msg
                    INVOKEVIRTUAL java.lang.StringBuilder.append (Ljava/lang/String;)Ljava/lang/StringBuilder;
                    INVOKEVIRTUAL java.lang.StringBuilder.toString ()Ljava/lang/String;
                    INVOKESPECIAL org.springframework.beans.FatalBeanException.<init> (Ljava/lang/String;)V
    constructor-execution(void org.springframework.beans.factory.BeanCreationException.<init>(java.lang.String, java.lang.String, java.lang.String))
    |               ALOAD_0     // Lorg/springframework/beans/factory/BeanCreationException; this   (line 90)
    |               ALOAD_1     // Ljava/lang/String; resourceDescription
    |               PUTFIELD org.springframework.beans.factory.BeanCreationException.resourceDescription Ljava/lang/String;
    |               ALOAD_0     // Lorg/springframework/beans/factory/BeanCreationException; this   (line 91)
    |               ALOAD_2     // Ljava/lang/String; beanName
    |               PUTFIELD org.springframework.beans.factory.BeanCreationException.beanName Ljava/lang/String;
    |               RETURN   (line 92)
    constructor-execution(void org.springframework.beans.factory.BeanCreationException.<init>(java.lang.String, java.lang.String, java.lang.String))
  end public void <init>(String, String, String)

  public void <init>(String, String, String, Throwable):
                    ALOAD_0     // Lorg/springframework/beans/factory/BeanCreationException; this   (line 103)
                    ALOAD_1     // Ljava/lang/String; resourceDescription
                    ALOAD_2     // Ljava/lang/String; beanName
                    ALOAD_3     // Ljava/lang/String; msg
                    INVOKESPECIAL org.springframework.beans.factory.BeanCreationException.<init> (Ljava/lang/String;Ljava/lang/String;Ljava/lang/String;)V
    constructor-execution(void org.springframework.beans.factory.BeanCreationException.<init>(java.lang.String, java.lang.String, java.lang.String, java.lang.Throwable))
    |               ALOAD_0     // Lorg/springframework/beans/factory/BeanCreationException; this   (line 104)
    |               ALOAD 4     // Ljava/lang/Throwable; cause
    |               INVOKEVIRTUAL org.springframework.beans.factory.BeanCreationException.initCause (Ljava/lang/Throwable;)Ljava/lang/Throwable;
    |               POP
    |               RETURN   (line 105)
    constructor-execution(void org.springframework.beans.factory.BeanCreationException.<init>(java.lang.String, java.lang.String, java.lang.String, java.lang.Throwable))
  end public void <init>(String, String, String, Throwable)

  public String getBeanName():
                    ALOAD_0     // Lorg/springframework/beans/factory/BeanCreationException; this   (line 112)
                    GETFIELD org.springframework.beans.factory.BeanCreationException.beanName Ljava/lang/String;
                    ARETURN
  end public String getBeanName()

  public String getResourceDescription():
                    ALOAD_0     // Lorg/springframework/beans/factory/BeanCreationException; this   (line 120)
                    GETFIELD org.springframework.beans.factory.BeanCreationException.resourceDescription Ljava/lang/String;
                    ARETURN
  end public String getResourceDescription()

  public void addRelatedCause(Throwable):
                    ALOAD_0     // Lorg/springframework/beans/factory/BeanCreationException; this   (line 130)
                    GETFIELD org.springframework.beans.factory.BeanCreationException.relatedCauses Ljava/util/List;
                    IFNONNULL L0
                    ALOAD_0     // Lorg/springframework/beans/factory/BeanCreationException; this   (line 131)
                    NEW java.util.LinkedList
                    DUP
                    INVOKESPECIAL java.util.LinkedList.<init> ()V
                    PUTFIELD org.springframework.beans.factory.BeanCreationException.relatedCauses Ljava/util/List;
                L0: ALOAD_0     // Lorg/springframework/beans/factory/BeanCreationException; this   (line 133)
                    GETFIELD org.springframework.beans.factory.BeanCreationException.relatedCauses Ljava/util/List;
                    ALOAD_1     // Ljava/lang/Throwable; ex
                    INVOKEINTERFACE java.util.List.add (Ljava/lang/Object;)Z
                    POP
                    RETURN   (line 134)
  end public void addRelatedCause(Throwable)

  public Throwable[] getRelatedCauses():
                    ALOAD_0     // Lorg/springframework/beans/factory/BeanCreationException; this   (line 141)
                    GETFIELD org.springframework.beans.factory.BeanCreationException.relatedCauses Ljava/util/List;
                    IFNONNULL L0
                    ACONST_NULL   (line 142)
                    ARETURN
                L0: ALOAD_0     // Lorg/springframework/beans/factory/BeanCreationException; this   (line 144)
                    GETFIELD org.springframework.beans.factory.BeanCreationException.relatedCauses Ljava/util/List;
                    ALOAD_0     // Lorg/springframework/beans/factory/BeanCreationException; this
                    GETFIELD org.springframework.beans.factory.BeanCreationException.relatedCauses Ljava/util/List;
                    INVOKEINTERFACE java.util.List.size ()I
                    ANEWARRAY java.lang.Throwable
                    INVOKEINTERFACE java.util.List.toArray ([Ljava/lang/Object;)[Ljava/lang/Object;
                    CHECKCAST [Ljava.lang.Throwable;
                    ARETURN
  end public Throwable[] getRelatedCauses()

  public String toString():
                    NEW java.lang.StringBuilder   (line 150)
                    DUP
                    ALOAD_0     // Lorg/springframework/beans/factory/BeanCreationException; this
                    INVOKESPECIAL org.springframework.beans.FatalBeanException.toString ()Ljava/lang/String;
                    INVOKESPECIAL java.lang.StringBuilder.<init> (Ljava/lang/String;)V
                    ASTORE_1
                    ALOAD_0     // Lorg/springframework/beans/factory/BeanCreationException; this   (line 151)
                    GETFIELD org.springframework.beans.factory.BeanCreationException.relatedCauses Ljava/util/List;
                    IFNULL L2
                    ALOAD_0     // Lorg/springframework/beans/factory/BeanCreationException; this   (line 152)
                    GETFIELD org.springframework.beans.factory.BeanCreationException.relatedCauses Ljava/util/List;
                    INVOKEINTERFACE java.util.List.iterator ()Ljava/util/Iterator;
                    ASTORE_3
                    GOTO L1
                L0: ALOAD_3
                    INVOKEINTERFACE java.util.Iterator.next ()Ljava/lang/Object;
                    CHECKCAST java.lang.Throwable
                    ASTORE_2
                    ALOAD_1     // Ljava/lang/StringBuilder; sb   (line 153)
                    LDC "\nRelated cause: "
                    INVOKEVIRTUAL java.lang.StringBuilder.append (Ljava/lang/String;)Ljava/lang/StringBuilder;
                    POP
                    ALOAD_1     // Ljava/lang/StringBuilder; sb   (line 154)
                    ALOAD_2     // Ljava/lang/Throwable; relatedCause
                    INVOKEVIRTUAL java.lang.StringBuilder.append (Ljava/lang/Object;)Ljava/lang/StringBuilder;
                    POP
                L1: ALOAD_3   (line 152)
                    INVOKEINTERFACE java.util.Iterator.hasNext ()Z
                    IFNE L0
                L2: ALOAD_1     // Ljava/lang/StringBuilder; sb   (line 157)
                    INVOKEVIRTUAL java.lang.StringBuilder.toString ()Ljava/lang/String;
                    ARETURN
  end public String toString()

  public void printStackTrace(java.io.PrintStream):
                    ALOAD_1     // Ljava/io/PrintStream; ps   (line 162)
                    DUP
                    ASTORE_2
                    MONITORENTER
    finally -> E1
    |               ALOAD_0     // Lorg/springframework/beans/factory/BeanCreationException; this   (line 163)
    |               ALOAD_1     // Ljava/io/PrintStream; ps
    |               INVOKESPECIAL org.springframework.beans.FatalBeanException.printStackTrace (Ljava/io/PrintStream;)V
    |               ALOAD_0     // Lorg/springframework/beans/factory/BeanCreationException; this   (line 164)
    |               GETFIELD org.springframework.beans.factory.BeanCreationException.relatedCauses Ljava/util/List;
    |               IFNULL L2
    |               ALOAD_0     // Lorg/springframework/beans/factory/BeanCreationException; this   (line 165)
    |               GETFIELD org.springframework.beans.factory.BeanCreationException.relatedCauses Ljava/util/List;
    |               INVOKEINTERFACE java.util.List.iterator ()Ljava/util/Iterator;
    |               ASTORE 4
    |               GOTO L1
    |           L0: ALOAD 4
    |               INVOKEINTERFACE java.util.Iterator.next ()Ljava/lang/Object;
    |               CHECKCAST java.lang.Throwable
    |               ASTORE_3
    |               ALOAD_1     // Ljava/io/PrintStream; ps   (line 166)
    |               LDC "Related cause:"
    |               INVOKEVIRTUAL java.io.PrintStream.println (Ljava/lang/String;)V
    |               ALOAD_3     // Ljava/lang/Throwable; relatedCause   (line 167)
    |               ALOAD_1     // Ljava/io/PrintStream; ps
    |               INVOKEVIRTUAL java.lang.Throwable.printStackTrace (Ljava/io/PrintStream;)V
    |           L1: ALOAD 4   (line 165)
    |               INVOKEINTERFACE java.util.Iterator.hasNext ()Z
    |               IFNE L0
    |           L2: ALOAD_2   (line 162)
    |               MONITOREXIT
    finally -> E1
                    GOTO L3
    finally -> E1
    |           E1: ALOAD_2
    |               MONITOREXIT
    finally -> E1
                    ATHROW
                L3: RETURN   (line 171)
  end public void printStackTrace(java.io.PrintStream)

  public void printStackTrace(java.io.PrintWriter):
                    ALOAD_1     // Ljava/io/PrintWriter; pw   (line 175)
                    DUP
                    ASTORE_2
                    MONITORENTER
    finally -> E1
    |               ALOAD_0     // Lorg/springframework/beans/factory/BeanCreationException; this   (line 176)
    |               ALOAD_1     // Ljava/io/PrintWriter; pw
    |               INVOKESPECIAL org.springframework.beans.FatalBeanException.printStackTrace (Ljava/io/PrintWriter;)V
    |               ALOAD_0     // Lorg/springframework/beans/factory/BeanCreationException; this   (line 177)
    |               GETFIELD org.springframework.beans.factory.BeanCreationException.relatedCauses Ljava/util/List;
    |               IFNULL L2
    |               ALOAD_0     // Lorg/springframework/beans/factory/BeanCreationException; this   (line 178)
    |               GETFIELD org.springframework.beans.factory.BeanCreationException.relatedCauses Ljava/util/List;
    |               INVOKEINTERFACE java.util.List.iterator ()Ljava/util/Iterator;
    |               ASTORE 4
    |               GOTO L1
    |           L0: ALOAD 4
    |               INVOKEINTERFACE java.util.Iterator.next ()Ljava/lang/Object;
    |               CHECKCAST java.lang.Throwable
    |               ASTORE_3
    |               ALOAD_1     // Ljava/io/PrintWriter; pw   (line 179)
    |               LDC "Related cause:"
    |               INVOKEVIRTUAL java.io.PrintWriter.println (Ljava/lang/String;)V
    |               ALOAD_3     // Ljava/lang/Throwable; relatedCause   (line 180)
    |               ALOAD_1     // Ljava/io/PrintWriter; pw
    |               INVOKEVIRTUAL java.lang.Throwable.printStackTrace (Ljava/io/PrintWriter;)V
    |           L1: ALOAD 4   (line 178)
    |               INVOKEINTERFACE java.util.Iterator.hasNext ()Z
    |               IFNE L0
    |           L2: ALOAD_2   (line 175)
    |               MONITOREXIT
    finally -> E1
                    GOTO L3
    finally -> E1
    |           E1: ALOAD_2
    |               MONITOREXIT
    finally -> E1
                    ATHROW
                L3: RETURN   (line 184)
  end public void printStackTrace(java.io.PrintWriter)

  public boolean contains(Class):
                    ALOAD_0     // Lorg/springframework/beans/factory/BeanCreationException; this   (line 188)
                    ALOAD_1     // Ljava/lang/Class; exClass
                    INVOKESPECIAL org.springframework.beans.FatalBeanException.contains (Ljava/lang/Class;)Z
                    IFEQ L0
                    ICONST_1   (line 189)
                    IRETURN
                L0: ALOAD_0     // Lorg/springframework/beans/factory/BeanCreationException; this   (line 191)
                    GETFIELD org.springframework.beans.factory.BeanCreationException.relatedCauses Ljava/util/List;
                    IFNULL L3
                    ALOAD_0     // Lorg/springframework/beans/factory/BeanCreationException; this   (line 192)
                    GETFIELD org.springframework.beans.factory.BeanCreationException.relatedCauses Ljava/util/List;
                    INVOKEINTERFACE java.util.List.iterator ()Ljava/util/Iterator;
                    ASTORE_3
                    GOTO L2
                L1: ALOAD_3
                    INVOKEINTERFACE java.util.Iterator.next ()Ljava/lang/Object;
                    CHECKCAST java.lang.Throwable
                    ASTORE_2
                    ALOAD_2     // Ljava/lang/Throwable; relatedCause   (line 193)
                    INSTANCEOF org.springframework.core.NestedRuntimeException
                    IFEQ L2
                    ALOAD_2     // Ljava/lang/Throwable; relatedCause   (line 194)
                    CHECKCAST org.springframework.core.NestedRuntimeException
                    ALOAD_1     // Ljava/lang/Class; exClass
                    INVOKEVIRTUAL org.springframework.core.NestedRuntimeException.contains (Ljava/lang/Class;)Z
                    IFEQ L2
                    ICONST_1   (line 195)
                    IRETURN
                L2: ALOAD_3   (line 192)
                    INVOKEINTERFACE java.util.Iterator.hasNext ()Z
                    IFNE L1
                L3: ICONST_0   (line 199)
                    IRETURN
  end public boolean contains(Class)

end public class org.springframework.beans.factory.BeanCreationException
 -- (NullPointerException) null
null
java.lang.NullPointerException
	at org.aspectj.weaver.UnresolvedType.forSignature(UnresolvedType.java:361)
	at org.aspectj.weaver.bcel.BcelObjectType.getDeclaredInterfaces(BcelObjectType.java:275)
	at org.aspectj.weaver.ReferenceType.getDeclaredInterfaces(ReferenceType.java:624)
	at org.aspectj.weaver.ResolvedType.getDirectSupertypes(ResolvedType.java:76)
	at org.aspectj.weaver.patterns.TypePattern.matchesSubtypes(TypePattern.java:178)
	at org.aspectj.weaver.patterns.ExactTypePattern.matchesSubtypes(ExactTypePattern.java:74)
	at org.aspectj.weaver.patterns.TypePattern.matchesStatically(TypePattern.java:130)
	at org.aspectj.weaver.patterns.OrTypePattern.matchesStatically(OrTypePattern.java:76)
	at org.aspectj.weaver.patterns.SignaturePattern.matchesExactlyMethod(SignaturePattern.java:505)
	at org.aspectj.weaver.patterns.SignaturePattern.matchesExactly(SignaturePattern.java:360)
	at org.aspectj.weaver.patterns.SignaturePattern.matches(SignaturePattern.java:320)
	at org.aspectj.weaver.patterns.KindedPointcut.matchInternal(KindedPointcut.java:202)
	at org.aspectj.weaver.patterns.Pointcut.match(Pointcut.java:137)
	at org.aspectj.weaver.patterns.AndPointcut.matchInternal(AndPointcut.java:51)
	at org.aspectj.weaver.patterns.Pointcut.match(Pointcut.java:137)
	at org.aspectj.weaver.patterns.OrPointcut.matchInternal(OrPointcut.java:54)
	at org.aspectj.weaver.patterns.Pointcut.match(Pointcut.java:137)
	at org.aspectj.weaver.ShadowMunger.match(ShadowMunger.java:113)
	at org.aspectj.weaver.Advice.match(Advice.java:109)
	at org.aspectj.weaver.bcel.BcelAdvice.match(BcelAdvice.java:149)
	at org.aspectj.weaver.bcel.BcelClassWeaver.match(BcelClassWeaver.java:3116)
	at org.aspectj.weaver.bcel.BcelClassWeaver.match(BcelClassWeaver.java:2550)
	at org.aspectj.weaver.bcel.BcelClassWeaver.weave(BcelClassWeaver.java:474)
	at org.aspectj.weaver.bcel.BcelClassWeaver.weave(BcelClassWeaver.java:100)
	at org.aspectj.weaver.bcel.BcelWeaver.weave(BcelWeaver.java:1687)
	at org.aspectj.weaver.bcel.BcelWeaver.weaveWithoutDump(BcelWeaver.java:1631)
	at org.aspectj.weaver.bcel.BcelWeaver.weaveAndNotify(BcelWeaver.java:1394)
	at org.aspectj.weaver.bcel.BcelWeaver.weave(BcelWeaver.java:1180)
	at org.aspectj.weaver.tools.WeavingAdaptor.getWovenBytes(WeavingAdaptor.java:467)
	at org.aspectj.weaver.tools.WeavingAdaptor.weaveClass(WeavingAdaptor.java:318)
	at org.aspectj.weaver.loadtime.Aj.preProcess(Aj.java:96)
	at org.aspectj.weaver.loadtime.ClassPreProcessorAgentAdapter.transform(ClassPreProcessorAgentAdapter.java:54)
	at sun.instrument.TransformerManager.transform(TransformerManager.java:188)
	at sun.instrument.InstrumentationImpl.transform(InstrumentationImpl.java:428)
	at java.lang.ClassLoader.defineClass1(Native Method)
	at java.lang.ClassLoader.defineClass(ClassLoader.java:760)
	at java.security.SecureClassLoader.defineClass(SecureClassLoader.java:142)
	at java.net.URLClassLoader.defineClass(URLClassLoader.java:467)
	at java.net.URLClassLoader.access$100(URLClassLoader.java:73)
	at java.net.URLClassLoader$1.run(URLClassLoader.java:368)
	at java.net.URLClassLoader$1.run(URLClassLoader.java:362)
	at java.security.AccessController.doPrivileged(Native Method)
	at java.net.URLClassLoader.findClass(URLClassLoader.java:361)
	at java.lang.ClassLoader.loadClass(ClassLoader.java:424)
	at sun.misc.Launcher$AppClassLoader.loadClass(Launcher.java:331)
	at java.lang.ClassLoader.loadClass(ClassLoader.java:357)
	at java.lang.ClassLoader.defineClass1(Native Method)
	at java.lang.ClassLoader.defineClass(ClassLoader.java:760)
	at java.security.SecureClassLoader.defineClass(SecureClassLoader.java:142)
	at java.net.URLClassLoader.defineClass(URLClassLoader.java:467)
	at java.net.URLClassLoader.access$100(URLClassLoader.java:73)
	at java.net.URLClassLoader$1.run(URLClassLoader.java:368)
	at java.net.URLClassLoader$1.run(URLClassLoader.java:362)
	at java.security.AccessController.doPrivileged(Native Method)
	at java.net.URLClassLoader.findClass(URLClassLoader.java:361)
	at java.lang.ClassLoader.loadClass(ClassLoader.java:424)
	at sun.misc.Launcher$AppClassLoader.loadClass(Launcher.java:331)
	at java.lang.ClassLoader.loadClass(ClassLoader.java:357)
	at org.springframework.context.support.AbstractRefreshableApplicationContext.createBeanFactory(AbstractRefreshableApplicationContext.java:194)
	at org.springframework.context.support.AbstractRefreshableApplicationContext.refreshBeanFactory(AbstractRefreshableApplicationContext.java:127)
	at org.springframework.context.support.AbstractApplicationContext.obtainFreshBeanFactory(AbstractApplicationContext.java:467)
	at org.springframework.context.support.AbstractApplicationContext.refresh(AbstractApplicationContext.java:397)
	at org.springframework.context.support.ClassPathXmlApplicationContext.<init>(ClassPathXmlApplicationContext.java:139)
	at org.springframework.context.support.ClassPathXmlApplicationContext.<init>(ClassPathXmlApplicationContext.java:83)
	at foo.ConfigureApp.main(ConfigureApp.java:9)

error can't determine annotations of missing type org.springframework.cache.annotation.CachePut
when weaving type org.springframework.beans.factory.BeanCreationNotAllowedException
when weaving classes 
when weaving 
 [Xlint:cantFindType]
error can't determine annotations of missing type org.springframework.cache.annotation.Cacheable
when weaving type org.springframework.beans.factory.BeanCreationNotAllowedException
when weaving classes 
when weaving 
 [Xlint:cantFindType]
error can't determine annotations of missing type org.springframework.cache.annotation.CacheEvict
when weaving type org.springframework.beans.factory.BeanCreationNotAllowedException
when weaving classes 
when weaving 
 [Xlint:cantFindType]
error can't determine annotations of missing type org.springframework.cache.annotation.Caching
when weaving type org.springframework.beans.factory.BeanCreationNotAllowedException
when weaving classes 
when weaving 
 [Xlint:cantFindType]
error can't determine annotations of missing type org.springframework.transaction.annotation.Transactional
when weaving type org.springframework.beans.factory.BeanCreationNotAllowedException
when weaving classes 
when weaving 
 [Xlint:cantFindType]
